Workbook

Sheet Rekap
A1: Neraca Fisik dan Moneter
A2: Sumber Daya Hutan Indonesia
A4: Perincian | B4: 1990 | C4: 1991 | D4: 1992 | E4: 1993 | F4: 1994 | G4: 1995 | H4: 1996 | I4: 1997 | J4: 1998 | K4: 1999 | L4: 2000 | M4: 2001 | N4: 2002 | O4: 2003 | P4: 2004 | Q4: 2005 | R4: 2006 | S4: 2007 | T4: 2008 | U4: 2009 | V4: 2010 | W4: 2011 | X4: 2012 | Y4: 2013 | Z4: 2014 | AA4: 2015 | AB4: 2016 | AC4: 2017 | AD4: 2018 | AE4: 2019 | AF4: 2020 | AG4: 2021 | AH4: 2022 | AI4: 2023 | AJ4: 2024
A6: I. Neraca Fisik (000 M3)
A8: 1. Persediaan awal | B8: 8644424.6 | C8: 8642977.8 | D8: 8640252.7 | E8: 8619007.2 | F8: 8589076 | G8: 8569181.9 | H8: 8548707.6 | I8: 8535616.3 | J8: 8478434.2 | K8: 8418105.1 | L8: 8345375.3 | M8: 8282251.8 | N8: 8191498.9 | O8: 8068944.1 | P8: 7925081.7 | Q8: 7753143.4 | R8: 7515887.8 | S8: 7232311.7 | T8: ='Rekap Transpose'!B3 -> 6941231.3 | U8: =T15 -> 6742572.6 | V8: =U15 -> 6520095.2 | W8: =V15 -> 6271702.1 | X8: =W15 -> 5998732.7 | Y8: =X15 -> 5670001.2 | Z8: =Y15 -> 5606293.1 | AA8: =Z15 -> 5423882.4 | AB8: =AA15 -> 4827604.5 | ... AJ8: =AI15 -> 3525379.2
A9: 2. Penambahan | T9: =SUM(T10:T11) -> 58307.641 | U9: =SUM(U10:U11) -> 57410.291 | V9: =SUM(V10:V11) -> 55446.93 | W9: =SUM(W10:W11) -> 56343.743 | X9: =SUM(X10:X11) -> 59091.588 | Y9: =SUM(Y10:Y11) -> 69758.026 | Z9: =SUM(Z10:Z11) -> 57882.121 | AA9: =SUM(AA10:AA11) -> 62487.426 | ... AJ9: =SUM(AJ10:AJ11) -> 54326.981
A10: Pertumbuhan | B10: 41982.9 | C10: 43088.146 | D10: 44320.021 | E10: 45618.543 | F10: 47003.13 | G10: 48595.51 | H10: 54426.46 | I10: 55032.56 | J10: 56761.47 | K10: 60762.237 | L10: 57911.827 | M10: 57766.75 | N10: 57353.36 | O10: 54498.139 | P10: 58396.028 | Q10: 53842.346 | R10: 52132.491 | S10: 51780.126 | T10: =INDIRECT("'Rekap Transpose'!C"&T32) -> 50170.417 | U10: =INDIRECT("'Rekap Transpose'!C"&U32) -> 51261.334 | V10: =INDIRECT("'Rekap Transpose'!C"&V32) -> 50866.651 | W10: =INDIRECT("'Rekap Transpose'!C"&W32) -> 51448.15 | X10: =INDIRECT("'Rekap Transpose'!C"&X32) -> 52887.133 | Y10: =INDIRECT("'Rekap Transpose'!C"&Y32) -> 58651.075 | Z10: =INDIRECT("'Rekap Transpose'!C"&Z32) -> 46687.165 | AA10: =INDIRECT("'Rekap Transpose'!C"&AA32) -> 46799.571 | ... AJ10: =INDIRECT("'Rekap Transpose'!C"&AJ32) -> 46599.387
A11: Penanaman | B11: 790 | C11: 1152.3 | D11: 1131.2 | E11: 1601.8 | F11: 1367.46 | G11: 1674.2 | H11: 2654.03 | I11: 2266.59 | J11: 1681.49 | K11: 1439.1997 | L11: 3484.9848 | M11: 1406.3486 | N11: 5053.5777 | O11: 5971.3368 | P11: 5670.3173 | Q11: 5580.4384 | R11: 7265.3378 | S11: 6472.9681 | T11: =INDIRECT("'Rekap Transpose'!D"&T32) -> 8137.2246 | U11: =INDIRECT("'Rekap Transpose'!D"&U32) -> 6148.9569 | V11: =INDIRECT("'Rekap Transpose'!D"&V32) -> 4580.2793 | W11: =INDIRECT("'Rekap Transpose'!D"&W32) -> 4895.5931 | X11: =INDIRECT("'Rekap Transpose'!D"&X32) -> 6204.4544 | Y11: =INDIRECT("'Rekap Transpose'!D"&Y32) -> 11106.951 | Z11: =INDIRECT("'Rekap Transpose'!D"&Z32) -> 11194.956 | AA11: =INDIRECT("'Rekap Transpose'!D"&AA32) -> 15687.856 | ... AJ11: =INDIRECT("'Rekap Transpose'!D"&AJ32) -> 7727.594
A12: 3.Pengurangan | T12: =SUM(T13:T14) -> 256966.35 | U12: =SUM(U13:U14) -> 279887.69 | V12: =SUM(V13:V14) -> 303840.08 | W12: =SUM(W13:W14) -> 329313.13 | X12: =SUM(X13:X14) -> 387823.01 | Y12: =SUM(Y13:Y14) -> 133466.13 | Z12: =SUM(Z13:Z14) -> 240292.85 | AA12: =SUM(AA13:AA14) -> 658765.38 | ... AJ12: =SUM(AJ13:AJ14) -> 151611.78
A13: Kerusakan | B13: 15665.8 | C13: 18825.8 | D13: 38007.4 | E13: 47597.7 | F13: 38563.3 | G13: 41077.1 | H13: 40078.83 | I13: 80250.98 | J13: 93239.38 | K13: 109191.15 | L13: 98258.31 | M13: 123847.92 | N13: 159469.84 | O13: 180187.66 | P13: 211464.92 | Q13: 253701.29 | R13: 304112.89 | S13: 293287.97 | T13: =INDIRECT("'Rekap Transpose'!E"&T32) -> 207360.8 | U13: =INDIRECT("'Rekap Transpose'!E"&U32) -> 227997.26 | V13: =INDIRECT("'Rekap Transpose'!E"&V32) -> 249399.69 | W13: =INDIRECT("'Rekap Transpose'!E"&W32) -> 278383.26 | X13: =INDIRECT("'Rekap Transpose'!E"&X32) -> 337879.87 | Y13: =INDIRECT("'Rekap Transpose'!E"&Y32) -> 92474.444 | Z13: =INDIRECT("'Rekap Transpose'!E"&Z32) -> 194261.6 | AA13: =INDIRECT("'Rekap Transpose'!E"&AA32) -> 613364.48 | ... AJ13: =INDIRECT("'Rekap Transpose'!E"&AJ32) -> 96304.46
A14: Penebangan | B14: 28553.9 | C14: 28139.7 | D14: 28689.4 | E14: 29553.8 | F14: 29701.4 | G14: 29666.9 | H14: 30092.97 | I14: 34230.235 | J14: 25532.743 | K14: 25740.012 | L14: 26262.063 | M14: 26078.075 | N14: 25491.862 | O14: 24144.223 | P14: 24539.787 | Q14: 42977.097 | R14: 38860.948 | S14: 56045.558 | T14: =INDIRECT("'Rekap Transpose'!F"&T32) -> 49605.554 | U14: =INDIRECT("'Rekap Transpose'!F"&U32) -> 51890.421 | V14: =INDIRECT("'Rekap Transpose'!F"&V32) -> 54440.397 | W14: =INDIRECT("'Rekap Transpose'!F"&W32) -> 50929.869 | X14: =INDIRECT("'Rekap Transpose'!F"&X32) -> 49943.141 | Y14: =INDIRECT("'Rekap Transpose'!F"&Y32) -> 40991.687 | Z14: =INDIRECT("'Rekap Transpose'!F"&Z32) -> 46031.25 | AA14: =INDIRECT("'Rekap Transpose'!F"&AA32) -> 45400.908 | ... AJ14: =INDIRECT("'Rekap Transpose'!F"&AJ32) -> 55307.319
A15: 4. Persediaan akhir | B15: 8642977.8 | C15: 8640252.7 | D15: 8619007.2 | E15: 8589076 | F15: 8569181.9 | G15: 8548707.6 | H15: 8535616.3 | I15: 8478434.2 | J15: 8418105.1 | K15: 8345375.3 | L15: 8282251.8 | M15: 8191498.9 | N15: 8068944.1 | O15: 7925081.7 | P15: 7753143.4 | Q15: 7515887.8 | R15: 7232311.7 | S15: 6941231.3 | T15: =T8+T9-T12 -> 6742572.6 | U15: =U8+U9-U12 -> 6520095.2 | V15: =V8+V9-V12 -> 6271702.1 | W15: =W8+W9-W12 -> 5998732.7 | X15: =X8+X9-X12 -> 5670001.2 | Y15: =Y8+Y9-Y12 -> 5606293.1 | Z15: =Z8+Z9-Z12 -> 5423882.4 | AA15: =AA8+AA9-AA12 -> 4827604.5 | ... AJ15: =AJ8+AJ9-AJ12 -> 3428094.4
U16: =U8-T15 -> 0 | V16: =V8-U15 -> 0 | W16: =W8-V15 -> 0 | X16: =X8-W15 -> 0 | Y16: =Y8-X15 -> 0 | Z16: =Z8-Y15 -> 0 | AA16: =AA8-Z15 -> 0 | AB16: =AB8-AA15 -> 0 | ... AJ16: =AJ8-AI15 -> 0
A18: III. Neraca Moneter
A19: (Miliar Rp)
A21: 1. Persediaan awal | B21: 74108.902 | C21: 83802.55 | D21: 97018.89 | E21: 92652.724 | F21: 104769.1 | G21: 128642.89 | H21: 138837.71 | I21: 149329.52 | J21: 160216.11 | K21: 197640.93 | L21: 244516.25 | M21: 255163.72 | N21: 245748.71 | O21: 251003.76 | P21: 261590.39 | Q21: 280224.95 | R21: 308313.84 | S21: 423393.61 | U21: ='Rekap Transpose'!B23 -> 6465702.8 | V21: =U29 -> 6835195.2 | W21: =V29 -> 4757481.7 | X21: =W29 -> 1381033.5 | Y21: =X29 -> 924382.72 | Z21: =Y29 -> 701661.76 | AA21: =Z29 -> 719985.09 | AB21: =AA29 -> 628834.11 | AC21: =AB29 -> 681499.89 | ... AJ21: =AI29 -> 1384227.4
A22: 2. Penambahan | U22: =SUM(U23:U24) -> 60348.218 | V22: =SUM(V23:V24) -> 33359.223 | W22: =SUM(W23:W24) -> 9696.0603 | X22: =SUM(X23:X24) -> 7068.9023 | Y22: =SUM(Y23:Y24) -> 5569.0193 | Z22: =SUM(Z23:Z24) -> 5639.768 | AA22: =SUM(AA23:AA24) -> 6211.529 | AB22: =SUM(AB23:AB24) -> 7110.7939 | ... AJ22: =SUM(AJ23:AJ24) -> 15703.442
A23: Pertumbuhan | B23: 689.56159 | C23: 686.14115 | D23: 654.21251 | E23: 1036.6145 | F23: 1466.4377 | G23: 1626.3811 | H23: 2001.1504 | I23: 2825.251 | J23: 3061.3912 | K23: 4046.3159 | L23: 4148.0219 | M23: 3363.0885 | N23: 3470.0661 | O23: 3412.1885 | P23: 3994.6146 | Q23: 3863.6905 | R23: 5493.5606 | S23: 6518.4084 | U23: =INDIRECT("'Rekap Transpose'!C"&U33) -> 53904.98 | V23: =INDIRECT("'Rekap Transpose'!C"&V33) -> 29763.587 | W23: =INDIRECT("'Rekap Transpose'!C"&W33) -> 8498.601 | X23: =INDIRECT("'Rekap Transpose'!C"&X33) -> 5979.9178 | Y23: =INDIRECT("'Rekap Transpose'!C"&Y33) -> 4064.8881 | Z23: =INDIRECT("'Rekap Transpose'!C"&Z33) -> 4013.4808 | AA23: =INDIRECT("'Rekap Transpose'!C"&AA33) -> 3927.0238 | AB23: =INDIRECT("'Rekap Transpose'!C"&AB33) -> 4254.0726 | ... AJ23: =INDIRECT("'Rekap Transpose'!C"&AJ33) -> 11987.894
A24: Penanaman | B24: 9.7480176 | C24: 14.128113 | D24: 12.869787 | E24: 21.547158 | F24: 23.634181 | G24: 30.60233 | H24: 45.795587 | I24: 44.783644 | J24: 41.357379 | K24: 53.677051 | L24: 116.11617 | M24: 53.491456 | N24: 156.99325 | O24: 189.63575 | P24: 195.59029 | Q24: 220.39693 | R24: 399.72037 | S24: 436.70366 | U24: =INDIRECT("'Rekap Transpose'!D"&U33) -> 6443.2381 | V24: =INDIRECT("'Rekap Transpose'!D"&V33) -> 3595.6356 | W24: =INDIRECT("'Rekap Transpose'!D"&W33) -> 1197.4593 | X24: =INDIRECT("'Rekap Transpose'!D"&X33) -> 1088.9846 | Y24: =INDIRECT("'Rekap Transpose'!D"&Y33) -> 1504.1311 | Z24: =INDIRECT("'Rekap Transpose'!D"&Z33) -> 1626.2872 | AA24: =INDIRECT("'Rekap Transpose'!D"&AA33) -> 2284.5052 | AB24: =INDIRECT("'Rekap Transpose'!D"&AB33) -> 2856.7213 | ... AJ24: =INDIRECT("'Rekap Transpose'!D"&AJ33) -> 3715.5482
A25: 3.Pengurangan | U25: =SUM(U26:U27) -> 293282.56 | V25: =SUM(V26:V27) -> 242436.18 | W25: =SUM(W26:W27) -> 80899.769 | X25: =SUM(X26:X27) -> 67797.272 | Y25: =SUM(Y26:Y27) -> 17825.468 | Z25: =SUM(Z26:Z27) -> 34762.947 | AA25: =SUM(AA26:AA27) -> 95890.196 | AB25: =SUM(AB26:AB27) -> 39606.994 | ... AJ25: =SUM(AJ26:AJ27) -> 72238.104
A26: Kerusakan | B26: 157.28271 | C26: 214.51114 | D26: 407.81127 | E26: 579.8117 | F26: 578.67353 | G26: 660.4917 | H26: 693.76421 | I26: 1386.6881 | J26: 2140.4004 | K26: 3061.1596 | L26: 2904.073 | M26: 3510.4357 | N26: 4595.9862 | O26: 5460.4588 | P26: 6918.4262 | Q26: 9443.8928 | R26: 15815.893 | S26: 17965.879 | U26: =INDIRECT("'Rekap Transpose'!E"&U33) -> 238894.12 | V26: =INDIRECT("'Rekap Transpose'!E"&V33) -> 199226.17 | W26: =INDIRECT("'Rekap Transpose'!E"&W33) -> 68481.629 | X26: =INDIRECT("'Rekap Transpose'!E"&X33) -> 59094.5 | Y26: =INDIRECT("'Rekap Transpose'!E"&Y33) -> 12341.657 | Z26: =INDIRECT("'Rekap Transpose'!E"&Z33) -> 28141.491 | AA26: =INDIRECT("'Rekap Transpose'!E"&AA33) -> 89344.514 | AB26: =INDIRECT("'Rekap Transpose'!E"&AB33) -> 32133.043 | ... AJ26: =INDIRECT("'Rekap Transpose'!E"&AJ33) -> 45904.98
A27: Penebangan | B27: 349.11397 | C27: 369.30281 | D27: 347.58733 | E27: 463.06348 | F27: 602.22903 | G27: 649.1225 | H27: 666.73428 | I27: 876.02304 | J27: 804.41131 | K27: 1023.0924 | L27: 1050.241 | M27: 899.14327 | N27: 916.83356 | O27: 839.95021 | P27: 951.20793 | Q27: 1683.74 | R27: 2231.8437 | S27: 3712.0011 | U27: =INDIRECT("'Rekap Transpose'!F"&U33) -> 54388.444 | V27: =INDIRECT("'Rekap Transpose'!F"&V33) -> 43210.017 | W27: =INDIRECT("'Rekap Transpose'!F"&W33) -> 12418.141 | X27: =INDIRECT("'Rekap Transpose'!F"&X33) -> 8702.7714 | Y27: =INDIRECT("'Rekap Transpose'!F"&Y33) -> 5483.811 | Z27: =INDIRECT("'Rekap Transpose'!F"&Z33) -> 6621.4561 | AA27: =INDIRECT("'Rekap Transpose'!F"&AA33) -> 6545.6817 | AB27: =INDIRECT("'Rekap Transpose'!F"&AB33) -> 7473.951 | ... AJ27: =INDIRECT("'Rekap Transpose'!F"&AJ33) -> 26333.124
A28: 4. Revaluasi | B28: 9500.7348 | C28: 13099.885 | D28: -4277.8497 | E28: 12101.093 | F28: 23564.616 | G28: 9847.4491 | H28: 9805.3696 | I28: 10279.262 | J28: 37266.886 | K28: 46859.577 | L28: 10337.648 | M28: -8422.0159 | N28: 7140.8153 | O28: 13285.217 | P28: 22313.988 | Q28: 35132.432 | R28: 127234.22 | S28: 75568.764 | U28: =INDIRECT("'Rekap Transpose'!G"&U33) -> 602426.75 | V28: =INDIRECT("'Rekap Transpose'!G"&V33) -> -1868636.5 | W28: =INDIRECT("'Rekap Transpose'!G"&W33) -> -3305244.6 | X28: =INDIRECT("'Rekap Transpose'!G"&X33) -> -395922.36 | Y28: =INDIRECT("'Rekap Transpose'!G"&Y33) -> -210464.51 | Z28: =INDIRECT("'Rekap Transpose'!G"&Z33) -> 47446.501 | AA28: =INDIRECT("'Rekap Transpose'!G"&AA33) -> -1472.309 | AB28: =INDIRECT("'Rekap Transpose'!G"&AB33) -> 85161.98 | ... AJ28: =INDIRECT("'Rekap Transpose'!G"&AJ33) -> -3776.6979
A29: 5. Persediaan akhir | B29: 83802.55 | C29: 97018.89 | D29: 92652.724 | E29: 104769.1 | F29: 128642.89 | G29: 138837.71 | H29: 149329.52 | I29: 160216.11 | J29: 197640.93 | K29: 244516.25 | L29: 255163.72 | M29: 245748.71 | N29: 251003.76 | O29: 261590.39 | P29: 280224.95 | Q29: 308313.84 | R29: 423393.61 | S29: 484239.6 | U29: =U21+U22-U25+U28 -> 6835195.2 | V29: =V21+V22-V25+V28 -> 4757481.7 | W29: =W21+W22-W25+W28 -> 1381033.5 | X29: =X21+X22-X25+X28 -> 924382.72 | Y29: =Y21+Y22-Y25+Y28 -> 701661.76 | Z29: =Z21+Z22-Z25+Z28 -> 719985.09 | AA29: =AA21+AA22-AA25+AA28 -> 628834.11 | AB29: =AB21+AB22-AB25+AB28 -> 681499.89 | ... AJ29: =AJ21+AJ22-AJ25+AJ28 -> 1323916.1
V30: =U29-V21 -> 0 | W30: =V29-W21 -> 0 | X30: =W29-X21 -> 0 | Y30: =X29-Y21 -> 0 | Z30: =Y29-Z21 -> 0 | AA30: =Z29-AA21 -> 0 | AB30: =AA29-AB21 -> 0 | AC30: =AB29-AC21 -> 0 | ... AJ30: =AI29-AJ21 -> 0
A32: nomor baris neraca fisik | T32: 3 | U32: =T32+1 -> 4 | V32: =U32+1 -> 5 | W32: =V32+1 -> 6 | X32: =W32+1 -> 7 | Y32: =X32+1 -> 8 | Z32: =Y32+1 -> 9 | AA32: =Z32+1 -> 10 | AB32: =AA32+1 -> 11 | ... AJ32: =AI32+1 -> 19
A33: nomor baris neraca moneter | U33: 23 | V33: =U33+1 -> 24 | W33: =V33+1 -> 25 | X33: =W33+1 -> 26 | Y33: =X33+1 -> 27 | Z33: =Y33+1 -> 28 | AA33: =Z33+1 -> 29 | AB33: =AA33+1 -> 30 | AC33: =AB33+1 -> 31 | ... AJ33: =AI33+1 -> 38

Sheet Rekap JJ
A1: Neraca Fisik dan Moneter
A2: Sumber Daya Hutan Jati Jawa
A4: Perincian | B4: 2008 | C4: 2009 | D4: 2010 | E4: 2011 | F4: 2012 | G4: 2013 | H4: 2014 | I4: 2015 | J4: 2016 | K4: 2017 | L4: 2018 | M4: 2019 | N4: 2020 | O4: 2021 | P4: 2022 | Q4: 2023 | R4: 2024
A6: I. Neraca Fisik (000 M3)
A8: 1. Persediaan awal | B8: ='Jati Jawa'!B4 -> 87707.889 | C8: =B15 -> 91665.246 | D8: =C15 -> 95691.987 | E8: =D15 -> 99600.194 | F8: =E15 -> 102983.4 | G8: =F15 -> 104859.17 | H8: =G15 -> 108505.1 | I8: =H15 -> 111792.49 | J8: =I15 -> 114986.68 | ... R8: =Q15 -> 143946.66
A9: 2. Penambahan | B9: =SUM(B10:B11) -> 4764.3122 | C9: =SUM(C10:C11) -> 4775.1077 | D9: =SUM(D10:D11) -> 4799.06 | E9: =SUM(E10:E11) -> 4833.5027 | F9: =SUM(F10:F11) -> 4852.1833 | G9: =SUM(G10:G11) -> 5475.6953 | H9: =SUM(H10:H11) -> 4788.2139 | I9: =SUM(I10:I11) -> 4815.2779 | ... R9: =SUM(R10:R11) -> 5110.829
A10: Pertumbuhan | B10: =INDIRECT("'Jati Jawa'!C"&B32) -> 4732.2962 | C10: =INDIRECT("'Jati Jawa'!C"&C32) -> 4755.9577 | D10: =INDIRECT("'Jati Jawa'!C"&D32) -> 4779.736 | E10: =INDIRECT("'Jati Jawa'!C"&E32) -> 4803.6347 | F10: =INDIRECT("'Jati Jawa'!C"&F32) -> 4827.6543 | G10: =INDIRECT("'Jati Jawa'!C"&G32) -> 5459.4625 | H10: =INDIRECT("'Jati Jawa'!C"&H32) -> 4764.8739 | I10: =INDIRECT("'Jati Jawa'!C"&I32) -> 4794.9495 | ... R10: =INDIRECT("'Jati Jawa'!C"&R32) -> 5096.753
A11: Penanaman | B11: =INDIRECT("'Jati Jawa'!D"&B32) -> 32.016 | C11: =INDIRECT("'Jati Jawa'!D"&C32) -> 19.15 | D11: =INDIRECT("'Jati Jawa'!D"&D32) -> 19.324 | E11: =INDIRECT("'Jati Jawa'!D"&E32) -> 29.868 | F11: =INDIRECT("'Jati Jawa'!D"&F32) -> 24.529 | G11: =INDIRECT("'Jati Jawa'!D"&G32) -> 16.23275 | H11: =INDIRECT("'Jati Jawa'!D"&H32) -> 23.34 | I11: =INDIRECT("'Jati Jawa'!D"&I32) -> 20.32837 | ... R11: =INDIRECT("'Jati Jawa'!D"&R32) -> 14.076
A12: 3.Pengurangan | B12: =SUM(B13:B14) -> 806.95483 | C12: =SUM(C13:C14) -> 748.36735 | D12: =SUM(D13:D14) -> 890.85249 | E12: =SUM(E13:E14) -> 1450.2983 | F12: =SUM(F13:F14) -> 2976.4148 | G12: =SUM(G13:G14) -> 1829.7577 | H12: =SUM(H13:H14) -> 1500.8289 | I12: =SUM(I13:I14) -> 1621.0865 | ... R12: =SUM(R13:R14) -> 1082.2608
A13: Kerusakan | B13: =INDIRECT("'Jati Jawa'!E"&B32) -> 329.24483 | C13: =INDIRECT("'Jati Jawa'!E"&C32) -> 293.16735 | D13: =INDIRECT("'Jati Jawa'!E"&D32) -> 440.82049 | E13: =INDIRECT("'Jati Jawa'!E"&E32) -> 1014.8983 | F13: =INDIRECT("'Jati Jawa'!E"&F32) -> 2572.9828 | G13: =INDIRECT("'Jati Jawa'!E"&G32) -> 1398.2411 | H13: =INDIRECT("'Jati Jawa'!E"&H32) -> 1044.8336 | I13: =INDIRECT("'Jati Jawa'!E"&I32) -> 1228.4299 | ... R13: =INDIRECT("'Jati Jawa'!E"&R32) -> 686.75276
A14: Penebangan | B14: =INDIRECT("'Jati Jawa'!F"&B32) -> 477.71 | C14: =INDIRECT("'Jati Jawa'!F"&C32) -> 455.2 | D14: =INDIRECT("'Jati Jawa'!F"&D32) -> 450.032 | E14: =INDIRECT("'Jati Jawa'!F"&E32) -> 435.4 | F14: =INDIRECT("'Jati Jawa'!F"&F32) -> 403.432 | G14: =INDIRECT("'Jati Jawa'!F"&G32) -> 431.5166 | H14: =INDIRECT("'Jati Jawa'!F"&H32) -> 455.99528 | I14: =INDIRECT("'Jati Jawa'!F"&I32) -> 392.65651 | ... R14: =INDIRECT("'Jati Jawa'!F"&R32) -> 395.508
A15: 4. Persediaan akhir | B15: =B8+B9-B12 -> 91665.246 | C15: =C8+C9-C12 -> 95691.987 | D15: =D8+D9-D12 -> 99600.194 | E15: =E8+E9-E12 -> 102983.4 | F15: =F8+F9-F12 -> 104859.17 | G15: =G8+G9-G12 -> 108505.1 | H15: =H8+H9-H12 -> 111792.49 | I15: =I8+I9-I12 -> 114986.68 | ... R15: =R8+R9-R12 -> 147975.23
C16: =C15-INDIRECT("'Jati Jawa'!G"&C32) -> 0 | D16: =D15-INDIRECT("'Jati Jawa'!G"&D32) -> 0 | E16: =E15-INDIRECT("'Jati Jawa'!G"&E32) -> 0 | F16: =F15-INDIRECT("'Jati Jawa'!G"&F32) -> 0 | G16: =G15-INDIRECT("'Jati Jawa'!G"&G32) -> 0 | H16: =H15-INDIRECT("'Jati Jawa'!G"&H32) -> 0 | I16: =I15-INDIRECT("'Jati Jawa'!G"&I32) -> 0 | J16: =J15-INDIRECT("'Jati Jawa'!G"&J32) -> 0 | ... R16: =R15-INDIRECT("'Jati Jawa'!G"&R32) -> 0
A18: III. Neraca Moneter
A19: (Miliar Rp)
A21: 1. Persediaan awal | C21: ='Jati Jawa'!B47 -> 92293.685 | D21: =C29 -> 104925.04 | E21: =D29 -> 61836.339 | F21: =E29 -> 12389.188 | G21: =F29 -> 7737.4453 | H21: =G29 -> 8404.6549 | I21: =H29 -> 8707.7924 | J21: =I29 -> 7463.7389 | K21: =J29 -> 5461.6171 | ... R21: =Q29 -> 14758.997
A22: 2. Penambahan | C22: =SUM(C23:C24) -> 5235.8445 | D22: =SUM(D23:D24) -> 2979.4751 | E22: =SUM(E23:E24) -> 581.48375 | F22: =SUM(F23:F24) -> 358.0374 | G22: =SUM(G23:G24) -> 424.13976 | H22: =SUM(H23:H24) -> 372.96578 | I22: =SUM(I23:I24) -> 312.55774 | J22: =SUM(J23:J24) -> 200.56968 | ... R22: =SUM(R23:R24) -> 435.17464
A23: Pertumbuhan | C23: =INDIRECT("'Jati Jawa'!C"&C33) -> 5214.8467 | D23: =INDIRECT("'Jati Jawa'!C"&D33) -> 2967.4779 | E23: =INDIRECT("'Jati Jawa'!C"&E33) -> 577.89055 | F23: =INDIRECT("'Jati Jawa'!C"&F33) -> 356.22743 | G23: =INDIRECT("'Jati Jawa'!C"&G33) -> 422.88239 | H23: =INDIRECT("'Jati Jawa'!C"&H33) -> 371.14777 | I23: =INDIRECT("'Jati Jawa'!C"&I33) -> 311.23823 | J23: =INDIRECT("'Jati Jawa'!C"&J33) -> 200.36266 | ... R23: =INDIRECT("'Jati Jawa'!C"&R33) -> 433.97611
A24: Penanaman | C24: =INDIRECT("'Jati Jawa'!D"&C33) -> 20.99773 | D24: =INDIRECT("'Jati Jawa'!D"&D33) -> 11.99722 | E24: =INDIRECT("'Jati Jawa'!D"&E33) -> 3.5932031 | F24: =INDIRECT("'Jati Jawa'!D"&F33) -> 1.8099686 | G24: =INDIRECT("'Jati Jawa'!D"&G33) -> 1.2573663 | H24: =INDIRECT("'Jati Jawa'!D"&H33) -> 1.8180101 | I24: =INDIRECT("'Jati Jawa'!D"&I33) -> 1.3195063 | J24: =INDIRECT("'Jati Jawa'!D"&J33) -> 0.20702234 | ... R24: =INDIRECT("'Jati Jawa'!D"&R33) -> 1.1985371
A25: 3.Pengurangan | C25: =SUM(C26:C27) -> 820.57523 | D25: =SUM(D26:D27) -> 553.08182 | E25: =SUM(E26:E27) -> 174.4749 | F25: =SUM(F26:F27) -> 219.62645 | G25: =SUM(G26:G27) -> 141.73049 | H25: =SUM(H26:H27) -> 116.90326 | I25: =SUM(I26:I27) -> 105.22407 | J25: =SUM(J26:J27) -> 52.526688 | ... R25: =SUM(R26:R27) -> 92.151867
A26: Kerusakan | C26: =INDIRECT("'Jati Jawa'!E"&C33) -> 321.45425 | D26: =INDIRECT("'Jati Jawa'!E"&D33) -> 273.68145 | E26: =INDIRECT("'Jati Jawa'!E"&E33) -> 122.09508 | F26: =INDIRECT("'Jati Jawa'!E"&F33) -> 189.85763 | G26: =INDIRECT("'Jati Jawa'!E"&G33) -> 108.30582 | H26: =INDIRECT("'Jati Jawa'!E"&H33) -> 81.384662 | I26: =INDIRECT("'Jati Jawa'!E"&I33) -> 79.73689 | J26: =INDIRECT("'Jati Jawa'!E"&J33) -> 40.94462 | ... R26: =INDIRECT("'Jati Jawa'!E"&R33) -> 58.475325
A27: Penebangan | C27: =INDIRECT("'Jati Jawa'!F"&C33) -> 499.12098 | D27: =INDIRECT("'Jati Jawa'!F"&D33) -> 279.40037 | E27: =INDIRECT("'Jati Jawa'!F"&E33) -> 52.379825 | F27: =INDIRECT("'Jati Jawa'!F"&F33) -> 29.768814 | G27: =INDIRECT("'Jati Jawa'!F"&G33) -> 33.424677 | H27: =INDIRECT("'Jati Jawa'!F"&H33) -> 35.518595 | I27: =INDIRECT("'Jati Jawa'!F"&I33) -> 25.487175 | J27: =INDIRECT("'Jati Jawa'!F"&J33) -> 11.582068 | ... R27: =INDIRECT("'Jati Jawa'!F"&R33) -> 33.676543
A28: 4. Revaluasi | C28: =INDIRECT("'Jati Jawa'!G"&C33) -> 8216.085 | D28: =INDIRECT("'Jati Jawa'!G"&D33) -> -45515.094 | E28: =INDIRECT("'Jati Jawa'!G"&E33) -> -49854.16 | F28: =INDIRECT("'Jati Jawa'!G"&F33) -> -4790.1535 | G28: =INDIRECT("'Jati Jawa'!G"&G33) -> 384.80033 | H28: =INDIRECT("'Jati Jawa'!G"&H33) -> 47.074999 | I28: =INDIRECT("'Jati Jawa'!G"&I33) -> -1451.3872 | J28: =INDIRECT("'Jati Jawa'!G"&J33) -> -2150.1648 | ... R28: =INDIRECT("'Jati Jawa'!G"&R33) -> -2502.2892
A29: 5. Persediaan akhir | C29: =C21+C22-C25+C28 -> 104925.04 | D29: =D21+D22-D25+D28 -> 61836.339 | E29: =E21+E22-E25+E28 -> 12389.188 | F29: =F21+F22-F25+F28 -> 7737.4453 | G29: =G21+G22-G25+G28 -> 8404.6549 | H29: =H21+H22-H25+H28 -> 8707.7924 | I29: =I21+I22-I25+I28 -> 7463.7389 | J29: =J21+J22-J25+J28 -> 5461.6171 | ... R29: =R21+R22-R25+R28 -> 12599.73
C30: =C29-INDIRECT("'Jati Jawa'!H"&C33) -> 0 | D30: =D29-INDIRECT("'Jati Jawa'!H"&D33) -> 0 | E30: =E29-INDIRECT("'Jati Jawa'!H"&E33) -> 0 | F30: =F29-INDIRECT("'Jati Jawa'!H"&F33) -> 0 | G30: =G29-INDIRECT("'Jati Jawa'!H"&G33) -> 0 | H30: =H29-INDIRECT("'Jati Jawa'!H"&H33) -> 0 | I30: =I29-INDIRECT("'Jati Jawa'!H"&I33) -> -8.1854523e-12 | J30: =J29-INDIRECT("'Jati Jawa'!H"&J33) -> -1.0004442e-11 | ... R30: =R29-INDIRECT("'Jati Jawa'!H"&R33) -> 0
A32: nomor baris neraca fisik | B32: 4 | C32: =B32+1 -> 5 | D32: =C32+1 -> 6 | E32: =D32+1 -> 7 | F32: =E32+1 -> 8 | G32: =F32+1 -> 9 | H32: =G32+1 -> 10 | I32: =H32+1 -> 11 | J32: =I32+1 -> 12 | ... R32: =Q32+1 -> 20
A33: nomor baris neraca moneter | C33: 47 | D33: =C33+1 -> 48 | E33: =D33+1 -> 49 | F33: =E33+1 -> 50 | G33: =F33+1 -> 51 | H33: =G33+1 -> 52 | I33: =H33+1 -> 53 | J33: =I33+1 -> 54 | K33: =J33+1 -> 55 | ... R33: =Q33+1 -> 62

Sheet Rekap RJ
A1: Neraca Fisik dan Moneter
A2: Sumber Daya Hutan Rimba Jawa
A4: Perincian | B4: 2008 | C4: 2009 | D4: 2010 | E4: 2011 | F4: 2012 | G4: 2013 | H4: 2014 | I4: 2015 | J4: 2016 | K4: 2017 | L4: 2018 | M4: 2019 | N4: 2020 | O4: 2021 | P4: 2022 | Q4: 2023 | R4: 2024
A6: I. Neraca Fisik (000 M3)
A8: 1. Persediaan awal | B8: ='Rimba Jawa'!B4 -> 352874.6 | C8: =B15 -> 368802.12 | D8: =C15 -> 385178.91 | E8: =D15 -> 401131.81 | F8: =E15 -> 416754.42 | G8: =F15 -> 432600.57 | H8: =G15 -> 461659.54 | I8: =H15 -> 478966.43 | J8: =I15 -> 496202.79 | ... R8: =Q15 -> 565494.79
A9: 2. Penambahan | B9: =SUM(B10:B11) -> 16820.472 | C9: =SUM(C10:C11) -> 17157.186 | D9: =SUM(D10:D11) -> 16777.587 | E9: =SUM(E10:E11) -> 17043.373 | F9: =SUM(F10:F11) -> 18620.283 | G9: =SUM(G10:G11) -> 30805.018 | H9: =SUM(H10:H11) -> 18682.609 | I9: =SUM(I10:I11) -> 18708.521 | ... R9: =SUM(R10:R11) -> 18219.534
A10: Pertumbuhan | B10: =INDIRECT("'Rimba Jawa'!C"&B32) -> 16669.278 | C10: =INDIRECT("'Rimba Jawa'!C"&C32) -> 17077.825 | D10: =INDIRECT("'Rimba Jawa'!C"&D32) -> 16669.3 | E10: =INDIRECT("'Rimba Jawa'!C"&E32) -> 17002.694 | F10: =INDIRECT("'Rimba Jawa'!C"&F32) -> 18588.711 | G10: =INDIRECT("'Rimba Jawa'!C"&G32) -> 30769.212 | H10: =INDIRECT("'Rimba Jawa'!C"&H32) -> 18645.347 | I10: =INDIRECT("'Rimba Jawa'!C"&I32) -> 18669.687 | ... R10: =INDIRECT("'Rimba Jawa'!C"&R32) -> 18205.292
A11: Penanaman | B11: =INDIRECT("'Rimba Jawa'!D"&B32) -> 151.19423 | C11: =INDIRECT("'Rimba Jawa'!D"&C32) -> 79.3611 | D11: =INDIRECT("'Rimba Jawa'!D"&D32) -> 108.28688 | E11: =INDIRECT("'Rimba Jawa'!D"&E32) -> 40.679275 | F11: =INDIRECT("'Rimba Jawa'!D"&F32) -> 31.57245 | G11: =INDIRECT("'Rimba Jawa'!D"&G32) -> 35.806225 | H11: =INDIRECT("'Rimba Jawa'!D"&H32) -> 37.262225 | I11: =INDIRECT("'Rimba Jawa'!D"&I32) -> 38.834 | ... R11: =INDIRECT("'Rimba Jawa'!D"&R32) -> 14.2415
A12: 3.Pengurangan | B12: =SUM(B13:B14) -> 892.95421 | C12: =SUM(C13:C14) -> 780.40155 | D12: =SUM(D13:D14) -> 824.68098 | E12: =SUM(E13:E14) -> 1420.7633 | F12: =SUM(F13:F14) -> 2774.1302 | G12: =SUM(G13:G14) -> 1746.0507 | H12: =SUM(H13:H14) -> 1375.7167 | I12: =SUM(I13:I14) -> 1472.1614 | ... R12: =SUM(R13:R14) -> 1008.3118
A13: Kerusakan | B13: =INDIRECT("'Rimba Jawa'!E"&B32) -> 287.74121 | C13: =INDIRECT("'Rimba Jawa'!E"&C32) -> 256.21155 | D13: =INDIRECT("'Rimba Jawa'!E"&D32) -> 385.25198 | E13: =INDIRECT("'Rimba Jawa'!E"&E32) -> 886.96329 | F13: =INDIRECT("'Rimba Jawa'!E"&F32) -> 2248.6402 | G13: =INDIRECT("'Rimba Jawa'!E"&G32) -> 1221.983 | H13: =INDIRECT("'Rimba Jawa'!E"&H32) -> 913.12499 | I13: =INDIRECT("'Rimba Jawa'!E"&I32) -> 1073.5777 | ... R13: =INDIRECT("'Rimba Jawa'!E"&R32) -> 600.18276
A14: Penebangan | B14: =INDIRECT("'Rimba Jawa'!F"&B32) -> 605.213 | C14: =INDIRECT("'Rimba Jawa'!F"&C32) -> 524.19 | D14: =INDIRECT("'Rimba Jawa'!F"&D32) -> 439.429 | E14: =INDIRECT("'Rimba Jawa'!F"&E32) -> 533.8 | F14: =INDIRECT("'Rimba Jawa'!F"&F32) -> 525.49 | G14: =INDIRECT("'Rimba Jawa'!F"&G32) -> 524.06771 | H14: =INDIRECT("'Rimba Jawa'!F"&H32) -> 462.59173 | I14: =INDIRECT("'Rimba Jawa'!F"&I32) -> 398.58371 | ... R14: =INDIRECT("'Rimba Jawa'!F"&R32) -> 408.129
A15: 4. Persediaan akhir | B15: =B8+B9-B12 -> 368802.12 | C15: =C8+C9-C12 -> 385178.91 | D15: =D8+D9-D12 -> 401131.81 | E15: =E8+E9-E12 -> 416754.42 | F15: =F8+F9-F12 -> 432600.57 | G15: =G8+G9-G12 -> 461659.54 | H15: =H8+H9-H12 -> 478966.43 | I15: =I8+I9-I12 -> 496202.79 | ... R15: =R8+R9-R12 -> 582706.01
C16: =C15-INDIRECT("'Rimba Jawa'!G"&C32) -> 0 | D16: =D15-INDIRECT("'Rimba Jawa'!G"&D32) -> 0 | E16: =E15-INDIRECT("'Rimba Jawa'!G"&E32) -> 0 | F16: =F15-INDIRECT("'Rimba Jawa'!G"&F32) -> 0 | G16: =G15-INDIRECT("'Rimba Jawa'!G"&G32) -> 0 | H16: =H15-INDIRECT("'Rimba Jawa'!G"&H32) -> 0 | I16: =I15-INDIRECT("'Rimba Jawa'!G"&I32) -> 0 | J16: =J15-INDIRECT("'Rimba Jawa'!G"&J32) -> 0 | ... R16: =R15-INDIRECT("'Rimba Jawa'!G"&R32) -> 0
A18: III. Neraca Moneter
A19: (Miliar Rp)
A21: 1. Persediaan awal | C21: ='Rimba Jawa'!B46 -> 351327.58 | D21: =C29 -> 402773.07 | E21: =D29 -> 78445.539 | F21: =E29 -> 14587.809 | G21: =F29 -> 9679.9898 | H21: =G29 -> 8929.8894 | I21: =H29 -> 6353.4534 | J21: =I29 -> 5513.4571 | K21: =J29 -> 4483.5833 | ... R21: =Q29 -> 11166.037
A22: 2. Penambahan | C22: =SUM(C23:C24) -> 17940.89 | D22: =SUM(D23:D24) -> 3281.0334 | E22: =SUM(E23:E24) -> 596.57547 | F22: =SUM(F23:F24) -> 416.6526 | G22: =SUM(G23:G24) -> 595.86205 | H22: =SUM(H23:H24) -> 247.82339 | I22: =SUM(I23:I24) -> 207.87595 | J22: =SUM(J23:J24) -> 98.523789 | ... R22: =SUM(R23:R24) -> 315.6115
A23: Pertumbuhan | C23: =INDIRECT("'Rimba Jawa'!C"&C33) -> 17857.904 | D23: =INDIRECT("'Rimba Jawa'!C"&D33) -> 3259.8567 | E23: =INDIRECT("'Rimba Jawa'!C"&E33) -> 595.15156 | F23: =INDIRECT("'Rimba Jawa'!C"&F33) -> 415.94613 | G23: =INDIRECT("'Rimba Jawa'!C"&G33) -> 595.16945 | H23: =INDIRECT("'Rimba Jawa'!C"&H33) -> 247.32911 | I23: =INDIRECT("'Rimba Jawa'!C"&I33) -> 207.44445 | J23: =INDIRECT("'Rimba Jawa'!C"&J33) -> 98.439731 | ... R23: =INDIRECT("'Rimba Jawa'!C"&R33) -> 315.3648
A24: Penanaman | C24: =INDIRECT("'Rimba Jawa'!D"&C33) -> 82.986148 | D24: =INDIRECT("'Rimba Jawa'!D"&D33) -> 21.176638 | E24: =INDIRECT("'Rimba Jawa'!D"&E33) -> 1.4239117 | F24: =INDIRECT("'Rimba Jawa'!D"&F33) -> 0.70647385 | G24: =INDIRECT("'Rimba Jawa'!D"&G33) -> 0.6926005 | H24: =INDIRECT("'Rimba Jawa'!D"&H33) -> 0.49428059 | I24: =INDIRECT("'Rimba Jawa'!D"&I33) -> 0.43149614 | J24: =INDIRECT("'Rimba Jawa'!D"&J33) -> 0.084058452 | ... R24: =INDIRECT("'Rimba Jawa'!D"&R33) -> 0.24670122
A25: 3.Pengurangan | C25: =SUM(C26:C27) -> 816.04866 | D25: =SUM(D26:D27) -> 161.27503 | E25: =SUM(E26:E27) -> 49.731502 | F25: =SUM(F26:F27) -> 62.074704 | G25: =SUM(G26:G27) -> 33.773892 | H25: =SUM(H26:H27) -> 18.248778 | I25: =SUM(I26:I27) -> 16.357624 | J25: =SUM(J26:J27) -> 9.4953569 | ... R25: =SUM(R26:R27) -> 17.466681
A26: Kerusakan | C26: =INDIRECT("'Rimba Jawa'!E"&C33) -> 267.91476 | D26: =INDIRECT("'Rimba Jawa'!E"&D33) -> 75.340071 | E26: =INDIRECT("'Rimba Jawa'!E"&E33) -> 31.046703 | F26: =INDIRECT("'Rimba Jawa'!E"&F33) -> 50.316195 | G26: =INDIRECT("'Rimba Jawa'!E"&G33) -> 23.636841 | H26: =INDIRECT("'Rimba Jawa'!E"&H33) -> 12.112534 | I26: =INDIRECT("'Rimba Jawa'!E"&I33) -> 11.928842 | J26: =INDIRECT("'Rimba Jawa'!E"&J33) -> 6.8579834 | ... R26: =INDIRECT("'Rimba Jawa'!E"&R33) -> 10.396785
A27: Penebangan | C27: =INDIRECT("'Rimba Jawa'!F"&C33) -> 548.1339 | D27: =INDIRECT("'Rimba Jawa'!F"&D33) -> 85.934957 | E27: =INDIRECT("'Rimba Jawa'!F"&E33) -> 18.684798 | F27: =INDIRECT("'Rimba Jawa'!F"&F33) -> 11.758509 | G27: =INDIRECT("'Rimba Jawa'!F"&G33) -> 10.137052 | H27: =INDIRECT("'Rimba Jawa'!F"&H33) -> 6.1362442 | I27: =INDIRECT("'Rimba Jawa'!F"&I33) -> 4.4287823 | J27: =INDIRECT("'Rimba Jawa'!F"&J33) -> 2.6373735 | ... R27: =INDIRECT("'Rimba Jawa'!F"&R33) -> 7.0698959
A28: 4. Revaluasi | C28: =INDIRECT("'Rimba Jawa'!G"&C33) -> 34320.643 | D28: =INDIRECT("'Rimba Jawa'!G"&D33) -> -327447.29 | E28: =INDIRECT("'Rimba Jawa'!G"&E33) -> -64404.575 | F28: =INDIRECT("'Rimba Jawa'!G"&F33) -> -5262.3969 | G28: =INDIRECT("'Rimba Jawa'!G"&G33) -> -1312.1886 | H28: =INDIRECT("'Rimba Jawa'!G"&H33) -> -2806.0106 | I28: =INDIRECT("'Rimba Jawa'!G"&I33) -> -1031.5146 | J28: =INDIRECT("'Rimba Jawa'!G"&J33) -> -1118.9022 | ... R28: =INDIRECT("'Rimba Jawa'!G"&R33) -> -1370.1405
A29: 5. Persediaan akhir | C29: =C21+C22-C25+C28 -> 402773.07 | D29: =D21+D22-D25+D28 -> 78445.539 | E29: =E21+E22-E25+E28 -> 14587.809 | F29: =F21+F22-F25+F28 -> 9679.9898 | G29: =G21+G22-G25+G28 -> 8929.8894 | H29: =H21+H22-H25+H28 -> 6353.4534 | I29: =I21+I22-I25+I28 -> 5513.4571 | J29: =J21+J22-J25+J28 -> 4483.5833 | ... R29: =R21+R22-R25+R28 -> 10094.041
D30: =D29-INDIRECT("'Rimba Jawa'!H"&D33) -> 0 | E30: =E29-INDIRECT("'Rimba Jawa'!H"&E33) -> 0 | F30: =F29-INDIRECT("'Rimba Jawa'!H"&F33) -> 0 | G30: =G29-INDIRECT("'Rimba Jawa'!H"&G33) -> 0 | H30: =H29-INDIRECT("'Rimba Jawa'!H"&H33) -> 1.0004442e-11 | I30: =I29-INDIRECT("'Rimba Jawa'!H"&I33) -> 1.0004442e-11 | J30: =J29-INDIRECT("'Rimba Jawa'!H"&J33) -> 1.0004442e-11 | K30: =K29-INDIRECT("'Rimba Jawa'!H"&K33) -> 1.0004442e-11 | ... R30: =R29-INDIRECT("'Rimba Jawa'!H"&R33) -> 0
A32: nomor baris neraca fisik | B32: 4 | C32: =B32+1 -> 5 | D32: =C32+1 -> 6 | E32: =D32+1 -> 7 | F32: =E32+1 -> 8 | G32: =F32+1 -> 9 | H32: =G32+1 -> 10 | I32: =H32+1 -> 11 | J32: =I32+1 -> 12 | ... R32: =Q32+1 -> 20
A33: nomor baris neraca moneter | C33: 46 | D33: =C33+1 -> 47 | E33: =D33+1 -> 48 | F33: =E33+1 -> 49 | G33: =F33+1 -> 50 | H33: =G33+1 -> 51 | I33: =H33+1 -> 52 | J33: =I33+1 -> 53 | K33: =J33+1 -> 54 | ... R33: =Q33+1 -> 61

Sheet Rekap RLJ
A1: Neraca Fisik dan Moneter
A2: Sumber Daya Hutan Rimba Luar Jawa
A4: Perincian | B4: 2008 | C4: 2009 | D4: 2010 | E4: 2011 | F4: 2012 | G4: 2013 | H4: 2014 | I4: 2015 | J4: 2016 | K4: 2017 | L4: 2018 | M4: 2019 | N4: 2020 | O4: 2021 | P4: 2022 | Q4: 2023 | R4: 2024
A6: I. Neraca Fisik (000 M3)
A8: 1. Persediaan awal | B8: ='Rimba Luar Jawa'!B4 -> 6500648.8 | C8: =B15 -> 6282105.2 | D8: =C15 -> 6039224.3 | E8: =D15 -> 5770970.1 | F8: =E15 -> 5478994.8 | G8: =F15 -> 5132541.5 | H8: =G15 -> 5036128.5 | I8: =H15 -> 4833123.5 | J8: =I15 -> 4216415 | ... R8: =Q15 -> 2815937.8
A9: 2. Penambahan | B9: =SUM(B10:B11) -> 36722.857 | C9: =SUM(C10:C11) -> 35477.997 | D9: =SUM(D10:D11) -> 33870.284 | E9: =SUM(E10:E11) -> 34466.867 | F9: =SUM(F10:F11) -> 35619.121 | G9: =SUM(G10:G11) -> 33477.313 | H9: =SUM(H10:H11) -> 34411.298 | I9: =SUM(I10:I11) -> 38963.628 | ... R9: =SUM(R10:R11) -> 30996.618
A10: Pertumbuhan | B10: =INDIRECT("'Rimba Luar Jawa'!C"&B32) -> 28768.843 | C10: =INDIRECT("'Rimba Luar Jawa'!C"&C32) -> 29427.551 | D10: =INDIRECT("'Rimba Luar Jawa'!C"&D32) -> 29417.615 | E10: =INDIRECT("'Rimba Luar Jawa'!C"&E32) -> 29641.821 | F10: =INDIRECT("'Rimba Luar Jawa'!C"&F32) -> 29470.768 | G10: =INDIRECT("'Rimba Luar Jawa'!C"&G32) -> 22422.401 | H10: =INDIRECT("'Rimba Luar Jawa'!C"&H32) -> 23276.945 | I10: =INDIRECT("'Rimba Luar Jawa'!C"&I32) -> 23334.934 | ... R10: =INDIRECT("'Rimba Luar Jawa'!C"&R32) -> 23297.342
A11: Penanaman | B11: =INDIRECT("'Rimba Luar Jawa'!D"&B32) -> 7954.0144 | C11: =INDIRECT("'Rimba Luar Jawa'!D"&C32) -> 6050.4458 | D11: =INDIRECT("'Rimba Luar Jawa'!D"&D32) -> 4452.6684 | E11: =INDIRECT("'Rimba Luar Jawa'!D"&E32) -> 4825.0458 | F11: =INDIRECT("'Rimba Luar Jawa'!D"&F32) -> 6148.3529 | G11: =INDIRECT("'Rimba Luar Jawa'!D"&G32) -> 11054.912 | H11: =INDIRECT("'Rimba Luar Jawa'!D"&H32) -> 11134.353 | I11: =INDIRECT("'Rimba Luar Jawa'!D"&I32) -> 15628.694 | ... R11: =INDIRECT("'Rimba Luar Jawa'!D"&R32) -> 7699.2765
A12: 3.Pengurangan | B12: =SUM(B13:B14) -> 255266.44 | C12: =SUM(C13:C14) -> 278358.92 | D12: =SUM(D13:D14) -> 302124.55 | E12: =SUM(E13:E14) -> 326442.07 | F12: =SUM(F13:F14) -> 382072.47 | G12: =SUM(G13:G14) -> 129890.32 | H12: =SUM(H13:H14) -> 237416.3 | I12: =SUM(I13:I14) -> 655672.14 | ... R12: =SUM(R13:R14) -> 149521.21
A13: Kerusakan | B13: =INDIRECT("'Rimba Luar Jawa'!E"&B32) -> 206743.81 | C13: =INDIRECT("'Rimba Luar Jawa'!E"&C32) -> 227447.89 | D13: =INDIRECT("'Rimba Luar Jawa'!E"&D32) -> 248573.61 | E13: =INDIRECT("'Rimba Luar Jawa'!E"&E32) -> 276481.4 | F13: =INDIRECT("'Rimba Luar Jawa'!E"&F32) -> 333058.25 | G13: =INDIRECT("'Rimba Luar Jawa'!E"&G32) -> 89854.22 | H13: =INDIRECT("'Rimba Luar Jawa'!E"&H32) -> 192303.64 | I13: =INDIRECT("'Rimba Luar Jawa'!E"&I32) -> 611062.47 | ... R13: =INDIRECT("'Rimba Luar Jawa'!E"&R32) -> 95017.524
A14: Penebangan | B14: =INDIRECT("'Rimba Luar Jawa'!F"&B32) -> 48522.631 | C14: =INDIRECT("'Rimba Luar Jawa'!F"&C32) -> 50911.031 | D14: =INDIRECT("'Rimba Luar Jawa'!F"&D32) -> 53550.936 | E14: =INDIRECT("'Rimba Luar Jawa'!F"&E32) -> 49960.669 | F14: =INDIRECT("'Rimba Luar Jawa'!F"&F32) -> 49014.219 | G14: =INDIRECT("'Rimba Luar Jawa'!F"&G32) -> 40036.102 | H14: =INDIRECT("'Rimba Luar Jawa'!F"&H32) -> 45112.663 | I14: =INDIRECT("'Rimba Luar Jawa'!F"&I32) -> 44609.668 | ... R14: =INDIRECT("'Rimba Luar Jawa'!F"&R32) -> 54503.682
A15: 4. Persediaan akhir | B15: =B8+B9-B12 -> 6282105.2 | C15: =C8+C9-C12 -> 6039224.3 | D15: =D8+D9-D12 -> 5770970.1 | E15: =E8+E9-E12 -> 5478994.8 | F15: =F8+F9-F12 -> 5132541.5 | G15: =G8+G9-G12 -> 5036128.5 | H15: =H8+H9-H12 -> 4833123.5 | I15: =I8+I9-I12 -> 4216415 | ... R15: =R8+R9-R12 -> 2697413.2
C16: =C15-INDIRECT("'Rimba Luar Jawa'!G"&C32) -> 0 | D16: =D15-INDIRECT("'Rimba Luar Jawa'!G"&D32) -> 0 | E16: =E15-INDIRECT("'Rimba Luar Jawa'!G"&E32) -> 0 | F16: =F15-INDIRECT("'Rimba Luar Jawa'!G"&F32) -> 0 | G16: =G15-INDIRECT("'Rimba Luar Jawa'!G"&G32) -> 0 | H16: =H15-INDIRECT("'Rimba Luar Jawa'!G"&H32) -> 0 | I16: =I15-INDIRECT("'Rimba Luar Jawa'!G"&I32) -> 0 | J16: =J15-INDIRECT("'Rimba Luar Jawa'!G"&J32) -> 0 | ... R16: =R15-INDIRECT("'Rimba Luar Jawa'!G"&R32) -> 0
A18: III. Neraca Moneter
A19: (Miliar Rp)
A21: 1. Persediaan awal | C21: ='Rimba Luar Jawa'!B46 -> 6022081.5 | D21: =C29 -> 6327497.1 | E21: =D29 -> 4617199.8 | F21: =E29 -> 1354056.5 | G21: =F29 -> 906965.29 | H21: =G29 -> 684327.22 | I21: =H29 -> 704923.84 | J21: =I29 -> 615856.91 | K21: =J29 -> 671554.69 | ... R21: =Q29 -> 1358302.4
A22: 2. Penambahan | C22: =SUM(C23:C24) -> 37171.483 | D22: =SUM(D23:D24) -> 27098.714 | E22: =SUM(E23:E24) -> 8518.001 | F22: =SUM(F23:F24) -> 6294.2124 | G22: =SUM(G23:G24) -> 4549.0174 | H22: =SUM(H23:H24) -> 5018.9788 | I22: =SUM(I23:I24) -> 5691.0954 | J22: =SUM(J23:J24) -> 6811.7005 | ... R22: =SUM(R23:R24) -> 14952.656
A23: Pertumbuhan | C23: =INDIRECT("'Rimba Luar Jawa'!C"&C33) -> 30832.229 | D23: =INDIRECT("'Rimba Luar Jawa'!C"&D33) -> 23536.252 | E23: =INDIRECT("'Rimba Luar Jawa'!C"&E33) -> 7325.5589 | F23: =INDIRECT("'Rimba Luar Jawa'!C"&F33) -> 5207.7442 | G23: =INDIRECT("'Rimba Luar Jawa'!C"&G33) -> 3046.8363 | H23: =INDIRECT("'Rimba Luar Jawa'!C"&H33) -> 3395.0039 | I23: =INDIRECT("'Rimba Luar Jawa'!C"&I33) -> 3408.3412 | J23: =INDIRECT("'Rimba Luar Jawa'!C"&J33) -> 3955.2703 | ... R23: =INDIRECT("'Rimba Luar Jawa'!C"&R33) -> 11238.553
A24: Penanaman | C24: =INDIRECT("'Rimba Luar Jawa'!D"&C33) -> 6339.2542 | D24: =INDIRECT("'Rimba Luar Jawa'!D"&D33) -> 3562.4617 | E24: =INDIRECT("'Rimba Luar Jawa'!D"&E33) -> 1192.4422 | F24: =INDIRECT("'Rimba Luar Jawa'!D"&F33) -> 1086.4681 | G24: =INDIRECT("'Rimba Luar Jawa'!D"&G33) -> 1502.1812 | H24: =INDIRECT("'Rimba Luar Jawa'!D"&H33) -> 1623.9749 | I24: =INDIRECT("'Rimba Luar Jawa'!D"&I33) -> 2282.7542 | J24: =INDIRECT("'Rimba Luar Jawa'!D"&J33) -> 2856.4302 | ... R24: =INDIRECT("'Rimba Luar Jawa'!D"&R33) -> 3714.103
A25: 3.Pengurangan | C25: =SUM(C26:C27) -> 291645.94 | D25: =SUM(D26:D27) -> 241721.83 | E25: =SUM(E26:E27) -> 80675.563 | F25: =SUM(F26:F27) -> 67515.57 | G25: =SUM(G26:G27) -> 17649.963 | H25: =SUM(H26:H27) -> 34627.795 | I25: =SUM(I26:I27) -> 95768.614 | J25: =SUM(J26:J27) -> 39544.972 | ... R25: =SUM(R26:R27) -> 72128.485
A26: Kerusakan | C26: =INDIRECT("'Rimba Luar Jawa'!E"&C33) -> 238304.75 | D26: =INDIRECT("'Rimba Luar Jawa'!E"&D33) -> 198877.15 | E26: =INDIRECT("'Rimba Luar Jawa'!E"&E33) -> 68328.487 | F26: =INDIRECT("'Rimba Luar Jawa'!E"&F33) -> 58854.326 | G26: =INDIRECT("'Rimba Luar Jawa'!E"&G33) -> 12209.714 | H26: =INDIRECT("'Rimba Luar Jawa'!E"&H33) -> 28047.994 | I26: =INDIRECT("'Rimba Luar Jawa'!E"&I33) -> 89252.848 | J26: =INDIRECT("'Rimba Luar Jawa'!E"&J33) -> 32085.24 | ... R26: =INDIRECT("'Rimba Luar Jawa'!E"&R33) -> 45836.107
A27: Penebangan | C27: =INDIRECT("'Rimba Luar Jawa'!F"&C33) -> 53341.189 | D27: =INDIRECT("'Rimba Luar Jawa'!F"&D33) -> 42844.681 | E27: =INDIRECT("'Rimba Luar Jawa'!F"&E33) -> 12347.076 | F27: =INDIRECT("'Rimba Luar Jawa'!F"&F33) -> 8661.2441 | G27: =INDIRECT("'Rimba Luar Jawa'!F"&G33) -> 5440.2493 | H27: =INDIRECT("'Rimba Luar Jawa'!F"&H33) -> 6579.8012 | I27: =INDIRECT("'Rimba Luar Jawa'!F"&I33) -> 6515.7658 | J27: =INDIRECT("'Rimba Luar Jawa'!F"&J33) -> 7459.7316 | ... R27: =INDIRECT("'Rimba Luar Jawa'!F"&R33) -> 26292.378
A28: 4. Revaluasi | C28: =INDIRECT("'Rimba Luar Jawa'!G"&C33) -> 559890.03 | D28: =INDIRECT("'Rimba Luar Jawa'!G"&D33) -> -1495674.2 | E28: =INDIRECT("'Rimba Luar Jawa'!G"&E33) -> -3190985.8 | F28: =INDIRECT("'Rimba Luar Jawa'!G"&F33) -> -385869.81 | G28: =INDIRECT("'Rimba Luar Jawa'!G"&G33) -> -209537.12 | H28: =INDIRECT("'Rimba Luar Jawa'!G"&H33) -> 50205.437 | I28: =INDIRECT("'Rimba Luar Jawa'!G"&I33) -> 1010.5928 | J28: =INDIRECT("'Rimba Luar Jawa'!G"&J33) -> 88431.047 | ... R28: =INDIRECT("'Rimba Luar Jawa'!G"&R33) -> 95.731758
A29: 5. Persediaan akhir | C29: =C21+C22-C25+C28 -> 6327497.1 | D29: =D21+D22-D25+D28 -> 4617199.8 | E29: =E21+E22-E25+E28 -> 1354056.5 | F29: =F21+F22-F25+F28 -> 906965.29 | G29: =G21+G22-G25+G28 -> 684327.22 | H29: =H21+H22-H25+H28 -> 704923.84 | I29: =I21+I22-I25+I28 -> 615856.91 | J29: =J21+J22-J25+J28 -> 671554.69 | ... R29: =R21+R22-R25+R28 -> 1301222.3
D30: =D29-INDIRECT("'Rimba Luar Jawa'!H"&D33) -> 0 | E30: =E29-INDIRECT("'Rimba Luar Jawa'!H"&E33) -> 0 | F30: =F29-INDIRECT("'Rimba Luar Jawa'!H"&F33) -> 0 | G30: =G29-INDIRECT("'Rimba Luar Jawa'!H"&G33) -> 0 | H30: =H29-INDIRECT("'Rimba Luar Jawa'!H"&H33) -> 0 | I30: =I29-INDIRECT("'Rimba Luar Jawa'!H"&I33) -> 0 | J30: =J29-INDIRECT("'Rimba Luar Jawa'!H"&J33) -> 0 | K30: =K29-INDIRECT("'Rimba Luar Jawa'!H"&K33) -> 0 | ... R30: =R29-INDIRECT("'Rimba Luar Jawa'!H"&R33) -> 0
A32: nomor baris neraca fisik | B32: 4 | C32: =B32+1 -> 5 | D32: =C32+1 -> 6 | E32: =D32+1 -> 7 | F32: =E32+1 -> 8 | G32: =F32+1 -> 9 | H32: =G32+1 -> 10 | I32: =H32+1 -> 11 | J32: =I32+1 -> 12 | ... R32: =Q32+1 -> 20
A33: nomor baris neraca moneter | C33: 46 | D33: =C33+1 -> 47 | E33: =D33+1 -> 48 | F33: =E33+1 -> 49 | G33: =F33+1 -> 50 | H33: =G33+1 -> 51 | I33: =H33+1 -> 52 | J33: =I33+1 -> 53 | K33: =J33+1 -> 54 | ... R33: =Q33+1 -> 61

Sheet Rekap Transpose
A1: Neraca Fisik Kayu (000 m3)
A2: Rincian | B2: Persediaan Awal | C2: Pertumbuhan | D2: Penanaman | E2: Konversi & Kerusakan | F2: Penebangan | G2: Persediaan Akhir | H2: Perkiraan Cadangan | I2: Laju Persediaan Akhir | J2: Cek Persediaan Akhir
A3: 2008 | B3: ='Jati Jawa'!B4+'Rimba Jawa'!B4+'Rimba Luar Jawa'!B4 -> 6941231.3 | C3: ='Jati Jawa'!C4+'Rimba Jawa'!C4+'Rimba Luar Jawa'!C4 -> 50170.417 | D3: ='Jati Jawa'!D4+'Rimba Jawa'!D4+'Rimba Luar Jawa'!D4 -> 8137.2246 | E3: ='Jati Jawa'!E4+'Rimba Jawa'!E4+'Rimba Luar Jawa'!E4 -> 207360.8 | F3: ='Jati Jawa'!F4+'Rimba Jawa'!F4+'Rimba Luar Jawa'!F4 -> 49605.554 | G3: ='Jati Jawa'!G4+'Rimba Jawa'!G4+'Rimba Luar Jawa'!G4 -> 6742572.6 | H3: =G3/F3 -> 135.92374 | J3: =B3+C3+D3-E3-F3-G3 -> 0
A4: 2009 | B4: ='Jati Jawa'!B5+'Rimba Jawa'!B5+'Rimba Luar Jawa'!B5 -> 6742572.6 | C4: ='Jati Jawa'!C5+'Rimba Jawa'!C5+'Rimba Luar Jawa'!C5 -> 51261.334 | D4: ='Jati Jawa'!D5+'Rimba Jawa'!D5+'Rimba Luar Jawa'!D5 -> 6148.9569 | E4: ='Jati Jawa'!E5+'Rimba Jawa'!E5+'Rimba Luar Jawa'!E5 -> 227997.26 | F4: ='Jati Jawa'!F5+'Rimba Jawa'!F5+'Rimba Luar Jawa'!F5 -> 51890.421 | G4: ='Jati Jawa'!G5+'Rimba Jawa'!G5+'Rimba Luar Jawa'!G5 -> 6520095.2 | H4: =G4/F4 -> 125.65123 | I4: =G4/G3*100-100 -> -3.2995921 | J4: =B4+C4+D4-E4-F4-G4 -> 0
A5: 2010 | B5: ='Jati Jawa'!B6+'Rimba Jawa'!B6+'Rimba Luar Jawa'!B6 -> 6520095.2 | C5: ='Jati Jawa'!C6+'Rimba Jawa'!C6+'Rimba Luar Jawa'!C6 -> 50866.651 | D5: ='Jati Jawa'!D6+'Rimba Jawa'!D6+'Rimba Luar Jawa'!D6 -> 4580.2793 | E5: ='Jati Jawa'!E6+'Rimba Jawa'!E6+'Rimba Luar Jawa'!E6 -> 249399.69 | F5: ='Jati Jawa'!F6+'Rimba Jawa'!F6+'Rimba Luar Jawa'!F6 -> 54440.397 | G5: ='Jati Jawa'!G6+'Rimba Jawa'!G6+'Rimba Luar Jawa'!G6 -> 6271702.1 | H5: =G5/F5 -> 115.20309 | I5: =G5/G4*100-100 -> -3.8096553 | J5: =B5+C5+D5-E5-F5-G5 -> 0
A6: 2011 | B6: ='Jati Jawa'!B7+'Rimba Jawa'!B7+'Rimba Luar Jawa'!B7 -> 6271702.1 | C6: ='Jati Jawa'!C7+'Rimba Jawa'!C7+'Rimba Luar Jawa'!C7 -> 51448.15 | D6: ='Jati Jawa'!D7+'Rimba Jawa'!D7+'Rimba Luar Jawa'!D7 -> 4895.5931 | E6: ='Jati Jawa'!E7+'Rimba Jawa'!E7+'Rimba Luar Jawa'!E7 -> 278383.26 | F6: ='Jati Jawa'!F7+'Rimba Jawa'!F7+'Rimba Luar Jawa'!F7 -> 50929.869 | G6: ='Jati Jawa'!G7+'Rimba Jawa'!G7+'Rimba Luar Jawa'!G7 -> 5998732.7 | H6: =G6/F6 -> 117.78418 | I6: =G6/G5*100-100 -> -4.3523973 | J6: =B6+C6+D6-E6-F6-G6 -> 0
A7: 2012 | B7: ='Jati Jawa'!B8+'Rimba Jawa'!B8+'Rimba Luar Jawa'!B8 -> 5998732.7 | C7: ='Jati Jawa'!C8+'Rimba Jawa'!C8+'Rimba Luar Jawa'!C8 -> 52887.133 | D7: ='Jati Jawa'!D8+'Rimba Jawa'!D8+'Rimba Luar Jawa'!D8 -> 6204.4544 | E7: ='Jati Jawa'!E8+'Rimba Jawa'!E8+'Rimba Luar Jawa'!E8 -> 337879.87 | F7: ='Jati Jawa'!F8+'Rimba Jawa'!F8+'Rimba Luar Jawa'!F8 -> 49943.141 | G7: ='Jati Jawa'!G8+'Rimba Jawa'!G8+'Rimba Luar Jawa'!G8 -> 5670001.2 | H7: =G7/F7 -> 113.52913 | I7: =G7/G6*100-100 -> -5.4800146 | J7: =B7+C7+D7-E7-F7-G7 -> 0
A8: 2013 | B8: ='Jati Jawa'!B9+'Rimba Jawa'!B9+'Rimba Luar Jawa'!B9 -> 5670001.2 | C8: ='Jati Jawa'!C9+'Rimba Jawa'!C9+'Rimba Luar Jawa'!C9 -> 58651.075 | D8: ='Jati Jawa'!D9+'Rimba Jawa'!D9+'Rimba Luar Jawa'!D9 -> 11106.951 | E8: ='Jati Jawa'!E9+'Rimba Jawa'!E9+'Rimba Luar Jawa'!E9 -> 92474.444 | F8: ='Jati Jawa'!F9+'Rimba Jawa'!F9+'Rimba Luar Jawa'!F9 -> 40991.687 | G8: ='Jati Jawa'!G9+'Rimba Jawa'!G9+'Rimba Luar Jawa'!G9 -> 5606293.1 | H8: =G8/F8 -> 136.76659 | I8: =G8/G7*100-100 -> -1.1235995 | J8: =B8+C8+D8-E8-F8-G8 -> 0 | K8: =G8/G7*100-100 -> -1.1235995
A9: 2014 | B9: ='Jati Jawa'!B10+'Rimba Jawa'!B10+'Rimba Luar Jawa'!B10 -> 5606293.1 | C9: ='Jati Jawa'!C10+'Rimba Jawa'!C10+'Rimba Luar Jawa'!C10 -> 46687.165 | D9: ='Jati Jawa'!D10+'Rimba Jawa'!D10+'Rimba Luar Jawa'!D10 -> 11194.956 | E9: ='Jati Jawa'!E10+'Rimba Jawa'!E10+'Rimba Luar Jawa'!E10 -> 194261.6 | F9: ='Jati Jawa'!F10+'Rimba Jawa'!F10+'Rimba Luar Jawa'!F10 -> 46031.25 | G9: ='Jati Jawa'!G10+'Rimba Jawa'!G10+'Rimba Luar Jawa'!G10 -> 5423882.4 | H9: =G9/F9 -> 117.83044 | I9: =G9/G8*100-100 -> -3.253678 | J9: =B9+C9+D9-E9-F9-G9 -> 0 | K9: =G9/G8*100-100 -> -3.253678
A10: 2015 | B10: ='Jati Jawa'!B11+'Rimba Jawa'!B11+'Rimba Luar Jawa'!B11 -> 5423882.4 | C10: ='Jati Jawa'!C11+'Rimba Jawa'!C11+'Rimba Luar Jawa'!C11 -> 46799.571 | D10: ='Jati Jawa'!D11+'Rimba Jawa'!D11+'Rimba Luar Jawa'!D11 -> 15687.856 | E10: ='Jati Jawa'!E11+'Rimba Jawa'!E11+'Rimba Luar Jawa'!E11 -> 613364.48 | F10: ='Jati Jawa'!F11+'Rimba Jawa'!F11+'Rimba Luar Jawa'!F11 -> 45400.908 | G10: ='Jati Jawa'!G11+'Rimba Jawa'!G11+'Rimba Luar Jawa'!G11 -> 4827604.5 | H10: =G10/F10 -> 106.33277 | I10: =G10/G9*100-100 -> -10.993564 | J10: =B10+C10+D10-E10-F10-G10 -> 0 | K10: =G10/G9*100-100 -> -10.993564
A11: 2016 | B11: ='Jati Jawa'!B12+'Rimba Jawa'!B12+'Rimba Luar Jawa'!B12 -> 4827604.5 | C11: ='Jati Jawa'!C12+'Rimba Jawa'!C12+'Rimba Luar Jawa'!C12 -> 39130.339 | D11: ='Jati Jawa'!D12+'Rimba Jawa'!D12+'Rimba Luar Jawa'!D12 -> 17114.782 | E11: ='Jati Jawa'!E12+'Rimba Jawa'!E12+'Rimba Luar Jawa'!E12 -> 193747.58 | F11: ='Jati Jawa'!F12+'Rimba Jawa'!F12+'Rimba Luar Jawa'!F12 -> 45208.181 | G11: ='Jati Jawa'!G12+'Rimba Jawa'!G12+'Rimba Luar Jawa'!G12 -> 4644893.8 | H11: =G11/F11 -> 102.74454 | I11: =G11/G10*100-100 -> -3.7847062 | J11: =B11+C11+D11-E11-F11-G11 -> 0 | K11: =G11/G10*100-100 -> -3.7847062
A12: 2017 | B12: ='Jati Jawa'!B13+'Rimba Jawa'!B13+'Rimba Luar Jawa'!B13 -> 4644893.8 | C12: ='Jati Jawa'!C13+'Rimba Jawa'!C13+'Rimba Luar Jawa'!C13 -> 39323.955 | D12: ='Jati Jawa'!D13+'Rimba Jawa'!D13+'Rimba Luar Jawa'!D13 -> 7358.6198 | E12: ='Jati Jawa'!E13+'Rimba Jawa'!E13+'Rimba Luar Jawa'!E13 -> 150327.39 | F12: ='Jati Jawa'!F13+'Rimba Jawa'!F13+'Rimba Luar Jawa'!F13 -> 47350.504 | G12: ='Jati Jawa'!G13+'Rimba Jawa'!G13+'Rimba Luar Jawa'!G13 -> 4493898.5 | H12: =G12/F12 -> 94.907088 | I12: =G12/G11*100-100 -> -3.2507808 | J12: =B12+C12+D12-E12-F12-G12 -> 0 | K12: =G12/G11*100-100 -> -3.2507808
A13: 2018 | B13: ='Jati Jawa'!B14+'Rimba Jawa'!B14+'Rimba Luar Jawa'!B14 -> 4493898.5 | C13: ='Jati Jawa'!C14+'Rimba Jawa'!C14+'Rimba Luar Jawa'!C14 -> 39685.752 | D13: ='Jati Jawa'!D14+'Rimba Jawa'!D14+'Rimba Luar Jawa'!D14 -> 9119.8912 | E13: ='Jati Jawa'!E14+'Rimba Jawa'!E14+'Rimba Luar Jawa'!E14 -> 129001.63 | F13: ='Jati Jawa'!F14+'Rimba Jawa'!F14+'Rimba Luar Jawa'!F14 -> 47270.063 | G13: ='Jati Jawa'!G14+'Rimba Jawa'!G14+'Rimba Luar Jawa'!G14 -> 4366432.4 | H13: =G13/F13 -> 92.372046 | I13: =G13/G12*100-100 -> -2.8364248 | J13: =B13+C13+D13-E13-F13-G13 -> 0 | K13: =G13/G12*100-100 -> -2.8364248
A14: 2019 | B14: ='Jati Jawa'!B15+'Rimba Jawa'!B15+'Rimba Luar Jawa'!B15 -> 4366432.4 | C14: ='Jati Jawa'!C15+'Rimba Jawa'!C15+'Rimba Luar Jawa'!C15 -> 39539.545 | D14: ='Jati Jawa'!D15+'Rimba Jawa'!D15+'Rimba Luar Jawa'!D15 -> 13004.311 | E14: ='Jati Jawa'!E15+'Rimba Jawa'!E15+'Rimba Luar Jawa'!E15 -> 325905.34 | F14: ='Jati Jawa'!F15+'Rimba Jawa'!F15+'Rimba Luar Jawa'!F15 -> 49365.234 | G14: ='Jati Jawa'!G15+'Rimba Jawa'!G15+'Rimba Luar Jawa'!G15 -> 4043705.7 | H14: =G14/F14 -> 81.914039 | I14: =G14/G13*100-100 -> -7.3910846 | J14: =B14+C14+D14-E14-F14-G14 -> 0 | K14: =G14/G13*100-100 -> -7.3910846
A15: 2020 | B15: ='Jati Jawa'!B16+'Rimba Jawa'!B16+'Rimba Luar Jawa'!B16 -> 4043705.7 | C15: ='Jati Jawa'!C16+'Rimba Jawa'!C16+'Rimba Luar Jawa'!C16 -> 34282.649 | D15: ='Jati Jawa'!D16+'Rimba Jawa'!D16+'Rimba Luar Jawa'!D16 -> 10760.199 | E15: ='Jati Jawa'!E16+'Rimba Jawa'!E16+'Rimba Luar Jawa'!E16 -> 68470.12 | F15: ='Jati Jawa'!F16+'Rimba Jawa'!F16+'Rimba Luar Jawa'!F16 -> 51980.746 | G15: ='Jati Jawa'!G16+'Rimba Jawa'!G16+'Rimba Luar Jawa'!G16 -> 3968297.7 | H15: =G15/F15 -> 76.341684 | I15: =G15/G14*100-100 -> -1.8648246 | J15: =B15+C15+D15-E15-F15-G15 -> 0 | K15: =G15/G14*100-100 -> -1.8648246
A16: 2021 | B16: ='Jati Jawa'!B17+'Rimba Jawa'!B17+'Rimba Luar Jawa'!B17 -> 3968297.7 | C16: ='Jati Jawa'!C17+'Rimba Jawa'!C17+'Rimba Luar Jawa'!C17 -> 34157.553 | D16: ='Jati Jawa'!D17+'Rimba Jawa'!D17+'Rimba Luar Jawa'!D17 -> 4748.4949 | E16: ='Jati Jawa'!E17+'Rimba Jawa'!E17+'Rimba Luar Jawa'!E17 -> 109629.58 | F16: ='Jati Jawa'!F17+'Rimba Jawa'!F17+'Rimba Luar Jawa'!F17 -> 54813.235 | G16: ='Jati Jawa'!G17+'Rimba Jawa'!G17+'Rimba Luar Jawa'!G17 -> 3842760.9 | H16: =G16/F16 -> 70.106443 | I16: =G16/G15*100-100 -> -3.1634916 | J16: =B16+C16+D16-E16-F16-G16 -> 0 | K16: =G16/G15*100-100 -> -3.1634916
A17: 2022 | B17: ='Jati Jawa'!B18+'Rimba Jawa'!B18+'Rimba Luar Jawa'!B18 -> 3842760.9 | C17: ='Jati Jawa'!C18+'Rimba Jawa'!C18+'Rimba Luar Jawa'!C18 -> 33987.37 | D17: ='Jati Jawa'!D18+'Rimba Jawa'!D18+'Rimba Luar Jawa'!D18 -> 6631.7194 | E17: ='Jati Jawa'!E18+'Rimba Jawa'!E18+'Rimba Luar Jawa'!E18 -> 55997.21 | F17: ='Jati Jawa'!F18+'Rimba Jawa'!F18+'Rimba Luar Jawa'!F18 -> 55055.541 | G17: ='Jati Jawa'!G18+'Rimba Jawa'!G18+'Rimba Luar Jawa'!G18 -> 3772327.3 | H17: =G17/F17 -> 68.518576 | I17: =G17/G16*100-100 -> -1.8328921 | J17: =B17+C17+D17-E17-F17-G17 -> 0 | K17: =G17/G16*100-100 -> -1.8328921
A18: 2023 | B18: ='Jati Jawa'!B19+'Rimba Jawa'!B19+'Rimba Luar Jawa'!B19 -> 3772327.3 | C18: ='Jati Jawa'!C19+'Rimba Jawa'!C19+'Rimba Luar Jawa'!C19 -> 46581.601 | D18: ='Jati Jawa'!D19+'Rimba Jawa'!D19+'Rimba Luar Jawa'!D19 -> 4360.2024 | E18: ='Jati Jawa'!E19+'Rimba Jawa'!E19+'Rimba Luar Jawa'!E19 -> 239754.96 | F18: ='Jati Jawa'!F19+'Rimba Jawa'!F19+'Rimba Luar Jawa'!F19 -> 58134.882 | G18: ='Jati Jawa'!G19+'Rimba Jawa'!G19+'Rimba Luar Jawa'!G19 -> 3525379.2 | H18: =G18/F18 -> 60.641376 | I18: =G18/G17*100-100 -> -6.5463047 | J18: =B18+C18+D18-E18-F18-G18 -> 0 | K18: =G18/G17*100-100 -> -6.5463047
A19: 2024 | B19: ='Jati Jawa'!B20+'Rimba Jawa'!B20+'Rimba Luar Jawa'!B20 -> 3525379.2 | C19: ='Jati Jawa'!C20+'Rimba Jawa'!C20+'Rimba Luar Jawa'!C20 -> 46599.387 | D19: ='Jati Jawa'!D20+'Rimba Jawa'!D20+'Rimba Luar Jawa'!D20 -> 7727.594 | E19: ='Jati Jawa'!E20+'Rimba Jawa'!E20+'Rimba Luar Jawa'!E20 -> 96304.46 | F19: ='Jati Jawa'!F20+'Rimba Jawa'!F20+'Rimba Luar Jawa'!F20 -> 55307.319 | G19: ='Jati Jawa'!G20+'Rimba Jawa'!G20+'Rimba Luar Jawa'!G20 -> 3428094.4 | H19: =G19/F19 -> 61.982654 | I19: =G19/G18*100-100 -> -2.7595555 | J19: =B19+C19+D19-E19-F19-G19 -> 0 | K19: =G19/G18*100-100 -> -2.7595555
F20: =G12/1000 -> 4493.8985 | G20: =(G12-G8)/1000 -> -1112.3946 | I20: =(G10-G9)/1000 -> -596.27796
A21: Neraca Moneter Kayu (miliar Rp) | F21: =F12/1000 -> 47.350504 | G21: =G12/G8*100-100 -> -19.841892
A22: Rincian | B22: Persediaan Awal | C22: Pertumbuhan | D22: Penanaman | E22: Konversi & Kerusakan | F22: Penebangan | G22: Revaluasi | H22: Stok Akhir
A23: 2009 | B23: ='Jati Jawa'!B47+'Rimba Jawa'!B46+'Rimba Luar Jawa'!B46 -> 6465702.8 | C23: ='Jati Jawa'!C47+'Rimba Jawa'!C46+'Rimba Luar Jawa'!C46 -> 53904.98 | D23: ='Jati Jawa'!D47+'Rimba Jawa'!D46+'Rimba Luar Jawa'!D46 -> 6443.2381 | E23: ='Jati Jawa'!E47+'Rimba Jawa'!E46+'Rimba Luar Jawa'!E46 -> 238894.12 | F23: ='Jati Jawa'!F47+'Rimba Jawa'!F46+'Rimba Luar Jawa'!F46 -> 54388.444 | G23: ='Jati Jawa'!G47+'Rimba Jawa'!G46+'Rimba Luar Jawa'!G46 -> 602426.75 | H23: ='Jati Jawa'!H47+'Rimba Jawa'!H46+'Rimba Luar Jawa'!H46 -> 6835195.2
A24: 2010 | B24: ='Jati Jawa'!B48+'Rimba Jawa'!B47+'Rimba Luar Jawa'!B47 -> 6835195.2 | C24: ='Jati Jawa'!C48+'Rimba Jawa'!C47+'Rimba Luar Jawa'!C47 -> 29763.587 | D24: ='Jati Jawa'!D48+'Rimba Jawa'!D47+'Rimba Luar Jawa'!D47 -> 3595.6356 | E24: ='Jati Jawa'!E48+'Rimba Jawa'!E47+'Rimba Luar Jawa'!E47 -> 199226.17 | F24: ='Jati Jawa'!F48+'Rimba Jawa'!F47+'Rimba Luar Jawa'!F47 -> 43210.017 | G24: ='Jati Jawa'!G48+'Rimba Jawa'!G47+'Rimba Luar Jawa'!G47 -> -1868636.5 | H24: ='Jati Jawa'!H48+'Rimba Jawa'!H47+'Rimba Luar Jawa'!H47 -> 4757481.7
A25: 2011 | B25: ='Jati Jawa'!B49+'Rimba Jawa'!B48+'Rimba Luar Jawa'!B48 -> 4757481.7 | C25: ='Jati Jawa'!C49+'Rimba Jawa'!C48+'Rimba Luar Jawa'!C48 -> 8498.601 | D25: ='Jati Jawa'!D49+'Rimba Jawa'!D48+'Rimba Luar Jawa'!D48 -> 1197.4593 | E25: ='Jati Jawa'!E49+'Rimba Jawa'!E48+'Rimba Luar Jawa'!E48 -> 68481.629 | F25: ='Jati Jawa'!F49+'Rimba Jawa'!F48+'Rimba Luar Jawa'!F48 -> 12418.141 | G25: ='Jati Jawa'!G49+'Rimba Jawa'!G48+'Rimba Luar Jawa'!G48 -> -3305244.6 | H25: ='Jati Jawa'!H49+'Rimba Jawa'!H48+'Rimba Luar Jawa'!H48 -> 1381033.5
A26: 2012 | B26: ='Jati Jawa'!B50+'Rimba Jawa'!B49+'Rimba Luar Jawa'!B49 -> 1381033.5 | C26: ='Jati Jawa'!C50+'Rimba Jawa'!C49+'Rimba Luar Jawa'!C49 -> 5979.9178 | D26: ='Jati Jawa'!D50+'Rimba Jawa'!D49+'Rimba Luar Jawa'!D49 -> 1088.9846 | E26: ='Jati Jawa'!E50+'Rimba Jawa'!E49+'Rimba Luar Jawa'!E49 -> 59094.5 | F26: ='Jati Jawa'!F50+'Rimba Jawa'!F49+'Rimba Luar Jawa'!F49 -> 8702.7714 | G26: ='Jati Jawa'!G50+'Rimba Jawa'!G49+'Rimba Luar Jawa'!G49 -> -395922.36 | H26: ='Jati Jawa'!H50+'Rimba Jawa'!H49+'Rimba Luar Jawa'!H49 -> 924382.72 | K26: =B26+C26+D26-E26-F26+G26-H26 -> 0
A27: 2013 | B27: ='Jati Jawa'!B51+'Rimba Jawa'!B50+'Rimba Luar Jawa'!B50 -> 924382.72 | C27: ='Jati Jawa'!C51+'Rimba Jawa'!C50+'Rimba Luar Jawa'!C50 -> 4064.8881 | D27: ='Jati Jawa'!D51+'Rimba Jawa'!D50+'Rimba Luar Jawa'!D50 -> 1504.1311 | E27: ='Jati Jawa'!E51+'Rimba Jawa'!E50+'Rimba Luar Jawa'!E50 -> 12341.657 | F27: ='Jati Jawa'!F51+'Rimba Jawa'!F50+'Rimba Luar Jawa'!F50 -> 5483.811 | G27: ='Jati Jawa'!G51+'Rimba Jawa'!G50+'Rimba Luar Jawa'!G50 -> -210464.51 | H27: ='Jati Jawa'!H51+'Rimba Jawa'!H50+'Rimba Luar Jawa'!H50 -> 701661.76 | K27: =B27+C27+D27-E27-F27+G27-H27 -> 0
A28: 2014 | B28: ='Jati Jawa'!B52+'Rimba Jawa'!B51+'Rimba Luar Jawa'!B51 -> 701661.76 | C28: ='Jati Jawa'!C52+'Rimba Jawa'!C51+'Rimba Luar Jawa'!C51 -> 4013.4808 | D28: ='Jati Jawa'!D52+'Rimba Jawa'!D51+'Rimba Luar Jawa'!D51 -> 1626.2872 | E28: ='Jati Jawa'!E52+'Rimba Jawa'!E51+'Rimba Luar Jawa'!E51 -> 28141.491 | F28: ='Jati Jawa'!F52+'Rimba Jawa'!F51+'Rimba Luar Jawa'!F51 -> 6621.4561 | G28: ='Jati Jawa'!G52+'Rimba Jawa'!G51+'Rimba Luar Jawa'!G51 -> 47446.501 | H28: ='Jati Jawa'!H52+'Rimba Jawa'!H51+'Rimba Luar Jawa'!H51 -> 719985.09 | J28: =H28/H27*100-100 -> 2.611418 | K28: =B28+C28+D28-E28-F28+G28-H28 -> 0
A29: 2015 | B29: ='Jati Jawa'!B53+'Rimba Jawa'!B52+'Rimba Luar Jawa'!B52 -> 719985.09 | C29: ='Jati Jawa'!C53+'Rimba Jawa'!C52+'Rimba Luar Jawa'!C52 -> 3927.0238 | D29: ='Jati Jawa'!D53+'Rimba Jawa'!D52+'Rimba Luar Jawa'!D52 -> 2284.5052 | E29: ='Jati Jawa'!E53+'Rimba Jawa'!E52+'Rimba Luar Jawa'!E52 -> 89344.514 | F29: ='Jati Jawa'!F53+'Rimba Jawa'!F52+'Rimba Luar Jawa'!F52 -> 6545.6817 | G29: ='Jati Jawa'!G53+'Rimba Jawa'!G52+'Rimba Luar Jawa'!G52 -> -1472.309 | H29: ='Jati Jawa'!H53+'Rimba Jawa'!H52+'Rimba Luar Jawa'!H52 -> 628834.11 | J29: =H29/H28*100-100 -> -12.66012 | K29: =B29+C29+D29-E29-F29+G29-H29 -> 0
A30: 2016 | B30: ='Jati Jawa'!B54+'Rimba Jawa'!B53+'Rimba Luar Jawa'!B53 -> 628834.11 | C30: ='Jati Jawa'!C54+'Rimba Jawa'!C53+'Rimba Luar Jawa'!C53 -> 4254.0726 | D30: ='Jati Jawa'!D54+'Rimba Jawa'!D53+'Rimba Luar Jawa'!D53 -> 2856.7213 | E30: ='Jati Jawa'!E54+'Rimba Jawa'!E53+'Rimba Luar Jawa'!E53 -> 32133.043 | F30: ='Jati Jawa'!F54+'Rimba Jawa'!F53+'Rimba Luar Jawa'!F53 -> 7473.951 | G30: ='Jati Jawa'!G54+'Rimba Jawa'!G53+'Rimba Luar Jawa'!G53 -> 85161.98 | H30: ='Jati Jawa'!H54+'Rimba Jawa'!H53+'Rimba Luar Jawa'!H53 -> 681499.89 | J30: =H30/H29*100-100 -> 8.3751469 | K30: =B30+C30+D30-E30-F30+G30-H30 -> 0
A31: 2017 | B31: ='Jati Jawa'!B55+'Rimba Jawa'!B54+'Rimba Luar Jawa'!B54 -> 681499.89 | C31: ='Jati Jawa'!C55+'Rimba Jawa'!C54+'Rimba Luar Jawa'!C54 -> 4901.6472 | D31: ='Jati Jawa'!D55+'Rimba Jawa'!D54+'Rimba Luar Jawa'!D54 -> 1401.2454 | E31: ='Jati Jawa'!E55+'Rimba Jawa'!E54+'Rimba Luar Jawa'!E54 -> 28424.101 | F31: ='Jati Jawa'!F55+'Rimba Jawa'!F54+'Rimba Luar Jawa'!F54 -> 8951.9533 | G31: ='Jati Jawa'!G55+'Rimba Jawa'!G54+'Rimba Luar Jawa'!G54 -> 99106.76 | H31: ='Jati Jawa'!H55+'Rimba Jawa'!H54+'Rimba Luar Jawa'!H54 -> 749533.49 | I31: =H31/H27*100-100 -> 6.8226213 | J31: =H31/H30*100-100 -> 9.9829215 | K31: =B31+C31+D31-E31-F31+G31-H31 -> 0
A32: 2018 | B32: ='Jati Jawa'!B56+'Rimba Jawa'!B55+'Rimba Luar Jawa'!B55 -> 749533.49 | C32: ='Jati Jawa'!C56+'Rimba Jawa'!C55+'Rimba Luar Jawa'!C55 -> 5087.0422 | D32: ='Jati Jawa'!D56+'Rimba Jawa'!D55+'Rimba Luar Jawa'!D55 -> 1773.0106 | E32: ='Jati Jawa'!E56+'Rimba Jawa'!E55+'Rimba Luar Jawa'!E55 -> 24829.202 | F32: ='Jati Jawa'!F56+'Rimba Jawa'!F55+'Rimba Luar Jawa'!F55 -> 9094.5459 | G32: ='Jati Jawa'!G56+'Rimba Jawa'!G55+'Rimba Luar Jawa'!G55 -> 17814.209 | H32: ='Jati Jawa'!H56+'Rimba Jawa'!H55+'Rimba Luar Jawa'!H55 -> 740284 | I32: =H32/H28*100-100 -> 2.8193525 | J32: =H32/H31*100-100 -> -1.2340324 | K32: =B32+C32+D32-E32-F32+G32-H32 -> 0
A33: 2019 | B33: ='Jati Jawa'!B57+'Rimba Jawa'!B56+'Rimba Luar Jawa'!B56 -> 740284 | C33: ='Jati Jawa'!C57+'Rimba Jawa'!C56+'Rimba Luar Jawa'!C56 -> 6109.567 | D33: ='Jati Jawa'!D57+'Rimba Jawa'!D56+'Rimba Luar Jawa'!D56 -> 3075.1912 | E33: ='Jati Jawa'!E57+'Rimba Jawa'!E56+'Rimba Luar Jawa'!E56 -> 76926.656 | F33: ='Jati Jawa'!F57+'Rimba Jawa'!F56+'Rimba Luar Jawa'!F56 -> 11560.738 | G33: ='Jati Jawa'!G57+'Rimba Jawa'!G56+'Rimba Luar Jawa'!G56 -> 157217.01 | H33: ='Jati Jawa'!H57+'Rimba Jawa'!H56+'Rimba Luar Jawa'!H56 -> 818198.38 | I33: =H33/H29*100-100 -> 30.113549 | J33: =H33/H32*100-100 -> 10.52493 | K33: =B33+C33+D33-E33-F33+G33-H33 -> 0
A34: 2020 | B34: ='Jati Jawa'!B58+'Rimba Jawa'!B57+'Rimba Luar Jawa'!B57 -> 818198.38 | C34: ='Jati Jawa'!C58+'Rimba Jawa'!C57+'Rimba Luar Jawa'!C57 -> 7281.4543 | D34: ='Jati Jawa'!D58+'Rimba Jawa'!D57+'Rimba Luar Jawa'!D57 -> 3032.543 | E34: ='Jati Jawa'!E58+'Rimba Jawa'!E57+'Rimba Luar Jawa'!E57 -> 19002.634 | F34: ='Jati Jawa'!F58+'Rimba Jawa'!F57+'Rimba Luar Jawa'!F57 -> 14524.238 | G34: ='Jati Jawa'!G58+'Rimba Jawa'!G57+'Rimba Luar Jawa'!G57 -> 157930.02 | H34: ='Jati Jawa'!H58+'Rimba Jawa'!H57+'Rimba Luar Jawa'!H57 -> 952915.52 | I34: =H34/H30*100-100 -> 39.826217 | J34: =H34/H33*100-100 -> 16.465095 | K34: =B34+C34+D34-E34-F34+G34-H34 -> 0
A35: 2021 | B35: ='Jati Jawa'!B59+'Rimba Jawa'!B58+'Rimba Luar Jawa'!B58 -> 952915.52 | C35: ='Jati Jawa'!C59+'Rimba Jawa'!C58+'Rimba Luar Jawa'!C58 -> 8648.7655 | D35: ='Jati Jawa'!D59+'Rimba Jawa'!D58+'Rimba Luar Jawa'!D58 -> 1586.855 | E35: ='Jati Jawa'!E59+'Rimba Jawa'!E58+'Rimba Luar Jawa'!E58 -> 36818.486 | F35: ='Jati Jawa'!F59+'Rimba Jawa'!F58+'Rimba Luar Jawa'!F58 -> 18268.671 | G35: ='Jati Jawa'!G59+'Rimba Jawa'!G58+'Rimba Luar Jawa'!G58 -> 185909.56 | H35: ='Jati Jawa'!H59+'Rimba Jawa'!H58+'Rimba Luar Jawa'!H58 -> 1093973.5 | I35: =H35/H31*100-100 -> 45.953925 | J35: =H35/H34*100-100 -> 14.802784 | K35: =B35+C35+D35-E35-F35+G35-H35 -> 0
A36: 2022 | B36: ='Jati Jawa'!B60+'Rimba Jawa'!B59+'Rimba Luar Jawa'!B59 -> 1093973.5 | C36: ='Jati Jawa'!C60+'Rimba Jawa'!C59+'Rimba Luar Jawa'!C59 -> 9402.4752 | D36: ='Jati Jawa'!D60+'Rimba Jawa'!D59+'Rimba Luar Jawa'!D59 -> 2447.6811 | E36: ='Jati Jawa'!E60+'Rimba Jawa'!E59+'Rimba Luar Jawa'!E59 -> 20409.484 | F36: ='Jati Jawa'!F60+'Rimba Jawa'!F59+'Rimba Luar Jawa'!F59 -> 20145.685 | G36: ='Jati Jawa'!G60+'Rimba Jawa'!G59+'Rimba Luar Jawa'!G59 -> 102581.11 | H36: ='Jati Jawa'!H60+'Rimba Jawa'!H59+'Rimba Luar Jawa'!H59 -> 1167849.6 | I36: =H36/H32*100-100 -> 57.756974 | J36: =H36/H35*100-100 -> 6.7530059 | K36: =B36+C36+D36-E36-F36+G36-H36 -> 0
A37: 2023 | B37: ='Jati Jawa'!B61+'Rimba Jawa'!B60+'Rimba Luar Jawa'!B60 -> 1167849.6 | C37: ='Jati Jawa'!C61+'Rimba Jawa'!C60+'Rimba Luar Jawa'!C60 -> 12123.111 | D37: ='Jati Jawa'!D61+'Rimba Jawa'!D60+'Rimba Luar Jawa'!D60 -> 2087.1019 | E37: ='Jati Jawa'!E61+'Rimba Jawa'!E60+'Rimba Luar Jawa'!E60 -> 114961.57 | F37: ='Jati Jawa'!F61+'Rimba Jawa'!F60+'Rimba Luar Jawa'!F60 -> 27656.598 | G37: ='Jati Jawa'!G61+'Rimba Jawa'!G60+'Rimba Luar Jawa'!G60 -> 344785.75 | H37: ='Jati Jawa'!H61+'Rimba Jawa'!H60+'Rimba Luar Jawa'!H60 -> 1384227.4 | I37: =H37/H33*100-100 -> 69.179929 | J37: =H37/H36*100-100 -> 18.527881 | K37: =B37+C37+D37-E37-F37+G37-H37 -> 0
A38: 2024 | B38: ='Jati Jawa'!B62+'Rimba Jawa'!B61+'Rimba Luar Jawa'!B61 -> 1384227.4 | C38: ='Jati Jawa'!C62+'Rimba Jawa'!C61+'Rimba Luar Jawa'!C61 -> 11987.894 | D38: ='Jati Jawa'!D62+'Rimba Jawa'!D61+'Rimba Luar Jawa'!D61 -> 3715.5482 | E38: ='Jati Jawa'!E62+'Rimba Jawa'!E61+'Rimba Luar Jawa'!E61 -> 45904.98 | F38: ='Jati Jawa'!F62+'Rimba Jawa'!F61+'Rimba Luar Jawa'!F61 -> 26333.124 | G38: ='Jati Jawa'!G62+'Rimba Jawa'!G61+'Rimba Luar Jawa'!G61 -> -3776.6979 | H38: ='Jati Jawa'!H62+'Rimba Jawa'!H61+'Rimba Luar Jawa'!H61 -> 1323916.1 | I38: =H38/H34*100-100 -> 38.933205 | J38: =H38/H37*100-100 -> -4.3570412 | K38: =B38+C38+D38-E38-F38+G38-H38 -> 0
H39: =H31/1000 -> 749.53349
H40: =H24-B25 -> 0
H41: =H25-B26 -> 0
H42: =H26-B27 -> 0
H43: =H27-B28 -> 0
H44: =H28-B29 -> 0

Sheet Jati Jawa
A1: Tabel 1. Neraca Fisik Jati Jawa (000m3)
C2: growth | D2: planting | E2: losses | F2: harvesting
A3: Rincian | B3: Persediaan Awal | C3: Pertumbuhan | D3: Penanaman | E3: Konversi & Kerusakan | F3: Penebangan | G3: Persediaan Akhir | H3: Perkiraan Cadangan | I3: Laju Persediaan Akhir | J3: Cek Persediaan Akhir
A4: 2008 | B4: ='[1]Jati Jawa'!$T$8 -> 87707.889 | C4: ='[1]Jati Jawa'!$T$9 -> 4732.2962 | D4: ='[1]Jati Jawa'!$T$10 -> 32.016 | E4: ='[1]Jati Jawa'!$T$11 -> 329.24483 | F4: ='[1]Jati Jawa'!$T$12 -> 477.71 | G4: ='[1]Jati Jawa'!$T$14 -> 91665.246 | H4: =G4/F4 -> 191.88471 | J4: =B4+C4+D4-E4-F4-G4 -> 0
A5: 2009 | B5: ='[1]Jati Jawa'!$U$8 -> 91665.246 | C5: ='[1]Jati Jawa'!$U$9 -> 4755.9577 | D5: ='[1]Jati Jawa'!$U$10 -> 19.15 | E5: ='[1]Jati Jawa'!$U$11 -> 293.16735 | F5: ='[1]Jati Jawa'!$U$12 -> 455.2 | G5: ='[1]Jati Jawa'!$U$14 -> 95691.987 | H5: =G5/F5 -> 210.21965 | I5: =G5/G4*100-100 -> 4.3928757 | J5: =B5+C5+D5-E5-F5-G5 -> 0
A6: 2010 | B6: ='[1]Jati Jawa'!$V$8 -> 95691.987 | C6: ='[1]Jati Jawa'!$V$9 -> 4779.736 | D6: ='[1]Jati Jawa'!$V$10 -> 19.324 | E6: ='[1]Jati Jawa'!$V$11 -> 440.82049 | F6: ='[1]Jati Jawa'!$V$12 -> 450.032 | G6: ='[1]Jati Jawa'!$V$14 -> 99600.194 | H6: =G6/F6 -> 221.31803 | I6: =G6/G5*100-100 -> 4.0841534 | J6: =B6+C6+D6-E6-F6-G6 -> 0
A7: 2011 | B7: ='[1]Jati Jawa'!$W$8 -> 99600.194 | C7: ='[1]Jati Jawa'!$W$9 -> 4803.6347 | D7: ='[1]Jati Jawa'!$W$10 -> 29.868 | E7: ='[1]Jati Jawa'!$W$11 -> 1014.8983 | F7: ='[1]Jati Jawa'!$W$12 -> 435.4 | G7: ='[1]Jati Jawa'!$W$14 -> 102983.4 | H7: =G7/F7 -> 236.52595 | I7: =G7/G6*100-100 -> 3.3967849 | J7: =B7+C7+D7-E7-F7-G7 -> 0
A8: 2012 | B8: ='[1]Jati Jawa'!$X$8 -> 102983.4 | C8: ='[1]Jati Jawa'!$X$9 -> 4827.6543 | D8: ='[1]Jati Jawa'!$X$10 -> 24.529 | E8: ='[1]Jati Jawa'!$X$11 -> 2572.9828 | F8: ='[1]Jati Jawa'!$X$12 -> 403.432 | G8: ='[1]Jati Jawa'!$X$14 -> 104859.17 | H8: =G8/F8 -> 259.91782 | I8: =G8/G7*100-100 -> 1.8214281 | J8: =B8+C8+D8-E8-F8-G8 -> 0
A9: 2013 | B9: ='[1]Jati Jawa'!$Y$8 -> 104859.17 | C9: ='[1]Jati Jawa'!$Y$9 -> 5459.4625 | D9: ='[1]Jati Jawa'!$Y$10 -> 16.23275 | E9: ='[1]Jati Jawa'!$Y$11 -> 1398.2411 | F9: ='[1]Jati Jawa'!$Y$12 -> 431.5166 | G9: ='[1]Jati Jawa'!$Y$14 -> 108505.1 | H9: =G9/F9 -> 251.45059 | I9: =G9/G8*100-100 -> 3.4769851 | J9: =B9+C9+D9-E9-F9-G9 -> 0
A10: 2014 | B10: =G9 -> 108505.1 | C10: 4764.8739 | D10: 23.34 | E10: 1044.8336 | F10: 455.99528 | G10: =B10+C10+D10-E10-F10 -> 111792.49 | H10: =G10/F10 -> 245.16151 | I10: =G10/G9*100-100 -> 3.0297055 | J10: =B10+C10+D10-E10-F10-G10 -> 0
A11: 2015 | B11: =G10 -> 111792.49 | C11: 4794.9495 | D11: 20.32837 | E11: 1228.4299 | F11: 392.65651 | G11: =B11+C11+D11-E11-F11 -> 114986.68 | H11: =G11/F11 -> 292.84292 | I11: =G11/G10*100-100 -> 2.8572505 | J11: =B11+C11+D11-E11-F11-G11 -> 0
A12: 2016 | B12: =G11 -> 114986.68 | C12: 4335.8832 | D12: 4.48 | E12: 886.0488 | F12: 250.638 | G12: =B12+C12+D12-E12-F12 -> 118190.36 | H12: =G12/F12 -> 471.55801 | I12: =G12/G11*100-100 -> 2.7861282 | J12: =B12+C12+D12-E12-F12-G12 -> 0
A13: 2017 | B13: =G12 -> 118190.36 | C13: 4331.5373 | D13: 7.26136 | E13: 1082.9537 | F13: 306.21708 | G13: =B13+C13+D13-E13-F13 -> 121139.99 | H13: =G13/F13 -> 395.60167 | I13: =G13/G12*100-100 -> 2.4956586 | J13: =B13+C13+D13-E13-F13-G13 -> 0
A14: 2018 | B14: =G13 -> 121139.99 | C14: 4306.2242 | D14: 15.307 | E14: 1163.8354 | F14: 400.112 | G14: =B14+C14+D14-E14-F14 -> 123897.57 | H14: =G14/F14 -> 309.65722 | I14: =G14/G13*100-100 -> 2.2763613 | J14: =B14+C14+D14-E14-F14-G14 -> 0
A15: 2019 | B15: =G14 -> 123897.57 | C15: 4330.231 | D15: 17.87 | E15: 1071.884 | F15: 406.076 | G15: =B15+C15+D15-E15-F15 -> 126767.71 | H15: =G15/F15 -> 312.1773 | I15: =G15/G14*100-100 -> 2.3165434 | J15: =B15+C15+D15-E15-F15-G15 -> 0
A16: 2020 | B16: =G15 -> 126767.71 | C16: 5581.2446 | D16: 16.851 | E16: 900.3891 | F16: 432.8173 | G16: =B16+C16+D16-E16-F16 -> 131032.6 | H16: =G16/F16 -> 302.74344 | I16: =G16/G15*100-100 -> 3.3643341 | J16: =B16+C16+D16-E16-F16-G16 -> 0
A17: 2021 | B17: =G16 -> 131032.6 | C17: 5609.155 | D17: 21.844 | E17: 516.34271 | F17: 494.76 | G17: =B17+C17+D17-E17-F17 -> 135652.5 | H17: =G17/F17 -> 274.17838 | I17: =G17/G16*100-100 -> 3.525761 | J17: =B17+C17+D17-E17-F17-G17 -> 0
A18: 2022 | B18: =G17 -> 135652.5 | C18: 5674.1047 | D18: 13.021 | E18: 641.39338 | F18: 500.476 | G18: =B18+C18+D18-E18-F18 -> 140197.75 | H18: =G18/F18 -> 280.12882 | I18: =G18/G17*100-100 -> 3.3506618 | J18: =B18+C18+D18-E18-F18-G18 -> 0
A19: 2023 | B19: =G18 -> 140197.75 | C19: 5071.3775 | D19: 16.859 | E19: 876.37468 | F19: 462.955 | G19: =B19+C19+D19-E19-F19 -> 143946.66 | H19: =G19/F19 -> 310.93013 | I19: =G19/G18*100-100 -> 2.6740135 | J19: =B19+C19+D19-E19-F19-G19 -> 0
A20: 2024 | B20: =G19 -> 143946.66 | C20: 5096.753 | D20: 14.076 | E20: 686.75276 | F20: 395.508 | G20: =B20+C20+D20-E20-F20 -> 147975.23 | H20: =G20/F20 -> 374.13966 | I20: =G20/G19*100-100 -> 2.7986536 | J20: =B20+C20+D20-E20-F20-G20 -> 0
G21: =(G13-G9)/1000 -> 12.634881 | I21: =((G9-G8)/1000 ) -> 3.6459376
A22: Note: data fisik lihat file LK Neraca Fisik & moneter hutan dengan metode harga netto | G22: =G13/G9*100-100 -> 11.644504
A24: Tabel 2. Penghitungan NPV | H24: Unit Rent
A25: Tahun | B25: Discount Rate | C25: GOS per unit (Rp/m3) | D25: Resource rent (miliar Rp) | E25: Umur cadangan | F25: Discount Factor | G25: NPV (miliar Rp) | H25: NPV per stok akhir (Rp/m3)
A27: 2008 | B27: ='Rate of Return'!L7 -> 0 | C27: ='GOS per unit'!E3 -> 1006855.8 | D27: =C27*F4/1000000 -> 480.98508 | E27: =H4 -> 191.88471 | F27: =(PV(B27,E27,-1/E27)) -> 1 | G27: =D27*E27*F27 -> 92293.685 | H27: =G27/G4*1000000 -> 1006855.8
A28: 2009 | B28: ='Rate of Return'!L8 -> 0 | C28: ='GOS per unit'!E4 -> 1096487.2 | D28: =C28*F5/1000000 -> 499.12098 | E28: =H5 -> 210.21965 | F28: =(PV(B28,E28,-1/E28)) -> 1 | G28: =D28*E28*F28 -> 104925.04 | H28: =G28/G5*1000000 -> 1096487.2
A29: 2010 | B29: ='Rate of Return'!L9 -> 0.0061 | C29: ='GOS per unit'!E5 -> 1133109.2 | D29: =C29*F6/1000000 -> 509.93538 | E29: =H6 -> 221.31803 | F29: =(PV(B29,E29,-1/E29)) -> 0.54791328 | G29: =D29*E29*F29 -> 61836.339 | H29: =G29/G6*1000000 -> 620845.56
A30: 2011 | B30: ='Rate of Return'!L10 -> 0.042941905 | C30: ='GOS per unit'!E6 -> 1221958.8 | D30: =C30*F7/1000000 -> 532.04085 | E30: =H7 -> 236.52595 | F30: =(PV(B30,E30,-1/E30)) -> 0.098450758 | G30: =D30*E30*F30 -> 12389.188 | H30: =G30/G7*1000000 -> 120302.77
A31: 2012 | B31: ='Rate of Return'!C11 -> 0.066462195 | C31: ='GOS per unit'!E7 -> 1274682.3 | D31: =C31*F8/1000000 -> 514.24763 | E31: =H8 -> 259.91782 | F31: =(PV(B31,E31,-1/E31)) -> 0.057888092 | G31: =D31*E31*F31 -> 7737.4453 | H31: =G31/G8*1000000 -> 73788.926 | I31: 244356.89
A32: 2013 | B32: ='Rate of Return'!C12 -> 0.075548571 | C32: ='GOS per unit'!E8 -> 1471460.6 | D32: =C32*F9/1000000 -> 634.95968 | E32: =H9 -> 251.45059 | F32: =(PV(B32,E32,-1/E32)) -> 0.052640629 | G32: =D32*E32*F32 -> 8404.6549 | H32: =G32/G9*1000000 -> 77458.613
A33: 2014 | B33: 0.086841975 | C33: 1658354.7 | D33: =C33*F10/1000000 -> 756.2019 | E33: =H10 -> 245.16151 | F33: =(PV(B33,E33,-1/E33)) -> 0.046969725 | G33: =D33*E33*F33 -> 8707.7924 | H33: =G33/G10*1000000 -> 77892.463
A34: 2015 | B34: 0.084721074 | C34: 1610404.9 | D34: =C34*F11/1000000 -> 632.33598 | E34: =H11 -> 292.84292 | F34: =(PV(B34,E34,-1/E34)) -> 0.040306382 | G34: =D34*E34*F34 -> 7463.7389 | H34: =G34/G11*1000000 -> 64909.595
A35: 2016 | B35: 0.079230488 | C35: 1726500.3 | D35: =C35*F12/1000000 -> 432.72659 | E35: =H12 -> 471.55801 | F35: =(PV(B35,E35,-1/E35)) -> 0.026765326 | G35: =D35*E35*F35 -> 5461.6171 | H35: =G35/G12*1000000 -> 46210.344
A36: 2017 | B36: 0.076071308 | C36: 1747045.8 | D36: =C36*F13/1000000 -> 534.97527 | E36: =H13 -> 395.60167 | F36: =(PV(B36,E36,-1/E36)) -> 0.033229286 | G36: =D36*E36*F36 -> 7032.5499 | H36: =G36/G13*1000000 -> 58053.085
A37: 2018 | B37: 0.07944346 | C37: 1839365.4 | D37: =C37*F14/1000000 -> 735.95218 | E37: =H14 -> 309.65722 | F37: =(PV(B37,E37,-1/E37)) -> 0.040650008 | G37: =D37*E37*F37 -> 9263.8485 | H37: =G37/G14*1000000 -> 74770.22
A38: 2019 | B38: 0.080219835 | C38: 2005737.7 | D38: =C38*F15/1000000 -> 814.48193 | E38: =H15 -> 312.1773 | F38: =(PV(B38,E38,-1/E38)) -> 0.039931619 | G38: =D38*E38*F38 -> 10153.124 | H38: =G38/G15*1000000 -> 80092.352
A39: 2020 | B39: 0.074857438 | C39: 2032729.2 | D39: =C39*F16/1000000 -> 879.80037 | E39: =H16 -> 302.74344 | F39: =(PV(B39,E39,-1/E39)) -> 0.044125567 | G39: =D39*E39*F39 -> 11753.012 | H39: =G39/G16*1000000 -> 89695.328
A40: 2021 | B40: 0.070489837 | C40: 2047200.5 | D40: =C40*F17/1000000 -> 1012.8729 | E40: =H17 -> 274.17838 | F40: =(PV(B40,E40,-1/E40)) -> 0.051741651 | G40: =D40*E40*F40 -> 14369.063 | H40: =G40/G17*1000000 -> 105925.53
A41: 2022 | B41: 0.072128455 | C41: 2096041.4 | D41: =C41*F18/1000000 -> 1049.0184 | E41: =H18 -> 280.12882 | F41: =(PV(B41,E41,-1/E41)) -> 0.049492065 | G41: =D41*E41*F41 -> 14543.753 | H41: =G41/G18*1000000 -> 103737.42
A42: 2023 | B42: 0.068520502 | C42: 2184432.3 | D42: =C42*F19/1000000 -> 1011.2939 | E42: =H19 -> 310.93013 | F42: =(PV(B42,E42,-1/E42)) -> 0.046937143 | G42: =D42*E42*F42 -> 14758.997 | H42: =G42/G19*1000000 -> 102531.01
A43: 2024 | B43: 0.069594937 | C43: 2217091.5 | D43: =C43*F20/1000000 -> 876.87742 | E43: =H20 -> 374.13966 | F43: =(PV(B43,E43,-1/E43)) -> 0.038405075 | G43: =D43*E43*F43 -> 12599.73 | H43: =G43/G20*1000000 -> 85147.564
G44: =G36/1000 -> 7.0325499 | H44: =H36/1000 -> 58.053085
A45: Tabel 3. Neraca Moneter Jati Jawa (miliar Rp) | G45: =G34/1000 -> 7.4637389 | H45: =H34/1000 -> 64.909595
A46: Rincian | B46: Persediaan Awal | C46: Pertumbuhan | D46: Penanaman | E46: Konversi & Kerusakan | F46: Penebangan | G46: Revaluasi | H46: Stok Akhir | I46: Unit Rent (ribu Rp/m3)
A47: 2009 | B47: =G27 -> 92293.685 | C47: =C5*$H28/1000000 -> 5214.8467 | D47: =D5*$H28/1000000 -> 20.99773 | E47: =E5*$H28/1000000 -> 321.45425 | F47: =F5*$H28/1000000 -> 499.12098 | G47: =(H28-H27)*B5/1000000 -> 8216.085 | H47: =G28 -> 104925.04 | I47: =H47/G5*1000 -> 1096.4872 | J47: =B47+C47+D47-E47-F47+G47-H47 -> 0
A48: 2010 | B48: =H47 -> 104925.04 | C48: =C6*$H29/1000000 -> 2967.4779 | D48: =D6*$H29/1000000 -> 11.99722 | E48: =E6*$H29/1000000 -> 273.68145 | F48: =F6*$H29/1000000 -> 279.40037 | G48: =(H29-H28)*B6/1000000 -> -45515.094 | H48: =G29 -> 61836.339 | I48: =H48/G6*1000 -> 620.84556 | J48: =B48+C48+D48-E48-F48+G48-H48 -> 0
A49: 2011 | B49: =H48 -> 61836.339 | C49: =C7*$H30/1000000 -> 577.89055 | D49: =D7*$H30/1000000 -> 3.5932031 | E49: =E7*$H30/1000000 -> 122.09508 | F49: =F7*$H30/1000000 -> 52.379825 | G49: =(H30-H29)*B7/1000000 -> -49854.16 | H49: =G30 -> 12389.188 | I49: =H49/G7*1000 -> 120.30277 | J49: =B49+C49+D49-E49-F49+G49-H49 -> 0
A50: 2012 | B50: =H49 -> 12389.188 | C50: =C8*$H31/1000000 -> 356.22743 | D50: =D8*$H31/1000000 -> 1.8099686 | E50: =E8*$H31/1000000 -> 189.85763 | F50: =F8*$H31/1000000 -> 29.768814 | G50: =(H31-H30)*B8/1000000 -> -4790.1535 | H50: =G31 -> 7737.4453 | I50: =H50/G8*1000 -> 73.788926 | J50: =B50+C50+D50-E50-F50+G50-H50 -> 0
A51: 2013 | B51: =H50 -> 7737.4453 | C51: =C9*$H32/1000000 -> 422.88239 | D51: =D9*$H32/1000000 -> 1.2573663 | E51: =E9*$H32/1000000 -> 108.30582 | F51: =F9*$H32/1000000 -> 33.424677 | G51: =(H32-H31)*B9/1000000 -> 384.80033 | H51: =G32 -> 8404.6549 | I51: =H51/G9*1000 -> 77.458613 | J51: =B51+C51+D51-E51-F51+G51-H51 -> 0
A52: 2014 | B52: =H51 -> 8404.6549 | C52: =C10*$H33/1000000 -> 371.14777 | D52: =D10*$H33/1000000 -> 1.8180101 | E52: =E10*$H33/1000000 -> 81.384662 | F52: =F10*$H33/1000000 -> 35.518595 | G52: =(H33-H32)*B10/1000000 -> 47.074999 | H52: =G33 -> 8707.7924 | I52: =H52/G10*1000 -> 77.892463 | J52: =B52+C52+D52-E52-F52+G52-H52 -> 0 | M52: 14701
A53: 2015 | B53: =H52 -> 8707.7924 | C53: =C11*$H34/1000000 -> 311.23823 | D53: =D11*$H34/1000000 -> 1.3195063 | E53: =E11*$H34/1000000 -> 79.73689 | F53: =F11*$H34/1000000 -> 25.487175 | G53: =(H34-H33)*B11/1000000 -> -1451.3872 | H53: =G34 -> 7463.7389 | I53: =H53/G11*1000 -> 64.909595 | J53: =B53+C53+D53-E53-F53+G53-H53 -> 0 | M53: =M52*1000000000 -> 14701000000000
A54: 2016 | B54: =H53 -> 7463.7389 | C54: =C12*$H35/1000000 -> 200.36266 | D54: =D12*$H35/1000000 -> 0.20702234 | E54: =E12*$H35/1000000 -> 40.94462 | F54: =F12*$H35/1000000 -> 11.582068 | G54: =(H35-H34)*B12/1000000 -> -2150.1648 | H54: =G35 -> 5461.6171 | I54: =H54/G12*1000 -> 46.210344 | J54: =B54+C54+D54-E54-F54+G54-H54 -> 0 | M54: 3197179000
A55: 2017 | B55: =H54 -> 5461.6171 | C55: =C13*$H36/1000000 -> 251.45911 | D55: =D13*$H36/1000000 -> 0.42154435 | E55: =E13*$H36/1000000 -> 62.868805 | F55: =F13*$H36/1000000 -> 17.776846 | G55: =(H36-H35)*B13/1000000 -> 1399.6978 | H55: =G36 -> 7032.5499 | I55: =H55/G13*1000 -> 58.053085 | J55: =B55+C55+D55-E55-F55+G55-H55 -> 0
A56: 2018 | B56: =H55 -> 7032.5499 | C56: =C14*$H37/1000000 -> 321.97733 | D56: =D14*$H37/1000000 -> 1.1445078 | E56: =E14*$H37/1000000 -> 87.020231 | F56: =F14*$H37/1000000 -> 29.916462 | G56: =(H37-H36)*B14/1000000 -> 2025.1135 | H56: =G37 -> 9263.8485 | I56: =H56/G14*1000 -> 74.77022 | J56: =B56+C56+D56-E56-F56+G56-H56 -> 0
A57: 2019 | B57: =H56 -> 9263.8485 | C57: =C15*$H38/1000000 -> 346.81838 | D57: =D15*$H38/1000000 -> 1.4312503 | E57: =E15*$H38/1000000 -> 85.849709 | F57: =F15*$H38/1000000 -> 32.523582 | G57: =(H38-H37)*B15/1000000 -> 659.39917 | H57: =G38 -> 10153.124 | I57: =H57/G15*1000 -> 80.092352 | J57: =B57+C57+D57-E57-F57+G57-H57 -> 0
A58: 2020 | B58: =H57 -> 10153.124 | C58: =C16*$H39/1000000 -> 500.61157 | D58: =D16*$H39/1000000 -> 1.511456 | E58: =E16*$H39/1000000 -> 80.760696 | F58: =F16*$H39/1000000 -> 38.82169 | G58: =(H39-H38)*B16/1000000 -> 1217.3474 | H58: =G39 -> 11753.012 | I58: =H58/G16*1000 -> 89.695328 | J58: =B58+C58+D58-E58-F58+G58-H58 -> 0
A59: 2021 | B59: =H58 -> 11753.012 | C59: =C17*$H40/1000000 -> 594.15273 | D59: =D17*$H40/1000000 -> 2.3138373 | E59: =E17*$H40/1000000 -> 54.693877 | F59: =F17*$H40/1000000 -> 52.407716 | G59: =(H40-H39)*B17/1000000 -> 2126.6858 | H59: =G40 -> 14369.063 | I59: =H59/G17*1000 -> 105.92553 | J59: =B59+C59+D59-E59-F59+G59-H59 -> 0
A60: 2022 | B60: =H59 -> 14369.063 | C60: =C18*$H41/1000000 -> 588.61697 | D60: =D18*$H41/1000000 -> 1.3507649 | E60: =E18*$H41/1000000 -> 66.536493 | F60: =F18*$H41/1000000 -> 51.918088 | G60: =(H41-H40)*B18/1000000 -> -296.82326 | H60: =G41 -> 14543.753 | I60: =H60/G18*1000 -> 103.73742 | J60: =B60+C60+D60-E60-F60+G60-H60 -> 0
A61: 2023 | B61: =H60 -> 14543.753 | C61: =C19*$H42/1000000 -> 519.97347 | D61: =D19*$H42/1000000 -> 1.7285703 | E61: =E19*$H42/1000000 -> 89.855582 | F61: =F19*$H42/1000000 -> 47.467244 | G61: =(H42-H41)*B19/1000000 -> -169.13543 | H61: =G42 -> 14758.997 | I61: =H61/G19*1000 -> 102.53101 | J61: =B61+C61+D61-E61-F61+G61-H61 -> 0
A62: 2024 | B62: =H61 -> 14758.997 | C62: =C20*$H43/1000000 -> 433.97611 | D62: =D20*$H43/1000000 -> 1.1985371 | E62: =E20*$H43/1000000 -> 58.475325 | F62: =F20*$H43/1000000 -> 33.676543 | G62: =(H43-H42)*B20/1000000 -> -2502.2892 | H62: =G43 -> 12599.73 | I62: =H62/G20*1000 -> 85.147564 | J62: =B62+C62+D62-E62-F62+G62-H62 -> 0
A92: Tahun | B92: Government Bond-Inflasi | C92: GOS per unit (Rp/m3) | D92: Resource rent (miliar Rp) | E92: Persediaan Awal | F92: Penambahan | G92: Pengurangan | H92: Umur cadangan | I92: Discount Factor | J92: NPV (miliar Rp) | K92: Unit Rent (Rp/m3)
A94: 2008 | B94: 0 | C94: 1006855.8 | D94: 480.98508 | E94: 87707.889 | F94: 4764.3122 | G94: 806.95483 | H94: 205.66857 | I94: 1 | J94: 98923.513 | K94: 1079182.3
A95: 2009 | B95: 0.0839 | C95: 1096487.2 | D95: 499.12098 | E95: 91665.246 | F95: 4775.1077 | G95: 748.36735 | H95: 219.45187 | I95: 0.054312369 | J95: 5948.9984 | K95: 62168.198
A96: 2010 | B96: 0.0149 | C96: 1133109.2 | D96: 509.93538 | E96: 95691.987 | F96: 4799.06 | G96: 890.85249 | H96: 231.24761 | I96: 0.28073374 | J96: 33104.498 | K96: 332373.83
A97: 2011 | B97: 0.0356 | C97: 1221958.8 | D97: 532.04085 | E97: 99600.194 | F97: 4833.5027 | G97: 1450.2983 | H97: 253.94642 | I97: 0.1105981 | J97: 14942.895 | K97: 145100.04
A98: 2012 | B98: 0.0151 | C98: 1274682.3 | D98: 514.24763 | E98: 102983.4 | F98: 4852.1833 | G98: 2976.4148 | H98: 276.74409 | I98: 0.23551959 | J98: 33517.969 | K98: 319647.48
A99: 2013 | B99: 0 | C99: 1471460.6 | D99: 634.9588 | E99: 104859.17 | F99: 5475.6955 | G99: 1829.7571 | H99: 261.27991 | I99: 1 | J99: 165901.98 | K99: 1528978.5
A100: 2014 | B100: 0 | C100: 1658354.7 | D100: 756.20144 | E100: 108505.11 | F100: 4788.2139 | G100: 1502.0843 | H100: 258.38424 | I100: 1 | J100: 195390.54 | K100: 1747816.2
A101: 2015 | B101: 0.047579552 | C101: 2030792.5 | D101: 797.40488 | E101: 111791.24 | F101: 4815.2775 | G101: 1621.0869 | H101: 308.82748 | I101: 0.068055537 | J101: 16759.393 | K101: 145752.33
F103: =F94+G94 -> 5571.267 | G103: =H94+I94 -> 206.66857
F104: =F95+G95 -> 5523.475 | G104: =H95+I95 -> 219.50618
F105: =F96+G96 -> 5689.9125 | G105: =H96+I96 -> 231.52834
F106: =F97+G97 -> 6283.8011 | G106: =H97+I97 -> 254.05702
F107: =F98+G98 -> 7828.5981 | G107: =H98+I98 -> 276.97961
F108: =F99+G99 -> 7305.4526 | G108: =H99+I99 -> 262.27991
F109: =F100+G100 -> 6290.2982 | G109: =H100+I100 -> 259.38424
F110: =F101+G101 -> 6436.3645 | G110: =H101+I101 -> 308.89553

Sheet Rimba Jawa
A1: Tabel 1. Neraca Fisik Rimba Jawa (000m3)
A3: Rincian | B3: Persediaan Awal | C3: Pertumbuhan | D3: Penanaman | E3: Konversi & Kerusakan | F3: Penebangan | G3: Persediaan Akhir | H3: Perkiraan Cadangan | I3: Laju Persediaan Akhir | J3: Cek Persediaan Akhir
A4: 2008 | B4: ='[1]Rimba Jawa'!$T$8 -> 352874.6 | C4: ='[1]Rimba Jawa'!$T$9 -> 16669.278 | D4: ='[1]Rimba Jawa'!$T$10 -> 151.19423 | E4: ='[1]Rimba Jawa'!$T$11 -> 287.74121 | F4: ='[1]Rimba Jawa'!$T$12 -> 605.213 | G4: ='[1]Rimba Jawa'!$T$14 -> 368802.12 | H4: =G4/F4 -> 609.37574 | J4: =B4+C4+D4-E4-F4-G4 -> 0
A5: 2009 | B5: ='[1]Rimba Jawa'!$U$8 -> 368802.12 | C5: ='[1]Rimba Jawa'!$U$9 -> 17077.825 | D5: ='[1]Rimba Jawa'!$U$10 -> 79.3611 | E5: ='[1]Rimba Jawa'!$U$11 -> 256.21155 | F5: ='[1]Rimba Jawa'!$U$12 -> 524.19 | G5: ='[1]Rimba Jawa'!$U$14 -> 385178.91 | H5: =G5/F5 -> 734.80781 | I5: =G5/G4*100-100 -> 4.4405343 | J5: =B5+C5+D5-E5-F5-G5 -> 0
A6: 2010 | B6: ='[1]Rimba Jawa'!$V$8 -> 385178.91 | C6: ='[1]Rimba Jawa'!$V$9 -> 16669.3 | D6: ='[1]Rimba Jawa'!$V$10 -> 108.28688 | E6: ='[1]Rimba Jawa'!$V$11 -> 385.25198 | F6: ='[1]Rimba Jawa'!$V$12 -> 439.429 | G6: ='[1]Rimba Jawa'!$V$14 -> 401131.81 | H6: =G6/F6 -> 912.84784 | I6: =G6/G5*100-100 -> 4.1416873 | J6: =B6+C6+D6-E6-F6-G6 -> 0
A7: 2011 | B7: ='[1]Rimba Jawa'!$W$8 -> 401131.81 | C7: ='[1]Rimba Jawa'!$W$9 -> 17002.694 | D7: ='[1]Rimba Jawa'!$W$10 -> 40.679275 | E7: ='[1]Rimba Jawa'!$W$11 -> 886.96329 | F7: ='[1]Rimba Jawa'!$W$12 -> 533.8 | G7: ='[1]Rimba Jawa'!$W$14 -> 416754.42 | H7: =G7/F7 -> 780.7314 | I7: =G7/G6*100-100 -> 3.8946324 | J7: =B7+C7+D7-E7-F7-G7 -> 0
A8: 2012 | B8: ='[1]Rimba Jawa'!$X$8 -> 416754.42 | C8: ='[1]Rimba Jawa'!$X$9 -> 18588.711 | D8: ='[1]Rimba Jawa'!$X$10 -> 31.57245 | E8: ='[1]Rimba Jawa'!$X$11 -> 2248.6402 | F8: ='[1]Rimba Jawa'!$X$12 -> 525.49 | G8: ='[1]Rimba Jawa'!$X$14 -> 432600.57 | H8: =G8/F8 -> 823.23274 | I8: =G8/G7*100-100 -> 3.802276 | J8: =B8+C8+D8-E8-F8-G8 -> 0
A9: 2013 | B9: ='[1]Rimba Jawa'!$Y$8 -> 432600.57 | C9: ='[1]Rimba Jawa'!$Y$9 -> 30769.212 | D9: ='[1]Rimba Jawa'!$Y$10 -> 35.806225 | E9: ='[1]Rimba Jawa'!$Y$11 -> 1221.983 | F9: ='[1]Rimba Jawa'!$Y$12 -> 524.06771 | G9: ='[1]Rimba Jawa'!$Y$14 -> 461659.54 | H9: =G9/F9 -> 880.91583 | I9: =G9/G8*100-100 -> 6.7172743 | J9: =B9+C9+D9-E9-F9-G9 -> 0 | K9: =G9-G8 -> 29058.967 | L9: =G9/G8*100-100 -> 6.7172743
A10: 2014 | B10: ='[1]Rimba Jawa'!$Z$8 -> 461659.54 | C10: ='[1]Rimba Jawa'!$Z$9 -> 18645.347 | D10: ='[1]Rimba Jawa'!$Z$10 -> 37.262225 | E10: ='[1]Rimba Jawa'!$Z$11 -> 913.12499 | F10: ='[1]Rimba Jawa'!$Z$12 -> 462.59173 | G10: ='[1]Rimba Jawa'!$Z$14 -> 478966.43 | H10: =G10/F10 -> 1035.3977 | I10: =G10/G9*100-100 -> 3.7488432 | J10: =B10+C10+D10-E10-F10-G10 -> 0 | K10: =G10-G9 -> 17306.892 | L10: =G10/G9*100-100 -> 3.7488432
A11: 2015 | B11: ='[1]Rimba Jawa'!$AA$8 -> 478966.43 | C11: ='[1]Rimba Jawa'!$AA$9 -> 18669.687 | D11: ='[1]Rimba Jawa'!$AA$10 -> 38.834 | E11: ='[1]Rimba Jawa'!$AA$11 -> 1073.5777 | F11: ='[1]Rimba Jawa'!$AA$12 -> 398.58371 | G11: ='[1]Rimba Jawa'!$AA$14 -> 496202.79 | H11: =G11/F11 -> 1244.9149 | I11: =G11/G10*100-100 -> 3.598657 | J11: =B11+C11+D11-E11-F11-G11 -> 0 | K11: =G11-G10 -> 17236.359 | L11: =G11/G10*100-100 -> 3.598657
A12: 2016 | B12: ='[1]Rimba Jawa'!$AB$8 -> 496202.79 | C12: ='[1]Rimba Jawa'!$AB$9 -> 11115.135 | D12: ='[1]Rimba Jawa'!$AB$10 -> 9.4913 | E12: ='[1]Rimba Jawa'!$AB$11 -> 774.35614 | F12: ='[1]Rimba Jawa'!$AB$12 -> 297.794 | G12: ='[1]Rimba Jawa'!$AB$14 -> 506255.27 | H12: =G12/F12 -> 1700.0184 | I12: =G12/G11*100-100 -> 2.0258805 | J12: =B12+C12+D12-E12-F12-G12 -> 0 | K12: =G12-G11 -> 10052.476 | L12: =G12/G11*100-100 -> 2.0258805
A13: 2017 | B13: ='[1]Rimba Jawa'!$AC$8 -> 506255.27 | C13: ='[1]Rimba Jawa'!$AC$9 -> 11264.08 | D13: ='[1]Rimba Jawa'!$AC$10 -> 25.468611 | E13: ='[1]Rimba Jawa'!$AC$11 -> 946.43982 | F13: ='[1]Rimba Jawa'!$AC$12 -> 330.07528 | G13: ='[1]Rimba Jawa'!$AC$14 -> 516268.3 | H13: =G13/F13 -> 1564.0926 | I13: =G13/G12*100-100 -> 1.9778627 | J13: =B13+C13+D13-E13-F13-G13 -> 0
A14: 2018 | B14: ='[1]Rimba Jawa'!$AD$8 -> 516268.3 | C14: ='[1]Rimba Jawa'!$AD$9 -> 11671.29 | D14: ='[1]Rimba Jawa'!$AD$10 -> 19.207825 | E14: ='[1]Rimba Jawa'!$AD$11 -> 1017.1258 | F14: ='[1]Rimba Jawa'!$AD$12 -> 409.822 | G14: ='[1]Rimba Jawa'!$AD$14 -> 526531.85 | H14: =G14/F14 -> 1284.7818 | I14: =G14/G13*100-100 -> 1.9880265 | J14: =B14+C14+D14-E14-F14-G14 -> 0
A15: 2019 | B15: ='[1]Rimba Jawa'!$AE$8 -> 526531.85 | C15: ='[1]Rimba Jawa'!$AE$9 -> 11477.648 | D15: ='[1]Rimba Jawa'!$AE$10 -> 29.65235 | E15: ='[1]Rimba Jawa'!$AE$11 -> 936.76549 | F15: ='[1]Rimba Jawa'!$AE$12 -> 377.444 | G15: ='[1]Rimba Jawa'!$AE$14 -> 536724.94 | H15: =G15/F15 -> 1421.9989 | I15: =G15/G14*100-100 -> 1.9358926 | J15: =B15+C15+D15-E15-F15-G15 -> 0
A16: 2020 | B16: ='[1]Rimba Jawa'!$AF$8 -> 536724.94 | C16: ='[1]Rimba Jawa'!$AF$9 -> 5004.9917 | D16: ='[1]Rimba Jawa'!$AF$10 -> 41.40045 | E16: ='[1]Rimba Jawa'!$AF$11 -> 786.88874 | F16: ='[1]Rimba Jawa'!$AF$12 -> 413.6883 | G16: ='[1]Rimba Jawa'!$AF$14 -> 540570.76 | H16: =G16/F16 -> 1306.7103 | I16: =G16/G15*100-100 -> 0.71653371 | J16: =B16+C16+D16-E16-F16-G16 -> 0
A17: 2021 | B17: ='[1]Rimba Jawa'!$AG$8 -> 540570.76 | C17: ='[1]Rimba Jawa'!$AG$9 -> 5004.9688 | D17: ='[1]Rimba Jawa'!$AG$10 -> 44.605925 | E17: ='[1]Rimba Jawa'!$AG$11 -> 451.25409 | F17: ='[1]Rimba Jawa'!$AG$12 -> 491.423 | G17: ='[1]Rimba Jawa'!$AG$14 -> 544677.66 | H17: =G17/F17 -> 1108.3683 | I17: =G17/G16*100-100 -> 0.75973359 | J17: =B17+C17+D17-E17-F17-G17 -> 0
A18: 2022 | B18: ='[1]Rimba Jawa'!$AH$8 -> 544677.66 | C18: ='[1]Rimba Jawa'!$AH$9 -> 4773.0653 | D18: ='[1]Rimba Jawa'!$AH$10 -> 27.557075 | E18: ='[1]Rimba Jawa'!$AH$11 -> 560.54125 | F18: ='[1]Rimba Jawa'!$AH$12 -> 425.291 | G18: ='[1]Rimba Jawa'!$AH$14 -> 548492.45 | H18: =G18/F18 -> 1289.6874 | I18: =G18/G17*100-100 -> 0.70037574 | J18: =B18+C18+D18-E18-F18-G18 -> 0
A19: 2023 | B19: ='[1]Rimba Jawa'!$AI$8 -> 548492.45 | C19: ='[1]Rimba Jawa'!$AI$9 -> 18200.447 | D19: ='[1]Rimba Jawa'!$AI$10 -> 20.950475 | E19: ='[1]Rimba Jawa'!$AI$11 -> 765.90151 | F19: ='[1]Rimba Jawa'!$AI$12 -> 453.153 | G19: ='[1]Rimba Jawa'!$AI$14 -> 565494.79 | H19: =G19/F19 -> 1247.9114
A20: 2024 | B20: ='[1]Rimba Jawa'!$AJ$8 -> 565494.79 | C20: ='[1]Rimba Jawa'!$AJ$9 -> 18205.292 | D20: ='[1]Rimba Jawa'!$AJ$10 -> 14.2415 | E20: ='[1]Rimba Jawa'!$AJ$11 -> 600.18276 | F20: ='[1]Rimba Jawa'!$AJ$12 -> 408.129 | G20: ='[1]Rimba Jawa'!$AJ$14 -> 582706.01 | H20: =G20/F20 -> 1427.7496
G21: =(G13-G9)/1000 -> 54.608761 | I21: =(G9-G8)/1000 -> 29.058967
A22: Tabel 2. Penghitungan NPV | G22: =G13/G9*100-100 -> 11.828795
A23: Rincian | B23: Government Bond-Inflasi | C23: GOS per unit (Rp/m3) | D23: Resource rent (miliar Rp) | E23: Umur cadangan | F23: Discount Factor | G23: NPV (miliar Rp) | H23: NPV per stok akhir (Rp/m3)
A25: 2008 | B25: ='Rate of Return'!L7 -> 0 | C25: ='GOS per unit'!K3 -> 952618.12 | D25: =C25*F4/1000000 -> 576.53687 | E25: =H4 -> 609.37574 | F25: =(PV(B25,E25,-1/E25)) -> 1 | G25: =D25*E25*F25 -> 351327.58 | H25: =G25/G4*1000000 -> 952618.12 | I25: =((1/E25)*(1+(B25*1))*(((1+B25)^E25)-1)/B25)/((1+B25)^E25) -> #DIV/0!
A26: 2009 | B26: ='Rate of Return'!L8 -> 0 | C26: ='GOS per unit'!K4 -> 1045677.9 | D26: =C26*F5/1000000 -> 548.1339 | E26: =H5 -> 734.80781 | F26: =(PV(B26,E26,-1/E26)) -> 1 | G26: =D26*E26*F26 -> 402773.07 | H26: =G26/G5*1000000 -> 1045677.9 | I26: =((1/E26)*(1+(B26*1))*(((1+B26)^E26)-1)/B26)/((1+B26)^E26) -> #DIV/0!
A27: 2010 | B27: ='Rate of Return'!L9 -> 0.0061 | C27: ='GOS per unit'!K5 -> 1093197.2 | D27: =C27*F6/1000000 -> 480.38254 | E27: =H6 -> 912.84784 | F27: =(PV(B27,E27,-1/E27)) -> 0.17888859 | G27: =D27*E27*F27 -> 78445.539 | H27: =G27/G6*1000000 -> 195560.5 | I27: =((1/E27)*(1+(B27*1))*(((1+B27)^E27)-1)/B27)/((1+B27)^E27) -> 0.17997981
A28: 2011 | B28: ='Rate of Return'!L10 -> 0.042941905 | C28: ='GOS per unit'!K6 -> 1173526.2 | D28: =C28*F7/1000000 -> 626.4283 | E28: =H7 -> 780.7314 | F28: =(PV(B28,E28,-1/E28)) -> 0.029827513 | G28: =D28*E28*F28 -> 14587.809 | H28: =G28/G7*1000000 -> 35003.369 | I28: =((1/E28)*(1+(B28*1))*(((1+B28)^E28)-1)/B28)/((1+B28)^E28) -> 0.031108364 | J28: =(1/E28)*(1+(B28*1)) -> 0.0013358524 | K28: =(((1+B28)^E28)-1)/B28 -> 4.2011266e+15 | L28: =((1+B28)^E28) -> 1.8040438e+14
A29: 2012 | B29: ='Rate of Return'!C11 -> 0.066462195 | C29: ='GOS per unit'!K7 -> 1224292.3 | D29: =C29*F8/1000000 -> 643.35337 | E29: =H8 -> 823.23274 | F29: =(PV(B29,E29,-1/E29)) -> 0.018276906 | G29: =D29*E29*F29 -> 9679.9898 | H29: =G29/G8*1000000 -> 22376.276 | I29: =((1/E29)*(1+(B29*1))*(((1+B29)^E29)-1)/B29)/((1+B29)^E29) -> 0.01949163
A30: 2013 | B30: ='Rate of Return'!C12 -> 0.075548571 | C30: ='GOS per unit'!K8 -> 1287315.3 | D30: =C30*F9/1000000 -> 674.64038 | E30: =H9 -> 880.91583 | F30: =(PV(B30,E30,-1/E30)) -> 0.01502586 | G30: =D30*E30*F30 -> 8929.8894 | H30: =G30/G9*1000000 -> 19343.019 | I30: =((1/E30)*(1+(B30*1))*(((1+B30)^E30)-1)/B30)/((1+B30)^E30) -> 0.016161042
A31: 2014 | B31: ='Rate of Return'!C13 -> 0.086841975 | C31: ='GOS per unit'!K9 -> 1192728.7 | D31: =C31*F10/1000000 -> 551.74644 | E31: =H10 -> 1035.3977 | F31: =(PV(B31,E31,-1/E31)) -> 0.011121493 | G31: =D31*E31*F31 -> 6353.4534 | H31: =G31/G10*1000000 -> 13264.924 | I31: =((1/E31)*(1+(B31*1))*(((1+B31)^E31)-1)/B31)/((1+B31)^E31) -> 0.012087305
A32: 2015 | B32: ='Rate of Return'!C14 -> 0.084721074 | C32: ='GOS per unit'!K10 -> 1171914.5 | D32: =C32*F11/1000000 -> 467.10601 | E32: =H11 -> 1244.9149 | F32: =(PV(B32,E32,-1/E32)) -> 0.0094813217 | G32: =D32*E32*F32 -> 5513.4571 | H32: =G32/G11*1000000 -> 11111.298 | I32: =((1/E32)*(1+(B32*1))*(((1+B32)^E32)-1)/B32)/((1+B32)^E32) -> 0.010284589
A33: 2016 | B33: ='Rate of Return'!C15 -> 0.079230488 | C33: ='GOS per unit'!K11 -> 1192893.4 | D33: =C33*F12/1000000 -> 355.23649 | E33: =H12 -> 1700.0184 | F33: =(PV(B33,E33,-1/E33)) -> 0.0074242751 | G33: =D33*E33*F33 -> 4483.5833 | H33: =G33/G12*1000000 -> 8856.3687 | I33: =((1/E33)*(1+(B33*1))*(((1+B33)^E33)-1)/B33)/((1+B33)^E33) -> 0.0080125041
A34: 2017 | B34: ='Rate of Return'!C16 -> 0.076071308 | C34: ='GOS per unit'!K12 -> 1202018.2 | D34: =C34*F13/1000000 -> 396.75648 | E34: =H13 -> 1564.0926 | F34: =(PV(B34,E34,-1/E34)) -> 0.0084045925 | G34: =D34*E34*F34 -> 5215.5864 | H34: =G34/G13*1000000 -> 10102.473
A35: 2018 | B35: ='Rate of Return'!C17 -> 0.07944346 | C35: ='GOS per unit'!K13 -> 1241818.4 | D35: =C35*F14/1000000 -> 508.92452 | E35: =H14 -> 1284.7818 | F35: =(PV(B35,E35,-1/E35)) -> 0.0097974368 | G35: =D35*E35*F35 -> 6406.1223 | H35: =G35/G14*1000000 -> 12166.638
A36: 2019 | B36: ='Rate of Return'!C18 -> 0.080219835 | C36: ='GOS per unit'!K14 -> 1326604.5 | D36: =C36*F15/1000000 -> 500.71891 | E36: =H15 -> 1421.9989 | F36: =(PV(B36,E36,-1/E36)) -> 0.0087663536 | G36: =D36*E36*F36 -> 6241.8342 | H36: =G36/G15*1000000 -> 11629.484
A37: 2020 | B37: ='Rate of Return'!C19 -> 0.074857438 | C37: ='GOS per unit'!K15 -> 1383391.1 | D37: =C37*F16/1000000 -> 572.29271 | E37: =H16 -> 1306.7103 | F37: =(PV(B37,E37,-1/E37)) -> 0.010223173 | G37: =D37*E37*F37 -> 7645.1015 | H37: =G37/G16*1000000 -> 14142.647
A38: 2021 | B38: ='Rate of Return'!C20 -> 0.070489837 | C38: ='GOS per unit'!K16 -> 1418974.3 | D38: =C38*F17/1000000 -> 697.31659 | E38: =H17 -> 1108.3683 | F38: =(PV(B38,E38,-1/E38)) -> 0.012799394 | G38: =D38*E38*F38 -> 9892.4415 | H38: =G38/G17*1000000 -> 18162.011
A39: 2022 | B39: ='Rate of Return'!C21 -> 0.072128455 | C39: ='GOS per unit'!K17 -> 1528524.2 | D39: =C39*F18/1000000 -> 650.06758 | E39: =H18 -> 1289.6874 | F39: =(PV(B39,E39,-1/E39)) -> 0.010750011 | G39: =D39*E39*F39 -> 9012.6369 | H39: =G39/G18*1000000 -> 16431.652
A40: 2023 | B40: ='Rate of Return'!C22 -> 0.068520502 | C40: ='GOS per unit'!K18 -> 1688397.6 | D40: =C40*F19/1000000 -> 765.10243 | E40: =H19 -> 1247.9114 | F40: =(PV(B40,E40,-1/E40)) -> 0.011694879 | G40: =D40*E40*F40 -> 11166.037 | H40: =G40/G19*1000000 -> 19745.605
A41: 2024 | B41: ='Rate of Return'!C23 -> 0.069594937 | C41: ='GOS per unit'!K19 -> 1721255.1 | D41: =C41*F20/1000000 -> 702.49414 | E41: =H20 -> 1427.7496 | F41: =(PV(B41,E41,-1/E41)) -> 0.010063993 | G41: =D41*E41*F41 -> 10094.041 | H41: =G41/G20*1000000 -> 17322.699
G42: =G34/1000 -> 5.2155864 | H42: =H34/1000 -> 10.102473
A43: Tabel 3. Neraca Moneter Rimba Jawa (miliar Rp) | G43: =G30/1000 -> 8.9298894 | H43: =H30/1000 -> 19.343019
A44: 2019 | B44: ='Rate of Return'!C22 -> 0.068520502 | G44: =G31/1000 -> 6.3534534 | H44: =H31/1000 -> 13.264924
A45: Rincian | B45: Persediaan Awal | C45: Pertumbuhan | D45: Penanaman | E45: Konversi & Kerusakan | F45: Penebangan | G45: Revaluasi | H45: Stok Akhir | I45: Unit Rent (ribu Rp/m3)
A46: 2009 | B46: =G25 -> 351327.58 | C46: =C5*$H26/1000000 -> 17857.904 | D46: =D5*$H26/1000000 -> 82.986148 | E46: =E5*$H26/1000000 -> 267.91476 | F46: =F5*$H26/1000000 -> 548.1339 | G46: =(H26-H25)*B5/1000000 -> 34320.643 | H46: =G26 -> 402773.07 | I46: =(H46/G5*1000) -> 1045.6779 | J46: =B46+C46+D46-E46-F46+G46-H46 -> 0
A47: 2010 | B47: =G26 -> 402773.07 | C47: =C6*$H27/1000000 -> 3259.8567 | D47: =D6*$H27/1000000 -> 21.176638 | E47: =E6*$H27/1000000 -> 75.340071 | F47: =F6*$H27/1000000 -> 85.934957 | G47: =(H27-H26)*B6/1000000 -> -327447.29 | H47: =G27 -> 78445.539 | I47: =(H47/G6*1000) -> 195.5605 | J47: =B47+C47+D47-E47-F47+G47-H47 -> 0
A48: 2011 | B48: =G27 -> 78445.539 | C48: =C7*$H28/1000000 -> 595.15156 | D48: =D7*$H28/1000000 -> 1.4239117 | E48: =E7*$H28/1000000 -> 31.046703 | F48: =F7*$H28/1000000 -> 18.684798 | G48: =(H28-H27)*B7/1000000 -> -64404.575 | H48: =G28 -> 14587.809 | I48: =(H48/G7*1000) -> 35.003369 | J48: =B48+C48+D48-E48-F48+G48-H48 -> -1.6370905e-11
A49: 2012 | B49: =G28 -> 14587.809 | C49: =C8*$H29/1000000 -> 415.94613 | D49: =D8*$H29/1000000 -> 0.70647385 | E49: =E8*$H29/1000000 -> 50.316195 | F49: =F8*$H29/1000000 -> 11.758509 | G49: =(H29-H28)*B8/1000000 -> -5262.3969 | H49: =G29 -> 9679.9898 | I49: =(H49/G8*1000) -> 22.376276 | J49: =B49+C49+D49-E49-F49+G49-H49 -> 0
A50: 2013 | B50: =G29 -> 9679.9898 | C50: =C9*$H30/1000000 -> 595.16945 | D50: =D9*$H30/1000000 -> 0.6926005 | E50: =E9*$H30/1000000 -> 23.636841 | F50: =F9*$H30/1000000 -> 10.137052 | G50: =(H30-H29)*B9/1000000 -> -1312.1886 | H50: =G30 -> 8929.8894 | I50: =(H50/G9*1000) -> 19.343019 | J50: =B50+C50+D50-E50-F50+G50-H50 -> 0 | K50: =H50/H49*100-100 -> -7.7489797
A51: 2014 | B51: =G30 -> 8929.8894 | C51: =C10*$H31/1000000 -> 247.32911 | D51: =D10*$H31/1000000 -> 0.49428059 | E51: =E10*$H31/1000000 -> 12.112534 | F51: =F10*$H31/1000000 -> 6.1362442 | G51: =(H31-H30)*B10/1000000 -> -2806.0106 | H51: =G31 -> 6353.4534 | I51: =(H51/G10*1000) -> 13.264924 | J51: =B51+C51+D51-E51-F51+G51-H51 -> 0 | K51: =H51/H50*100-100 -> -28.851824
A52: 2015 | B52: =G31 -> 6353.4534 | C52: =C11*$H32/1000000 -> 207.44445 | D52: =D11*$H32/1000000 -> 0.43149614 | E52: =E11*$H32/1000000 -> 11.928842 | F52: =F11*$H32/1000000 -> 4.4287823 | G52: =(H32-H31)*B11/1000000 -> -1031.5146 | H52: =G32 -> 5513.4571 | I52: =(H52/G11*1000) -> 11.111298 | J52: =B52+C52+D52-E52-F52+G52-H52 -> 0 | K52: =H52/H51*100-100 -> -13.221098
A53: 2016 | B53: =G32 -> 5513.4571 | C53: =C12*$H33/1000000 -> 98.439731 | D53: =D12*$H33/1000000 -> 0.084058452 | E53: =E12*$H33/1000000 -> 6.8579834 | F53: =F12*$H33/1000000 -> 2.6373735 | G53: =(H33-H32)*B12/1000000 -> -1118.9022 | H53: =G33 -> 4483.5833 | I53: =(H53/G12*1000) -> 8.8563687 | J53: =B53+C53+D53-E53-F53+G53-H53 -> 0 | K53: =H53/H52*100-100 -> -18.679274
A54: 2017 | B54: =G33 -> 4483.5833 | C54: =C13*$H34/1000000 -> 113.79506 | D54: =D13*$H34/1000000 -> 0.25729595 | E54: =E13*$H34/1000000 -> 9.5613824 | F54: =F13*$H34/1000000 -> 3.3345765 | G54: =(H34-H33)*B13/1000000 -> 630.84672 | H54: =G34 -> 5215.5864 | I54: =(H54/G13*1000) -> 10.102473 | J54: =B54+C54+D54-E54-F54+G54-H54 -> 0 | K54: =H54/H53*100-100 -> 16.326297
A55: 2018 | B55: =G34 -> 5215.5864 | C55: =C14*$H35/1000000 -> 142.00036 | D55: =D14*$H35/1000000 -> 0.23369465 | E55: =E14*$H35/1000000 -> 12.375001 | F55: =F14*$H35/1000000 -> 4.9861558 | G55: =(H35-H34)*B14/1000000 -> 1065.663 | H55: =G35 -> 6406.1223 | I55: =(H55/G14*1000) -> 12.166638 | J55: =B55+C55+D55-E55-F55+G55-H55 -> 0 | K55: =H55/H54*100-100 -> 22.826501
A56: 2019 | B56: =G35 -> 6406.1223 | C56: =C15*$H36/1000000 -> 133.47913 | D56: =D15*$H36/1000000 -> 0.34484153 | E56: =E15*$H36/1000000 -> 10.894099 | F56: =F15*$H36/1000000 -> 4.389479 | G56: =(H36-H35)*B15/1000000 -> -282.82849 | H56: =G36 -> 6241.8342 | I56: =(H56/G15*1000) -> 11.629484 | J56: =B56+C56+D56-E56-F56+G56-H56 -> 0 | K56: =H56/H55*100-100 -> -2.5645483
A57: 2020 | B57: =G36 -> 6241.8342 | C57: =C16*$H37/1000000 -> 70.783832 | D57: =D16*$H37/1000000 -> 0.58551195 | E57: =E16*$H37/1000000 -> 11.12869 | F57: =F16*$H37/1000000 -> 5.8506476 | G57: =(H37-H36)*B16/1000000 -> 1348.8772 | H57: =G37 -> 7645.1015 | I57: =(H57/G16*1000) -> 14.142647 | J57: =B57+C57+D57-E57-F57+G57-H57 -> 0 | K57: =H57/H56*100-100 -> 22.481649
A58: 2021 | B58: =G37 -> 7645.1015 | C58: =C17*$H38/1000000 -> 90.900297 | D58: =D17*$H38/1000000 -> 0.81013329 | E58: =E17*$H38/1000000 -> 8.1956817 | F58: =F17*$H38/1000000 -> 8.9252299 | G58: =(H38-H37)*B17/1000000 -> 2172.7506 | H58: =G38 -> 9892.4415 | I58: =(H58/G17*1000) -> 18.162011 | J58: =B58+C58+D58-E58-F58+G58-H58 -> 0 | K58: =H58/H57*100-100 -> 29.395818
A59: 2022 | B59: =G38 -> 9892.4415 | C59: =C18*$H39/1000000 -> 78.429348 | D59: =D18*$H39/1000000 -> 0.45280826 | E59: =E18*$H39/1000000 -> 9.2106187 | F59: =F18*$H39/1000000 -> 6.9882336 | G59: =(H39-H38)*B18/1000000 -> -942.48791 | H59: =G39 -> 9012.6369 | I59: =(H59/G18*1000) -> 16.431652 | J59: =B59+C59+D59-E59-F59+G59-H59 -> 0 | K59: =H59/H58*100-100 -> -8.8937054
A60: 2023 | B60: =G39 -> 9012.6369 | C60: =C19*$H40/1000000 -> 359.37884 | D60: =D19*$H40/1000000 -> 0.4136798 | E60: =E19*$H40/1000000 -> 15.123188 | F60: =F19*$H40/1000000 -> 8.94778 | G60: =(H40-H39)*B19/1000000 -> 1817.6781 | H60: =G40 -> 11166.037 | I60: =(H60/G19*1000) -> 19.745605 | J60: =B60+C60+D60-E60-F60+G60-H60 -> 0 | K60: =H60/H59*100-100 -> 23.893114
A61: 2024 | B61: =G40 -> 11166.037 | C61: =C20*$H41/1000000 -> 315.3648 | D61: =D20*$H41/1000000 -> 0.24670122 | E61: =E20*$H41/1000000 -> 10.396785 | F61: =F20*$H41/1000000 -> 7.0698959 | G61: =(H41-H40)*B20/1000000 -> -1370.1405 | H61: =G41 -> 10094.041 | I61: =(H61/G20*1000) -> 17.322699 | J61: =B61+C61+D61-E61-F61+G61-H61 -> 0 | K61: =H61/H60*100-100 -> -9.6005026

Sheet Rimba Luar Jawa
A1: Tabel 1. Neraca Fisik Rimba Luar Jawa (000m3)
A3: Rincian | B3: Persediaan Awal | C3: Pertumbuhan | D3: Penanaman | E3: Konversi & Kerusakan | F3: Penebangan | G3: Persediaan Akhir | H3: Perkiraan Cadangan | I3: Laju Persediaan Akhir | J3: Cek Persediaan Akhir
A4: 2008 | B4: ='[1]Rimba Luar Jawa'!$T$8 -> 6500648.8 | C4: ='[1]Rimba Luar Jawa'!$T$9 -> 28768.843 | D4: ='[1]Rimba Luar Jawa'!$T$10 -> 7954.0144 | E4: ='[1]Rimba Luar Jawa'!$T$11 -> 206743.81 | F4: ='[1]Rimba Luar Jawa'!$T$12 -> 48522.631 | G4: ='[1]Rimba Luar Jawa'!$T$14 -> 6282105.2 | H4: =G4/F4 -> 129.46753 | J4: =B4+C4+D4-E4-F4-G4 -> 0
A5: 2009 | B5: ='[1]Rimba Luar Jawa'!$U$8 -> 6282105.2 | C5: ='[1]Rimba Luar Jawa'!$U$9 -> 29427.551 | D5: ='[1]Rimba Luar Jawa'!$U$10 -> 6050.4458 | E5: ='[1]Rimba Luar Jawa'!$U$11 -> 227447.89 | F5: ='[1]Rimba Luar Jawa'!$U$12 -> 50911.031 | G5: ='[1]Rimba Luar Jawa'!$U$14 -> 6039224.3 | H5: =G5/F5 -> 118.6231 | I5: =G5/G4*100-100 -> -3.8662345 | J5: =B5+C5+D5-E5-F5-G5 -> 0
A6: 2010 | B6: ='[1]Rimba Luar Jawa'!$V$8 -> 6039224.3 | C6: ='[1]Rimba Luar Jawa'!$V$9 -> 29417.615 | D6: ='[1]Rimba Luar Jawa'!$V$10 -> 4452.6684 | E6: ='[1]Rimba Luar Jawa'!$V$11 -> 248573.61 | F6: ='[1]Rimba Luar Jawa'!$V$12 -> 53550.936 | G6: ='[1]Rimba Luar Jawa'!$V$14 -> 5770970.1 | H6: =G6/F6 -> 107.766 | I6: =G6/G5*100-100 -> -4.4418662 | J6: =B6+C6+D6-E6-F6-G6 -> 0
A7: 2011 | B7: ='[1]Rimba Luar Jawa'!$W$8 -> 5770970.1 | C7: ='[1]Rimba Luar Jawa'!$W$9 -> 29641.821 | D7: ='[1]Rimba Luar Jawa'!$W$10 -> 4825.0458 | E7: ='[1]Rimba Luar Jawa'!$W$11 -> 276481.4 | F7: ='[1]Rimba Luar Jawa'!$W$12 -> 49960.669 | G7: ='[1]Rimba Luar Jawa'!$W$14 -> 5478994.8 | H7: =G7/F7 -> 109.66616 | I7: =G7/G6*100-100 -> -5.0593783 | J7: =B7+C7+D7-E7-F7-G7 -> 0
A8: 2012 | B8: ='[1]Rimba Luar Jawa'!$X$8 -> 5478994.8 | C8: ='[1]Rimba Luar Jawa'!$X$9 -> 29470.768 | D8: ='[1]Rimba Luar Jawa'!$X$10 -> 6148.3529 | E8: ='[1]Rimba Luar Jawa'!$X$11 -> 333058.25 | F8: ='[1]Rimba Luar Jawa'!$X$12 -> 49014.219 | G8: ='[1]Rimba Luar Jawa'!$X$14 -> 5132541.5 | H8: =G8/F8 -> 104.71536 | I8: =G8/G7*100-100 -> -6.3233012 | J8: =B8+C8+D8-E8-F8-G8 -> 0
A9: 2013 | B9: ='[1]Rimba Luar Jawa'!$Y$8 -> 5132541.5 | C9: ='[1]Rimba Luar Jawa'!$Y$9 -> 22422.401 | D9: ='[1]Rimba Luar Jawa'!$Y$10 -> 11054.912 | E9: ='[1]Rimba Luar Jawa'!$Y$11 -> 89854.22 | F9: ='[1]Rimba Luar Jawa'!$Y$12 -> 40036.102 | G9: ='[1]Rimba Luar Jawa'!$Y$14 -> 5036128.5 | H9: =G9/F9 -> 125.78968 | I9: =G9/G8*100-100 -> -1.8784653 | J9: =B9+C9+D9-E9-F9-G9 -> 0 | K9: =G9-G8 -> -96413.01 | L9: =G9/G8*100-100 -> -1.8784653
A10: 2014 | B10: ='[1]Rimba Luar Jawa'!$Z$8 -> 5036128.5 | C10: ='[1]Rimba Luar Jawa'!$Z$9 -> 23276.945 | D10: ='[1]Rimba Luar Jawa'!$Z$10 -> 11134.353 | E10: ='[1]Rimba Luar Jawa'!$Z$11 -> 192303.64 | F10: ='[1]Rimba Luar Jawa'!$Z$12 -> 45112.663 | G10: ='[1]Rimba Luar Jawa'!$Z$14 -> 4833123.5 | H10: =G10/F10 -> 107.13452 | I10: =G10/G9*100-100 -> -4.0309735 | J10: =B10+C10+D10-E10-F10-G10 -> 0 | K10: =G10-G9 -> -203005 | L10: =G10/G9*100-100 -> -4.0309735
A11: 2015 | B11: ='[1]Rimba Luar Jawa'!$AA$8 -> 4833123.5 | C11: ='[1]Rimba Luar Jawa'!$AA$9 -> 23334.934 | D11: ='[1]Rimba Luar Jawa'!$AA$10 -> 15628.694 | E11: ='[1]Rimba Luar Jawa'!$AA$11 -> 611062.47 | F11: ='[1]Rimba Luar Jawa'!$AA$12 -> 44609.668 | G11: ='[1]Rimba Luar Jawa'!$AA$14 -> 4216415 | H11: =G11/F11 -> 94.517964 | I11: =G11/G10*100-100 -> -12.76004 | J11: =B11+C11+D11-E11-F11-G11 -> 0 | K11: =G11-G10 -> -616708.51 | L11: =G11/G10*100-100 -> -12.76004
A12: 2016 | B12: ='[1]Rimba Luar Jawa'!$AB$8 -> 4216415 | C12: ='[1]Rimba Luar Jawa'!$AB$9 -> 23679.321 | D12: ='[1]Rimba Luar Jawa'!$AB$10 -> 17100.811 | E12: ='[1]Rimba Luar Jawa'!$AB$11 -> 192087.18 | F12: ='[1]Rimba Luar Jawa'!$AB$12 -> 44659.749 | G12: ='[1]Rimba Luar Jawa'!$AB$14 -> 4020448.2 | H12: =G12/F12 -> 90.023975 | I12: =G12/G11*100-100 -> -4.6477113 | J12: =B12+C12+D12-E12-F12-G12 -> 0 | K12: =G12-G11 -> -195966.8 | L12: =G12/G11*100-100 -> -4.6477113
A13: 2017 | B13: ='[1]Rimba Luar Jawa'!$AC$8 -> 4020448.2 | C13: ='[1]Rimba Luar Jawa'!$AC$9 -> 23728.337 | D13: ='[1]Rimba Luar Jawa'!$AC$10 -> 7325.8898 | E13: ='[1]Rimba Luar Jawa'!$AC$11 -> 148297.99 | F13: ='[1]Rimba Luar Jawa'!$AC$12 -> 46714.212 | G13: ='[1]Rimba Luar Jawa'!$AC$14 -> 3856490.2 | H13: =G13/F13 -> 82.554966 | I13: =G13/G12*100-100 -> -4.0781021 | J13: =B13+C13+D13-E13-F13-G13 -> 0
A14: 2018 | B14: ='[1]Rimba Luar Jawa'!$AD$8 -> 3856490.2 | C14: ='[1]Rimba Luar Jawa'!$AD$9 -> 23708.237 | D14: ='[1]Rimba Luar Jawa'!$AD$10 -> 9085.3763 | E14: ='[1]Rimba Luar Jawa'!$AD$11 -> 126820.67 | F14: ='[1]Rimba Luar Jawa'!$AD$12 -> 46460.129 | G14: ='[1]Rimba Luar Jawa'!$AD$14 -> 3716003 | H14: =G14/F14 -> 79.982623 | I14: =G14/G13*100-100 -> -3.6428768 | J14: =B14+C14+D14-E14-F14-G14 -> 0
A15: 2019 | B15: ='[1]Rimba Luar Jawa'!$AE$8 -> 3716003 | C15: ='[1]Rimba Luar Jawa'!$AE$9 -> 23731.665 | D15: ='[1]Rimba Luar Jawa'!$AE$10 -> 12956.789 | E15: ='[1]Rimba Luar Jawa'!$AE$11 -> 323896.69 | F15: ='[1]Rimba Luar Jawa'!$AE$12 -> 48581.714 | G15: ='[1]Rimba Luar Jawa'!$AE$14 -> 3380213.1 | H15: =G15/F15 -> 69.577888 | I15: =G15/G14*100-100 -> -9.0363207 | J15: =B15+C15+D15-E15-F15-G15 -> 0
A16: 2020 | B16: ='[1]Rimba Luar Jawa'!$AF$8 -> 3380213.1 | C16: ='[1]Rimba Luar Jawa'!$AF$9 -> 23696.412 | D16: ='[1]Rimba Luar Jawa'!$AF$10 -> 10701.947 | E16: ='[1]Rimba Luar Jawa'!$AF$11 -> 66782.842 | F16: ='[1]Rimba Luar Jawa'!$AF$12 -> 51134.241 | G16: ='[1]Rimba Luar Jawa'!$AF$14 -> 3296694.3 | H16: =G16/F16 -> 64.471366 | I16: =G16/G15*100-100 -> -2.4708124 | J16: =B16+C16+D16-E16-F16-G16 -> 0
A17: 2021 | B17: ='[1]Rimba Luar Jawa'!$AG$8 -> 3296694.3 | C17: ='[1]Rimba Luar Jawa'!$AG$9 -> 23543.429 | D17: ='[1]Rimba Luar Jawa'!$AG$10 -> 4682.045 | E17: ='[1]Rimba Luar Jawa'!$AG$11 -> 108661.98 | F17: ='[1]Rimba Luar Jawa'!$AG$12 -> 53827.052 | G17: ='[1]Rimba Luar Jawa'!$AG$14 -> 3162430.8 | H17: =G17/F17 -> 58.751699 | I17: =G17/G16*100-100 -> -4.0726724 | J17: =B17+C17+D17-E17-F17-G17 -> 0
A18: 2022 | B18: ='[1]Rimba Luar Jawa'!$AH$8 -> 3162430.8 | C18: ='[1]Rimba Luar Jawa'!$AH$9 -> 23540.2 | D18: ='[1]Rimba Luar Jawa'!$AH$10 -> 6591.1413 | E18: ='[1]Rimba Luar Jawa'!$AH$11 -> 54795.275 | F18: ='[1]Rimba Luar Jawa'!$AH$12 -> 54129.774 | G18: ='[1]Rimba Luar Jawa'!$AH$14 -> 3083637.1 | H18: =G18/F18 -> 56.967485 | I18: =G18/G17*100-100 -> -2.4915552 | J18: =B18+C18+D18-E18-F18-G18 -> 0
A19: 2023 | B19: ='[1]Rimba Luar Jawa'!$AI$8 -> 3083637.1 | C19: ='[1]Rimba Luar Jawa'!$AI$9 -> 23309.776 | D19: ='[1]Rimba Luar Jawa'!$AI$10 -> 4322.3929 | E19: ='[1]Rimba Luar Jawa'!$AI$11 -> 238112.68 | F19: ='[1]Rimba Luar Jawa'!$AI$12 -> 57218.774 | G19: ='[1]Rimba Luar Jawa'!$AI$14 -> 2815937.8 | H19: =G19/F19 -> 49.213529 | I19: =G19/G18*100-100 -> -8.6812839 | J19: =B19+C19+D19-E19-F19-G19 -> 0
A20: 2024 | B20: ='[1]Rimba Luar Jawa'!$AJ$8 -> 2815937.8 | C20: ='[1]Rimba Luar Jawa'!$AJ$9 -> 23297.342 | D20: ='[1]Rimba Luar Jawa'!$AJ$10 -> 7699.2765 | E20: ='[1]Rimba Luar Jawa'!$AJ$11 -> 95017.524 | F20: ='[1]Rimba Luar Jawa'!$AJ$12 -> 54503.682 | G20: ='[1]Rimba Luar Jawa'!$AJ$14 -> 2697413.2 | H20: =G20/F20 -> 49.490476 | I20: =G20/G19*100-100 -> -4.2090627 | J20: =B20+C20+D20-E20-F20-G20 -> 0
F21: =F13/1000 -> 46.714212 | G21: =(G13-G9)/1000 -> -1179.6383 | H21: =G13/1000 -> 3856.4902 | I21: =(G11-G10)/1000 -> -616.70851
A22: Tabel 2. Penghitungan NPV | G22: =G13/G9*100-100 -> -23.423515 | H22: =H13 -> 82.554966
A23: Rincian | B23: Government Bond-Inflasi | C23: GOS per unit (Rp/m3) | D23: Resource rent (miliar Rp) | E23: Umur cadangan | F23: Discount Factor | G23: NPV (miliar Rp) | H23: NPV per stok akhir (Rp/m3)
A25: 2008 | B25: ='Rate of Return'!L7 -> 0 | C25: ='GOS per unit'!Q3 -> 958608.83 | D25: =C25*F4/1000000 -> 46514.223 | E25: =H4 -> 129.46753 | F25: =(PV(B25,E25,-1/E25)) -> 1 | G25: =D25*E25*F25 -> 6022081.5 | H25: =G25/G4*1000000 -> 958608.83
A26: 2009 | B26: ='Rate of Return'!L8 -> 0 | C26: ='GOS per unit'!Q4 -> 1047733.4 | D26: =C26*F5/1000000 -> 53341.189 | E26: =H5 -> 118.6231 | F26: =(PV(B26,E26,-1/E26)) -> 1 | G26: =D26*E26*F26 -> 6327497.1 | H26: =G26/G5*1000000 -> 1047733.4
A27: 2010 | B27: ='Rate of Return'!L9 -> 0.0061 | C27: ='GOS per unit'!Q5 -> 1094005.2 | D27: =C27*F6/1000000 -> 58585.001 | E27: =H6 -> 107.766 | F27: =(PV(B27,E27,-1/E27)) -> 0.73132509 | G27: =D27*E27*F27 -> 4617199.8 | H27: =G27/G6*1000000 -> 800073.44
A28: 2011 | B28: ='Rate of Return'!L10 -> 0.042941905 | C28: ='GOS per unit'!Q6 -> 1175518 | D28: =C28*F7/1000000 -> 58729.666 | E28: =H7 -> 109.66616 | F28: =(PV(B28,E28,-1/E28)) -> 0.21023576 | G28: =D28*E28*F28 -> 1354056.5 | H28: =G28/G7*1000000 -> 247135.92
A29: 2012 | B29: ='Rate of Return'!C11 -> 0.066462195 | C29: ='GOS per unit'!Q7 -> 1231283.8 | D29: =C29*F8/1000000 -> 60350.413 | E29: =H8 -> 104.71536 | F29: =(PV(B29,E29,-1/E29)) -> 0.1435159 | G29: =D29*E29*F29 -> 906965.29 | H29: =G29/G8*1000000 -> 176708.81
A30: 2013 | B30: ='Rate of Return'!C12 -> 0.075548571 | C30: ='GOS per unit'!Q8 -> 1291468.7 | D30: =C30*F9/1000000 -> 51705.374 | E30: =H9 -> 125.78968 | F30: =(PV(B30,E30,-1/E30)) -> 0.10521632 | G30: =D30*E30*F30 -> 684327.22 | H30: =G30/G9*1000000 -> 135883.59 | K30: =H30/H29*100-100 -> -23.103103
A31: 2014 | B31: ='Rate of Return'!C13 -> 0.086841975 | C31: ='GOS per unit'!Q9 -> 1357161.1 | D31: =C31*F10/1000000 -> 61225.149 | E31: =H10 -> 107.13452 | F31: =(PV(B31,E31,-1/E31)) -> 0.10746893 | G31: =D31*E31*F31 -> 704923.84 | H31: =G31/G10*1000000 -> 145852.64 | K31: =H31/H30*100-100 -> 7.3364664
A32: 2015 | B32: ='Rate of Return'!C14 -> 0.084721074 | C32: ='GOS per unit'!Q10 -> 1170150.4 | D32: =C32*F11/1000000 -> 52200.019 | E32: =H11 -> 94.517964 | F32: =(PV(B32,E32,-1/E32)) -> 0.12482305 | G32: =D32*E32*F32 -> 615856.91 | H32: =G32/G11*1000000 -> 146061.74 | K32: =H32/H31*100-100 -> 0.14336199
A33: 2016 | B33: ='Rate of Return'!C15 -> 0.079230488 | C33: ='GOS per unit'!Q11 -> 1192645.3 | D33: =C33*F12/1000000 -> 53263.242 | E33: =H12 -> 90.023975 | F33: =(PV(B33,E33,-1/E33)) -> 0.14005403 | G33: =D33*E33*F33 -> 671554.69 | H33: =G33/G12*1000000 -> 167034.78 | K33: =H33/H32*100-100 -> 14.359025 | L33: =H34/H30*100-100 -> 40.694254
A34: 2017 | B34: ='Rate of Return'!C16 -> 0.076071308 | C34: ='GOS per unit'!Q12 -> 1203455.3 | D34: =C34*F13/1000000 -> 56218.464 | E34: =H13 -> 82.554966 | F34: =(PV(B34,E34,-1/E34)) -> 0.15885958 | G34: =D34*E34*F34 -> 737285.35 | H34: =G34/G13*1000000 -> 191180.4 | K34: =H34/H33*100-100 -> 14.455445 | L34: =G34/G30*100-100 -> 7.738715
A35: 2018 | B35: ='Rate of Return'!C17 -> 0.07944346 | C35: ='GOS per unit'!Q13 -> 1241783.1 | D35: =C35*F14/1000000 -> 57693.405 | E35: =H14 -> 79.982623 | F35: =(PV(B35,E35,-1/E35)) -> 0.15703083 | G35: =D35*E35*F35 -> 724614.03 | H35: =G35/G14*1000000 -> 194998.24 | K35: =H35/H34*100-100 -> 1.9969789 | L35: =G35/G31*100-100 -> 2.7932368
A36: 2019 | B36: ='Rate of Return'!C18 -> 0.080219835 | C36: ='GOS per unit'!Q14 -> 1330163.3 | D36: =C36*F15/1000000 -> 64621.612 | E36: =H15 -> 69.577888 | F36: =(PV(B36,E36,-1/E36)) -> 0.17832773 | G36: =D36*E36*F36 -> 801803.42 | H36: =G36/G15*1000000 -> 237204.99 | K36: =H36/H35*100-100 -> 21.644687 | L36: =G36/G32*100-100 -> 30.193134
A37: 2020 | B37: ='Rate of Return'!C19 -> 0.074857438 | C37: ='GOS per unit'!Q15 -> 1379752.2 | D37: =C37*F16/1000000 -> 70552.583 | E37: =H16 -> 64.471366 | F37: =(PV(B37,E37,-1/E37)) -> 0.20523084 | G37: =D37*E37*F37 -> 933517.41 | H37: =G37/G16*1000000 -> 283167.72 | K37: =H37/H36*100-100 -> 19.376794 | L37: =G37/G33*100-100 -> 39.008396
A38: 2021 | B38: ='Rate of Return'!C20 -> 0.070489837 | C38: ='GOS per unit'!Q16 -> 1426938.1 | D38: =C38*F17/1000000 -> 76807.872 | E38: =H17 -> 58.751699 | F38: =(PV(B38,E38,-1/E38)) -> 0.23705042 | G38: =D38*E38*F38 -> 1069712 | H38: =G38/G17*1000000 -> 338256.27 | K38: =H38/H37*100-100 -> 19.454391 | L38: =G38/G34*100-100 -> 45.087928
A39: 2022 | B39: ='Rate of Return'!C21 -> 0.072128455 | C39: ='GOS per unit'!Q17 -> 1554186.8 | D39: =C39*F18/1000000 -> 84127.778 | E39: =H18 -> 56.967485 | F39: =(PV(B39,E39,-1/E39)) -> 0.23876511 | G39: =D39*E39*F39 -> 1144293.3 | H39: =G39/G18*1000000 -> 371085.58 | K39: =H39/H38*100-100 -> 9.7054551 | L39: =G39/G35*100-100 -> 57.917623
A40: 2023 | B40: ='Rate of Return'!C22 -> 0.068520502 | C40: ='GOS per unit'!Q18 -> 1691416.6 | D40: =C40*F19/1000000 -> 96780.786 | E40: =H19 -> 49.213529 | F40: =(PV(B40,E40,-1/E40)) -> 0.28518246 | G40: =D40*E40*F40 -> 1358302.4 | H40: =G40/G19*1000000 -> 482362.36
A41: 2024 | B41: ='Rate of Return'!C23 -> 0.069594937 | C41: ='GOS per unit'!Q19 -> 1723207.5 | D41: =C41*F20/1000000 -> 93921.155 | E41: =H20 -> 49.490476 | F41: =(PV(B41,E41,-1/E41)) -> 0.27994095 | G41: =D41*E41*F41 -> 1301222.3 | H41: =G41/G20*1000000 -> 482396.36
G42: =G34/1000 -> 737.28535 | H42: =H34/1000 -> 191.1804 | K42: =H34/H30*100-100 -> 40.694254
A43: Tabel 3. Neraca Moneter rimba Luar Jawa (miliar Rp) | G43: =G30/1000 -> 684.32722 | H43: =H30/1000 -> 135.88359
A44: 2019 | B44: ='Rate of Return'!C22 -> 0.068520502 | G44: =G31/1000 -> 704.92384 | H44: =H31/1000 -> 145.85264
A45: Rincian | B45: Persediaan Awal | C45: Pertumbuhan | D45: Penanaman | E45: Konversi & Kerusakan | F45: Penebangan | G45: Revaluasi | H45: Stok Akhir | I45: Unit Rent (ribu Rp/m3)
A46: 2009 | B46: =G25 -> 6022081.5 | C46: =C5*$H26/1000000 -> 30832.229 | D46: =D5*$H26/1000000 -> 6339.2542 | E46: =E5*$H26/1000000 -> 238304.75 | F46: =F5*$H26/1000000 -> 53341.189 | G46: =(H26-H25)*B5/1000000 -> 559890.03 | H46: =G26 -> 6327497.1 | I46: =(H46/G5)*1000 -> 1047.7334
A47: 2010 | B47: =G26 -> 6327497.1 | C47: =C6*$H27/1000000 -> 23536.252 | D47: =D6*$H27/1000000 -> 3562.4617 | E47: =E6*$H27/1000000 -> 198877.15 | F47: =F6*$H27/1000000 -> 42844.681 | G47: =(H27-H26)*B6/1000000 -> -1495674.2 | H47: =G27 -> 4617199.8 | I47: =(H47/G6)*1000 -> 800.07344
A48: 2011 | B48: =G27 -> 4617199.8 | C48: =C7*$H28/1000000 -> 7325.5589 | D48: =D7*$H28/1000000 -> 1192.4422 | E48: =E7*$H28/1000000 -> 68328.487 | F48: =F7*$H28/1000000 -> 12347.076 | G48: =(H28-H27)*B7/1000000 -> -3190985.8 | H48: =G28 -> 1354056.5 | I48: =(H48/G7)*1000 -> 247.13592
A49: 2012 | B49: =G28 -> 1354056.5 | C49: =C8*$H29/1000000 -> 5207.7442 | D49: =D8*$H29/1000000 -> 1086.4681 | E49: =E8*$H29/1000000 -> 58854.326 | F49: =F8*$H29/1000000 -> 8661.2441 | G49: =(H29-H28)*B8/1000000 -> -385869.81 | H49: =G29 -> 906965.29 | I49: =(H49/G8)*1000 -> 176.70881
A50: 2013 | B50: =G29 -> 906965.29 | C50: =C9*$H30/1000000 -> 3046.8363 | D50: =D9*$H30/1000000 -> 1502.1812 | E50: =E9*$H30/1000000 -> 12209.714 | F50: =F9*$H30/1000000 -> 5440.2493 | G50: =(H30-H29)*B9/1000000 -> -209537.12 | H50: =G30 -> 684327.22 | I50: =(H50/G9)*1000 -> 135.88359 | J50: =B50+C50+D50-E50-F50+G50-H50 -> 0 | K50: =H50/H49*100-100 -> -24.547584 | L50: =I50/I49*100-100 -> -23.103103
A51: 2014 | B51: =G30 -> 684327.22 | C51: =C10*$H31/1000000 -> 3395.0039 | D51: =D10*$H31/1000000 -> 1623.9749 | E51: =E10*$H31/1000000 -> 28047.994 | F51: =F10*$H31/1000000 -> 6579.8012 | G51: =(H31-H30)*B10/1000000 -> 50205.437 | H51: =G31 -> 704923.84 | I51: =(H51/G10)*1000 -> 145.85264 | J51: =B51+C51+D51-E51-F51+G51-H51 -> 0 | K51: =H51/H50*100-100 -> 3.0097619 | L51: =I51/I50*100-100 -> 7.3364664
A52: 2015 | B52: =G31 -> 704923.84 | C52: =C11*$H32/1000000 -> 3408.3412 | D52: =D11*$H32/1000000 -> 2282.7542 | E52: =E11*$H32/1000000 -> 89252.848 | F52: =F11*$H32/1000000 -> 6515.7658 | G52: =(H32-H31)*B11/1000000 -> 1010.5928 | H52: =G32 -> 615856.91 | I52: =(H52/G11)*1000 -> 146.06174 | J52: =B52+C52+D52-E52-F52+G52-H52 -> 0 | K52: =H52/H51*100-100 -> -12.634971 | L52: =I52/I51*100-100 -> 0.14336199
A53: 2016 | B53: =G32 -> 615856.91 | C53: =C12*$H33/1000000 -> 3955.2703 | D53: =D12*$H33/1000000 -> 2856.4302 | E53: =E12*$H33/1000000 -> 32085.24 | F53: =F12*$H33/1000000 -> 7459.7316 | G53: =(H33-H32)*B12/1000000 -> 88431.047 | H53: =G33 -> 671554.69 | I53: =(H53/G12)*1000 -> 167.03478 | J53: =B53+C53+D53-E53-F53+G53-H53 -> 0 | K53: =H53/H52*100-100 -> 9.0439475 | L53: =I53/I52*100-100 -> 14.359025
A54: 2017 | B54: =G33 -> 671554.69 | C54: =C13*$H34/1000000 -> 4536.3931 | D54: =D13*$H34/1000000 -> 1400.5666 | E54: =E13*$H34/1000000 -> 28351.67 | F54: =F13*$H34/1000000 -> 8930.8419 | G54: =(H34-H33)*B13/1000000 -> 97076.216 | H54: =G34 -> 737285.35 | I54: =(H54/G13)*1000 -> 191.1804 | J54: =B54+C54+D54-E54-F54+G54-H54 -> 0 | K54: =H54/H53*100-100 -> 9.7878347
A55: 2018 | B55: =G34 -> 737285.35 | C55: =C14*$H35/1000000 -> 4623.0645 | D55: =D14*$H35/1000000 -> 1771.6324 | E55: =E14*$H35/1000000 -> 24729.807 | F55: =F14*$H35/1000000 -> 9059.6432 | G55: =(H35-H34)*B14/1000000 -> 14723.433 | H55: =G35 -> 724614.03 | I55: =(H55/G14)*1000 -> 194.99824 | J55: =B55+C55+D55-E55-F55+G55-H55 -> 0 | K55: =H55/H54*100-100 -> -1.7186454
A56: 2019 | B56: =G35 -> 724614.03 | C56: =C15*$H36/1000000 -> 5629.2695 | D56: =D15*$H36/1000000 -> 3073.4151 | E56: =E15*$H36/1000000 -> 76829.912 | F56: =F15*$H36/1000000 -> 11523.825 | G56: =(H36-H35)*B15/1000000 -> 156840.44 | H56: =G36 -> 801803.42 | I56: =(H56/G15)*1000 -> 237.20499 | J56: =B56+C56+D56-E56-F56+G56-H56 -> 0 | K56: =H56/H55*100-100 -> 10.652483
A57: 2020 | B57: =G36 -> 801803.42 | C57: =C16*$H37/1000000 -> 6710.0589 | D57: =D16*$H37/1000000 -> 3030.446 | E57: =E16*$H37/1000000 -> 18910.745 | F57: =F16*$H37/1000000 -> 14479.566 | G57: =(H37-H36)*B16/1000000 -> 155363.79 | H57: =G37 -> 933517.41 | I57: =(H57/G16)*1000 -> 283.16772 | J57: =B57+C57+D57-E57-F57+G57-H57 -> 0 | K57: =H57/H56*100-100 -> 16.427217
A58: 2021 | B58: =G37 -> 933517.41 | C58: =C17*$H38/1000000 -> 7963.7125 | D58: =D17*$H38/1000000 -> 1583.7311 | E58: =E17*$H38/1000000 -> 36755.597 | F58: =F17*$H38/1000000 -> 18207.338 | G58: =(H38-H37)*B17/1000000 -> 181610.13 | H58: =G38 -> 1069712 | I58: =(H58/G17)*1000 -> 338.25627 | J58: =B58+C58+D58-E58-F58+G58-H58 -> 0 | K58: =H58/H57*100-100 -> 14.589405
A59: 2022 | B59: =G38 -> 1069712 | C59: =C18*$H39/1000000 -> 8735.4288 | D59: =D18*$H39/1000000 -> 2445.8775 | E59: =E18*$H39/1000000 -> 20333.736 | F59: =F18*$H39/1000000 -> 20086.779 | G59: =(H39-H38)*B18/1000000 -> 103820.42 | H59: =G39 -> 1144293.3 | I59: =(H59/G18)*1000 -> 371.08558 | J59: =B59+C59+D59-E59-F59+G59-H59 -> 0 | K59: =H59/H58*100-100 -> 6.9720832
A60: 2023 | B60: =G39 -> 1144293.3 | C60: =C19*$H40/1000000 -> 11243.759 | D60: =D19*$H40/1000000 -> 2084.9596 | E60: =E19*$H40/1000000 -> 114856.6 | F60: =F19*$H40/1000000 -> 27600.183 | G60: =(H40-H39)*B19/1000000 -> 343137.21 | H60: =G40 -> 1358302.4 | I60: =(H60/G19)*1000 -> 482.36236
A61: 2024 | B61: =G40 -> 1358302.4 | C61: =C20*$H41/1000000 -> 11238.553 | D61: =D20*$H41/1000000 -> 3714.103 | E61: =E20*$H41/1000000 -> 45836.107 | F61: =F20*$H41/1000000 -> 26292.378 | G61: =(H41-H40)*B20/1000000 -> 95.731758 | H61: =G41 -> 1301222.3 | I61: =(H61/G20)*1000 -> 482.39636

Sheet Sheet1
A1: Tahun | B1: Government Bond | C1: Jati Jawa | E1: Rimba Jawa | G1: Luar Jawa
C2: cadangan | D2: unit rent | E2: cadangan | F2: unit rent | G2: cadangan | H2: unit rent
A3: 2013 | B3: 0.075548571 | C3: 251.45094 | D3: 77458.505 | E3: 880.93217 | F3: 19342.66 | G3: 120.32134 | H3: 142051.9
A4: 2014 | B4: 0.086841975 | C4: 245.15891 | D4: 77893.29 | E4: 1035.3948 | F4: 13264.962 | G4: 88.796166 | H4: 175889.74
A5: 2015 | B5: 0.084721074 | C5: 292.83936 | D5: 81854.892 | E5: 1244.9112 | F5: 14011.884 | G5: 68.574186 | H5: 253030.57
A6: 2016 | B6: 0.079230488 | C6: 471.55301 | D6: 58273.926 | E6: 1700.0147 | F6: 11168.3 | G6: 53.183799 | H6: 350892.12
A7: 2017 | B7: 0.076071308 | C7: 395.59757 | D7: 73208.29 | E7: 1564.0893 | F7: 12739.696 | G7: 33.332666 | H7: 546343.47

Sheet Rate of Return
A1: TAHUN | B1: Sumber: DJPPR | E1: Sumber: BPS | H1: Return to Capital Rate | I1: Return to Capital Rate
B2: Government Bond Rate | E2: Indeks Harga Konsumen | H2: Bond rate minus CPI (Consumer Price Indeks)
B3: Rate | C3: Convert | E3: Index (2007=100) | F3: Annual Growth (%) | J3: rata2 GBR (3th) | K3: rata2 CPI (3th)
A4: 2005 | B4: 3.59 | C4: =B4/100 -> 0.0359 | E4: 88.008847 | H4: =IF((C4-F4)>0,C4-F4,0) -> 0.0359
A5: 2006 | B5: 4.12 | C5: =B5/100 -> 0.0412 | E5: 93.817431 | F5: =(E5/E4*100-100)/100 -> 0.066 | H5: =IF((C5-F5)>0,C5-F5,0) -> 0
A6: 2007 | B6: 4.22 | C6: =B6/100 -> 0.0422 | E6: 100 | F6: =(E6/E5*100-100)/100 -> 0.0659 | H6: =IF((C6-F6)>0,C6-F6,0) -> 0
A7: 2008 | B7: 3.01 | C7: =B7/100 -> 0.0301 | E7: 111.06 | F7: =(E7/E6*100-100)/100 -> 0.1106 | H7: =IF((C7-F7)>0,C7-F7,0) -> 0 | I7: 0 | J7: =AVERAGE(C5:C7) -> 0.037833333 | K7: =AVERAGE(F5:F7) -> 0.080833333 | L7: =(IF((J7-K7)>0,J7-K7,0)) -> 0
A8: 2009 | B8: 11.17 | C8: =B8/100 -> 0.1117 | E8: 114.14747 | F8: =(E8/E7*100-100)/100 -> 0.0278 | H8: =IF((C8-F8)>0,C8-F8,0) -> 0.0839 | I8: 0 | J8: =AVERAGE(C6:C8) -> 0.061333333 | K8: =AVERAGE(F6:F8) -> 0.0681 | L8: =(IF((J8-K8)>0,J8-K8,0)) -> 0
A9: 2010 | B9: 8.45 | C9: =B9/100 -> 0.0845 | E9: 122.09213 | F9: =(E9/E8*100-100)/100 -> 0.0696 | H9: =IF((C9-F9)>0,C9-F9,0) -> 0.0149 | I9: =(AVERAGE(B7:B9)-AVERAGE(F7:F9)) -> 7.474 | J9: =AVERAGE(C7:C9) -> 0.075433333 | K9: =AVERAGE(F7:F9) -> 0.069333333 | L9: =(IF((J9-K9)>0,J9-K9,0)) -> 0.0061
A10: 2011 | B10: 7.35 | C10: =B10/100 -> 0.0735 | E10: 127.4 | F10: =(E10/E9*100-100)/100 -> 0.043474286 | H10: =IF((C10-F10)>0,C10-F10,0) -> 0.030025714 | I10: =AVERAGE(B8:B10)-AVERAGE(F8:F10) -> 8.9430419 | J10: =AVERAGE(C8:C10) -> 0.0899 | K10: =AVERAGE(F8:F10) -> 0.046958095 | L10: =(IF((J10-K10)>0,J10-K10,0)) -> 0.042941905
A11: 2012 | B11: =AVERAGE('2012'!I7:I252)*100 -> 6.6462195 | C11: =B11/100 -> 0.066462195 | E11: 132.9 | F11: =(E11/E10*100-100)/100 -> 0.043171115 | H11: =IF((C11-F11)>0,C11-F11,0) -> 0.023291081 | I11: =AVERAGE(B9:B11)-AVERAGE(F9:F11) -> 7.4299914 | J11: =AVERAGE(C9:C11) -> 0.074820732 | K11: =AVERAGE(F9:F11) -> 0.0520818 | L11: =(IF((J11-K11)>0,J11-K11,0)) -> 0.022738932
A12: 2013 | B12: =AVERAGE('2013'!I7:I251)*100 -> 7.5548571 | C12: =B12/100 -> 0.075548571 | E12: 144.03702 | F12: =(E12/E11*100-100)/100 -> 0.0838 | H12: =IF((C12-F12)>0,C12-F12,0) -> 0 | I12: =AVERAGE(B10:B12)-AVERAGE(F10:F12) -> 7.1268771 | J12: =AVERAGE(C10:C12) -> 0.071836922 | K12: =AVERAGE(F10:F12) -> 0.056815133 | L12: =(IF((J12-K12)>0,J12-K12,0)) -> 0.015021789
A13: 2014 | B13: =AVERAGE('2014'!I7:I249)*100 -> 8.6841975 | C13: =B13/100 -> 0.086841975 | E13: 156.07851 | F13: =(E13/E12*100-100)/100 -> 0.0836 | H13: =IF((C13-F13)>0,C13-F13,0) -> 0.0032419753 | I13: 0 | J13: =AVERAGE(C11:C13) -> 0.076284247 | K13: =AVERAGE(F11:F13) -> 0.070190372 | L13: =(IF((J13-K13)>0,J13-K13,0)) -> 0.0060938758
A14: 2015 | B14: =AVERAGE('2015'!I7:I248)*100 -> 8.4721074 | C14: =B14/100 -> 0.084721074 | E14: 161.30715 | F14: =(E14/E13*100-100)/100 -> 0.0335 | H14: =IF((C14-F14)>0,C14-F14,0) -> 0.051221074 | I14: =AVERAGE(B12:B14)-AVERAGE(F12:F14) -> 8.1700874 | J14: =AVERAGE(C12:C14) -> 0.08237054 | K14: =AVERAGE(F12:F14) -> 0.066966667 | L14: =(IF((J14-K14)>0,J14-K14,0)) -> 0.015403874
A15: 2016 | B15: =AVERAGE('2016'!I7:I252)*100 -> 7.9230488 | C15: =B15/100 -> 0.079230488 | E15: 166.17862 | F15: =(E15/E14*100-100)/100 -> 0.0302 | H15: =IF((C15-F15)>0,C15-F15,0) -> 0.049030488 | I15: =AVERAGE(B13:B15)-AVERAGE(F13:F15) -> 8.3106846 | J15: =AVERAGE(C13:C15) -> 0.083597846 | K15: =AVERAGE(F13:F15) -> 0.0491 | L15: =(IF((J15-K15)>0,J15-K15,0)) -> 0.034497846
A16: 2017 | B16: =AVERAGE('2017'!I7:I244)*100 -> 7.6071308 | C16: =B16/100 -> 0.076071308 | E16: =((F16+100)/100)*E15 -> 166.23861 | F16: 0.0361 | H16: =IF((C16-F16)>0,C16-F16,0) -> 0.039971308 | I16: =AVERAGE(B14:B16)-AVERAGE(F14:F16) -> 7.9674957 | J16: =AVERAGE(C14:C16) -> 0.080007623 | K16: =AVERAGE(F14:F16) -> 0.033266667 | L16: =(IF((J16-K16)>0,J16-K16,0)) -> 0.046740957
A17: 2018 | B17: =AVERAGE('2018'!I7:I243)*100 -> 7.944346 | C17: =B17/100 -> 0.07944346 | H17: =IF((C17-F17)>0,C17-F17,0) -> 0.07944346 | I17: =AVERAGE(B15:B17)-AVERAGE(F15:F17) -> 7.7916919 | J17: =AVERAGE(C15:C17) -> 0.078248419
A18: 2019 | B18: =AVERAGE('2019'!I7:I251)*100 -> 8.0219835 | C18: =B18/100 -> 0.080219835 | H18: =IF((C18-F18)>0,C18-F18,0) -> 0.080219835 | I18: =AVERAGE(B16:B18)-AVERAGE(F16:F18) -> 7.8217201 | J18: =AVERAGE(C16:C18) -> 0.078578201
A19: 2020 | B19: =AVERAGE('2020'!I7:I248)*100 -> 7.4857438 | C19: =B19/100 -> 0.074857438 | H19: =IF((C19-F19)>0,C19-F19,0) -> 0.074857438 | I19: =AVERAGE(B17:B19)-AVERAGE(F17:F19) -> #DIV/0! | J19: =AVERAGE(C17:C19) -> 0.078173578
A20: 2021 | B20: =AVERAGE('2021'!I7:I252)*100 -> 7.0489837 | C20: =B20/100 -> 0.070489837 | H20: =IF((C20-F20)>0,C20-F20,0) -> 0.070489837 | I20: =AVERAGE(B18:B20)-AVERAGE(F18:F20) -> #DIV/0! | J20: =AVERAGE(C18:C20) -> 0.075189037
A21: 2022 | B21: =AVERAGE('2022'!I7:I252)*100 -> 7.2128455 | C21: =B21/100 -> 0.072128455 | H21: =IF((C21-F21)>0,C21-F21,0) -> 0.072128455 | I21: =AVERAGE(B19:B21)-AVERAGE(F19:F21) -> #DIV/0! | J21: =AVERAGE(C19:C21) -> 0.07249191
A22: 2023 | B22: =AVERAGE('2023'!I7:I245)*100 -> 6.8520502 | C22: =B22/100 -> 0.068520502 | H22: =IF((C22-F22)>0,C22-F22,0) -> 0.068520502 | I22: =AVERAGE(B20:B22)-AVERAGE(F20:F22) -> #DIV/0! | J22: =AVERAGE(C20:C22) -> 0.070379598
A23: 2024 | B23: =AVERAGE('2024'!I7:I243)*100 -> 6.9594937 | C23: =B23/100 -> 0.069594937 | H23: =IF((C23-F23)>0,C23-F23,0) -> 0.069594937 | I23: =AVERAGE(B21:B23)-AVERAGE(F21:F23) -> #DIV/0! | J23: =AVERAGE(C21:C23) -> 0.070081298

Sheet GOS per unit
C1: Jati Jawa | I1: Rimba Jawa | O1: Rimba Luar Jawa
B2: Harga | C2: Output (juta Rp) | D2: Produksi (000 m3) | E2: GOS per Unit (Rp/m3) | H2: Harga | I2: Output (juta Rp) | J2: Produksi (000 m3) | K2: GOS per Unit (Rp/m3) | N2: Harga | O2: Output (juta Rp) | P2: Produksi (000 m3) | Q2: GOS per Unit (Rp/m3)
A3: 2008 | B3: 1544955.3 | C3: =B3*D3/1000 -> 769387.74 | D3: 498 | E3: =$D$21*C3/D3*1000 -> 1006855.8 | G3: =A3 -> 2008 | H3: 1461731.1 | I3: =H3*J3/1000 -> 1249780.1 | J3: 855 | K3: =$D$21*I3/J3*1000 -> 952618.12 | M3: =A3 -> 2008 | N3: 1470923.4 | O3: =N3*P3/1000 -> 30587853 | P3: 20795 | Q3: =$D$21*O3/P3*1000 -> 958608.83
A4: 2009 | B4: 1682488.9 | C4: =B4*D4/1000 -> 765532.45 | D4: 455 | E4: =$D$21*C4/D4*1000 -> 1096487.2 | G4: =A4 -> 2009 | H4: 1604525.3 | I4: =H4*J4/1000 -> 840771.26 | J4: 524 | K4: =$D$21*I4/J4*1000 -> 1045677.9 | M4: =A4 -> 2009 | N4: 1607679.4 | O4: =N4*P4/1000 -> 30687384 | P4: 19088 | Q4: =$D$21*O4/P4*1000 -> 1047733.4
A5: 2010 | B5: 1738683 | C5: =B5*D5/1000 -> 782407.33 | D5: 450 | E5: =$D$21*C5/D5*1000 -> 1133109.2 | G5: =A5 -> 2010 | H5: 1677440.6 | I5: =H5*J5/1000 -> 739751.29 | J5: 441 | K5: =$D$21*I5/J5*1000 -> 1093197.2 | M5: =A5 -> 2010 | N5: 1678680.4 | O5: =N5*P5/1000 -> 31816030 | P5: 18953 | Q5: =$D$21*O5/P5*1000 -> 1094005.2
A6: 2011 | B6: 1875016.9 | C6: =B6*D6/1000 -> 851257.69 | D6: 454 | E6: =$D$21*C6/D6*1000 -> 1221958.8 | G6: =A6 -> 2011 | H6: 1800700.3 | I6: =H6*J6/1000 -> 1107430.7 | J6: 615 | K6: =$D$21*I6/J6*1000 -> 1173526.2 | M6: =A6 -> 2011 | N6: 1803756.6 | O6: =N6*P6/1000 -> 29592430 | P6: 16406 | Q6: =$D$21*O6/P6*1000 -> 1175518
A7: 2012 | B7: 1955917.8 | C7: =B7*D7/1000 -> 788234.87 | D7: 403 | E7: =$D$21*C7/D7*1000 -> 1274682.3 | G7: =A7 -> 2012 | H7: 1878597.6 | I7: =H7*J7/1000 -> 986263.75 | J7: 525 | K7: =$D$21*I7/J7*1000 -> 1224292.3 | M7: =A7 -> 2012 | N7: 1889325.6 | O7: =N7*P7/1000 -> 26010345 | P7: 13767 | Q7: =$D$21*O7/P7*1000 -> 1231283.8
A8: 2013 | B8: 2257861.4 | C8: =B8*D8/1000 -> 975396.14 | D8: 432 | E8: =$D$21*C8/D8*1000 -> 1471460.6 | G8: =A8 -> 2013 | H8: 1975302.3 | I8: =H8*J8/1000 -> 1035058.4 | J8: 524 | K8: =$D$21*I8/J8*1000 -> 1287315.3 | M8: =A8 -> 2013 | N8: 1981675.5 | O8: =N8*P8/1000 -> 24828412 | P8: 12529 | Q8: =$D$21*O8/P8*1000 -> 1291468.7
A9: 2014 | B9: =[2]Sheet1!B4 -> 2544638.3 | C9: =B9*D9/1000 -> 1160335.5 | D9: =[2]Sheet1!D4 -> 455.9923 | E9: =$D$21*C9/D9*1000 -> 1658354.7 | G9: =A9 -> 2014 | H9: =[2]Sheet1!E4 -> 1830165.3 | I9: =H9*J9/1000 -> 959131.07 | J9: =[2]Sheet1!G4 -> 524.068 | K9: =$D$21*I9/J9*1000 -> 1192728.7 | M9: =A9 -> 2014 | N9: =[2]Sheet1!H4 -> 2082476.1 | O9: =N9*P9/1000 -> 23133648 | P9: =[2]Sheet1!J4 -> 11108.722 | Q9: =$D$21*O9/P9*1000 -> 1357161.1
A10: 2015 | B10: =[2]Sheet1!B5 -> 3116120.1 | C10: =B10*D10/1000 -> 1223571.8 | D10: =[2]Sheet1!D5 -> 392.65874 | E10: =$D$23*C10/D10*1000 -> 1610404.9 | G10: =A10 -> 2015 | H10: =[2]Sheet1!E5 -> 2267644.7 | I10: =H10*J10/1000 -> 903851.28 | J10: =[2]Sheet1!G5 -> 398.58593 | K10: =$D$23*I10/J10*1000 -> 1171914.5 | M10: =A10 -> 2015 | N10: =[2]Sheet1!H5 -> 2264231.2 | O10: =N10*P10/1000 -> 33250740 | P10: =[2]Sheet1!J5 -> 14685.223 | Q10: =$D$23*O10/P10*1000 -> 1170150.4
A11: 2016 | B11: =[2]Sheet1!B6 -> 3340763.8 | C11: =B11*D11/1000 -> 837201.82 | D11: =[2]Sheet1!D6 -> 250.60192 | E11: =$D$23*C11/D11*1000 -> 1726500.3 | G11: =A11 -> 2016 | H11: =[2]Sheet1!E6 -> 2308238.8 | I11: =H11*J11/1000 -> 687287.92 | J11: =[2]Sheet1!G6 -> 297.75426 | K11: =$D$23*I11/J11*1000 -> 1192893.4 | M11: =A11 -> 2016 | N11: =[2]Sheet1!H6 -> 2307758.8 | O11: =N11*P11/1000 -> 32434603 | P11: =[2]Sheet1!J6 -> 14054.59 | Q11: =$D$23*O11/P11*1000 -> 1192645.3
A12: 2017 | B12: =[2]Sheet1!B7 -> 3380519.2 | C12: =B12*D12/1000 -> 1245110.5 | D12: =[2]Sheet1!D7 -> 368.31931 | E12: =$D$23*C12/D12*1000 -> 1747045.8 | G12: =A12 -> 2017 | H12: =[2]Sheet1!E7 -> 2325895.1 | I12: =H12*J12/1000 -> 1007758.1 | J12: =[2]Sheet1!G7 -> 433.27752 | K12: =$D$23*I12/J12*1000 -> 1202018.2 | M12: =A12 -> 2017 | N12: =[2]Sheet1!H7 -> 2328675.9 | O12: =N12*P12/1000 -> 31826572 | P12: =[2]Sheet1!J7 -> 13667.24 | Q12: =$D$23*O12/P12*1000 -> 1203455.3
A13: 2018 | B13: =[2]Sheet1!B8 -> 3559156.8 | C13: =B13*D13/1000 -> 1351830.6 | D13: =[2]Sheet1!D8 -> 379.81766 | E13: =$D$23*C13/D13*1000 -> 1839365.4 | G13: =A13 -> 2018 | H13: =[2]Sheet1!E8 -> 2402908.4 | I13: =H13*J13/1000 -> 1016995.7 | J13: =[2]Sheet1!G8 -> 423.23533 | K13: =$D$23*I13/J13*1000 -> 1241818.4 | M13: =A13 -> 2018 | N13: =[2]Sheet1!H8 -> 2402840 | O13: =N13*P13/1000 -> 38574916 | P13: =[2]Sheet1!J8 -> 16053.885 | Q13: =$D$23*O13/P13*1000 -> 1241783.1
A14: 2019 | B14: =[2]Sheet1!B9 -> 3881085.7 | C14: =B14*D14/1000 -> 1433975.7 | D14: =[2]Sheet1!D9 -> 369.47799 | E14: =$D$23*C14/D14*1000 -> 2005737.7 | G14: =A14 -> 2019 | H14: =[2]Sheet1!E9 -> 2566968.7 | I14: =H14*J14/1000 -> 1034665 | J14: =[2]Sheet1!G9 -> 403.06879 | K14: =$D$23*I14/J14*1000 -> 1326604.5 | M14: =A14 -> 2019 | N14: =[2]Sheet1!H9 -> 2573854.8 | O14: =N14*P14/1000 -> 39594103 | P14: =[2]Sheet1!J9 -> 15383.192 | Q14: =$D$23*O14/P14*1000 -> 1330163.3
A15: 2020 | B15: =[2]Sheet1!B10 -> 3933314.1 | C15: =B15*D15/1000 -> 1385215.4 | D15: =[2]Sheet1!D10 -> 352.17512 | E15: =$D$23*C15/D15*1000 -> 2032729.2 | G15: =A15 -> 2020 | H15: =[2]Sheet1!E10 -> 2676850.2 | I15: =H15*J15/1000 -> 1047142 | J15: =[2]Sheet1!G10 -> 391.18436 | K15: =$D$23*I15/J15*1000 -> 1383391.1 | M15: =A15 -> 2020 | N15: =[2]Sheet1!H10 -> 2669809.1 | O15: =N15*P15/1000 -> 34948199 | P15: =[2]Sheet1!J10 -> 13090.149 | Q15: =$D$23*O15/P15*1000 -> 1379752.2
A16: 2021 | B16: =[2]Sheet1!B11 -> 3961315.9 | C16: =B16*D16/1000 -> 1363003.2 | D16: =[2]Sheet1!D11 -> 344.0784 | E16: =$D$23*C16/D16*1000 -> 2047200.5 | G16: =A16 -> 2021 | H16: =[2]Sheet1!E11 -> 2745703.4 | I16: =H16*J16/1000 -> 1070011.7 | J16: =[2]Sheet1!G11 -> 389.70405 | K16: =$D$23*I16/J16*1000 -> 1418974.3 | M16: =A16 -> 2021 | N16: =[2]Sheet1!H11 -> 2761113.3 | O16: =N16*P16/1000 -> 41600802 | P16: =[2]Sheet1!J11 -> 15066.677 | Q16: =$D$23*O16/P16*1000 -> 1426938.1
A17: 2022* | B17: =[2]Sheet1!B12 -> 4055822.7 | C17: =B17*D17/1000 -> 1471345.8 | D17: =[2]Sheet1!D12 -> 362.7737 | E17: =$D$23*C17/D17*1000 -> 2096041.4 | G17: =A17 -> 2022* | H17: =[2]Sheet1!E12 -> 2957681.6 | I17: =H17*J17/1000 -> 1207012.1 | J17: =[2]Sheet1!G12 -> 408.09401 | K17: =$D$23*I17/J17*1000 -> 1528524.2 | M17: =A17 -> 2022* | N17: =[2]Sheet1!H12 -> 3007338.4 | O17: =N17*P17/1000 -> 39636298 | P17: =[2]Sheet1!J12 -> 13179.86 | Q17: =$D$23*O17/P17*1000 -> 1554186.8
A18: 2023** | B18: ='[3]LK PDB'!B13 -> 4226858.3 | C18: =B18*D18/1000 -> 1528704.9 | D18: ='[3]LK PDB'!D13 -> 361.66457 | E18: =$D$23*C18/D18*1000 -> 2184432.3 | G18: =A18 -> 2023** | H18: ='[3]LK PDB'!E13 -> 3267035.3 | I18: =H18*J18/1000 -> 1316802.4 | J18: ='[3]LK PDB'!G13 -> 403.05731 | K18: =$D$23*I18/J18*1000 -> 1688397.6 | M18: =A18 -> 2023** | N18: ='[3]LK PDB'!H13 -> 3272877.1 | O18: =N18*P18/1000 -> 38900711 | P18: ='[3]LK PDB'!J13 -> 11885.784 | Q18: =$D$23*O18/P18*1000 -> 1691416.6
A19: 2024*** | B19: ='[3]LK PDB'!B14 -> 4290053.6 | C19: =B19*D19/1000 -> 1535984.9 | D19: ='[3]LK PDB'!D14 -> 358.03396 | E19: =$D$23*C19/D19*1000 -> 2217091.5 | G19: =A19 -> 2024*** | H19: ='[3]LK PDB'!E14 -> 3330614.4 | I19: =H19*J19/1000 -> 1328987.4 | J19: ='[3]LK PDB'!G14 -> 399.02171 | K19: =$D$23*I19/J19*1000 -> 1721255.1 | M19: =A19 -> 2024*** | N19: ='[3]LK PDB'!H14 -> 3334392.2 | O19: =N19*P19/1000 -> 46742999 | P19: ='[3]LK PDB'!J14 -> 14018.447 | Q19: =$D$23*O19/P19*1000 -> 1723207.5
A21: Rasio GOS/Output (SUT 2010) | D21: 0.65170546 | E21: 0.75943138
A23: Rasio GOS/Output (IO 2016) | D23: 0.51679809

Sheet 2012
A1: Daftar Kuotasi Harga SUN Seri Benchmark Harian
A2: Tanggal/ Date | B2: 5 Y | D2: 10 Y | F2: 15 Y | H2: 20 Y
B3: FR0060 | D3: FR0061 | F3: FR0059 | H3: FR0058
B4: 0.0625 | D4: 0.07 | F4: 0.07 | H4: 0.0825
B5: 42840 | D5: 44696 | F5: 46522 | H5: 11855
B6: Harga/ Price | C6: Yield | D6: Harga/ Price | E6: Yield | F6: Harga/ Price | G6: Yield | H6: Harga/ Price | I6: Yield
A7: 40910 | B7: 104.51 | C7: 0.0526 | D7: 107.22 | E7: 0.0606 | F7: 105.81 | G7: 0.064 | H7: 113.01 | I7: 0.0704
A8: 40911 | B8: 104.25 | C8: 0.0532 | D8: 107.3 | E8: 0.0605 | F8: 105.73 | G8: 0.0641 | H8: 112.98 | I8: 0.0705
A9: 40912 | B9: 104.42 | C9: 0.0528 | D9: 107.4 | E9: 0.0603 | F9: 105.73 | G9: 0.0641 | H9: 113.21 | I9: 0.0703
A10: 40913 | B10: 104.23 | C10: 0.0532 | D10: 106.93 | E10: 0.0609 | F10: 105.32 | G10: 0.0645 | H10: 112.65 | I10: 0.0707
A11: 40914 | B11: 104.26 | C11: 0.0532 | D11: 106.28 | E11: 0.0617 | F11: 104.72 | G11: 0.0651 | H11: 111.91 | I11: 0.0714
A12: 40917 | B12: 104.02 | C12: 0.0537 | D12: 106.05 | E12: 0.062 | F12: 104.63 | G12: 0.0652 | H12: 111.81 | I12: 0.0715
A13: 40918 | B13: 103.77 | C13: 0.0542 | D13: 105.97 | E13: 0.0621 | F13: 104.88 | G13: 0.065 | H13: 111.79 | I13: 0.0715
A14: 40919 | B14: 103.9 | C14: 0.0539 | D14: 106.22 | E14: 0.0618 | F14: 105.16 | G14: 0.0647 | H14: 112.18 | I14: 0.0711
A15: 40920 | B15: 103.99 | C15: 0.0537 | D15: 106.13 | E15: 0.0619 | F15: 105.51 | G15: 0.0643 | H15: 112.05 | I15: 0.0713
A16: 40921 | B16: 104.4 | C16: 0.0528 | D16: 106.68 | E16: 0.0612 | F16: 105.55 | G16: 0.0643 | H16: 112.71 | I16: 0.0707
A17: 40924 | B17: 104.24 | C17: 0.0532 | D17: 106.54 | E17: 0.0614 | F17: 105.32 | G17: 0.0645 | H17: 112.32 | I17: 0.071
A18: 40925 | B18: 104.47 | C18: 0.0527 | D18: 107.07 | E18: 0.0607 | F18: 105.5 | G18: 0.0643 | H18: 112.59 | I18: 0.0708
... A252: 41271 | B252: 106.04 | C252: 0.0468 | D252: 113.63 | E252: 0.0515 | F252: 110.8 | G252: 0.0588 | H252: 122.49 | I252: 0.0624

Sheet 2013
A1: Daftar Kuotasi Harga SUN Seri Benchmark Harian
A2: Tanggal/ Date | B2: 5 Y | D2: 10 Y | F2: 15 Y | H2: 20 Y
B3: FR0066 | D3: FR0063 | F3: FR0064 | H3: FR0065
B4: 0.0525 | D4: 0.05625 | F4: 0.06125 | H4: 0.06625
B5: 43235 | D5: 45061 | F5: 46888 | H5: 12220
B6: Harga/ Price | C6: Yield | D6: Harga/ Price | E6: Yield | F6: Harga/ Price | G6: Yield | H6: Harga/ Price | I6: Yield
A7: 41276 | B7: 102.7 | C7: 0.0468 | D7: 104.21 | E7: 0.051 | F7: 103.99 | G7: 0.0574 | H7: 106.3 | I7: 0.0609
A8: 41277 | B8: 102.94 | C8: 0.0463 | D8: 104.48 | E8: 0.0507 | F8: 104.01 | G8: 0.0573 | H8: 106.32 | I8: 0.0609
A9: 41278 | B9: 103.12 | C9: 0.0459 | D9: 104.51 | E9: 0.0506 | F9: 103.96 | G9: 0.0574 | H9: 106.39 | I9: 0.0608
A10: 41281 | B10: 103.36 | C10: 0.0454 | D10: 104.62 | E10: 0.0505 | F10: 103.76 | G10: 0.0576 | H10: 106.04 | I10: 0.0611
A11: 41282 | B11: 103.5 | C11: 0.0451 | D11: 104.6 | E11: 0.0505 | F11: 103.56 | G11: 0.0578 | H11: 106.02 | I11: 0.0611
A12: 41283 | B12: 103.48 | C12: 0.0451 | D12: 104.56 | E12: 0.0506 | F12: 103.38 | G12: 0.0579 | H12: 105.88 | I12: 0.0612
A13: 41284 | B13: 103.14 | C13: 0.0458 | D13: 103.56 | E13: 0.0518 | F13: 102.36 | G13: 0.0589 | H13: 104.52 | I13: 0.0624
A14: 41285 | B14: 102.91 | C14: 0.0463 | D14: 103.24 | E14: 0.0522 | F14: 102.26 | G14: 0.059 | H14: 104.56 | I14: 0.0623
A15: 41288 | B15: 103.02 | C15: 0.0461 | D15: 103.3 | E15: 0.0521 | F15: 102.28 | G15: 0.059 | H15: 103.87 | I15: 0.0629
A16: 41289 | B16: 103.05 | C16: 0.046 | D16: 103.33 | E16: 0.0521 | F16: 102.24 | G16: 0.059 | H16: 104.02 | I16: 0.0628
A17: 41290 | B17: 103.74 | C17: 0.0446 | D17: 103.74 | E17: 0.0516 | F17: 102.19 | G17: 0.0591 | H17: 103.55 | I17: 0.0632
A18: 41291 | B18: 103.81 | C18: 0.0444 | D18: 103.1 | E18: 0.0524 | F18: 102.03 | G18: 0.0593 | H18: 103.32 | I18: 0.0634
... A251: 41639 | B251: 90.28 | C251: 0.0793 | D251: 82.2 | E251: 0.0841 | F251: 77.71 | G251: 0.0891 | H251: 78.72 | I251: 0.0896

Sheet 2014
A1: Daftar Kuotasi Harga SUN Seri Benchmark Harian
A2: Tanggal/ Date | B2: 5 Y | D2: 10 Y | F2: 15 Y | H2: 20 Y
B3: FR0069 | D3: FR0070 | F3: FR0071 | H3: FR0068
B4: 0.07875 | D4: 0.08375 | F4: 0.09 | H4: 0.08375
B5: 43570 | D5: 45366 | F5: 47192 | H5: 49018
B6: Harga/ Price | C6: Yield | D6: Harga/ Price | E6: Yield | F6: Harga/ Price | G6: Yield | H6: Harga/ Price | I6: Yield
A7: 41641 | B7: 100.86 | C7: 0.0767 | D7: 95.37 | E7: 0.0908 | F7: 99.54 | G7: 0.0906 | H7: 99.89 | I7: 0.0839
A8: 41642 | B8: 99.88 | C8: 0.079 | D8: 94.39 | E8: 0.0924 | F8: 98.78 | G8: 0.0915 | H8: 98.73 | I8: 0.0851
A9: 41645 | B9: 97 | C9: 0.086 | D9: 90.93 | E9: 0.098 | F9: 97.64 | G9: 0.093 | H9: 96.22 | I9: 0.0878
A10: 41646 | B10: 97.08 | C10: 0.0858 | D10: 95.21 | E10: 0.0911 | F10: 96.02 | G10: 0.095 | H10: 89.95 | I10: 0.0951
A11: 41647 | B11: 97.46 | C11: 0.0848 | D11: 96.65 | E11: 0.0888 | F11: 96.59 | G11: 0.0943 | H11: 90.2 | I11: 0.0948
A12: 41648 | B12: 97.86 | C12: 0.0839 | D12: 96.24 | E12: 0.0895 | F12: 96.6 | G12: 0.0943 | H12: 90.35 | I12: 0.0946
A13: 41649 | B13: 98.73 | C13: 0.0818 | D13: 97.57 | E13: 0.0874 | F13: 97.47 | G13: 0.0932 | H13: 91.15 | I13: 0.0936
A14: 41652 | B14: 99.47 | C14: 0.08 | D14: 99.09 | E14: 0.0851 | F14: 99.01 | G14: 0.0912 | H14: 92.54 | I14: 0.092
A15: 41654 | B15: 99.76 | C15: 0.0793 | D15: 98.73 | E15: 0.0857 | F15: 98.77 | G15: 0.0915 | H15: 93.58 | I15: 0.0908
A16: 41655 | B16: 99.88 | C16: 0.079 | D16: 99.65 | E16: 0.0843 | F16: 100.01 | G16: 0.09 | H16: 95.09 | I16: 0.0891
A17: 41656 | B17: 100.76 | C17: 0.077 | D17: 100.11 | E17: 0.0836 | F17: 100.73 | G17: 0.0891 | H17: 96.34 | I17: 0.0877
A18: 41659 | B18: 100.48 | C18: 0.0776 | D18: 99.66 | E18: 0.0843 | F18: 100.23 | G18: 0.0897 | H18: 95.95 | I18: 0.0881
... A249: 42004 | B249: 100.62 | C249: 0.077 | D249: 103.62 | E249: 0.0782 | F249: 106.78 | G249: 0.0819 | H249: 100.77 | I249: 0.083

Sheet 2015
A1: Daftar Kuotasi Harga SUN Seri Benchmark Harian
A2: Tanggal/ Date | B2: 5 Y | D2: 10 Y | F2: 15 Y | H2: 20 Y
B3: FR0069 | D3: FR0070 | F3: FR0071 | H3: FR0068
B4: 0.07875 | D4: 0.08375 | F4: 0.09 | H4: 0.08375
B5: 43570 | D5: 45366 | F5: 47192 | H5: 49018
B6: Harga/ Price | C6: Yield | D6: Harga/ Price | E6: Yield | F6: Harga/ Price | G6: Yield | H6: Harga/ Price | I6: Yield
A7: 42006 | B7: 100.97 | C7: 0.0761 | D7: 104.4 | E7: 0.077 | F7: 107.68 | G7: 0.0808 | H7: 101.45 | I7: 0.0823
A8: 42009 | B8: 100.58 | C8: 0.0771 | D8: 102.99 | E8: 0.0791 | F8: 106.89 | G8: 0.0817 | H8: 100.63 | I8: 0.0831
A9: 42010 | B9: 100.41 | C9: 0.0776 | D9: 102.53 | E9: 0.0798 | F9: 106.06 | G9: 0.0827 | H9: 99.86 | I9: 0.0839
A10: 42011 | B10: 101.08 | C10: 0.0757 | D10: 102.91 | E10: 0.0793 | F10: 106.65 | G10: 0.082 | H10: 99.96 | I10: 0.0838
A11: 42012 | B11: 101.3 | C11: 0.0751 | D11: 103.47 | E11: 0.0784 | F11: 107.25 | G11: 0.0813 | H11: 100.57 | I11: 0.0832
A12: 42013 | B12: 101.67 | C12: 0.0741 | D12: 104.72 | E12: 0.0765 | F12: 108.74 | G12: 0.0796 | H12: 102.76 | I12: 0.0809
A13: 42016 | B13: 101.76 | C13: 0.0739 | D13: 104.73 | E13: 0.0765 | F13: 108.76 | G13: 0.0796 | H13: 103.03 | I13: 0.0807
A14: 42017 | B14: 101.64 | C14: 0.0742 | D14: 104.32 | E14: 0.0771 | F14: 108.34 | G14: 0.0801 | H14: 102.38 | I14: 0.0813
A15: 42018 | B15: 101.89 | C15: 0.0735 | D15: 104.97 | E15: 0.0761 | F15: 109.14 | G15: 0.0792 | H15: 103.07 | I15: 0.0806
A16: 42019 | B16: 101.82 | C16: 0.0737 | D16: 104.67 | E16: 0.0766 | F16: 108.67 | G16: 0.0797 | H16: 102.58 | I16: 0.0811
A17: 42020 | B17: 102.14 | C17: 0.0728 | D17: 105.34 | E17: 0.0756 | F17: 109.34 | G17: 0.079 | H17: 103.37 | I17: 0.0803
A18: 42023 | B18: 102.02 | C18: 0.0731 | D18: 105.37 | E18: 0.0755 | F18: 109.41 | G18: 0.0789 | H18: 103.41 | I18: 0.0803
... A248: 42369 | B248: 97.44 | C248: 0.0879 | D248: 97.45 | E248: 0.0882 | F248: 100.43 | G248: 0.0895 | H248: 93.89 | I248: 0.0907

Sheet 2016
A1: Daftar Kuotasi Harga SUN Seri Benchmark Harian
A2: Tanggal/ Date | B2: 5 Y | D2: 10 Y | F2: 15 Y | H2: 20 Y
B3: FR0053 | D3: FR0056 | F3: FR0073 | H3: FR0072
B4: 0.0825 | D4: 0.08375 | F4: 0.0875 | H4: 0.0825
B5: 44392 | D5: 46280 | F5: 47983 | H5: 49810
B6: Harga/ Price | C6: Yield | D6: Harga/ Price | E6: Yield | F6: Harga/ Price | G6: Yield | H6: Harga/ Price | I6: Yield
A7: 42373 | B7: 97.91 | C7: 0.0874 | D7: 97.76 | E7: 0.087 | F7: 98.49 | G7: 0.0894 | H7: 93.89 | I7: 0.0891
A8: 42374 | B8: 97.51 | C8: 0.0883 | D8: 97.25 | E8: 0.0878 | F8: 98.25 | G8: 0.0897 | H8: 92.68 | I8: 0.0905
A9: 42375 | B9: 97.62 | C9: 0.0881 | D9: 97.14 | E9: 0.088 | F9: 98.47 | G9: 0.0894 | H9: 93.05 | I9: 0.09
A10: 42376 | B10: 97.49 | C10: 0.0884 | D10: 97.2 | E10: 0.0879 | F10: 98.16 | G10: 0.0898 | H10: 93.36 | I10: 0.0897
A11: 42377 | B11: 97.69 | C11: 0.0879 | D11: 97.74 | E11: 0.0871 | F11: 98.79 | G11: 0.089 | H11: 93.55 | I11: 0.0895
A12: 42380 | B12: 97.52 | C12: 0.0883 | D12: 97.27 | E12: 0.0878 | F12: 98.74 | G12: 0.089 | H12: 93.72 | I12: 0.0893
A13: 42381 | B13: 98.46 | C13: 0.0861 | D13: 98.24 | E13: 0.0863 | F13: 99.29 | G13: 0.0884 | H13: 94.38 | I13: 0.0885
A14: 42382 | B14: 99.02 | C14: 0.0848 | D14: 98.85 | E14: 0.0854 | F14: 100.77 | G14: 0.0866 | H14: 95.01 | I14: 0.0878
A15: 42383 | B15: 99.02 | C15: 0.0848 | D15: 98.85 | E15: 0.0854 | F15: 100.77 | G15: 0.0866 | H15: 95.01 | I15: 0.0878
A16: 42384 | B16: 99.19 | C16: 0.0844 | D16: 99.24 | E16: 0.0849 | F16: 101.1 | G16: 0.0862 | H16: 95.85 | I16: 0.0869
A17: 42387 | B17: 98.79 | C17: 0.0854 | D17: 98.52 | E17: 0.0859 | F17: 99.95 | G17: 0.0876 | H17: 95.29 | I17: 0.0875
A18: 42388 | B18: 98.78 | C18: 0.0854 | D18: 98.43 | E18: 0.0861 | F18: 99.49 | G18: 0.0881 | H18: 94.84 | I18: 0.088
... A252: 42734 | B252: 102.61 | C252: 0.0756 | D252: 102.59 | E252: 0.0799 | F252: 104.88 | G252: 0.0817 | H252: 100.7 | I252: 0.0818

Sheet 2017
A1: Daftar Kuotasi Harga SUN Seri Benchmark Harian
A2: Tanggal/ Date | B2: 5 Y | D2: 10 Y | F2: 15 Y | H2: 20 Y
B3: FR0061 | D3: FR0059 | F3: FR0074 | H3: FR0072
B4: 0.07 | D4: 0.07 | F4: 0.075 | H4: 0.0825
B5: 44696 | D5: 46522 | F5: 48441 | H5: 49810
B6: Harga/ Price | C6: Yield | D6: Harga/ Price | E6: Yield | F6: Harga/ Price | G6: Yield | H6: Harga/ Price | I6: Yield
A7: 42738 | B7: 97.66 | C7: 0.0754 | D7: 94.53 | E7: 0.0778 | F7: 97.74 | G7: 0.0776 | H7: 100.87 | I7: 0.0816
A8: 42739 | B8: 97.78 | C8: 0.0751 | D8: 94.88 | E8: 0.0773 | F8: 97.8 | G8: 0.0775 | H8: 101.33 | I8: 0.0812
A9: 42740 | B9: 98.32 | C9: 0.0739 | D9: 96.08 | E9: 0.0756 | F9: 98.7 | G9: 0.0765 | H9: 102.4 | I9: 0.0801
A10: 42741 | B10: 98.43 | C10: 0.0736 | D10: 95.99 | E10: 0.0757 | F10: 98.55 | G10: 0.0766 | H10: 102.15 | I10: 0.0803
A11: 42744 | B11: 98.39 | C11: 0.0737 | D11: 95.89 | E11: 0.0758 | F11: 98.3 | G11: 0.0769 | H11: 101.82 | I11: 0.0807
A12: 42745 | B12: 98.73 | C12: 0.0729 | D12: 95.99 | E12: 0.0757 | F12: 98.38 | G12: 0.0768 | H12: 101.87 | I12: 0.0806
A13: 42746 | B13: 98.85 | C13: 0.0727 | D13: 96.09 | E13: 0.0755 | F13: 98.32 | G13: 0.0769 | H13: 101.92 | I13: 0.0806
A14: 42747 | B14: 98.94 | C14: 0.0724 | D14: 96.15 | E14: 0.0755 | F14: 98.31 | G14: 0.0769 | H14: 102.02 | I14: 0.0805
A15: 42748 | B15: 99.14 | C15: 0.072 | D15: 96.94 | E15: 0.0743 | F15: 98.43 | G15: 0.0768 | H15: 102.78 | I15: 0.0797
A16: 42751 | B16: 99.1 | C16: 0.0721 | D16: 96.62 | E16: 0.0748 | F16: 98.32 | G16: 0.0769 | H16: 102.6 | I16: 0.0799
A17: 42752 | B17: 99.1 | C17: 0.0721 | D17: 96.55 | E17: 0.0749 | F17: 98.3 | G17: 0.0769 | H17: 102.58 | I17: 0.0799
A18: 42753 | B18: 99.33 | C18: 0.0716 | D18: 96.57 | E18: 0.0749 | F18: 97.77 | G18: 0.0775 | H18: 102.66 | I18: 0.0798
... A93: 42867 | B93: 100.67 | C93: 0.0684 | D93: 98.94 | E93: 0.0716 | F93: 98.5 | G93: 0.0767 | H93: 103.45 | I93: 0.079
A94: 42870
A95: 42871 | B95: 101.23 | C95: 0.0671 | D95: 99.99 | E95: 0.0701 | F95: 99.97 | G95: 0.0751 | H95: 105 | I95: 0.0775
A96: 42872 | B96: 101.22 | C96: 0.0671 | D96: 99.97 | E96: 0.0701 | F96: 100.07 | G96: 0.075 | H96: 105 | I96: 0.0775
A97: 42873 | B97: 101.17 | C97: 0.0672 | D97: 99.71 | E97: 0.0705 | F97: 99.61 | G97: 0.0755 | H97: 104.67 | I97: 0.0778
A98: 42874 | B98: 100.99 | C98: 0.0677 | D98: 99.18 | E98: 0.0712 | F98: 98.99 | G98: 0.0762 | H98: 103.98 | I98: 0.0785
A99: 42877 | B99: 101.52 | C99: 0.0664 | D99: 100.53 | E99: 0.0693 | F99: 101.08 | G99: 0.0738 | H99: 106.57 | I99: 0.076
A100: 42878 | B100: 101.45 | C100: 0.0666 | D100: 100.46 | E100: 0.0694 | F100: 101.12 | G100: 0.0738 | H100: 106.54 | I100: 0.076
A101: 42879 | B101: 101.42 | C101: 0.0666 | D101: 100.62 | E101: 0.0692 | F101: 101.46 | G101: 0.0734 | H101: 106.68 | I101: 0.0758
A102: 42881 | B102: 101.48 | C102: 0.0665 | D102: 100.61 | E102: 0.0692 | F102: 101.35 | G102: 0.0735 | H102: 106.56 | I102: 0.076
A103: 42884 | B103: 101.49 | C103: 0.0665 | D103: 100.6 | E103: 0.0692 | F103: 101.43 | G103: 0.0735 | H103: 106.71 | I103: 0.0758
A104: 42885 | B104: 101.35 | C104: 0.0668 | D104: 100.48 | E104: 0.0694 | F104: 101.26 | G104: 0.0736 | H104: 106.53 | I104: 0.076
A105: 42886 | B105: 101.33 | C105: 0.0668 | D105: 100.49 | E105: 0.0694 | F105: 101.26 | G105: 0.0736 | H105: 106.59 | I105: 0.0759
A106: 42888 | B106: 101.37 | C106: 0.0667 | D106: 100.48 | E106: 0.0694 | F106: 101.25 | G106: 0.0737 | H106: 106.65 | I106: 0.0759
... A244: 43098 | B244: 104.14 | C244: 0.0591 | D244: 105.03 | E244: 0.0629 | F244: 105.54 | G244: 0.069 | H244: 111.73 | I244: 0.071

Sheet 2018
A1: Daftar Kuotasi Harga SUN Seri Benchmark Harian
A2: Tanggal/ Date | B2: 5 Y | D2: 10 Y | F2: 15 Y | H2: 20 Y
B3: FR0063 | D3: FR0064 | F3: FR0065 | H3: FR0075
B4: 0.05625 | D4: 0.06125 | F4: 0.06625 | H4: 0.075
B5: 45061 | D5: 46888 | F5: 48714 | H5: 50540
B6: Harga/ Price | C6: Yield | D6: Harga/ Price | E6: Yield | F6: Harga/ Price | G6: Yield | H6: Harga/ Price | I6: Yield
A7: 43102 | B7: 98.67 | C7: 0.0592 | D7: 98.02 | E7: 0.0639 | F7: 98.06 | G7: 0.0683 | H7: 105 | I7: 0.0704
A8: 43103 | B8: 98.83 | C8: 0.0589 | D8: 98.89 | E8: 0.0628 | F8: 98.77 | G8: 0.0676 | H8: 105.23 | I8: 0.0702
A9: 43104 | B9: 100.04 | C9: 0.0562 | D9: 100.35 | E9: 0.0608 | F9: 100.28 | G9: 0.066 | H9: 106.1 | I9: 0.0694
A10: 43105 | B10: 100.42 | C10: 0.0554 | D10: 100.52 | E10: 0.0606 | F10: 100.58 | G10: 0.0657 | H10: 107.09 | I10: 0.0685
A11: 43108 | B11: 100.59 | C11: 0.055 | D11: 100.61 | E11: 0.0605 | F11: 100.71 | G11: 0.0655 | H11: 107.26 | I11: 0.0684
A12: 43109 | B12: 100.43 | C12: 0.0553 | D12: 100.67 | E12: 0.0604 | F12: 100.76 | G12: 0.0655 | H12: 107.66 | I12: 0.068
A13: 43110 | B13: 99.9 | C13: 0.0565 | D13: 99.83 | E13: 0.0615 | F13: 99.95 | G13: 0.0663 | H13: 106.37 | I13: 0.0692
A14: 43111 | B14: 100 | C14: 0.0563 | D14: 100.08 | E14: 0.0612 | F14: 100.14 | G14: 0.0661 | H14: 106.1 | I14: 0.0694
A15: 43112 | B15: 100.4 | C15: 0.0554 | D15: 100.75 | E15: 0.0603 | F15: 100.61 | G15: 0.0657 | H15: 106.81 | I15: 0.0688
A16: 43115 | B16: 100.37 | C16: 0.0555 | D16: 100.54 | E16: 0.0606 | F16: 100.52 | G16: 0.0657 | H16: 106.59 | I16: 0.069
A17: 43116 | B17: 100.38 | C17: 0.0554 | D17: 100.55 | E17: 0.0606 | F17: 100.39 | G17: 0.0659 | H17: 106.66 | I17: 0.0689
A18: 43117 | B18: 100.44 | C18: 0.0553 | D18: 100.55 | E18: 0.0606 | F18: 100.67 | G18: 0.0656 | H18: 107 | I18: 0.0686
... A243: 43465 | B243: 92.24 | C243: 0.0776 | D243: 87.98 | E243: 0.0797 | F243: 87.09 | G243: 0.0817 | H243: 91.88 | I243: 0.0836

Sheet 2019
A2: Tanggal/ Date | B2: 5 Y | D2: 10 Y | F2: 15 Y | H2: 20 Y
B3: FR0077 | D3: FR0078 | F3: FR0068 | H3: FR0079
B4: 0.08125 | D4: 0.0825 | F4: 0.08375 | H4: 0.08375
B5: 45427 | D5: 47253 | F5: 12493 | H5: 50875
B6: Harga/ Price | C6: Yield | D6: Harga/ Price | E6: Yield | F6: Harga/ Price | G6: Yield | H6: Harga/ Price | I6: Yield
A7: 43467 | B7: 101.15 | C7: 0.0786 | D7: 102.13 | E7: 0.0795 | F7: 100.93 | G7: 0.0827
A8: 43468 | B8: 100.75 | C8: 0.0795 | D8: 101.38 | E8: 0.0805 | F8: 100.31 | G8: 0.0834
A9: 43469 | B9: 100.92 | C9: 0.0791 | D9: 101.9 | E9: 0.0798 | F9: 100.43 | G9: 0.0833
A10: 43472 | B10: 101.58 | C10: 0.0776 | D10: 102.82 | E10: 0.0785 | F10: 101.38 | G10: 0.0822 | H10: 100.45 | I10: 0.0833
A11: 43473 | B11: 101.68 | C11: 0.0774 | D11: 103.14 | E11: 0.078 | F11: 102.03 | G11: 0.0814 | H11: 101.3 | I11: 0.0824
A12: 43474 | B12: 101.33 | C12: 0.0782 | D12: 102.52 | E12: 0.0789 | F12: 101.25 | G12: 0.0823 | H12: 100.63 | I12: 0.0831
A13: 43475 | B13: 101.38 | C13: 0.0781 | D13: 102.45 | E13: 0.079 | F13: 100.93 | G13: 0.0827 | H13: 100.61 | I13: 0.0832
A14: 43476 | B14: 101.11 | C14: 0.0787 | D14: 102.09 | E14: 0.0795 | F14: 100.45 | G14: 0.0832 | H14: 100.15 | I14: 0.0836
A15: 43479 | B15: 101.14 | C15: 0.0786 | D15: 102.16 | E15: 0.0794 | F15: 100.52 | G15: 0.0832 | H15: 100.16 | I15: 0.0836
A16: 43480 | B16: 100.84 | C16: 0.0793 | D16: 101.74 | E16: 0.08 | F16: 100.01 | G16: 0.0838 | H16: 99.53 | I16: 0.0843
A17: 43481 | B17: 100.7 | C17: 0.0796 | D17: 101.37 | E17: 0.0805 | F17: 99.26 | G17: 0.0847 | H17: 99.04 | I17: 0.0848
A18: 43482 | B18: 100.72 | C18: 0.0796 | D18: 101.42 | E18: 0.0805 | F18: 99.21 | G18: 0.0847 | H18: 98.8 | I18: 0.085
A19: 43483 | B19: 100.68 | C19: 0.0797 | D19: 100.97 | E19: 0.0811 | F19: 98.86 | G19: 0.0851 | H19: 98.37 | I19: 0.0855
A20: 43486 | B20: 100.69 | C20: 0.0796 | D20: 101.34 | E20: 0.0806 | F20: 98.7 | G20: 0.0853 | H20: 98.5 | I20: 0.0853
A21: 43487 | B21: 100.7 | C21: 0.0796 | D21: 101.13 | E21: 0.0809 | F21: 98.76 | G21: 0.0853 | H21: 98.52 | I21: 0.0853
... A251: 43830 | B251: 106.61 | C251: 0.0637 | D251: 108.32 | E251: 0.0703 | F251: 107.15 | G251: 0.0755 | H251: 107.3 | I251: 0.0765

Sheet 2020
A2: Tanggal/ Date | B2: 5 Y | D2: 10 Y | F2: 15 Y | H2: 20 Y
B3: FR0081 | D3: FR0082 | F3: FR0080 | H3: FR0083
B4: 0.065 | D4: 0.07 | F4: 0.075 | H4: 0.075
B5: 45823 | D5: 47741 | F5: 49475 | H5: 51241
B6: Harga/ Price | C6: Yield | D6: Harga/ Price | E6: Yield | F6: Harga/ Price | G6: Yield | H6: Harga/ Price | I6: Yield
A7: 43832 | B7: 100.485 | C7: 0.064 | D7: 99.47 | E7: 0.0707 | F7: 100.48 | G7: 0.0745 | H7: 99.64 | I7: 0.0754
A8: 43833 | B8: 100.61125 | C8: 0.0637 | D8: 99.69 | E8: 0.0704 | F8: 100.88 | G8: 0.0741 | H8: 99.86 | I8: 0.0752
A9: 43836 | B9: 100.25875 | C9: 0.0645 | D9: 99 | E9: 0.0714 | F9: 100.39 | G9: 0.0746 | H9: 99.28 | I9: 0.0757
A10: 43837 | B10: 100.4775 | C10: 0.064 | D10: 99.24 | E10: 0.0711 | F10: 100.59 | G10: 0.0744 | H10: 99.65 | I10: 0.0754
A11: 43838 | B11: 100.515 | C11: 0.0639 | D11: 99.46 | E11: 0.0708 | F11: 100.39 | G11: 0.0746 | H11: 99.65 | I11: 0.0754
A12: 43839 | B12: 100.935 | C12: 0.063 | D12: 100.06 | E12: 0.07 | F12: 100.92 | G12: 0.074 | H12: 99.81 | I12: 0.0752
A13: 43840 | B13: 100.515 | C13: 0.0639 | D13: 99.46 | E13: 0.0708 | F13: 100.39 | G13: 0.0746 | H13: 99.65 | I13: 0.0754
A14: 43843 | B14: 101.70875 | C14: 0.0613 | D14: 101.06 | E14: 0.0686 | F14: 102.05 | G14: 0.0728 | H14: 100.69 | I14: 0.0744
A15: 43844 | B15: 101.38125 | C15: 0.062 | D15: 101.06 | E15: 0.0686 | F15: 101.68 | G15: 0.0732 | H15: 100.59 | I15: 0.0745
A16: 43845 | B16: 101.38125 | C16: 0.062 | D16: 100.96 | E16: 0.0687 | F16: 101.61 | G16: 0.0733 | H16: 100.49 | I16: 0.0746
A17: 43846 | B17: 101.54875 | C17: 0.0616 | D17: 101.29 | E17: 0.0683 | F17: 101.66 | G17: 0.0732 | H17: 100.65 | I17: 0.0744
A18: 43847 | B18: 101.62625 | C18: 0.0615 | D18: 101.39 | E18: 0.0682 | F18: 101.62 | G18: 0.0733 | H18: 100.73 | I18: 0.0743
... A248: 44195 | B248: 105.41125 | C248: 0.0513 | D248: 108.34 | E248: 0.0586 | F248: 111.1 | G248: 0.0632 | H248: 111.13 | I248: 0.0648

Sheet 2021
A2: Tanggal/ Date | B2: 5 Y | D2: 10 Y | F2: 15 Y | H2: 20 Y
B3: FR0086 | D3: FR0087 | F3: FR0088 | H3: FR0083
B4: 0.055 | D4: 0.065 | F4: 0.0625 | H4: 0.075
B5: 46127 | D5: 47894 | F5: 49841 | H5: 51241
B6: Harga/ Price | C6: Yield | D6: Harga/ Price | E6: Yield | F6: Harga/ Price | G6: Yield | H6: Harga/ Price | I6: Yield
A7: 44200 | B7: 101.77 | C7: 0.0512 | D7: 104.76 | E7: 0.0587 | F7: NA | G7: NA | H7: 110.9 | I7: 0.065
A8: 44201 | B8: 101.69 | C8: 0.0513 | D8: 104.54 | E8: 0.059 | F8: NA | G8: NA | H8: 110.73 | I8: 0.0652
A9: 44202 | B9: 101.84 | C9: 0.051 | D9: 104.47 | E9: 0.0591 | F9: NA | G9: NA | H9: 110.24 | I9: 0.0656
A10: 44203 | B10: 101.72 | C10: 0.0513 | D10: 104.19 | E10: 0.0595 | F10: NA | G10: NA | H10: 109.78 | I10: 0.066
A11: 44204 | B11: 101.59 | C11: 0.0515 | D11: 102.87 | E11: 0.0612 | F11: 100.4 | G11: 0.0621 | H11: 109.34 | I11: 0.0664
A12: 44207 | B12: 101.44 | C12: 0.0519 | D12: 102.72 | E12: 0.0614 | F12: 101.33 | G12: 0.0612 | H12: 108.55 | I12: 0.0671
A13: 44208 | B13: 101.4 | C13: 0.0519 | D13: 102.19 | E13: 0.0621 | F13: 101.04 | G13: 0.0615 | H13: 108.18 | I13: 0.0674
A14: 44209 | B14: 101.29 | C14: 0.0522 | D14: 102.41 | E14: 0.0618 | F14: 100.99 | G14: 0.0615 | H14: 107.66 | I14: 0.0679
A15: 44210 | B15: 101.35 | C15: 0.0521 | D15: 102.43 | E15: 0.0618 | F15: 101.2 | G15: 0.0613 | H15: 107.36 | I15: 0.0681
A16: 44214 | B16: 101.49 | C16: 0.0517 | D16: 102.48 | E16: 0.0617 | F16: 101.34 | G16: 0.0612 | H16: 107.22 | I16: 0.0682
A17: 44215 | B17: 101.33 | C17: 0.0521 | D17: 102.26 | E17: 0.062 | F17: 101.3 | G17: 0.0612 | H17: 107.17 | I17: 0.0683
A18: 44216 | B18: 101.33 | C18: 0.0521 | D18: 101.99 | E18: 0.0624 | F18: 100.35 | G18: 0.0622 | H18: 106.96 | I18: 0.0685
A19: 44217 | B19: 101.12 | C19: 0.0526 | D19: 101.46 | E19: 0.0631 | F19: 99.99 | G19: 0.0626 | H19: 106.63 | I19: 0.0688
A20: 44218 | B20: 101.35 | C20: 0.052 | D20: 102.01 | E20: 0.0623 | F20: 100.27 | G20: 0.0623 | H20: 107.01 | I20: 0.0684
A21: 44221 | B21: 101.25 | C21: 0.0523 | D21: 101.79 | E21: 0.0626 | F21: 100.11 | G21: 0.0624 | H21: 106.64 | I21: 0.0688
A22: 44222 | B22: 101.69 | C22: 0.0513 | D22: 101.88 | E22: 0.0625 | F22: 100.12 | G22: 0.0624 | H22: 106.94 | I22: 0.0685
... A252: 44560 | B252: 101.63 | C252: 0.0507 | D252: 101.08 | E252: 0.0635 | F252: 100.27 | G252: 0.0623 | H252: 104.64 | I252: 0.0705

Sheet 2022
A2: Tanggal/ Date | B2: 5 Y | D2: 10 Y | F2: 15 Y | H2: 20 Y
B3: FR0090 | D3: FR0091 | F3: FR0093 | H3: FR0092
B4: 0.05125 | D4: 0.06375 | F4: 0.06375 | H4: 0.07125
B5: 46492 | D5: 48319 | F5: 50236 | H5: 52032
B6: Harga/ Price | C6: Yield | D6: Harga/ Price | E6: Yield | F6: Harga/ Price | G6: Yield | H6: Harga/ Price | I6: Yield
A7: 44564 | B7: 100.76 | C7: 0.0496 | D7: 100.83 | E7: 0.0627 | F7: NA | G7: NA | H7: 102.72 | I7: 0.0688
A8: 44565 | B8: 100.58 | C8: 0.05 | D8: 100.72 | E8: 0.0628 | F8: NA | G8: NA | H8: 102.51 | I8: 0.069
A9: 44566 | B9: 100.52 | C9: 0.0501 | D9: 100.49 | E9: 0.0631 | F9: NA | G9: NA | H9: 102.54 | I9: 0.069
A10: 44567 | B10: 100.52 | C10: 0.0501 | D10: 100.49 | E10: 0.0631 | F10: NA | G10: NA | H10: 102.54 | I10: 0.069
A11: 44568 | B11: 99.73 | C11: 0.0519 | D11: 99.51 | E11: 0.0644 | F11: 99.95 | G11: 0.0638 | H11: 101.89 | I11: 0.0695
A12: 44571 | B12: 99.48 | C12: 0.0524 | D12: 99.47 | E12: 0.0645 | F12: 99.87 | G12: 0.0639 | H12: 101.43 | I12: 0.07
A13: 44572 | B13: 99.41 | C13: 0.0526 | D13: 99.52 | E13: 0.0644 | F13: 99.81 | G13: 0.064 | H13: 101.19 | I13: 0.0702
A14: 44573 | B14: 99.65 | C14: 0.0521 | D14: 99.86 | E14: 0.064 | F14: 100.01 | G14: 0.0638 | H14: 101.11 | I14: 0.0703
A15: 44574 | B15: 99.63 | C15: 0.0521 | D15: 99.87 | E15: 0.064 | F15: 99.91 | G15: 0.0639 | H15: 100.56 | I15: 0.0708
A16: 44575 | B16: 99.79 | C16: 0.0517 | D16: 100 | E16: 0.0638 | F16: 99.97 | G16: 0.0638 | H16: 101.01 | I16: 0.0704
A17: 44578 | B17: 99.71 | C17: 0.0519 | D17: 100.04 | E17: 0.0637 | F17: 99.97 | G17: 0.0638 | H17: 101.18 | I17: 0.0702
A18: 44579 | B18: 99.74 | C18: 0.0519 | D18: 99.96 | E18: 0.0638 | F18: 99.85 | G18: 0.064 | H18: 101.13 | I18: 0.0702
A19: 44580 | B19: 99.68 | C19: 0.052 | D19: 99.76 | E19: 0.0641 | F19: 99.7 | G19: 0.0641 | H19: 101.24 | I19: 0.0701
A20: 44581 | B20: 99.61 | C20: 0.0521 | D20: 99.72 | E20: 0.0642 | F20: 99.67 | G20: 0.0641 | H20: 101.3 | I20: 0.0701
A21: 44582 | B21: 99.57 | C21: 0.0522 | D21: 99.77 | E21: 0.0641 | F21: 99.66 | G21: 0.0641 | H21: 101.52 | I21: 0.0699
A22: 44585 | B22: 99.63 | C22: 0.0521 | D22: 99.75 | E22: 0.0641 | F22: 99.69 | G22: 0.0641 | H22: 101.7 | I22: 0.0697
... A252: 44925 | B252: 96.5 | C252: 0.0607 | D252: 96.63 | E252: 0.0687 | F252: 96.62 | G252: 0.0675 | H252: 100.39 | I252: 0.0709

Sheet 2023
A2: Tanggal/ Date | B2: 5 Y | D2: 10 Y | F2: 15 Y | H2: 20 Y
B3: FR0095 | D3: FR0096 | F3: FR0098 | H3: FR0097
B4: 0.06375 | D4: 0.07 | F4: 0.07125 | H4: 0.07125
B5: 46980 | D5: 48625 | F5: 50571 | H5: 52397
B6: Harga/ Price | C6: Yield | D6: Harga/ Price | E6: Yield | F6: Harga/ Price | G6: Yield | H6: Harga/ Price | I6: Yield
A7: 44928 | B7: 99.18 | C7: 0.0655 | D7: 100.26 | E7: 0.0697 | F7: 100.89 | G7: 0.0703 | H7: 100.4 | I7: 0.0709
A8: 44929 | B8: 98.99 | C8: 0.066 | D8: 99.85 | E8: 0.0702 | F8: 100.37 | G8: 0.0709 | H8: 100.02 | I8: 0.0713
A9: 44930 | B9: 98.79 | C9: 0.0664 | D9: 99.57 | E9: 0.0706 | F9: 99.82 | G9: 0.0715 | H9: 99.59 | I9: 0.0717
A10: 44931 | B10: 99.01 | C10: 0.0659 | D10: 99.9 | E10: 0.0702 | F10: 100.2 | G10: 0.0711 | H10: 100.12 | I10: 0.0712
A11: 44932 | B11: 99.05 | C11: 0.0658 | D11: 100.06 | E11: 0.07 | F11: 100.16 | G11: 0.0711 | H11: 100.1 | I11: 0.0712
A12: 44935 | B12: 99.36 | C12: 0.0652 | D12: 100.54 | E12: 0.0693 | F12: 100.58 | G12: 0.0707 | H12: 100.69 | I12: 0.0706
A13: 44936 | B13: 99.55 | C13: 0.0648 | D13: 100.84 | E13: 0.0689 | F13: 100.8 | G13: 0.0704 | H13: 100.71 | I13: 0.0706
A14: 44937 | B14: 99.7 | C14: 0.0644 | D14: 101.09 | E14: 0.0685 | F14: 101.42 | G14: 0.0698 | H14: 101.61 | I14: 0.0698
A15: 44938 | B15: 99.92 | C15: 0.064 | D15: 101.59 | E15: 0.0678 | F15: 102.55 | G15: 0.0686 | H15: 102.9 | I15: 0.0686
A16: 44939 | B16: 100.18 | C16: 0.0634 | D16: 102.38 | E16: 0.0668 | F16: 104.02 | G16: 0.0671 | H16: 104.32 | I16: 0.0674
A17: 44942 | B17: 99.86 | C17: 0.0641 | D17: 101.7 | E17: 0.0677 | F17: 103.46 | G17: 0.0676 | H17: 103.75 | I17: 0.0679
A18: 44943 | B18: 99.59 | C18: 0.0647 | D18: 101.21 | E18: 0.0684 | F18: 102.51 | G18: 0.0686 | H18: 102.6 | I18: 0.0689
... A178: 45191 | B178: 99.89 | C178: 0.064 | D178: 101.68 | E178: 0.0676 | F178: 101.94 | G178: 0.0692 | H178: 101.48 | I178: 0.0699
A179: 45194 | B179: 100.07 | C179: 0.0636 | D179: 102 | E179: 0.0671 | F179: 102.82 | G179: 0.0682 | H179: 102.65 | I179: 0.0689 | J179: =AVERAGE(I174,I155) -> 0.0689
A180: 45195 | B180: 99.78 | C180: 0.0643 | D180: 101.37 | E180: 0.068 | F180: 101.53 | G180: 0.0696 | H180: 101.56 | I180: 0.0698 | J180: =AVERAGE(I175,I178) -> 0.06985
A181: 45196 | B181: 99.56 | C181: 0.0648 | D181: 100.94 | E181: 0.0687 | F181: 101.33 | G181: 0.0698 | H181: 101.21 | I181: 0.0701
A182: 45198 | B182: 99.46 | C182: 0.0651 | D182: 100.83 | E182: 0.0688 | F182: 101.15 | G182: 0.07 | H182: 101.1 | I182: 0.0702
A183: 45201 | B183: 99.21 | C183: 0.0657 | D183: 100.36 | E183: 0.0695 | F183: 100.82 | G183: 0.0704 | H183: 100.76 | I183: 0.0706
A184: 45202 | B184: 98.85 | C184: 0.0666 | D184: 99.78 | E184: 0.0704 | F184: 99.92 | G184: 0.0714 | H184: 99.95 | I184: 0.0713
A185: 45203 | B185: 98.12 | C185: 0.0684 | D185: 99.3 | E185: 0.0711 | F185: 98.84 | G185: 0.0726 | H185: 98.73 | I185: 0.0725
A186: 45204 | B186: 98.32 | C186: 0.0679 | D186: 100.04 | E186: 0.07 | F186: 99.47 | G186: 0.0719 | H186: 99.21 | I186: 0.072
A187: 45205 | B187: 98.25 | C187: 0.0681 | D187: 100.15 | E187: 0.0698 | F187: 99.51 | G187: 0.0718 | H187: 99.42 | I187: 0.0718
A188: 45208 | B188: 98.38 | C188: 0.0677 | D188: 99.98 | E188: 0.0701 | F188: 99.34 | G188: 0.072 | H188: 100.3 | I188: 0.071
A189: 45209 | B189: 98.66 | C189: 0.0671 | D189: 100.54 | E189: 0.0692 | F189: 100.36 | G189: 0.0709 | H189: 101.17 | I189: 0.0702
A190: 45210 | B190: 98.8 | C190: 0.0667 | D190: 100.94 | E190: 0.0687 | F190: 100.43 | G190: 0.0708 | H190: 100.99 | I190: 0.0704
A191: 45211 | B191: 99.26 | C191: 0.0656 | D191: 101.67 | E191: 0.0676 | F191: 101.44 | G191: 0.0697 | H191: 101.18 | I191: 0.0702
A192: 45212 | B192: 99.01 | C192: 0.0662 | D192: 101.34 | E192: 0.0681 | F192: 100.81 | G192: 0.0704 | H192: 100.81 | I192: 0.0705
... A245: 45289 | B245: 99.83 | C245: 0.0642 | D245: 103.71 | E245: 0.0646 | F245: 104.72 | G245: 0.0662 | H245: 103.86 | I245: 0.0677
I247: =AVERAGE(I7:I245) -> 0.068520502

Sheet 2024
A2: Tanggal/ Date | B2: 5 Y | D2: 10 Y | F2: 15 Y | H2: 20 Y
B3: FR0101 | D3: FR0100 | F3: FR0098 | H3: FR0097
B4: 0.06875 | D4: 0.06625 | F4: 0.07125 | H4: 0.07125
B5: 47223 | D5: 48990 | F5: 50571 | H5: 52397
B6: Harga/ Price | C6: Yield | D6: Harga/ Price | E6: Yield | F6: Harga/ Price | G6: Yield | H6: Harga/ Price | I6: Yield
A7: 45293 | B7: 101.63 | C7: 0.0651 | D7: 100.61 | E7: 0.0655 | F7: 104.54 | G7: 0.0664 | H7: 103.93 | I7: 0.0676
A8: 45294 | B8: 101.33 | C8: 0.0657 | D8: 100.15 | E8: 0.0661 | F8: 104.24 | G8: 0.0667 | H8: 103.25 | I8: 0.0683
A9: 45295 | B9: 101.16 | C9: 0.0661 | D9: 99.74 | E9: 0.0667 | F9: 103.6 | G9: 0.0674 | H9: 102.76 | I9: 0.0687
A10: 45296 | B10: 101.13 | C10: 0.0662 | D10: 99.59 | E10: 0.0669 | F10: 103.44 | G10: 0.0675 | H10: 102.5 | I10: 0.0689
A11: 45299 | B11: 101.1 | C11: 0.0663 | D11: 99.5 | E11: 0.067 | F11: 103.14 | G11: 0.0678 | H11: 102.39 | I11: 0.069
A12: 45300 | B12: 101.18 | C12: 0.0661 | D12: 99.42 | E12: 0.0671 | F12: 103.13 | G12: 0.0679 | H12: 102.4 | I12: 0.069
A13: 45301 | B13: 101.21 | C13: 0.066 | D13: 99.34 | E13: 0.0672 | F13: 102.91 | G13: 0.0681 | H13: 102.35 | I13: 0.0691
A14: 45302 | B14: 101.42 | C14: 0.0655 | D14: 99.54 | E14: 0.0669 | F14: 103.29 | G14: 0.0677 | H14: 102.56 | I14: 0.0689
A15: 45303 | B15: 101.42 | C15: 0.0655 | D15: 99.54 | E15: 0.0669 | F15: 103.29 | G15: 0.0677 | H15: 102.56 | I15: 0.0689
A16: 45306 | B16: 101.74 | C16: 0.0648 | D16: 99.99 | E16: 0.0663 | F16: 103.53 | G16: 0.0674 | H16: 102.68 | I16: 0.0688
A17: 45307 | B17: 101.54 | C17: 0.0653 | D17: 99.67 | E17: 0.0668 | F17: 103.26 | G17: 0.0677 | H17: 102.61 | I17: 0.0688
A18: 45308 | B18: 101.61 | C18: 0.0651 | D18: 99.52 | E18: 0.067 | F18: 103.08 | G18: 0.0679 | H18: 102.48 | I18: 0.069
... A243: 45656 | B243: 99.63 | C243: 0.0698 | D243: 97.29 | E243: 0.0704 | F243: 100.47 | G243: 0.0707 | H243: 100.44 | I243: 0.0709
