Workbook

Sheet Rekap Hutan Indonesia
A1: Neraca Fisik dan Moneter
A2: Sumber Daya Hutan Indonesia
A4: Perincian | B4: 1990 | C4: 1991 | D4: 1992 | E4: 1993 | F4: 1994 | G4: 1995 | H4: 1996 | I4: 1997 | J4: 1998 | K4: 1999 | L4: 2000 | M4: 2001 | N4: 2002 | O4: 2003 | P4: 2004 | Q4: 2005 | R4: 2006 | S4: 2007 | T4: 2008 | U4: 2009 | V4: 2010 | W4: 2011 | X4: 2012 | Y4: 2013 | Z4: 2014 | AA4: 2015 | AB4: 2016 | AF4: 2004 | AG4: 2005 | AH4: 2006 | AI4: 2007 | AJ4: 2008 | AK4: 2009 | AL4: 2010 | AM4: 2011 | AN4: 2012 | AO4: 2013 | AP4: 2014 | AQ4: 2015 | AR4: 2016
A6: I. Neraca Fisik (000 M3) | AF6: Laju Pertumbuhan
A8: 1. Persediaan awal | B8: ='Rimba Luar Jawa'!B8+'Rimba Jawa'!B8+'Jati Jawa'!B8 -> 8644424.6 | C8: ='Rimba Luar Jawa'!C8+'Rimba Jawa'!C8+'Jati Jawa'!C8 -> 8642977.8 | D8: ='Rimba Luar Jawa'!D8+'Rimba Jawa'!D8+'Jati Jawa'!D8 -> 8640252.7 | E8: ='Rimba Luar Jawa'!E8+'Rimba Jawa'!E8+'Jati Jawa'!E8 -> 8619007.2 | F8: ='Rimba Luar Jawa'!F8+'Rimba Jawa'!F8+'Jati Jawa'!F8 -> 8589076 | G8: ='Rimba Luar Jawa'!G8+'Rimba Jawa'!G8+'Jati Jawa'!G8 -> 8569181.9 | H8: ='Rimba Luar Jawa'!H8+'Rimba Jawa'!H8+'Jati Jawa'!H8 -> 8548707.6 | I8: ='Rimba Luar Jawa'!I8+'Rimba Jawa'!I8+'Jati Jawa'!I8 -> 8535616.3 | ... AB8: ='Rimba Luar Jawa'!AB8+'Rimba Jawa'!AB8+'Jati Jawa'!AB8 -> 4827604.5 | AF8: =P8/O8*100-100 -> -1.782915 | AG8: =Q8/P8*100-100 -> -2.1695468 | AH8: =R8/Q8*100-100 -> -3.0601215 | AI8: =S8/R8*100-100 -> -3.7730208 | AJ8: =T8/S8*100-100 -> -4.0247219 | AK8: =U8/T8*100-100 -> -2.8620096 | AL8: =V8/U8*100-100 -> -3.2995921 | AM8: =W8/V8*100-100 -> -3.8096553 | ... AR8: =AB8/AA8*100-100 -> -10.993564
A9: 2. Pertumbuhan | B9: ='Rimba Luar Jawa'!B9+'Rimba Jawa'!B9+'Jati Jawa'!B9 -> 41982.9 | C9: ='Rimba Luar Jawa'!C9+'Rimba Jawa'!C9+'Jati Jawa'!C9 -> 43088.146 | D9: ='Rimba Luar Jawa'!D9+'Rimba Jawa'!D9+'Jati Jawa'!D9 -> 44320.021 | E9: ='Rimba Luar Jawa'!E9+'Rimba Jawa'!E9+'Jati Jawa'!E9 -> 45618.543 | F9: ='Rimba Luar Jawa'!F9+'Rimba Jawa'!F9+'Jati Jawa'!F9 -> 47003.13 | G9: ='Rimba Luar Jawa'!G9+'Rimba Jawa'!G9+'Jati Jawa'!G9 -> 48595.51 | H9: ='Rimba Luar Jawa'!H9+'Rimba Jawa'!H9+'Jati Jawa'!H9 -> 54426.46 | I9: ='Rimba Luar Jawa'!I9+'Rimba Jawa'!I9+'Jati Jawa'!I9 -> 55032.56 | ... AB9: ='Rimba Luar Jawa'!AB9+'Rimba Jawa'!AB9+'Jati Jawa'!AB9 -> 39130.339 | AF9: =P9/O9*100-100 -> 7.1523339 | AG9: =Q9/P9*100-100 -> -7.79793 | AH9: =R9/Q9*100-100 -> -3.1756713 | AI9: =S9/R9*100-100 -> -0.67590124 | AJ9: =T9/S9*100-100 -> -3.1087404 | AK9: =U9/T9*100-100 -> 2.1744234 | AL9: =V9/U9*100-100 -> -0.76994235 | AM9: =W9/V9*100-100 -> 1.143182 | ... AR9: =AB9/AA9*100-100 -> -16.387397
A10: 3. Penanaman | B10: ='Rimba Luar Jawa'!B10+'Rimba Jawa'!B10+'Jati Jawa'!B10 -> 790 | C10: ='Rimba Luar Jawa'!C10+'Rimba Jawa'!C10+'Jati Jawa'!C10 -> 1152.3 | D10: ='Rimba Luar Jawa'!D10+'Rimba Jawa'!D10+'Jati Jawa'!D10 -> 1131.2 | E10: ='Rimba Luar Jawa'!E10+'Rimba Jawa'!E10+'Jati Jawa'!E10 -> 1601.8 | F10: ='Rimba Luar Jawa'!F10+'Rimba Jawa'!F10+'Jati Jawa'!F10 -> 1367.46 | G10: ='Rimba Luar Jawa'!G10+'Rimba Jawa'!G10+'Jati Jawa'!G10 -> 1674.2 | H10: ='Rimba Luar Jawa'!H10+'Rimba Jawa'!H10+'Jati Jawa'!H10 -> 2654.03 | I10: ='Rimba Luar Jawa'!I10+'Rimba Jawa'!I10+'Jati Jawa'!I10 -> 2266.59 | ... AB10: ='Rimba Luar Jawa'!AB10+'Rimba Jawa'!AB10+'Jati Jawa'!AB10 -> 17114.782 | AF10: =P10/O10*100-100 -> -5.0410739 | AG10: =Q10/P10*100-100 -> -1.5850762 | AH10: =R10/Q10*100-100 -> 30.192958 | AI10: =S10/R10*100-100 -> -10.906165 | AJ10: =T10/S10*100-100 -> 25.710872 | AK10: =U10/T10*100-100 -> -24.434225 | AL10: =V10/U10*100-100 -> -25.51128 | AM10: =W10/V10*100-100 -> 6.8841612 | ... AR10: =AB10/AA10*100-100 -> 9.0957365
A11: 4. Konversi & kerusakan | B11: ='Rimba Luar Jawa'!B11+'Rimba Jawa'!B11+'Jati Jawa'!B11 -> 15665.8 | C11: ='Rimba Luar Jawa'!C11+'Rimba Jawa'!C11+'Jati Jawa'!C11 -> 18825.8 | D11: ='Rimba Luar Jawa'!D11+'Rimba Jawa'!D11+'Jati Jawa'!D11 -> 38007.4 | E11: ='Rimba Luar Jawa'!E11+'Rimba Jawa'!E11+'Jati Jawa'!E11 -> 47597.7 | F11: ='Rimba Luar Jawa'!F11+'Rimba Jawa'!F11+'Jati Jawa'!F11 -> 38563.3 | G11: ='Rimba Luar Jawa'!G11+'Rimba Jawa'!G11+'Jati Jawa'!G11 -> 41077.1 | H11: ='Rimba Luar Jawa'!H11+'Rimba Jawa'!H11+'Jati Jawa'!H11 -> 40078.83 | I11: ='Rimba Luar Jawa'!I11+'Rimba Jawa'!I11+'Jati Jawa'!I11 -> 80250.98 | ... AB11: ='Rimba Luar Jawa'!AB11+'Rimba Jawa'!AB11+'Jati Jawa'!AB11 -> 193747.58 | AF11: =P11/O11*100-100 -> 17.358154 | AG11: =Q11/P11*100-100 -> 19.973232 | AH11: =R11/Q11*100-100 -> 19.870452 | AI11: =S11/R11*100-100 -> -3.5595066 | AJ11: =T11/S11*100-100 -> -29.297886 | AK11: =U11/T11*100-100 -> 9.9519626 | AL11: =V11/U11*100-100 -> 9.3871395 | AM11: =W11/V11*100-100 -> 11.621337 | ... AR11: =AB11/AA11*100-100 -> -68.412324
A12: 5. Penebangan | B12: ='Rimba Luar Jawa'!B12+'Rimba Jawa'!B12+'Jati Jawa'!B12 -> 28553.9 | C12: ='Rimba Luar Jawa'!C12+'Rimba Jawa'!C12+'Jati Jawa'!C12 -> 28139.7 | D12: ='Rimba Luar Jawa'!D12+'Rimba Jawa'!D12+'Jati Jawa'!D12 -> 28689.4 | E12: ='Rimba Luar Jawa'!E12+'Rimba Jawa'!E12+'Jati Jawa'!E12 -> 29553.8 | F12: ='Rimba Luar Jawa'!F12+'Rimba Jawa'!F12+'Jati Jawa'!F12 -> 29701.4 | G12: ='Rimba Luar Jawa'!G12+'Rimba Jawa'!G12+'Jati Jawa'!G12 -> 29666.9 | H12: ='Rimba Luar Jawa'!H12+'Rimba Jawa'!H12+'Jati Jawa'!H12 -> 30092.97 | I12: ='Rimba Luar Jawa'!I12+'Rimba Jawa'!I12+'Jati Jawa'!I12 -> 34230.235 | ... AB12: ='Rimba Luar Jawa'!AB12+'Rimba Jawa'!AB12+'Jati Jawa'!AB12 -> 45208.181 | AF12: =P12/O12*100-100 -> 1.6383374 | AG12: =Q12/P12*100-100 -> 75.132315 | AH12: =R12/Q12*100-100 -> -9.5775418 | AI12: =S12/R12*100-100 -> 44.22077 | AJ12: =T12/S12*100-100 -> -11.490658 | AK12: =U12/T12*100-100 -> 4.6060709 | AL12: =V12/U12*100-100 -> 4.9141543 | AM12: =W12/V12*100-100 -> -6.4483877 | ... AR12: =AB12/AA12*100-100 -> -0.42449946
A13: 6. Perubahan Neto | B13: ='Rimba Luar Jawa'!B13+'Rimba Jawa'!B13+'Jati Jawa'!B13 -> -1446.8 | C13: ='Rimba Luar Jawa'!C13+'Rimba Jawa'!C13+'Jati Jawa'!C13 -> -2725.0544 | D13: ='Rimba Luar Jawa'!D13+'Rimba Jawa'!D13+'Jati Jawa'!D13 -> -21245.579 | E13: ='Rimba Luar Jawa'!E13+'Rimba Jawa'!E13+'Jati Jawa'!E13 -> -29931.157 | F13: ='Rimba Luar Jawa'!F13+'Rimba Jawa'!F13+'Jati Jawa'!F13 -> -19894.11 | G13: ='Rimba Luar Jawa'!G13+'Rimba Jawa'!G13+'Jati Jawa'!G13 -> -20474.29 | H13: ='Rimba Luar Jawa'!H13+'Rimba Jawa'!H13+'Jati Jawa'!H13 -> -13091.31 | I13: ='Rimba Luar Jawa'!I13+'Rimba Jawa'!I13+'Jati Jawa'!I13 -> -57182.065 | ... AB13: ='Rimba Luar Jawa'!AB13+'Rimba Jawa'!AB13+'Jati Jawa'!AB13 -> -182710.64 | AF13: =P13/O13*100-100 -> 19.515832 | AG13: =Q13/P13*100-100 -> 37.988758 | AH13: =R13/Q13*100-100 -> 19.523417 | AI13: =S13/R13*100-100 -> 2.6463543 | AJ13: =T13/S13*100-100 -> -31.751267 | AK13: =U13/T13*100-100 -> 11.989752 | AL13: =V13/U13*100-100 -> 11.648715 | AM13: =W13/V13*100-100 -> 9.8940882 | ... AR13: =AB13/AA13*100-100 -> -69.358142
A14: 7. Persediaan akhir | B14: ='Rimba Luar Jawa'!B14+'Rimba Jawa'!B14+'Jati Jawa'!B14 -> 8642977.8 | C14: ='Rimba Luar Jawa'!C14+'Rimba Jawa'!C14+'Jati Jawa'!C14 -> 8640252.7 | D14: ='Rimba Luar Jawa'!D14+'Rimba Jawa'!D14+'Jati Jawa'!D14 -> 8619007.2 | E14: ='Rimba Luar Jawa'!E14+'Rimba Jawa'!E14+'Jati Jawa'!E14 -> 8589076 | F14: ='Rimba Luar Jawa'!F14+'Rimba Jawa'!F14+'Jati Jawa'!F14 -> 8569181.9 | G14: ='Rimba Luar Jawa'!G14+'Rimba Jawa'!G14+'Jati Jawa'!G14 -> 8548707.6 | H14: ='Rimba Luar Jawa'!H14+'Rimba Jawa'!H14+'Jati Jawa'!H14 -> 8535616.3 | I14: ='Rimba Luar Jawa'!I14+'Rimba Jawa'!I14+'Jati Jawa'!I14 -> 8478434.2 | ... AB14: ='Rimba Luar Jawa'!AB14+'Rimba Jawa'!AB14+'Jati Jawa'!AB14 -> 4644893.8 | AF14: =P14/O14*100-100 -> -2.1695468 | AG14: =Q14/P14*100-100 -> -3.0601215 | AH14: =R14/Q14*100-100 -> -3.7730208 | AI14: =S14/R14*100-100 -> -4.0247219 | AJ14: =T14/S14*100-100 -> -2.8620096 | AK14: =U14/T14*100-100 -> -3.2995921 | AL14: =V14/U14*100-100 -> -3.8096553 | AM14: =W14/V14*100-100 -> -4.3523973 | ... AR14: =AB14/AA14*100-100 -> -3.7847062
A16: III. Neraca Moneter
A17: (Miliar Rp)
A19: 1. Persediaan awal | B19: ='Rimba Luar Jawa'!B21+'Rimba Jawa'!B21+'Jati Jawa'!B21 -> 74108.902 | C19: ='Rimba Luar Jawa'!C21+'Rimba Jawa'!C21+'Jati Jawa'!C21 -> 83802.55 | D19: ='Rimba Luar Jawa'!D21+'Rimba Jawa'!D21+'Jati Jawa'!D21 -> 97018.89 | E19: ='Rimba Luar Jawa'!E21+'Rimba Jawa'!E21+'Jati Jawa'!E21 -> 92652.724 | F19: ='Rimba Luar Jawa'!F21+'Rimba Jawa'!F21+'Jati Jawa'!F21 -> 104769.1 | G19: ='Rimba Luar Jawa'!G21+'Rimba Jawa'!G21+'Jati Jawa'!G21 -> 128642.89 | H19: ='Rimba Luar Jawa'!H21+'Rimba Jawa'!H21+'Jati Jawa'!H21 -> 138837.71 | I19: ='Rimba Luar Jawa'!I21+'Rimba Jawa'!I21+'Jati Jawa'!I21 -> 149329.52 | ... AB19: ='Rimba Luar Jawa'!AB21+'Rimba Jawa'!AB21+'Jati Jawa'!AB21 -> 1001943.7 | AF19: =P19/O19*100-100 -> 4.2177187 | AG19: =Q19/P19*100-100 -> 7.123564 | AH19: =R19/Q19*100-100 -> 10.023692 | AI19: =S19/R19*100-100 -> 37.325528 | AJ19: =T19/S19*100-100 -> 14.371024 | AK19: =U19/T19*100-100 -> 7.7994752 | AL19: =V19/U19*100-100 -> 6.1733903 | AM19: =W19/V19*100-100 -> -0.086126526 | ... AR19: =AB19/AA19*100-100 -> -7.3640577
A20: 2. Pertumbuhan | B20: ='Rimba Luar Jawa'!B22+'Rimba Jawa'!B22+'Jati Jawa'!B22 -> 689.56159 | C20: ='Rimba Luar Jawa'!C22+'Rimba Jawa'!C22+'Jati Jawa'!C22 -> 686.14115 | D20: ='Rimba Luar Jawa'!D22+'Rimba Jawa'!D22+'Jati Jawa'!D22 -> 654.21251 | E20: ='Rimba Luar Jawa'!E22+'Rimba Jawa'!E22+'Jati Jawa'!E22 -> 1036.6145 | F20: ='Rimba Luar Jawa'!F22+'Rimba Jawa'!F22+'Jati Jawa'!F22 -> 1466.4377 | G20: ='Rimba Luar Jawa'!G22+'Rimba Jawa'!G22+'Jati Jawa'!G22 -> 1626.3811 | H20: ='Rimba Luar Jawa'!H22+'Rimba Jawa'!H22+'Jati Jawa'!H22 -> 2001.1504 | I20: ='Rimba Luar Jawa'!I22+'Rimba Jawa'!I22+'Jati Jawa'!I22 -> 2825.251 | ... AB20: ='Rimba Luar Jawa'!AB22+'Rimba Jawa'!AB22+'Jati Jawa'!AB22 -> -2525.7221 | AF20: =P20/O20*100-100 -> 17.068992 | AG20: =Q20/P20*100-100 -> -3.2775169 | AH20: =R20/Q20*100-100 -> 42.184283 | AI20: =S20/R20*100-100 -> 18.655438 | AJ20: =T20/S20*100-100 -> -0.79609712 | AK20: =U20/T20*100-100 -> 8.7516055 | AL20: =V20/U20*100-100 -> -0.36677119 | AM20: =W20/V20*100-100 -> -10.265108 | ... AR20: =AB20/AA20*100-100 -> -115.86664
A21: 3. Penanaman | B21: ='Rimba Luar Jawa'!B23+'Rimba Jawa'!B23+'Jati Jawa'!B23 -> 9.7480176 | C21: ='Rimba Luar Jawa'!C23+'Rimba Jawa'!C23+'Jati Jawa'!C23 -> 14.128113 | D21: ='Rimba Luar Jawa'!D23+'Rimba Jawa'!D23+'Jati Jawa'!D23 -> 12.869787 | E21: ='Rimba Luar Jawa'!E23+'Rimba Jawa'!E23+'Jati Jawa'!E23 -> 21.547158 | F21: ='Rimba Luar Jawa'!F23+'Rimba Jawa'!F23+'Jati Jawa'!F23 -> 23.634181 | G21: ='Rimba Luar Jawa'!G23+'Rimba Jawa'!G23+'Jati Jawa'!G23 -> 30.60233 | H21: ='Rimba Luar Jawa'!H23+'Rimba Jawa'!H23+'Jati Jawa'!H23 -> 45.795587 | I21: ='Rimba Luar Jawa'!I23+'Rimba Jawa'!I23+'Jati Jawa'!I23 -> 44.783644 | ... AB21: ='Rimba Luar Jawa'!AB23+'Rimba Jawa'!AB23+'Jati Jawa'!AB23 -> 2839.3617 | AF21: =P21/O21*100-100 -> 3.1399899 | AG21: =Q21/P21*100-100 -> 12.682957 | AH21: =R21/Q21*100-100 -> 81.363859 | AI21: =S21/R21*100-100 -> 9.2522886 | AJ21: =T21/S21*100-100 -> 32.571534 | AK21: =U21/T21*100-100 -> -18.262002 | AL21: =V21/U21*100-100 -> -21.735246 | AM21: =W21/V21*100-100 -> 10.479551 | ... AR21: =AB21/AA21*100-100 -> 9.9110494
A22: 4. Konversi & kerusakan | B22: ='Rimba Luar Jawa'!B24+'Rimba Jawa'!B24+'Jati Jawa'!B24 -> 157.28271 | C22: ='Rimba Luar Jawa'!C24+'Rimba Jawa'!C24+'Jati Jawa'!C24 -> 214.51114 | D22: ='Rimba Luar Jawa'!D24+'Rimba Jawa'!D24+'Jati Jawa'!D24 -> 407.81127 | E22: ='Rimba Luar Jawa'!E24+'Rimba Jawa'!E24+'Jati Jawa'!E24 -> 579.8117 | F22: ='Rimba Luar Jawa'!F24+'Rimba Jawa'!F24+'Jati Jawa'!F24 -> 578.67353 | G22: ='Rimba Luar Jawa'!G24+'Rimba Jawa'!G24+'Jati Jawa'!G24 -> 660.4917 | H22: ='Rimba Luar Jawa'!H24+'Rimba Jawa'!H24+'Jati Jawa'!H24 -> 693.76421 | I22: ='Rimba Luar Jawa'!I24+'Rimba Jawa'!I24+'Jati Jawa'!I24 -> 1386.6881 | ... AB22: ='Rimba Luar Jawa'!AB24+'Rimba Jawa'!AB24+'Jati Jawa'!AB24 -> 31195.557 | AF22: =P22/O22*100-100 -> 26.700455 | AG22: =Q22/P22*100-100 -> 36.503484 | AH22: =R22/Q22*100-100 -> 67.472181 | AI22: =S22/R22*100-100 -> 13.593828 | AJ22: =T22/S22*100-100 -> -20.017502 | AK22: =U22/T22*100-100 -> 19.683742 | AL22: =V22/U22*100-100 -> 13.958352 | AM22: =W22/V22*100-100 -> 17.313094 | ... AR22: =AB22/AA22*100-100 -> -69.136929
A23: 5. Penebangan | B23: ='Rimba Luar Jawa'!B25+'Rimba Jawa'!B25+'Jati Jawa'!B25 -> 349.11397 | C23: ='Rimba Luar Jawa'!C25+'Rimba Jawa'!C25+'Jati Jawa'!C25 -> 369.30281 | D23: ='Rimba Luar Jawa'!D25+'Rimba Jawa'!D25+'Jati Jawa'!D25 -> 347.58733 | E23: ='Rimba Luar Jawa'!E25+'Rimba Jawa'!E25+'Jati Jawa'!E25 -> 463.06348 | F23: ='Rimba Luar Jawa'!F25+'Rimba Jawa'!F25+'Jati Jawa'!F25 -> 602.22903 | G23: ='Rimba Luar Jawa'!G25+'Rimba Jawa'!G25+'Jati Jawa'!G25 -> 649.1225 | H23: ='Rimba Luar Jawa'!H25+'Rimba Jawa'!H25+'Jati Jawa'!H25 -> 666.73428 | I23: ='Rimba Luar Jawa'!I25+'Rimba Jawa'!I25+'Jati Jawa'!I25 -> 876.02304 | ... AB23: ='Rimba Luar Jawa'!AB25+'Rimba Jawa'!AB25+'Jati Jawa'!AB25 -> 7185.0842 | AF23: =P23/O23*100-100 -> 13.245752 | AG23: =Q23/P23*100-100 -> 77.010719 | AH23: =R23/Q23*100-100 -> 32.55275 | AI23: =S23/R23*100-100 -> 66.319942 | AJ23: =T23/S23*100-100 -> -1.4148499 | AK23: =U23/T23*100-100 -> 12.651127 | AL23: =V23/U23*100-100 -> 8.1422955 | AM23: =W23/V23*100-100 -> -3.4715028 | ... AR23: =AB23/AA23*100-100 -> -7.0745472
A24: 6. Perubahan Neto | B24: ='Rimba Luar Jawa'!B26+'Rimba Jawa'!B26+'Jati Jawa'!B26 -> 192.91293 | C24: ='Rimba Luar Jawa'!C26+'Rimba Jawa'!C26+'Jati Jawa'!C26 -> 116.45531 | D24: ='Rimba Luar Jawa'!D26+'Rimba Jawa'!D26+'Jati Jawa'!D26 -> -88.316307 | E24: ='Rimba Luar Jawa'!E26+'Rimba Jawa'!E26+'Jati Jawa'!E26 -> 15.286464 | F24: ='Rimba Luar Jawa'!F26+'Rimba Jawa'!F26+'Jati Jawa'!F26 -> 309.16929 | G24: ='Rimba Luar Jawa'!G26+'Rimba Jawa'!G26+'Jati Jawa'!G26 -> 347.36928 | H24: ='Rimba Luar Jawa'!H26+'Rimba Jawa'!H26+'Jati Jawa'!H26 -> 686.4475 | I24: ='Rimba Luar Jawa'!I26+'Rimba Jawa'!I26+'Jati Jawa'!I26 -> 607.3235 | ... AB24: ='Rimba Luar Jawa'!AB26+'Rimba Jawa'!AB26+'Jati Jawa'!AB26 -> -38067.001 | AF24: =P24/O24*100-100 -> 36.346619 | AG24: =Q24/P24*100-100 -> 91.430382 | AH24: =R24/Q24*100-100 -> 72.561619 | AI24: =S24/R24*100-100 -> 21.130618 | AJ24: =T24/S24*100-100 -> -25.397314 | AK24: =U24/T24*100-100 -> 25.776982 | AL24: =V24/U24*100-100 -> 20.737669 | AM24: =W24/V24*100-100 -> 23.494361 | ... AR24: =AB24/AA24*100-100 -> -57.847409
A25: 7. Revaluasi | B25: ='Rimba Luar Jawa'!B27+'Rimba Jawa'!B27+'Jati Jawa'!B27 -> 9500.7348 | C25: ='Rimba Luar Jawa'!C27+'Rimba Jawa'!C27+'Jati Jawa'!C27 -> 13099.885 | D25: ='Rimba Luar Jawa'!D27+'Rimba Jawa'!D27+'Jati Jawa'!D27 -> -4277.8497 | E25: ='Rimba Luar Jawa'!E27+'Rimba Jawa'!E27+'Jati Jawa'!E27 -> 12101.093 | F25: ='Rimba Luar Jawa'!F27+'Rimba Jawa'!F27+'Jati Jawa'!F27 -> 23564.616 | G25: ='Rimba Luar Jawa'!G27+'Rimba Jawa'!G27+'Jati Jawa'!G27 -> 9847.4491 | H25: ='Rimba Luar Jawa'!H27+'Rimba Jawa'!H27+'Jati Jawa'!H27 -> 9805.3696 | I25: ='Rimba Luar Jawa'!I27+'Rimba Jawa'!I27+'Jati Jawa'!I27 -> 10279.262 | ... AB25: ='Rimba Luar Jawa'!AB27+'Rimba Jawa'!AB27+'Jati Jawa'!AB27 -> -546755.31 | AF25: =P25/O25*100-100 -> 67.961034 | AG25: =Q25/P25*100-100 -> 57.445775 | AH25: =R25/Q25*100-100 -> 262.15604 | AI25: =S25/R25*100-100 -> -40.606574 | AJ25: =T25/S25*100-100 -> -35.486932 | AK25: =U25/T25*100-100 -> -5.5615188 | AL25: =V25/U25*100-100 -> -64.808413 | AM25: =W25/V25*100-100 -> -96.353451 | ... AR25: =AB25/AA25*100-100 -> -5229.7573
A26: 8. Persediaan akhir | B26: ='Rimba Luar Jawa'!B28+'Rimba Jawa'!B28+'Jati Jawa'!B28 -> 83802.55 | C26: ='Rimba Luar Jawa'!C28+'Rimba Jawa'!C28+'Jati Jawa'!C28 -> 97018.89 | D26: ='Rimba Luar Jawa'!D28+'Rimba Jawa'!D28+'Jati Jawa'!D28 -> 92652.724 | E26: ='Rimba Luar Jawa'!E28+'Rimba Jawa'!E28+'Jati Jawa'!E28 -> 104769.1 | F26: ='Rimba Luar Jawa'!F28+'Rimba Jawa'!F28+'Jati Jawa'!F28 -> 128642.89 | G26: ='Rimba Luar Jawa'!G28+'Rimba Jawa'!G28+'Jati Jawa'!G28 -> 138837.71 | H26: ='Rimba Luar Jawa'!H28+'Rimba Jawa'!H28+'Jati Jawa'!H28 -> 149329.52 | I26: ='Rimba Luar Jawa'!I28+'Rimba Jawa'!I28+'Jati Jawa'!I28 -> 160216.11 | ... AB26: ='Rimba Luar Jawa'!AB28+'Rimba Jawa'!AB28+'Jati Jawa'!AB28 -> 417121.36 | AF26: =P26/O26*100-100 -> 7.123564 | AG26: =Q26/P26*100-100 -> 10.023692 | AH26: =R26/Q26*100-100 -> 37.325528 | AI26: =S26/R26*100-100 -> 14.371024 | AJ26: =T26/S26*100-100 -> 7.7994752 | AK26: =U26/T26*100-100 -> 6.1733903 | AL26: =V26/U26*100-100 -> -0.086126526 | AM26: =W26/V26*100-100 -> -3.6130798 | ... AR26: =AB26/AA26*100-100 -> -58.368781
A31: Neraca Fisik dan Moneter Sumber Daya Hutan Indonesia Konstan
A33: Perincian | B33: 1990 | C33: 1991 | D33: 1992 | E33: 1993 | F33: 1994 | G33: 1995 | H33: 1996 | I33: 1997 | J33: 1998 | K33: 1999 | L33: 2000
A35: I. Neraca Fisik (000 m3)
A37: 1. Persediaan awal | B37: ='Kayu Rimba Luar Jawa slh '!B94+'Kayu Rimba Jawa slh '!B59+'Kayu Jati Jawa slh'!B58 -> 8644424.6 | C37: ='Kayu Rimba Luar Jawa slh '!C94+'Kayu Rimba Jawa slh '!C59+'Kayu Jati Jawa slh'!C58 -> 8642977.8 | D37: ='Kayu Rimba Luar Jawa slh '!D94+'Kayu Rimba Jawa slh '!D59+'Kayu Jati Jawa slh'!D58 -> 8640252.7 | E37: ='Kayu Rimba Luar Jawa slh '!E94+'Kayu Rimba Jawa slh '!E59+'Kayu Jati Jawa slh'!E58 -> 8619007.2 | F37: ='Kayu Rimba Luar Jawa slh '!F94+'Kayu Rimba Jawa slh '!F59+'Kayu Jati Jawa slh'!F58 -> 8589076 | G37: ='Kayu Rimba Luar Jawa slh '!G94+'Kayu Rimba Jawa slh '!G59+'Kayu Jati Jawa slh'!G58 -> 8569181.9 | H37: ='Kayu Rimba Luar Jawa slh '!H94+'Kayu Rimba Jawa slh '!H59+'Kayu Jati Jawa slh'!H58 -> 8548707.6 | I37: ='Kayu Rimba Luar Jawa slh '!I94+'Kayu Rimba Jawa slh '!I59+'Kayu Jati Jawa slh'!I58 -> 8535616.3 | ... L37: ='Kayu Rimba Luar Jawa slh '!L94+'Kayu Rimba Jawa slh '!L59+'Kayu Jati Jawa slh'!L58 -> 8345375.3
A38: 2. Pertumbuhan | B38: ='Kayu Rimba Luar Jawa slh '!B95+'Kayu Rimba Jawa slh '!B60+'Kayu Jati Jawa slh'!B59 -> 41982.9 | C38: ='Kayu Rimba Luar Jawa slh '!C95+'Kayu Rimba Jawa slh '!C60+'Kayu Jati Jawa slh'!C59 -> 43088.146 | D38: ='Kayu Rimba Luar Jawa slh '!D95+'Kayu Rimba Jawa slh '!D60+'Kayu Jati Jawa slh'!D59 -> 44320.021 | E38: ='Kayu Rimba Luar Jawa slh '!E95+'Kayu Rimba Jawa slh '!E60+'Kayu Jati Jawa slh'!E59 -> 45618.543 | F38: ='Kayu Rimba Luar Jawa slh '!F95+'Kayu Rimba Jawa slh '!F60+'Kayu Jati Jawa slh'!F59 -> 47003.13 | G38: ='Kayu Rimba Luar Jawa slh '!G95+'Kayu Rimba Jawa slh '!G60+'Kayu Jati Jawa slh'!G59 -> 48595.51 | H38: ='Kayu Rimba Luar Jawa slh '!H95+'Kayu Rimba Jawa slh '!H60+'Kayu Jati Jawa slh'!H59 -> 54426.46 | I38: ='Kayu Rimba Luar Jawa slh '!I95+'Kayu Rimba Jawa slh '!I60+'Kayu Jati Jawa slh'!I59 -> 55032.56 | ... L38: ='Kayu Rimba Luar Jawa slh '!L95+'Kayu Rimba Jawa slh '!L60+'Kayu Jati Jawa slh'!L59 -> 62462.422
A39: 3. Penanaman | B39: ='Kayu Rimba Luar Jawa slh '!B96+'Kayu Rimba Jawa slh '!B61+'Kayu Jati Jawa slh'!B60 -> 790 | C39: ='Kayu Rimba Luar Jawa slh '!C96+'Kayu Rimba Jawa slh '!C61+'Kayu Jati Jawa slh'!C60 -> 1152.3 | D39: ='Kayu Rimba Luar Jawa slh '!D96+'Kayu Rimba Jawa slh '!D61+'Kayu Jati Jawa slh'!D60 -> 1131.2 | E39: ='Kayu Rimba Luar Jawa slh '!E96+'Kayu Rimba Jawa slh '!E61+'Kayu Jati Jawa slh'!E60 -> 1601.8 | F39: ='Kayu Rimba Luar Jawa slh '!F96+'Kayu Rimba Jawa slh '!F61+'Kayu Jati Jawa slh'!F60 -> 1367.46 | G39: ='Kayu Rimba Luar Jawa slh '!G96+'Kayu Rimba Jawa slh '!G61+'Kayu Jati Jawa slh'!G60 -> 1674.2 | H39: ='Kayu Rimba Luar Jawa slh '!H96+'Kayu Rimba Jawa slh '!H61+'Kayu Jati Jawa slh'!H60 -> 2654.03 | I39: ='Kayu Rimba Luar Jawa slh '!I96+'Kayu Rimba Jawa slh '!I61+'Kayu Jati Jawa slh'!I60 -> 2266.59 | ... L39: ='Kayu Rimba Luar Jawa slh '!L96+'Kayu Rimba Jawa slh '!L61+'Kayu Jati Jawa slh'!L60 -> 1486.6887
A40: 4. Konversi & kerusakan | B40: ='Kayu Rimba Luar Jawa slh '!B97+'Kayu Rimba Jawa slh '!B62+'Kayu Jati Jawa slh'!B61 -> 15665.8 | C40: ='Kayu Rimba Luar Jawa slh '!C97+'Kayu Rimba Jawa slh '!C62+'Kayu Jati Jawa slh'!C61 -> 18825.8 | D40: ='Kayu Rimba Luar Jawa slh '!D97+'Kayu Rimba Jawa slh '!D62+'Kayu Jati Jawa slh'!D61 -> 38007.4 | E40: ='Kayu Rimba Luar Jawa slh '!E97+'Kayu Rimba Jawa slh '!E62+'Kayu Jati Jawa slh'!E61 -> 47597.7 | F40: ='Kayu Rimba Luar Jawa slh '!F97+'Kayu Rimba Jawa slh '!F62+'Kayu Jati Jawa slh'!F61 -> 38563.3 | G40: ='Kayu Rimba Luar Jawa slh '!G97+'Kayu Rimba Jawa slh '!G62+'Kayu Jati Jawa slh'!G61 -> 41077.1 | H40: ='Kayu Rimba Luar Jawa slh '!H97+'Kayu Rimba Jawa slh '!H62+'Kayu Jati Jawa slh'!H61 -> 40078.83 | I40: ='Kayu Rimba Luar Jawa slh '!I97+'Kayu Rimba Jawa slh '!I62+'Kayu Jati Jawa slh'!I61 -> 80250.98 | ... L40: ='Kayu Rimba Luar Jawa slh '!L97+'Kayu Rimba Jawa slh '!L62+'Kayu Jati Jawa slh'!L61 -> 100341.42
A41: 5. Penebangan | B41: ='Kayu Rimba Luar Jawa slh '!B98+'Kayu Rimba Jawa slh '!B63+'Kayu Jati Jawa slh'!B62 -> 28553.9 | C41: ='Kayu Rimba Luar Jawa slh '!C98+'Kayu Rimba Jawa slh '!C63+'Kayu Jati Jawa slh'!C62 -> 28139.7 | D41: ='Kayu Rimba Luar Jawa slh '!D98+'Kayu Rimba Jawa slh '!D63+'Kayu Jati Jawa slh'!D62 -> 28689.4 | E41: ='Kayu Rimba Luar Jawa slh '!E98+'Kayu Rimba Jawa slh '!E63+'Kayu Jati Jawa slh'!E62 -> 29553.8 | F41: ='Kayu Rimba Luar Jawa slh '!F98+'Kayu Rimba Jawa slh '!F63+'Kayu Jati Jawa slh'!F62 -> 29701.4 | G41: ='Kayu Rimba Luar Jawa slh '!G98+'Kayu Rimba Jawa slh '!G63+'Kayu Jati Jawa slh'!G62 -> 29666.9 | H41: ='Kayu Rimba Luar Jawa slh '!H98+'Kayu Rimba Jawa slh '!H63+'Kayu Jati Jawa slh'!H62 -> 30092.97 | I41: ='Kayu Rimba Luar Jawa slh '!I98+'Kayu Rimba Jawa slh '!I63+'Kayu Jati Jawa slh'!I62 -> 34230.24 | ... L41: ='Kayu Rimba Luar Jawa slh '!L98+'Kayu Rimba Jawa slh '!L63+'Kayu Jati Jawa slh'!L62 -> 26264.207
A42: 6. Perubahan Neto | B42: ='Kayu Rimba Luar Jawa slh '!B99+'Kayu Rimba Jawa slh '!B64+'Kayu Jati Jawa slh'!B63 -> -1446.8 | C42: ='Kayu Rimba Luar Jawa slh '!C99+'Kayu Rimba Jawa slh '!C64+'Kayu Jati Jawa slh'!C63 -> -2725.0544 | D42: ='Kayu Rimba Luar Jawa slh '!D99+'Kayu Rimba Jawa slh '!D64+'Kayu Jati Jawa slh'!D63 -> -21245.579 | E42: ='Kayu Rimba Luar Jawa slh '!E99+'Kayu Rimba Jawa slh '!E64+'Kayu Jati Jawa slh'!E63 -> -29931.157 | F42: ='Kayu Rimba Luar Jawa slh '!F99+'Kayu Rimba Jawa slh '!F64+'Kayu Jati Jawa slh'!F63 -> -19894.11 | G42: ='Kayu Rimba Luar Jawa slh '!G99+'Kayu Rimba Jawa slh '!G64+'Kayu Jati Jawa slh'!G63 -> -20474.29 | H42: ='Kayu Rimba Luar Jawa slh '!H99+'Kayu Rimba Jawa slh '!H64+'Kayu Jati Jawa slh'!H63 -> -13091.31 | I42: ='Kayu Rimba Luar Jawa slh '!I99+'Kayu Rimba Jawa slh '!I64+'Kayu Jati Jawa slh'!I63 -> -57182.07 | ... L42: ='Kayu Rimba Luar Jawa slh '!L99+'Kayu Rimba Jawa slh '!L64+'Kayu Jati Jawa slh'!L63 -> -62656.517
A43: 7. Persediaan akhir | B43: ='Kayu Rimba Luar Jawa slh '!B100+'Kayu Rimba Jawa slh '!B65+'Kayu Jati Jawa slh'!B64 -> 8642977.8 | C43: ='Kayu Rimba Luar Jawa slh '!C100+'Kayu Rimba Jawa slh '!C65+'Kayu Jati Jawa slh'!C64 -> 8640252.7 | D43: ='Kayu Rimba Luar Jawa slh '!D100+'Kayu Rimba Jawa slh '!D65+'Kayu Jati Jawa slh'!D64 -> 8619007.2 | E43: ='Kayu Rimba Luar Jawa slh '!E100+'Kayu Rimba Jawa slh '!E65+'Kayu Jati Jawa slh'!E64 -> 8589076 | F43: ='Kayu Rimba Luar Jawa slh '!F100+'Kayu Rimba Jawa slh '!F65+'Kayu Jati Jawa slh'!F64 -> 8569181.9 | G43: ='Kayu Rimba Luar Jawa slh '!G100+'Kayu Rimba Jawa slh '!G65+'Kayu Jati Jawa slh'!G64 -> 8548707.6 | H43: ='Kayu Rimba Luar Jawa slh '!H100+'Kayu Rimba Jawa slh '!H65+'Kayu Jati Jawa slh'!H64 -> 8535616.3 | I43: ='Kayu Rimba Luar Jawa slh '!I100+'Kayu Rimba Jawa slh '!I65+'Kayu Jati Jawa slh'!I64 -> 8478434.2 | ... L43: ='Kayu Rimba Luar Jawa slh '!L100+'Kayu Rimba Jawa slh '!L65+'Kayu Jati Jawa slh'!L64 -> 8282718.8
A45: III. Neraca Moneter
A46: (miliar Rp)
A48: 1. Persediaan awal | B48: ='Kayu Rimba Luar Jawa slh '!B107+'Kayu Rimba Jawa slh '!B72+'Kayu Jati Jawa slh'!B71 -> 122116.4 | C48: ='Kayu Rimba Luar Jawa slh '!C107+'Kayu Rimba Jawa slh '!C72+'Kayu Jati Jawa slh'!C71 -> 122375.52 | D48: ='Kayu Rimba Luar Jawa slh '!D107+'Kayu Rimba Jawa slh '!D72+'Kayu Jati Jawa slh'!D71 -> 122643.99 | E48: ='Kayu Rimba Luar Jawa slh '!E107+'Kayu Rimba Jawa slh '!E72+'Kayu Jati Jawa slh'!E71 -> 122691.99 | F48: ='Kayu Rimba Luar Jawa slh '!F107+'Kayu Rimba Jawa slh '!F72+'Kayu Jati Jawa slh'!F71 -> 122616.51 | G48: ='Kayu Rimba Luar Jawa slh '!G107+'Kayu Rimba Jawa slh '!G72+'Kayu Jati Jawa slh'!G71 -> 122703.82 | H48: ='Kayu Rimba Luar Jawa slh '!H107+'Kayu Rimba Jawa slh '!H72+'Kayu Jati Jawa slh'!H71 -> 122811.38 | I48: ='Kayu Rimba Luar Jawa slh '!I107+'Kayu Rimba Jawa slh '!I72+'Kayu Jati Jawa slh'!I71 -> 123249.66 | ... L48: ='Kayu Rimba Luar Jawa slh '!L107+'Kayu Rimba Jawa slh '!L72+'Kayu Jati Jawa slh'!L71 -> 122397.7
A49: 2. Pertumbuhan | B49: ='Kayu Rimba Luar Jawa slh '!B108+'Kayu Rimba Jawa slh '!B73+'Kayu Jati Jawa slh'!B72 -> 972.99424 | C49: ='Kayu Rimba Luar Jawa slh '!C108+'Kayu Rimba Jawa slh '!C73+'Kayu Jati Jawa slh'!C72 -> 1011.8988 | D49: ='Kayu Rimba Luar Jawa slh '!D108+'Kayu Rimba Jawa slh '!D73+'Kayu Jati Jawa slh'!D72 -> 1054.9103 | E49: ='Kayu Rimba Luar Jawa slh '!E108+'Kayu Rimba Jawa slh '!E73+'Kayu Jati Jawa slh'!E72 -> 1101.4978 | F49: ='Kayu Rimba Luar Jawa slh '!F108+'Kayu Rimba Jawa slh '!F73+'Kayu Jati Jawa slh'!F72 -> 1149.003 | G49: ='Kayu Rimba Luar Jawa slh '!G108+'Kayu Rimba Jawa slh '!G73+'Kayu Jati Jawa slh'!G72 -> 1201.7464 | H49: ='Kayu Rimba Luar Jawa slh '!H108+'Kayu Rimba Jawa slh '!H73+'Kayu Jati Jawa slh'!H72 -> 1504.003 | I49: ='Kayu Rimba Luar Jawa slh '!I108+'Kayu Rimba Jawa slh '!I73+'Kayu Jati Jawa slh'!I72 -> 1488.5662 | ... L49: ='Kayu Rimba Luar Jawa slh '!L108+'Kayu Rimba Jawa slh '!L73+'Kayu Jati Jawa slh'!L72 -> 1578.3994
A50: 3. Penanaman | B50: ='Kayu Rimba Luar Jawa slh '!B109+'Kayu Rimba Jawa slh '!B74+'Kayu Jati Jawa slh'!B73 -> 14.075115 | C50: ='Kayu Rimba Luar Jawa slh '!C109+'Kayu Rimba Jawa slh '!C74+'Kayu Jati Jawa slh'!C73 -> 19.592988 | D50: ='Kayu Rimba Luar Jawa slh '!D109+'Kayu Rimba Jawa slh '!D74+'Kayu Jati Jawa slh'!D73 -> 18.59191 | E50: ='Kayu Rimba Luar Jawa slh '!E109+'Kayu Rimba Jawa slh '!E74+'Kayu Jati Jawa slh'!E73 -> 24.626651 | F50: ='Kayu Rimba Luar Jawa slh '!F109+'Kayu Rimba Jawa slh '!F74+'Kayu Jati Jawa slh'!F73 -> 21.394791 | G50: ='Kayu Rimba Luar Jawa slh '!G109+'Kayu Rimba Jawa slh '!G74+'Kayu Jati Jawa slh'!G73 -> 26.030519 | H50: ='Kayu Rimba Luar Jawa slh '!H109+'Kayu Rimba Jawa slh '!H74+'Kayu Jati Jawa slh'!H73 -> 37.901668 | I50: ='Kayu Rimba Luar Jawa slh '!I109+'Kayu Rimba Jawa slh '!I74+'Kayu Jati Jawa slh'!I73 -> 33.511564 | ... L50: ='Kayu Rimba Luar Jawa slh '!L109+'Kayu Rimba Jawa slh '!L74+'Kayu Jati Jawa slh'!L73 -> 26.432726
A51: 4. Konversi & kerusakan | B51: ='Kayu Rimba Luar Jawa slh '!B110+'Kayu Rimba Jawa slh '!B75+'Kayu Jati Jawa slh'!B74 -> 228.81886 | C51: ='Kayu Rimba Luar Jawa slh '!C110+'Kayu Rimba Jawa slh '!C75+'Kayu Jati Jawa slh'!C74 -> 271.91001 | D51: ='Kayu Rimba Luar Jawa slh '!D110+'Kayu Rimba Jawa slh '!D75+'Kayu Jati Jawa slh'!D74 -> 537.46483 | E51: ='Kayu Rimba Luar Jawa slh '!E110+'Kayu Rimba Jawa slh '!E75+'Kayu Jati Jawa slh'!E74 -> 679.50206 | F51: ='Kayu Rimba Luar Jawa slh '!F110+'Kayu Rimba Jawa slh '!F75+'Kayu Jati Jawa slh'!F74 -> 553.13991 | G51: ='Kayu Rimba Luar Jawa slh '!G110+'Kayu Rimba Jawa slh '!G75+'Kayu Jati Jawa slh'!G74 -> 587.06076 | H51: ='Kayu Rimba Luar Jawa slh '!H110+'Kayu Rimba Jawa slh '!H75+'Kayu Jati Jawa slh'!H74 -> 573.51453 | I51: ='Kayu Rimba Luar Jawa slh '!I110+'Kayu Rimba Jawa slh '!I75+'Kayu Jati Jawa slh'!I74 -> 1115.3044 | ... L51: ='Kayu Rimba Luar Jawa slh '!L110+'Kayu Rimba Jawa slh '!L75+'Kayu Jati Jawa slh'!L74 -> 1441.9489
A52: 5. Penebangan | B52: ='Kayu Rimba Luar Jawa slh '!B111+'Kayu Rimba Jawa slh '!B76+'Kayu Jati Jawa slh'!B75 -> 499.12636 | C52: ='Kayu Rimba Luar Jawa slh '!C111+'Kayu Rimba Jawa slh '!C76+'Kayu Jati Jawa slh'!C75 -> 491.11015 | D52: ='Kayu Rimba Luar Jawa slh '!D111+'Kayu Rimba Jawa slh '!D76+'Kayu Jati Jawa slh'!D75 -> 488.04028 | E52: ='Kayu Rimba Luar Jawa slh '!E111+'Kayu Rimba Jawa slh '!E76+'Kayu Jati Jawa slh'!E75 -> 522.10191 | F52: ='Kayu Rimba Luar Jawa slh '!F111+'Kayu Rimba Jawa slh '!F76+'Kayu Jati Jawa slh'!F75 -> 529.94625 | G52: ='Kayu Rimba Luar Jawa slh '!G111+'Kayu Rimba Jawa slh '!G76+'Kayu Jati Jawa slh'!G75 -> 533.16013 | H52: ='Kayu Rimba Luar Jawa slh '!H111+'Kayu Rimba Jawa slh '!H76+'Kayu Jati Jawa slh'!H75 -> 530.11179 | I52: ='Kayu Rimba Luar Jawa slh '!I111+'Kayu Rimba Jawa slh '!I76+'Kayu Jati Jawa slh'!I75 -> 590.86758 | ... L52: ='Kayu Rimba Luar Jawa slh '!L111+'Kayu Rimba Jawa slh '!L76+'Kayu Jati Jawa slh'!L75 -> 457.9535
A53: 6. Perubahan Neto | B53: ='Kayu Rimba Luar Jawa slh '!B112+'Kayu Rimba Jawa slh '!B77+'Kayu Jati Jawa slh'!B76 -> 259.12414 | C53: ='Kayu Rimba Luar Jawa slh '!C112+'Kayu Rimba Jawa slh '!C77+'Kayu Jati Jawa slh'!C76 -> 268.47161 | D53: ='Kayu Rimba Luar Jawa slh '!D112+'Kayu Rimba Jawa slh '!D77+'Kayu Jati Jawa slh'!D76 -> 47.997132 | E53: ='Kayu Rimba Luar Jawa slh '!E112+'Kayu Rimba Jawa slh '!E77+'Kayu Jati Jawa slh'!E76 -> -75.479541 | F53: ='Kayu Rimba Luar Jawa slh '!F112+'Kayu Rimba Jawa slh '!F77+'Kayu Jati Jawa slh'!F76 -> 87.311663 | G53: ='Kayu Rimba Luar Jawa slh '!G112+'Kayu Rimba Jawa slh '!G77+'Kayu Jati Jawa slh'!G76 -> 107.55598 | H53: ='Kayu Rimba Luar Jawa slh '!H112+'Kayu Rimba Jawa slh '!H77+'Kayu Jati Jawa slh'!H76 -> 438.27831 | I53: ='Kayu Rimba Luar Jawa slh '!I112+'Kayu Rimba Jawa slh '!I77+'Kayu Jati Jawa slh'!I76 -> -184.09419 | ... L53: ='Kayu Rimba Luar Jawa slh '!L112+'Kayu Rimba Jawa slh '!L77+'Kayu Jati Jawa slh'!L76 -> -295.07023
A54: 7. Revaluasi | B54: ='Kayu Rimba Luar Jawa slh '!B113+'Kayu Rimba Jawa slh '!B78+'Kayu Jati Jawa slh'!B77 -> 0 | C54: ='Kayu Rimba Luar Jawa slh '!C113+'Kayu Rimba Jawa slh '!C78+'Kayu Jati Jawa slh'!C77 -> 0 | D54: ='Kayu Rimba Luar Jawa slh '!D113+'Kayu Rimba Jawa slh '!D78+'Kayu Jati Jawa slh'!D77 -> 0 | E54: ='Kayu Rimba Luar Jawa slh '!E113+'Kayu Rimba Jawa slh '!E78+'Kayu Jati Jawa slh'!E77 -> 0 | F54: ='Kayu Rimba Luar Jawa slh '!F113+'Kayu Rimba Jawa slh '!F78+'Kayu Jati Jawa slh'!F77 -> 0 | G54: ='Kayu Rimba Luar Jawa slh '!G113+'Kayu Rimba Jawa slh '!G78+'Kayu Jati Jawa slh'!G77 -> 0 | H54: ='Kayu Rimba Luar Jawa slh '!H113+'Kayu Rimba Jawa slh '!H78+'Kayu Jati Jawa slh'!H77 -> 0 | I54: ='Kayu Rimba Luar Jawa slh '!I113+'Kayu Rimba Jawa slh '!I78+'Kayu Jati Jawa slh'!I77 -> 0 | ... L54: ='Kayu Rimba Luar Jawa slh '!L113+'Kayu Rimba Jawa slh '!L78+'Kayu Jati Jawa slh'!L77 -> 0
A55: 8. Persediaan akhir | B55: ='Kayu Rimba Luar Jawa slh '!B114+'Kayu Rimba Jawa slh '!B79+'Kayu Jati Jawa slh'!B78 -> 122375.52 | C55: ='Kayu Rimba Luar Jawa slh '!C114+'Kayu Rimba Jawa slh '!C79+'Kayu Jati Jawa slh'!C78 -> 122643.99 | D55: ='Kayu Rimba Luar Jawa slh '!D114+'Kayu Rimba Jawa slh '!D79+'Kayu Jati Jawa slh'!D78 -> 122691.99 | E55: ='Kayu Rimba Luar Jawa slh '!E114+'Kayu Rimba Jawa slh '!E79+'Kayu Jati Jawa slh'!E78 -> 122616.51 | F55: ='Kayu Rimba Luar Jawa slh '!F114+'Kayu Rimba Jawa slh '!F79+'Kayu Jati Jawa slh'!F78 -> 122703.82 | G55: ='Kayu Rimba Luar Jawa slh '!G114+'Kayu Rimba Jawa slh '!G79+'Kayu Jati Jawa slh'!G78 -> 122811.38 | H55: ='Kayu Rimba Luar Jawa slh '!H114+'Kayu Rimba Jawa slh '!H79+'Kayu Jati Jawa slh'!H78 -> 123249.66 | I55: ='Kayu Rimba Luar Jawa slh '!I114+'Kayu Rimba Jawa slh '!I79+'Kayu Jati Jawa slh'!I78 -> 123065.56 | ... L55: ='Kayu Rimba Luar Jawa slh '!L114+'Kayu Rimba Jawa slh '!L79+'Kayu Jati Jawa slh'!L78 -> 122102.63

Sheet Data Penunjang
A1: Data Penunjang Penghitungan | C1: estimasi
A2: Sisnerling Hutan | C2: link based on sumber data | D2: estimasi? | AC2: =5307.51+170979.77 -> 176287.28 | AG2: =191633+27479.36+362574.64+784816.57 -> 1366503.6
A3: Tahun 1993 - 2013 | AA3: 7089.58 | AB3: =(100+BF7)/100*AA3 -> 8124.0353 | AC3: 4918.75 | AD3: 1491.6078 | AG3: =13234.28+173.35 -> 13407.63
B4: *Menggunakan data saldo akhir | C4: formula | AF4: 102807.89 | AQ4: Pertumbuhan 2011-2015
A5: No. | B5: Uraian | C5: Sumber Data | D5: Rujukan | E5: Satuan | F5: 1990 | G5: 1991 | H5: 1992 | I5: 1993 | J5: 1994 | K5: 1995 | L5: 1996 | M5: 1997 | N5: 1998 | O5: 1999 | P5: 2000 | Q5: 2001 | R5: 2002 | S5: 2003 | T5: 2004 | U5: 2005 | V5: 2006 | W5: 2007 | X5: 2008 | Y5: 2009 | Z5: 2010 | AA5: 2011 | AB5: 2012 | AC5: 2013 | AD5: 2014 | AE5: 2015 | AF5: 2016 | AG5: 2017 | AH5: 2018 | AI5: 2019 | AJ5: 2020 | AK5: 2021 | AL5: 2022 | AM5: 2023 | AN5: 2024 | AQ5: 2011 | AR5: 2012 | AS5: 2013 | AT5: 2014 | AU5: 2015 | AV5: Rata-rata | AW5: Estimasi 2016 | AY5: 2005 | AZ5: 2006 | BA5: 2007 | BB5: 2008 | BC5: 2009 | BD5: 2010 | BE5: 2011 | BF5: 2012 | BG5: 2013 | BH5: 2014
B6: Nasional | E6: laju kebakaran | AC6: =AC3/AB3*100-100 -> -39.45435 | AD6: =AD7/AC3*100-100 -> 144.95959 | AE6: =AE7/AD7*100-100 -> 9389.7984 | AF6: =AF7/AE7*100-100 -> -83.366492 | AG6: =AG7/AF7*100-100 -> -76.728876 | AH6: =AH7/AG7*100-100 -> 294.32426 | AI6: =AI7/AH7*100-100 -> 222.94589 | AJ6: =AJ7/AI7*100-100 -> -82.067922 | AK6: =AK7/AJ7*100-100 -> 27.461819 | AL6: =AL7/AK7*100-100 -> -41.306722 | ... AN6: =AN7/AM7*100-100 -> -68.153142
A7: 1 | B7: Luas Kebakaran Hutan Indonesia | C7: NSDH | E7: Ha | O7: 44090 | P7: 3016.5 | Q7: 14329.5 | R7: 35496.73 | S7: 3545.45 | T7: 3343.99 | U7: 5502.47 | V7: 4241.59 | W7: 6974.62 | X7: 6793.08 | Y7: 7619.41 | Z7: 3493.12 | AA7: =0+3107.06+0 -> 3107.06 | AB7: =0+1365.3+0 -> 1365.3 | AC7: =0+1723.59+0 -> 1723.59 | AD7: =0+12048.95+0 -> 12048.95 | AE7: =145035.24+734500.52+263885.3 -> 1143421.1 | AF7: =23473.33+96509.7+70208 -> 190191.03 | AG7: =9602.84+16781.88+17874.87 -> 44259.59 | AH7: =33289.79+77416.46+63820.05 -> 174526.3 | AI7: =78516.93+325970.15+159138.44 -> 563625.52 | AJ7: =20358.13+46490.52+34221.12 -> 101069.77 | AK7: =(((AK81/AJ81*100-100)+100)*AJ7)/100 -> 128825.37 | AL7: =(((AL81/AK81*100-100)+100)*AK7)/100 -> 75611.831 | AM7: =(((AM81/AL81*100-100)+100)*AL7)/100 -> 411203.09 | AN7: =(((AN81/AM81*100-100)+100)*AM7)/100 -> 130955.26 | AQ7: =AA3/Z7-1 -> 1.0295839 | AR7: =AB3/AA3-1 -> 0.14591208 | AS7: =AC3/AB3-1 -> -0.3945435 | AT7: =AD7/AC3-1 -> 1.4495959 | AU7: =AE7/AD7-1 -> 93.897984 | AV7: =AVERAGE(AQ7:AU7) -> 19.225706 | AW7: =AVERAGE(AA7:AE7) -> 232333.19 | AX7: =(100+AV7)*AE7/100 -> 1363251.8 | BB7: =X7/W7*100-100 -> -2.6028658 | BC7: =Y7/X7*100-100 -> 12.164291 | BD7: =Z7/Y7*100-100 -> -54.154981 | BE7: =AA3/Z7*100-100 -> 102.95839 | BF7: =AVERAGE(BB7:BE7) -> 14.591208 | BG7: =AVERAGE(BB7:BF7) -> 14.591208 | BH7: =AVERAGE(BB7:BG7) -> 14.591208
A8: 2 | B8: Realisasi Reboisasi (Penanaman) Indonesia | C8: NSDH | E8: Ha | K8: 41762 | L8: 44824 | M8: 35725 | N8: 23615 | O8: 12002 | P8: 8986 | Q8: 7049 | R8: 35433 | S8: 52200 | T8: =T10-T9 -> 332482 | U8: =U10-U9 -> 23709 | V8: =V10-V9 -> 242871 | W8: =W10-W9 -> 74968 | X8: =X10-X9 -> 266721 | Y8: =Y10-Y9 -> 200758 | Z8: =Z10-Z9 -> 142093.75 | AA8: =AA10-AA9 -> 145332.15 | AB8: =AB10-AB9 -> 168787.52 | AC8: 105656 | AD8: =23031.36+258097.65 -> 281129.01 | AE8: =179412.05+343310.13 -> 522722.18 | AF8: =33083.4+361249.7 -> 394333.1 | AG8: =24865+219744.18 -> 244609.18 | AH8: =20864.87+282840.4 -> 303705.27 | AI8: =22723.05+384104.81 -> 406827.86 | AJ8: =15494.77+342787 -> 358281.77 | AK8: ='[1]5. Penanaman'!H89 -> 156257 | AL8: ='[1]5. Penanaman'!I89 -> 220185 | AM8: =(100+[2]StatHut!F15)/100*AL8 -> 143936.82 | AN8: =AVERAGE(AI8:AM8) -> 257097.69 | AQ8: =AA8/Z8-1 -> 0.022790565 | AR8: =AB8/AA8-1 -> 0.16139151 | AS8: =AC8/AB8-1 -> -0.37402955 | AT8: =AD8/AC8-1 -> 1.6607955 | AU8: =AE8/AD8-1 -> 0.85936763 | AV8: =AVERAGE(AQ8:AU8) -> 0.46606313 | AW8: =AVERAGE(AA8:AE8) -> 244725.37 | AX8: =AVERAGE(AA8:AE8) -> 244725.37 | AY8: =(1+AW8)*AE8 -> 1.279239e+11 | BB8: =X8/W8*100-100 -> 255.7798 | BC8: =Y8/X8*100-100 -> -24.731086 | BD8: =Z8/Y8*100-100 -> -29.221376 | BE8: =AA8/Z8*100-100 -> 2.2790565 | BF8: =AB8/AA8*100-100 -> 16.139151 | BG8: =AC8/AB8*100-100 -> -37.402955 | BH8: =AVERAGE(BB8:BG8) -> 30.473765
A9: 3 | B9: Penanaman Hutan Kemasyarakatan Indonesia | C9: NSDH | E9: Ha | K9: 17631 | L9: 11755 | M9: 7990 | N9: 7087 | O9: 850 | P9: 24556 | Q9: 5436 | R9: 13436 | S9: 9597 | T9: 6684 | U9: 3254 | V9: 3171 | W9: 1750 | X9: 200 | Y9: 2283 | Z9: 7329 | AA9: =(1+BE9)/100*Z9 -> 16586.853 | AB9: =(1+BF9)/100*AA9 -> 37539.05 | AC9: 265325 | AD9: =30064.24+42234.37+20219.27 -> 92517.88 | AE9: =127+1086.88+532 -> 1745.88 | AF9: =4+12.75+0+44970+107849.24+26700.31 -> 179536.3 | AG9: =98+55+212+274+230.2+364 -> 1233.2 | AH9: =120+75+645+75+267 -> 1182 | AI9: =75+75+60+12598.15+13201.22+1967 -> 27976.37 | AJ9: =0+82.21+564.51+207.71 -> 854.43 | AK9: =(((AK82/AJ82*100-100)+100)*AJ9)/100 -> 863.17508 | AL9: =(((AL82/AK82*100-100)+100)*AK9)/100 -> 1000.6721 | AM9: =(((AM82/AL82*100-100)+100)*AL9)/100 -> 1114.1367 | AN9: =(((AN82/AM82*100-100)+100)*AM9)/100 -> 1274.8099 | AQ9: =AA9/Z9-1 -> 1.2631809 | AR9: =AB9/AA9-1 -> 1.2631809 | AS9: =AC9/AB9-1 -> 6.0679733 | AT9: =AD9/AC9-1 -> -0.65130357 | AU9: =AE9/AD9-1 -> -0.98112927 | AV9: =AVERAGE(AQ9:AU9) -> 1.3923805 | AW9: =AVERAGE(AA9:AE9) -> 82742.933 | AX9: =AVERAGE(AA9:AE9) -> 82742.933 | AZ9: =V9/U9*100-100 -> -2.5507068 | BA9: =W9/V9*100-100 -> -44.812362 | BB9: =X9/W9*100-100 -> -88.571429 | BC9: =Y9/X9*100-100 -> 1041.5 | BD9: =Z9/Y9*100-100 -> 221.02497 | BE9: =AVERAGE(AZ9:BD9) -> 225.31809 | BF9: =AVERAGE(AZ9:BE9) -> 225.31809 | BG9: =AVERAGE(AZ9:BF9) -> 225.31809 | BH9: =AVERAGE(AZ9:BG9) -> 225.31809
A10: 4 | B10: Luas Reboisasi + Penanaman | C10: NSDH | E10: Ha | K10: 59393 | L10: 56579 | M10: 43715 | N10: 30702 | O10: 12852 | P10: 33542 | Q10: 12485 | R10: 48869 | S10: 61797 | T10: 339166 | U10: 26963 | V10: 246042 | W10: 76718 | X10: 266921 | Y10: =113041+90000 -> 203041 | Z10: =149422.75 -> 149422.75 | AA10: =151498+10421 -> 161919 | AB10: =AA10*(100+BF10)/100 -> 206326.57 | AC10: =AC8+AC9 -> 370981 | AD10: =AD8+AD9 -> 373646.89 | AE10: =AE8+AE9 -> 524468.06 | AF10: =AF8+AF9 -> 573869.4 | AG10: =AG8+AG9 -> 245842.38 | AH10: =AH8+AH9 -> 304887.27 | AI10: =AI8+AI9 -> 434804.23 | AJ10: =AJ8+AJ9 -> 359136.2 | ... AN10: =AN8+AN9 -> 258372.5 | AQ10: =AA10/Z10-1 -> 0.08363017 | AR10: =AB10/AA10-1 -> 0.27425794 | AS10: =AC10/AB10-1 -> 0.79802824 | AT10: =AD10/AC10-1 -> 0.0071860554 | AU10: =AE10/AD10-1 -> 0.40364626 | AV10: =AVERAGE(AQ10:AU10) -> 0.31334973 | AW10: =(1+AV10)*AE10 -> 688809.99 | AY10: =U10/T10*100-100 -> -92.050206 | AZ10: =V10/U10*100-100 -> 812.51715 | BA10: =W10/V10*100-100 -> -68.819145 | BB10: =X10/W10*100-100 -> 247.92487 | BC10: =Y10/X10*100-100 -> -23.932175 | BD10: =Z10/Y10*100-100 -> -26.407597 | BE10: =AA10/Z10*100-100 -> 8.363017 | BF10: =AVERAGE(BA10:BE10) -> 27.425794
A11: 5 | B11: Produksi Kayu Bulat Indonesia | C11: PDB kehutanan | E11: M3 | O11: 20619942 | P11: 13798240 | Q11: 11155400 | R11: 9004105 | S11: 11423501 | T11: 13548938 | U11: 24222638 | V11: 21792144 | W11: 31491584 | X11: 27837337 | Y11: 29207400 | Z11: 30721759 | AA11: 29630421 | AB11: 29047187 | AC11: =23923.3225033*1000 -> 23923323 | AD11: 26798625 | AE11: 26382722 | AF11: 26168644 | AG11: 27435100 | AH11: =[3]Olah!$L$5 -> 27462980 | AI11: =[3]Olah!$M$5 -> 28653668 | AJ11: =[3]Olah!$N$5 -> 30180976 | AK11: =[3]Olah!O$5 -> 31865454 | AL11: =[3]Olah!P$5 -> 31978702 | AM11: =(100+[2]StatHut!F6)/100*AL11 -> 33741127 | AN11: =(100+[2]StatHut!G6)/100*AM11 -> 32071074 | AO11: =(100+[4]StatHut!$G$6)/100*AM11 -> 32071074 | AQ11: =AA11/Z11-1 -> -0.035523299 | AR11: =AB11/AA11-1 -> -0.019683607 | AS11: =AC11/AB11-1 -> -0.17639797 | AT11: =AD11/AC11-1 -> 0.12018825 | AU11: =AE11/AD11-1 -> -0.015519566 | AV11: =AVERAGE(AQ11:AU11) -> -0.025387237 | AW11: =(1+AV11)*AE11 -> 25712937
B12: - Luar Jawa | C12: selisih | E12: M3 | O12: =+O11-O13 -> 20618181 | P12: =+P11-P13 -> 13796633 | Q12: =+Q11-Q13 -> 11153944 | R12: =+R11-R13 -> 9002620.1 | S12: =+S11-S13 -> 11422524 | T12: =+T11-T13 -> 13548014 | U12: =+U11-U13 -> 24221883 | V12: =+V11-V13 -> 21791268 | ... AN12: =+AN11-AN13 -> 31267437 | AO12: =AN12+AN13 -> 32071074 | AQ12: =AA12/Z12-1 -> -0.067043961 | AR12: =AB12/AA12-1 -> -0.018943909 | AS12: =AC12/AB12-1 -> -0.18317371 | AT12: =AD12/AC12-1 -> 0.12679958 | AU12: =AE12/AD12-1 -> -0.011149761 | AV12: =AVERAGE(AQ12:AU12) -> -0.030702352 | AW12: =(1+AV12)*AE12 -> 24805763
B13: - Jawa | C13: Perhutani | E13: M3 | F13: =+F50 -> 1267.733 | G13: =+G50 -> 1328.78 | H13: =+H50 -> 1315.452 | I13: =+I50 -> 1624.791 | J13: =+J50 -> 1711.463 | K13: =+K50 -> 1601.269 | L13: =+L50 -> 0 | M13: =+M50 -> 1861.863 | ... Z13: =+Z50 -> 889.461 | AA13: =+AA50*1000 -> 969200 | AB13: =+AB50*1000 -> 928922 | AC13: =+AC50*1000 -> 955584.31 | AD13: =+AD50*1000 -> 918587.01 | AE13: =+AE50*1000 -> 791240.22 | AF13: =+AF50*1000 -> 548432 | AG13: =+AG50*1000 -> 636292.36 | AH13: =+AH50*1000 -> 809934 | ... AN13: =+AN50*1000 -> 803637 | AQ13: =AA13/Z13-1 -> 1088.6487 | AR13: =AB13/AA13-1 -> -0.041557986 | AS13: =AC13/AB13-1 -> 0.028702419 | AT13: =AD13/AC13-1 -> -0.038716942 | AU13: =AE13/AD13-1 -> -0.13863334 | AV13: =AVERAGE(AQ13:AU13) -> 217.69169 | AW13: =(1+AV13)*AE13 -> 1.7303766e+08
A14: 6 | B14: Luas Hutan Produksi Luar Jawa: | C14: selisih | D14: lamp 5 | E14: Ha | I14: 31387324 | L14: 31570726 | M14: 33134599 | N14: 31366474 | O14: 31366374 | P14: 26262311 | Q14: 26262311 | R14: 26262311 | S14: 35222373 | T14: 34669774 | U14: 34665979 | V14: 34665979 | W14: 34861921 | X14: =X15-X16 -> 33939195 | Y14: =Y15-Y16 -> 34716287 | Z14: =Z15-Z16 -> 34704565 | AA14: =AA15-AA16 -> 34969065 | AB14: =AB15-AB16 -> 34767270 | AC14: =AC15-AC16 -> 26452167 | AD14: =AD15-AD16 -> 27460290 | AE14: =AE15-AE16 -> 27528702 | ... AN14: =AN15-AN16 -> 27484353 | AQ14: =AA14/Z14-1 -> 0.007621491 | AR14: =AB14/AA14-1 -> -0.0057706777 | AS14: =AC14/AB14-1 -> -0.2391647 | AT14: =AD14/AC14-1 -> 0.038111172 | AV14: =AVERAGE(AQ14:AU14) -> -0.049800678 | AW14: =(1+AV14)*AE14 -> 26157754
B15: - Indonesia | C15: NSDH | D15: lamp 6 | E15: Ha | I15: 33401655 | L15: 33203202 | M15: 34765452 | N15: 33238754 | O15: 33238654 | P15: 27823177 | Q15: 27823177 | R15: 27823177 | S15: 36608241 | T15: 36055156 | U15: 36056531 | V15: 36056531 | W15: 36279706 | X15: 35706500 | Y15: 36483592 | Z15: 36471870 | AA15: 36736370 | AB15: =(100+-0.38)/100*AA15 -> 36596772 | AC15: 28897173 | AD15: 29266920 | AE15: 29337690 | AF15: 29339772 | AG15: =29397651.71 -> 29397652 | AH15: 29379517 | AI15: 29400106 | AJ15: 29373977 | AK15: 29193500 | AL15: 29188600 | AM15: =AVERAGE(AH15:AL15) -> 29307140 | AN15: =AVERAGE(AI15:AM15) -> 29292665 | AQ15: =AA15/Z15-1 -> 0.0072521873 | AR15: =AB15/AA15-1 -> -0.0038 | AS15: =AC15/AB15-1 -> -0.21039013 | AT15: =AD15/AC15-1 -> 0.012795268 | AU15: =AE15/AD15-1 -> 0.0024180987 | AV15: =AVERAGE(AQ15:AU15) -> -0.038344915 | AW15: =AVERAGE(AA15:AE15) -> 32166985 | AX15: =AVERAGE(AA15:AE15) -> 32166985 | AY15: =U15/T15*100-100 -> 0.0038124922 | AZ15: =V15/U15*100-100 -> 0 | BA15: =W15/V15*100-100 -> 0.6189593 | BB15: =X15/W15*100-100 -> -1.5799632 | BC15: =Y15/X15*100-100 -> 2.1763312 | BD15: =Z15/Y15*100-100 -> -0.032129759 | BE15: =AA15/Z15*100-100 -> 0.72521873 | BF15: =AVERAGE(BA15:BE15) -> 0.38168325 | BL15: HP | BM15: HPT
B16: - Jawa | C16: Perhutani | D16: lamp 7 | E16: Ha | I16: 2014331.5 | L16: 1632476 | M16: 1630852.9 | N16: 1872280 | O16: 1872280 | P16: 1560866.3 | Q16: 1560866.3 | R16: 1560866.3 | S16: 1385868.3 | T16: 1385382.1 | U16: 1390552.1 | V16: 1390552.1 | W16: 1417785 | X16: =X37+X38 -> 1767305 | Y16: =Y37+Y38 -> 1767305 | Z16: =Z37+Z38 -> 1767304.7 | AA16: =AA37+AA38 -> 1767305 | AB16: =AB37+AB38 -> 1829502 | AC16: =AC37+AC38 -> 2445006 | AD16: =AD37+AD38 -> 1806630 | AE16: =AE37+AE38 -> 1808988.4 | ... AN16: =AN37+AN38 -> 1808312 | AQ16: =AA16/Z16-1 -> 1.6975002e-07 | AR16: =AB16/AA16-1 -> 0.035193133 | AS16: =AC16/AB16-1 -> 0.33643254 | AT16: =AD16/AC16-1 -> -0.26109384 | AU16: =AE16/AD16-1 -> 0.0013054139 | AV16: =AVERAGE(AQ16:AU16) -> 0.022367483 | AW16: =(1+AV16)*AE16 -> 1849450.9 | AY16: =U16/T16*100-100 -> 0.37318226 | AZ16: =V16/U16*100-100 -> 0 | BA16: =W16/V16*100-100 -> 1.9584272 | BB16: =X16/W16*100-100 -> 24.652539 | BC16: =Y16/X16*100-100 -> 0 | BD16: =Z16/Y16*100-100 -> -1.6974999e-05 | BE16: =AA16/Z16*100-100 -> 1.6975002e-05 | BF16: =AB16/AA16*100-100 -> 3.5193133 | BK16: DKI Jakarta | BL16: 158.35 | BM16: 0
A17: 7 | B17: Luas Hutan Produksi Terbatas Luar Jawa: | C17: selisih | D17: lamp 8 | E17: Ha | I17: 29570656 | L17: 29445705 | M17: 23473987 | N17: 29607522 | O17: 28907521 | P17: 15821515 | Q17: 15828380 | R17: 15828380 | S17: 22060329 | T17: 22019690 | U17: 22019690 | V17: 22019690 | W17: 21293788 | X17: 24414500 | Y17: =Y18-Y19 -> 21667857 | Z17: =Z18-Z19 -> 21587880 | AA17: =AA18-AA19 -> 21920298 | AB17: =AB18-AB19 -> 21986429 | AC17: =AC18-AC19 -> 27263154 | AD17: =AD18-AD19 -> 26419582 | AE17: =AE18-AE19 -> 26387880 | AF17: =AF18-AF19 -> 26312927 | ... AN17: =AN18-AN19 -> 26368663 | AQ17: =AA17/Z17-1 -> 0.015398391 | AR17: =AB17/AA17-1 -> 0.0030168636 | AS17: =AC17/AB17-1 -> 0.23999919 | AT17: =AD17/AC17-1 -> -0.030941841 | AV17: =AVERAGE(AQ17:AU17) -> 0.056868152 | AW17: =(1+AV17)*AE17 -> 27888510 | AY17: =U17/T17*100-100 -> 0 | AZ17: =V17/U17*100-100 -> 0 | BA17: =W17/V17*100-100 -> -3.2966052 | BB17: =X17/W17*100-100 -> 14.655504 | BC17: =Y17/X17*100-100 -> -11.250049 | BD17: =Z17/Y17*100-100 -> -0.36910453 | BE17: =AA17/Z17*100-100 -> 1.5398391 | BF17: =AB17/AA17*100-100 -> 0.30168636 | BK17: Jabar | BL17: 202965 | BM17: 190152
B18: - Indonesia | C18: NSDH | D18: lamp 9 | E18: Ha | I18: 29570656 | L18: 29833302 | M18: 23863206 | N18: 29607522 | O18: 28907521 | P18: 16209112 | Q18: 16215977 | R18: 16215977 | S18: 22451468 | T18: 22798381 | U18: 22325383 | V18: 22410793 | W18: 21717309 | X18: 24786100 | Y18: 22036484 | Z18: 21953005 | AA18: 22343819 | AB18: =(100+0.27)/100*AA18 -> 22404148 | AC18: 27686675 | AD18: 26808058 | AE18: 26768748 | AF18: 26694255 | AG18: =26735549.22 -> 26735549 | AH18: 26735850 | AI18: 26723211 | AJ18: 26745961 | AK18: 26791700 | AL18: 26759500 | AM18: =AVERAGE(AH18:AL18) -> 26751244 | AN18: =AVERAGE(AI18:AM18) -> 26754323 | AQ18: =AA18/Z18-1 -> 0.017802318 | AR18: =AB18/AA18-1 -> 0.0027 | AS18: =AC18/AB18-1 -> 0.23578346 | AT18: =AD18/AC18-1 -> -0.031734293 | AU18: =AE18/AD18-1 -> -0.0014663487 | AV18: =AVERAGE(AQ18:AU18) -> 0.044617027 | AW18: =AVERAGE(AA18:AE18) -> 25202290 | AX18: =AVERAGE(AA18:AE18) -> 25202290 | AY18: =U18/T18*100-100 -> -2.0747 | AZ18: =V18/U18*100-100 -> 0.3825688 | BA18: =W18/V18*100-100 -> -3.0944195 | BB18: =X18/W18*100-100 -> 14.130623 | BC18: =Y18/X18*100-100 -> -11.093379 | BD18: =Z18/Y18*100-100 -> -0.37882178 | BE18: =AA18/Z18*100-100 -> 1.7802318 | BF18: =AVERAGE(BA18:BE18) -> 0.26884676 | BK18: Banten | BL18: 26998 | BM18: 49439
B19: - Jawa | C19: Perhutani | D19: lamp 10 | E19: Ha | I19: 0 | L19: 387597 | M19: 389219.25 | N19: 0 | O19: 0 | P19: 387597 | Q19: 387597 | R19: 387597 | S19: 391138.5 | T19: 391102.69 | U19: 391102.69 | V19: 391102.69 | W19: 423521 | X19: 371600 | Y19: =(100-0.8)/100*X19 -> 368627.2 | Z19: =(100-0.95)/100*Y19 -> 365125.24 | AA19: =190152+49439+183930 -> 423521 | AB19: =(100-1.37)/100*AA19 -> 417718.76 | AC19: =SUM(BM16:BM21) -> 423521 | AD19: 388476.1 | AE19: =[2]Rekap!F7 -> 380868 | AF19: =[2]Rekap!G7 -> 381328 | AG19: =[2]Rekap!H7 -> 381242 | AH19: =[2]Rekap!I7 -> 380527 | AI19: =[2]Rekap!J7 -> 394212.1 | AJ19: =[2]Rekap!K7 -> 380931.2 | AK19: =[2]Rekap!L7 -> 380931.2 | AL19: =[2]Rekap!M7 -> 383395.35 | ... AN19: =[2]Rekap!O7 -> 385660.5 | AQ19: =AA19/Z19-1 -> 0.1599335 | AR19: =AB19/AA19-1 -> -0.0137 | AS19: =AC19/AB19-1 -> 0.013890297 | AT19: =AD19/AC19-1 -> -0.082746546 | AU19: =AE19/AD19-1 -> -0.019584474 | AV19: =AVERAGE(AQ19:AU19) -> 0.011558556 | AW19: =(1+AV19)*AE19 -> 385270.28 | AY19: =U19/T19*100-100 -> 0 | AZ19: =V19/U19*100-100 -> 0 | BA19: =W19/V19*100-100 -> 8.2889509 | BB19: =X19/W19*100-100 -> -12.259368 | BC19: =AVERAGE(AV19:BB19) -> 64211.054 | BD19: =AVERAGE(AY19:BC19) -> 12841.417 | BE19: =AVERAGE(AZ19:BD19) -> 15409.7 | BF19: =AVERAGE(BA19:BE19) -> 18491.64 | BK19: Jateng | BL19: 362360 | BM19: 183930
A20: 8 | B20: Luas Hutan Produksi yang Dapat Dikonversi Luar Jawa: | C20: selisih | D20: lamp 11 | E20: Ha | I20: 19039329 | L20: 18461538 | M20: 8350243.4 | N20: 36701812 | O20: 18961249 | P20: 13670535 | Q20: 13670535 | R20: 13670535 | S20: 22792495 | T20: 22730824 | U20: 22683618 | V20: 22551180 | W20: 22795961 | X20: 22351500 | Y20: =Y21-Y22 -> 19603162 | Z20: =Z21-Z22 -> 19665354 | AA20: =AA21-AA22 -> 22744932 | AB20: =AB21-AB22 -> 22872304 | AC20: =AC21-AC22 -> 15525433 | AD20: =AD21-AD22 -> 12561893 | AE20: =AE21-AE22 -> 12228730 | AF20: =AF21-AF22 -> 11980831 | ... AN20: =AN21-AN22 -> 11430295 | AQ20: =AA20/Z20-1 -> 0.15659917 | AR20: =AB20/AA20-1 -> 0.0056 | AS20: =AC20/AB20-1 -> -0.32121255 | AT20: =AD20/AC20-1 -> -0.19088288 | AV20: =AVERAGE(AQ20:AU20) -> -0.087474065 | AW20: =(1+AV20)*AE20 -> 11159034 | AY20: =U20/T20*100-100 -> -0.20767509 | AZ20: =V20/U20*100-100 -> -0.58384924 | BA20: =W20/V20*100-100 -> 1.0854483 | BB20: =X20/W20*100-100 -> -1.9497357 | BC20: =Y20/X20*100-100 -> -12.295989 | BD20: =Z20/Y20*100-100 -> 0.31725504 | BE20: =AA20/Z20*100-100 -> 15.659917 | BF20: =AB20/AA20*100-100 -> 0.56 | BK20: DIY | BL20: 13851.28 | BM20: 0
B21: - Indonesia | C21: NSDH | D21: lamp 12 | E21: Ha | I21: 19039329 | L21: 18461538 | M21: 8350243.4 | N21: 36701812 | O21: 18961249 | P21: 13670535 | Q21: 13670535 | R21: 13670535 | S21: 22792495 | T21: 22730824 | U21: 22683618 | V21: 22551180 | W21: 22795961 | X21: 22351500 | Y21: 19603162 | Z21: 19665354 | AA21: 22744932 | AB21: =(100+0.56)/100*AA21 -> 22872304 | AC21: 15525433 | AD21: 12561893 | AE21: 12228730 | AF21: 11980831 | AG21: =11745407.44 -> 11745407 | AH21: 11693458 | AI21: 11572023 | AJ21: 11554196 | AK21: 11335500 | AL21: 11215600 | AM21: =AVERAGE(AH21:AL21) -> 11474155 | AN21: =AVERAGE(AI21:AM21) -> 11430295 | AQ21: =AA21/Z21-1 -> 0.15659917 | AR21: =AB21/AA21-1 -> 0.0056 | AS21: =AC21/AB21-1 -> -0.32121255 | AT21: =AD21/AC21-1 -> -0.19088288 | AU21: =AE21/AD21-1 -> -0.026521722 | AV21: =AVERAGE(AQ21:AU21) -> -0.075283596 | AW21: =AVERAGE(AA21:AE21) -> 17186658 | AX21: =AVERAGE(AA21:AE21) -> 17186658 | AY21: =U21/T21*100-100 -> -0.20767509 | AZ21: =V21/U21*100-100 -> -0.58384924 | BA21: =W21/V21*100-100 -> 1.0854483 | BB21: =X21/W21*100-100 -> -1.9497357 | BC21: =Y21/X21*100-100 -> -12.295989 | BD21: =Z21/Y21*100-100 -> 0.31725504 | BE21: =AA21/Z21*100-100 -> 15.659917 | BF21: =AVERAGE(BA21:BE21) -> 0.56337898 | BK21: Jatim | BL21: 782772 | BM21: 0
B22: - Jawa | C22: Perhutani | D22: lamp 13 | E22: Ha | I22: 0 | L22: 0 | M22: 0 | N22: 0 | O22: 0 | P22: 0 | Q22: 0 | R22: 0 | S22: 0 | T22: 0 | U22: 0 | V22: 0 | W22: 0 | X22: 0 | Y22: 0 | Z22: 0 | AA22: 0 | AC22: 0 | AD22: 0 | AE22: 0 | AF22: 0 | AW22: =(1+AV22)*AE22 -> 0 | AY22: =U22/T22*100-100 -> #DIV/0! | AZ22: =V22/U22*100-100 -> #DIV/0! | BA22: =W22/V22*100-100 -> #DIV/0! | BB22: =X22/W22*100-100 -> #DIV/0! | BC22: =Y22/X22*100-100 -> #DIV/0! | BD22: =Z22/Y22*100-100 -> #DIV/0! | BE22: =AA22/Z22*100-100 -> #DIV/0! | BF22: =AB22/AA22*100-100 -> #DIV/0! | BK22: JAWA | BL22: =SUM(BL16:BL21) -> 1389104.6 | BM22: =SUM(BM16:BM21) -> 423521
A23: 9 | B23: Luas Hutan Produksi Seluruhnya Luar Jawa: | C23: = jumlah (6)+(7)+(8) | E23: Ha | I23: 79997309 | L23: 79477969 | M23: 64958830 | N23: 97675807 | O23: 79235144 | P23: 55754361 | Q23: 55761226 | R23: 55761226 | S23: 80075197 | T23: 79420288 | U23: 79369287 | V23: =V20+V17+V14 -> 79236849 | W23: =W20+W17+W14 -> 78951670 | X23: =X20+X17+X14 -> 80705195 | Y23: =Y20+Y17+Y14 -> 75987305 | Z23: =Z20+Z17+Z14 -> 75957798 | AA23: =AA20+AA17+AA14 -> 79634296 | AB23: =AB20+AB17+AB14 -> 79626003 | AC23: =AC20+AC17+AC14 -> 69240753 | ... AN23: =AN20+AN17+AN14 -> 65283310 | AQ23: =AA23/Z23-1 -> 0.04840184 | AR23: =AB23/AA23-1 -> -0.00010413904 | AS23: =AC23/AB23-1 -> -0.13042535 | AT23: =AD23/AC23-1 -> -0.040424002 | AV23: =AVERAGE(AQ23:AU23) -> -0.030637913 | AW23: =(1+AV23)*AE23 -> 64118758 | AY23: =U23/T23*100-100 -> -0.06421742 | AZ23: =V23/U23*100-100 -> -0.1668632 | BA23: =W23/V23*100-100 -> -0.3599065 | BB23: =X23/W23*100-100 -> 2.2210107 | BC23: =Y23/X23*100-100 -> -5.8458315 | BD23: =Z23/Y23*100-100 -> -0.038831238 | BE23: =AA23/Z23*100-100 -> 4.840184 | BF23: =AB23/AA23*100-100 -> -0.010413904
B24: - Indonesia | E24: Ha | I24: 82011641 | L24: 81498042 | M24: 66978902 | N24: 99548087 | O24: 81107424 | P24: 57702825 | Q24: 57709690 | R24: 57709690 | S24: 81852204 | T24: 81196773 | U24: 81150941 | V24: 81018503 | W24: =W21+W18+W15 -> 80792976 | X24: =X21+X18+X15 -> 82844100 | Y24: =Y21+Y18+Y15 -> 78123237 | Z24: =Z21+Z18+Z15 -> 78090228 | AA24: =AA21+AA18+AA15 -> 81825122 | AB24: =AB21+AB18+AB15 -> 81873223 | AC24: =AC21+AC18+AC15 -> 72109280 | AD24: =AD21+AD18+AD15 -> 68636871 | ... AN24: =AN21+AN18+AN15 -> 67477283 | AQ24: =AA24/Z24-1 -> 0.047827921 | AR24: =AB24/AA24-1 -> 0.00058786009 | AS24: =AC24/AB24-1 -> -0.11925686 | AT24: =AD24/AC24-1 -> -0.048154818 | AV24: =AVERAGE(AQ24:AU24) -> -0.029748973 | AW24: =(1+AV24)*AE24 -> 66302267 | AY24: =U24/T24*100-100 -> -0.056445174 | AZ24: =V24/U24*100-100 -> -0.16319975 | BA24: =W24/V24*100-100 -> -0.27836519 | BB24: =X24/W24*100-100 -> 2.5387405 | BC24: =Y24/X24*100-100 -> -5.6984897 | BD24: =Z24/Y24*100-100 -> -0.042252563 | BE24: =AA24/Z24*100-100 -> 4.7827921 | BF24: =AB24/AA24*100-100 -> 0.058786009
B25: - Jawa | E25: Ha | I25: 2014331.5 | L25: 2020073 | M25: 2020072.2 | N25: 1872280 | O25: 1872280 | P25: 1948463.3 | Q25: 1948463.3 | R25: 1948463.3 | S25: 1777006.8 | T25: 1776484.7 | U25: 1781654.7 | V25: 1781654.7 | W25: =W22+W19+W16 -> 1841306 | X25: =X22+X19+X16 -> 2138905 | Y25: =Y22+Y19+Y16 -> 2135932.2 | Z25: =Z22+Z19+Z16 -> 2132429.9 | AA25: =AA22+AA19+AA16 -> 2190826 | AB25: =AB22+AB19+AB16 -> 2247220.8 | AC25: =AC22+AC19+AC16 -> 2868527 | AD25: =AD22+AD19+AD16 -> 2195106.1 | ... AN25: =AN22+AN19+AN16 -> 2193972.5 | AQ25: =AA25/Z25-1 -> 0.027384749 | AR25: =AB25/AA25-1 -> 0.025741324 | AS25: =AC25/AB25-1 -> 0.27647762 | AT25: =AD25/AC25-1 -> -0.23476192 | AU25: =AE25/AD25-1 -> -0.0023915473 | AV25: =AVERAGE(AQ25:AU25) -> 0.018490045 | AW25: =(1+AV25)*AE25 -> 2230346.9 | AY25: =U25/T25*100-100 -> 0.29102417 | AZ25: =V25/U25*100-100 -> 0 | BA25: =W25/V25*100-100 -> 3.3480819 | BB25: =X25/W25*100-100 -> 16.162387 | BC25: =Y25/X25*100-100 -> -0.13898701 | BD25: =Z25/Y25*100-100 -> -0.16396861 | BE25: =AA25/Z25*100-100 -> 2.7384749 | BF25: =AB25/AA25*100-100 -> 2.5741324
A26: 10 | B26: Banyaknya kerugian & Kerusakan Hutan (Kayu Bulat) | C26: NSDH | E26: M3 | P26: 42466.6 | Q26: 279014.02 | R26: 233637.23 | S26: 228273.6 | W26: 3650.59 | X26: 14632.36 | AW26: =(1+AV26)*AE26 -> 0 | AY26: =U26/T26*100-100 -> #DIV/0! | AZ26: =V26/U26*100-100 -> #DIV/0! | BA26: =W26/V26*100-100 -> #DIV/0! | BB26: =X26/W26*100-100 -> 300.82178 | BC26: =Y26/X26*100-100 -> -100 | BD26: =Z26/Y26*100-100 -> #DIV/0! | BE26: =AA26/Z26*100-100 -> #DIV/0! | BF26: =AB26/AA26*100-100 -> #DIV/0!
A27: 12 | B27: Luas Hutan yang Rusak | C27: NSDH | E27: Ha | P27: 253740.56 | Q27: 2747678.6 | R27: 2993759.1 | S27: 5384269.3 | AW27: =(1+AV27)*AE27 -> 0 | AY27: =U27/T27*100-100 -> #DIV/0! | AZ27: =V27/U27*100-100 -> #DIV/0! | BA27: =W27/V27*100-100 -> #DIV/0! | BB27: =X27/W27*100-100 -> #DIV/0! | BC27: =Y27/X27*100-100 -> #DIV/0! | BD27: =Z27/Y27*100-100 -> #DIV/0! | BE27: =AA27/Z27*100-100 -> #DIV/0! | BF27: =AB27/AA27*100-100 -> #DIV/0!
A28: 13 | B28: Luas Konversi Hutan untuk Transmigrasi | C28: NSDH | D28: lamp 10 | E28: Ha | X28: 43465 | AA28: 4051.61 | AB28: 6328.13 | AC28: 5307.51 | AD28: =993.25 -> 993.25 | AF28: =3774.43 -> 3774.43 | AG28: 195.76 | AH28: 0 | AI28: 2772.46 | AJ28: 0 | AK28: 0 | AL28: 0 | AM28: 0 | AN28: 0 | AQ28: =AA28/Z28-1 -> #DIV/0! | AR28: =AB28/AA28-1 -> 0.56188034 | AS28: =AC28/AB28-1 -> -0.16128303 | AT28: =AD28/AC28-1 -> -0.81285951 | AU28: =AE29/AD28-1 -> 66.615787 | AV28: =AVERAGE(AQ28:AU28) -> #DIV/0! | AW28: =(1+AV28)*AE29 -> #DIV/0! | AY28: =U28/T28*100-100 -> #DIV/0! | AZ28: =V28/U28*100-100 -> #DIV/0! | BA28: =W28/V28*100-100 -> #DIV/0! | BB28: =X28/W28*100-100 -> #DIV/0! | BC28: =Y28/X28*100-100 -> -100 | BD28: =Z28/Y28*100-100 -> #DIV/0! | BE28: =AA28/Z28*100-100 -> #DIV/0! | BF28: =AB28/AA28*100-100 -> 56.188034 | BN28: buku statistik pktl tabel IV.2 dan IV.3
A29: 14 | B29: Luas Konversi Hutan untuk Budidaya Non Hutan | C29: NSDH | D29: lamp 11 | E29: Ha | P29: 235101.65 | Q29: 13612.3 | R29: 0 | S29: 0 | T29: 0 | U29: 59744.56 | X29: 77216.73 | AA29: 540580.71 | AB29: 652130.77 | AC29: 170979.77 | AD29: 367931.98 | AE29: =67159.38 -> 67159.38 | AF29: 186579.89 | AG29: 249338.92 | AH29: 76719.08 | AI29: 75276.18 | AJ29: 31234.22 | AK29: 86445.7 | AL29: 32943.5 | AM29: =AVERAGE(AH29:AL29) -> 60523.736 | AN29: =AVERAGE(AI29:AM29) -> 57284.667 | AQ29: =AA29/Z29-1 -> #DIV/0! | AR29: =AB29/AA29-1 -> 0.20635228 | AS29: =AC29/AB29-1 -> -0.73781368 | AT29: =AD29/AC29-1 -> 1.1519036 | AU29: =#REF!/AD29-1 -> #REF! | AV29: =AVERAGE(AQ29:AU29) -> #DIV/0! | AW29: =(1+AV29)*#REF! -> #DIV/0! | AY29: =U29/T29*100-100 -> #DIV/0! | AZ29: =V29/U29*100-100 -> -100 | BA29: =W29/V29*100-100 -> #DIV/0! | BB29: =X29/W29*100-100 -> #DIV/0! | BC29: =Y29/X29*100-100 -> -100 | BD29: =Z29/Y29*100-100 -> #DIV/0! | BE29: =AA29/Z29*100-100 -> #DIV/0! | BF29: =AB29/AA29*100-100 -> 20.635228 | BN29: https://pktl.menlhk.go.id/publikasi/buku_statistik
A30: 15 | B30: Luas Hutan (Pinjam Pakai) untuk Pemb. Non Hutan | C30: NSDH | D30: lamp 39 | E30: Ha | P30: 90022.08 | Q30: 44494.37 | R30: 21466.32 | S30: 13294.85 | AA30: 41940.93 | AD30: =11214.82+34521.53+6320.36 -> 52056.71 | AE30: =3159.43+7522.92+1999.29 -> 12681.64 | AQ30: =AA30/Z30-1 -> #DIV/0! | AR30: =AB30/AA30-1 -> -1 | AS30: =AC30/AB30-1 -> #DIV/0! | AT30: =AD30/AC30-1 -> #DIV/0! | AU30: =AE30/AD30-1 -> -0.75638799 | AV30: =AVERAGE(AQ30:AU30) -> #DIV/0! | AW30: =(1+AV30)*AE30 -> #DIV/0! | AY30: =U30/T30*100-100 -> #DIV/0! | AZ30: =V30/U30*100-100 -> #DIV/0! | BA30: =W30/V30*100-100 -> #DIV/0! | BB30: =X30/W30*100-100 -> #DIV/0! | BC30: =Y30/X30*100-100 -> #DIV/0! | BD30: =Z30/Y30*100-100 -> #DIV/0! | BE30: =AA30/Z30*100-100 -> #DIV/0! | BF30: =AB30/AA30*100-100 -> -100
A31: 16 | B31: Luas Konversi Hutan untuk Non Hutan | C31: NSDH | E31: Ha | P31: 325123.73 | Q31: 58106.67 | R31: 21466.32 | S31: 13294.85 | AQ31: =AA31/Z31-1 -> #DIV/0! | AR31: =AB31/AA31-1 -> #DIV/0! | AS31: =AC31/AB31-1 -> #DIV/0! | AT31: =AD31/AC31-1 -> #DIV/0! | AU31: =AE31/AD31-1 -> #DIV/0! | AV31: =AVERAGE(AQ31:AU31) -> #DIV/0! | AW31: =(1+AV31)*AE31 -> #DIV/0! | AY31: =U31/T31*100-100 -> #DIV/0! | AZ31: =V31/U31*100-100 -> #DIV/0! | BA31: =W31/V31*100-100 -> #DIV/0! | BB31: =X31/W31*100-100 -> #DIV/0! | BC31: =Y31/X31*100-100 -> #DIV/0! | BD31: =Z31/Y31*100-100 -> #DIV/0! | BE31: =AA31/Z31*100-100 -> #DIV/0! | BF31: =AB31/AA31*100-100 -> #DIV/0!
A32: 17 | B32: Penanaman Hutan Rakyat/Kebun Rakyat | C32: NSDH | D32: lamp 35 hutan alam | E32: Ha | R32: 38341 | S32: 214296 | T32: 333291 | U32: 32164 | V32: 248133 | W32: =(100-(Y32/X32))/100*X32 -> 56144.322 | X32: =(100-(Z32/Y32))/100*Y32 -> 56713.83 | Y32: 56950.8 | Z32: 23697 | AA32: 51654.44 | AB32: =(100+(AA32/Z32))/100*AA32 -> 52780.397 | AC32: =(100+(AB32/AA32))/100*AB32 -> 53319.706 | AD32: =(100+(AC32/AB32))/100*AC32 -> 53858.352 | AQ32: =AA32/Z32-1 -> 1.1797882 | AR32: =AB32/AA32-1 -> 0.021797882 | AS32: =AC32/AB32-1 -> 0.010217979 | AT32: =AD32/AC32-1 -> 0.01010218 | AU32: =AE32/AD32-1 -> -1 | AV32: =AVERAGE(AQ32:AU32) -> 0.04438124 | AW32: =(1+AV32)*AE32 -> 0 | AY32: =U32/T32*100-100 -> -90.349574 | AZ32: =V32/U32*100-100 -> 671.46188 | BA32: =W32/V32*100-100 -> -77.373295 | BB32: =X32/W32*100-100 -> 1.0143644 | BC32: =Y32/X32*100-100 -> 0.41783459 | BD32: =Z32/Y32*100-100 -> -58.3904 | BE32: =AA32/Z32*100-100 -> 117.97882 | BF32: =AB32/AA32*100-100 -> 2.1797882
A33: 18 | B33: Penanaman/Rehabilitasi Tanaman Bakau | C33: NSDH | D33: lamp 39 | E33: Ha | R33: 4297 | S33: 1655 | T33: 9536 | U33: 2775 | V33: 7952 | W33: =(100-(Y33/X33))/100*X33 -> 78996.485 | X33: 79269 | Y33: 27251.5 | Z33: 69005.42 | AA33: 2920.09 | AB33: =(100+(AA33/Z33))/100*AA33 -> 2921.3257 | AC33: 12403 | AQ33: =AA33/Z33-1 -> -0.95768318 | AR33: =AB33/AA33-1 -> 0.00042316821 | AS33: =AC33/AB33-1 -> 3.2456752 | AT33: =AD33/AC33-1 -> -1 | AU33: =AE33/AD33-1 -> #DIV/0! | AV33: =AVERAGE(AQ33:AU33) -> #DIV/0! | AW33: =(1+AV33)*AE33 -> #DIV/0! | AY33: =U33/T33*100-100 -> -70.899748 | AZ33: =V33/U33*100-100 -> 186.55856 | BA33: =W33/V33*100-100 -> 893.41656 | BB33: =X33/W33*100-100 -> 0.34497105 | BC33: =Y33/X33*100-100 -> -65.621491 | BD33: =Z33/Y33*100-100 -> 153.21696 | BE33: =AA33/Z33*100-100 -> -95.768318 | BF33: =AB33/AA33*100-100 -> 0.042316821
A34: 19 | B34: Realisasi Penanaman HTI | C34: NSDH | D34: lamp 37 | E34: Ha | R34: 118508 | S34: 124691 | T34: 131914 | U34: 163125 | V34: 231953.87 | W34: 334838.71 | X34: 291984 | Y34: =(100+20.64)/100*X34 -> 352249.5 | Z34: =(100+23.61)/100*Y34 -> 435415.6 | AA34: =458675+135004.39 -> 593679.39 | AB34: =(100+19.88)/100*AA34 -> 711702.85 | AC34: =(100+19.88)/100*AB34 -> 853189.38 | AD34: =(100+19.88)/100*AC34 -> 1022803.4 | AQ34: =AA34/Z34-1 -> 0.36347752 | AR34: =AB34/AA34-1 -> 0.1988 | AS34: =AC34/AB34-1 -> 0.1988 | AT34: =AD34/AC34-1 -> 0.1988 | AU34: =AE34/AD34-1 -> -1 | AV34: =AVERAGE(AQ34:AU34) -> -0.008024495 | AW34: =(1+AV34)*AE34 -> 0 | AY34: =U34/T34*100-100 -> 23.660112 | AZ34: =V34/U34*100-100 -> 42.193943 | BA34: =W34/V34*100-100 -> 44.355733 | BB34: =X34/W34*100-100 -> -12.798613 | BC34: =AVERAGE(AV34:BB34) -> 16.233859 | BD34: =AVERAGE(AY34:BC34) -> 22.729007 | BE34: =AVERAGE(AZ34:BD34) -> 22.542786 | BF34: =AVERAGE(BA34:BE34) -> 18.612554
B35: Potensi tegakan hutan rata-rata secara nasional | E35: ribu m3/Ha | X35: 52.15 | AA35: =$X$35*AA84/1000 -> 28564.609 | AB35: =$X$35*AB84/1000 -> 34409.832 | AC35: =$X$35*AC84/1000 -> 9283.2669 | AD35: =$X$35*AD84/1000 -> 19867.803 | AE35: =$X$35*AE84/1000 -> 63131.77 | AF35: =$X$35*AF84/1000 -> 19845.44 | AG35: =$X$35*AG84/1000 -> 15321.371 | AH35: =$X$35*AH84/1000 -> 13102.447 | ... AN35: =$X$35*AN84/1000 -> 9816.7123 | AQ35: =AA35/Z35-1 -> #DIV/0! | AR35: =AB35/AA35-1 -> 0.20463166 | AS35: =AC35/AB35-1 -> -0.7302147 | AT35: =AD35/AC35-1 -> 1.1401737 | AU35: =AE35/AD35-1 -> 2.1775918 | AV35: =AVERAGE(AQ35:AU35) -> #DIV/0! | AW35: =(1+AV35)*AE35 -> #DIV/0!
B36: PT Perhutani (Jawa) | P36: -0.8981224 | AP36: 2015 | AQ36: =AA36/Z36-1 -> #DIV/0! | AR36: =AB36/AA36-1 -> #DIV/0! | AS36: =AC36/AB36-1 -> #DIV/0! | AT36: =AD36/AC36-1 -> #DIV/0! | AU36: =AE36/AD36-1 -> #DIV/0! | AV36: =AVERAGE(AQ36:AU36) -> #DIV/0! | AW36: =(1+AV36)*AE36 -> #DIV/0!
A37: 1 | B37: Luas Hutan Produksi (HP) Jati | C37: Perhutani T.2.1.3 (hal.17) | D37: Total 2008 | E37: Ha | H37: 1028817.1 | I37: 1066532.1 | J37: 1059585 | K37: 1106189 | L37: 1103608.3 | M37: 1101033.5 | N37: 1098464.8 | O37: 1095902.1 | P37: 1093345.6 | Q37: 1083924.6 | R37: 1048896.2 | S37: 1074270.1 | T37: 1079908.2 | U37: 1099411.3 | V37: 1100533.7 | W37: 1099402.4 | X37: 1100534 | Y37: 1100534 | Z37: 1100533.7 | AA37: 1100533.7 | AB37: 1100534 | AC37: 1238372 | AD37: 1075441 | AE37: 1076844.9 | AF37: =[2]Rekap!G16 -> 968903.72 | AG37: =[2]Rekap!H16 -> 963117 | AH37: =[2]Rekap!I16 -> 952725 | AI37: =[2]Rekap!J16 -> 953270 | AJ37: =[2]Rekap!K16 -> 1222559.1 | AK37: =[2]Rekap!L16 -> 1222560 | AL37: =[2]Rekap!M16 -> 1230563.5 | AM37: =[2]Rekap!N16 -> 1094376 | AN37: =[2]Rekap!O16 -> 1094380 | AP37: =(AE37/AD37) -> 1.0013054 | AQ37: =AA37/Z37-1 -> 0 | AR37: =AB37/AA37-1 -> 2.9985452e-07 | AS37: =AC37/AB37-1 -> 0.12524647 | AT37: =AD37/AC37-1 -> -0.1315687 | AU37: =AE37/AD37-1 -> 0.0013054139 | AV37: =AVERAGE(AQ37:AU37) -> -0.0010033039 | AW37: =(1+AV37)*AE37 -> 1075764.5
A38: 2 | B38: Luas Hutan Produksi (HP) Rimba | C38: Perhutani T.2.1.3 (hal.17): Total-jati-payau-mangrove | D38: Total 2007 | E38: Ha | H38: 907349.96 | I38: 890242.58 | J38: 879231 | K38: 861622 | L38: 853883.6 | M38: 846214.7 | N38: 838614.68 | O38: 831082.91 | P38: 823618.69 | Q38: 833038.91 | R38: 821985.87 | S38: 705374.62 | T38: 863541.34 | U38: 695530.32 | V38: 666771.03 | W38: 692698.32 | X38: 666771 | Y38: 666771 | Z38: 666771.03 | AA38: 666771.33 | AB38: 728968 | AC38: 1206634 | AD38: 731189 | AE38: 732143.5 | AF38: =[2]Rekap!G17 -> 435887 | AG38: =[2]Rekap!H17 -> 441728 | AH38: =[2]Rekap!I17 -> 457697 | AI38: =[2]Rekap!J17 -> 450103.2 | AJ38: =[2]Rekap!K17 -> 196273.9 | AK38: =[2]Rekap!L17 -> 196273 | AL38: =[2]Rekap!M17 -> 187178.76 | AM38: =[2]Rekap!N17 -> 713742 | AN38: =[2]Rekap!O17 -> 713932 | AP38: =(AE38/AD38) -> 1.0013054 | AQ38: =AA38/Z38-1 -> 4.4992957e-07 | AR38: =AB38/AA38-1 -> 0.09328036 | AS38: =AC38/AB38-1 -> 0.65526333 | AT38: =AD38/AC38-1 -> -0.39402586 | AU38: =AE38/AD38-1 -> 0.0013054139 | AV38: =AVERAGE(AQ38:AU38) -> 0.071164739 | AW38: =(1+AV38)*AE38 -> 784246.31
A39: 3 | B39: Perubahan Luas Hutan Produksi Jati | D39: Total 2009 | E39: Ha | I39: -37714.94 | J39: 6947.07 | K39: -46604 | L39: 2580.7389 | M39: 2574.7181 | N39: 2568.7113 | O39: 2562.7185 | P39: 2556.5033 | Q39: -9420.96 | R39: -35028.43 | S39: 25373.83 | T39: 5638.16 | U39: 19503.06 | V39: 1122.4 | W39: =W37-V37 -> -1131.3 | X39: =X37-W37 -> 1131.63 | Y39: =Y37-X37 -> 0 | Z39: =Z37-Y37 -> -0.33 | AA39: =AA37-Z37 -> 0 | AB39: =AB37-AA37 -> 0.33 | AC39: =AC37-AB37 -> 137838 | AD39: =AD37-AC37 -> -162931 | ... AN39: =AN37-AM37 -> 4 | AP39: =(AE39/AD39) -> -0.0086165044 | AQ39: =AA39/Z39-1 -> -1 | AS39: =AC39/AB39-1 -> 417689.91 | AT39: =AD39/AC39-1 -> -2.182047 | AU39: =AE39/AD39-1 -> -1.0086165 | AV39: =AVERAGE(AQ39:AU39) -> 104421.43 | AW39: =(1+AV39)*AE39 -> 1.465982e+08
A40: 4 | B40: Perubahan Luas Hutan Produksi Rimba | D40: total 2010 | E40: Ha | I40: 17107.38 | J40: 11011.58 | K40: 17609 | L40: 7738.3995 | M40: 7668.8994 | N40: 7600.0235 | O40: 7531.7661 | P40: 7464.2215 | Q40: 9420.22 | R40: -11053.04 | S40: -116611.25 | T40: 158166.72 | U40: -168011.02 | V40: -28759.29 | W40: =W38-V38 -> 25927.29 | X40: =X38-W38 -> -25927.32 | Y40: =Y38-X38 -> 0 | Z40: =Z38-Y38 -> 0.03 | AA40: =AA38-Z38 -> 0.3 | AB40: =AB38-AA38 -> 62196.67 | AC40: =AC38-AB38 -> 477666 | AD40: =AD38-AC38 -> -475445 | ... AN40: =AN38-AM38 -> 190 | AP40: =(AE40/AD40) -> -0.002007602 | AQ40: =AA40/Z40-1 -> 9 | AR40: =AB40/AA40-1 -> 207321.23 | AS40: =AC40/AB40-1 -> 6.6799288 | AT40: =AD40/AC40-1 -> -1.9953503 | AU40: =AE40/AD40-1 -> -1.0020076 | AV40: =AVERAGE(AQ40:AU40) -> 41466.783 | AW40: =(1+AV40)*AE40 -> 39581178
A41: 5 | B41: Luas Reboisasi Rutin: | E41: Ha | F41: 11719.56 | G41: 14193.38 | H41: 9368.92 | I41: 9928.42 | J41: 10205.2 | K41: 9775 | M41: 9656 | N41: 9266 | O41: 10566 | P41: 9966 | Q41: 9765 | R41: 8770 | S41: 7101.2 | T41: 7003 | U41: 5249 | V41: 3657 | W41: 5046 | X41: 3922 | Y41: =+Y42+Y43 -> 3082 | Z41: =+Z42+Z43 -> 4192.63 | AA41: =+AA42+AA43 -> 3810 | AB41: =+AB42+AB43 -> 3173 | AC41: 3614.75 | AD41: 4184 | AE41: 4001.63 | AF41: =+AF42+AF43 -> 3791 | AG41: =+AG42+AG43 -> 3185.53 | AH41: =+AH42+AH43 -> 4736 | AI41: =+AI42+AI43 -> 4847 | AJ41: =+AJ42+AJ43 -> 6060 | AK41: =+AK42+AK43 -> 5632 | AL41: =+AL42+AL43 -> 5145 | AM41: =+AM42+AM43 -> 5305 | AN41: =+AN42+AN43 -> 5730 | AP41: =(AE41/AD41) -> 0.95641252 | AQ41: =AA41/Z41-1 -> -0.091262525 | AR41: =AB41/AA41-1 -> -0.1671916 | AS41: =AC41/AB41-1 -> 0.13922156 | AT41: =AD41/AC41-1 -> 0.15747977 | AU41: =AE41/AD41-1 -> -0.043587476 | AV41: =AVERAGE(AQ41:AU41) -> -0.001068055 | AW41: =(1+AV41)*AE41 -> 3997.356
B42: a. Jati | C42: Perhutani T.2.2.2 (hal.15) | E42: Ha | F42: 6357.6 | G42: 5811.45 | H42: 5556.6 | I42: 4590.17 | J42: 5710.2 | K42: 5544.14 | M42: 4963 | N42: 4775 | O42: 5873 | P42: 5746 | Q42: 4984 | R42: 4678 | S42: 4348.6 | T42: 3705 | U42: 4059 | V42: 2438 | W42: 3374 | X42: 2566 | Y42: 2170 | Z42: 2344 | AA42: 2604 | AB42: 2554 | AC42: 2277.75 | AD42: 2938 | AE42: 2600.34 | AF42: =[2]Rekap!G19 -> 2863 | AG42: =[2]Rekap!H19 -> 2356.18 | AH42: =[2]Rekap!I19 -> 3264 | AI42: =[2]Rekap!J19 -> 3338 | AJ42: =[2]Rekap!K19 -> 3382 | AK42: =[2]Rekap!L19 -> 3307 | AL42: =[2]Rekap!M19 -> 3024 | AM42: =[2]Rekap!N19 -> 3601 | AN42: =[2]Rekap!O19 -> 3807 | AP42: =(AE42/AD42) -> 0.88507148 | AQ42: =AA42/Z42-1 -> 0.1109215 | AR42: =AB42/AA42-1 -> -0.019201229 | AS42: =AC42/AB42-1 -> -0.10816366 | AT42: =AD42/AC42-1 -> 0.28986939 | AU42: =AE42/AD42-1 -> -0.11492852 | AV42: =AVERAGE(AQ42:AU42) -> 0.031699495 | AW42: =(1+AV42)*AE42 -> 2682.7695
B43: b. Rimba | E43: Ha | F43: 5361.96 | G43: 8381.93 | H43: 3812.32 | I43: 5338.25 | J43: 4495 | K43: 4230.86 | M43: 4693 | N43: 4491 | O43: 4693 | P43: 4220 | Q43: 4781 | R43: 4092 | S43: 2752.6 | T43: 3298 | U43: 1190 | V43: 1219 | W43: 1672 | X43: 1356 | Y43: 912 | Z43: 1848.63 | AA43: 1206 | AB43: 619 | AC43: 1337 | AD43: 1246 | AE43: 1401.29 | AF43: =[2]Rekap!G20 -> 928 | AG43: =[2]Rekap!H20 -> 829.35 | AH43: =[2]Rekap!I20 -> 1472 | AI43: =[2]Rekap!J20 -> 1509 | AJ43: =[2]Rekap!K20 -> 2678 | AK43: =[2]Rekap!L20 -> 2325 | AL43: =[2]Rekap!M20 -> 2121 | AM43: =[2]Rekap!N20 -> 1704 | AN43: =[2]Rekap!O20 -> 1923 | AP43: =(AE43/AD43) -> 1.1246308 | AQ43: =AA43/Z43-1 -> -0.347625 | AR43: =AB43/AA43-1 -> -0.486733 | AS43: =AC43/AB43-1 -> 1.1599354 | AT43: =AD43/AC43-1 -> -0.068062827 | AU43: =AE43/AD43-1 -> 0.12463082 | AV43: =AVERAGE(AQ43:AU43) -> 0.076429074 | AW43: =(1+AV43)*AE43 -> 1508.3893
A44: 6 | B44: Luas Reboisasi Pembangunan: | E44: Ha | F44: 44088.63 | G44: 57605.41 | H44: 49673.65 | I44: 37676.1 | J44: 32153.9 | K44: 34008.94 | M44: 39181 | N44: 40522 | O44: 61260 | P44: 65398 | Q44: 72750 | R44: 80208 | S44: 64473 | T44: 63585 | U44: 78063 | V44: 93603 | W44: 159376 | X44: 94553 | Y44: =+Y45+Y46 -> 50952 | Z44: =+Z45+Z46 -> 62730 | AA44: =+AA45+AA46 -> 43939 | AB44: =+AB45+AB46 -> 35234 | AC44: 28357 | AD44: 35535 | AE44: 33396.63 | AF44: =+AF45+AF46 -> 4861 | AG44: =+AG45+AG46 -> 15270.824 | AH44: =+AH45+AH46 -> 19014 | AI44: =+AI45+AI46 -> 26057 | AJ44: =+AJ45+AJ46 -> 28989 | AK44: =+AK45+AK46 -> 35819 | AL44: =+AL45+AL46 -> 19989 | AM44: =+AM45+AM46 -> 20763 | AN44: =+AN45+AN46 -> 14606 | AP44: =(AE44/AD44) -> 0.93982355 | AQ44: =AA44/Z44-1 -> -0.29955364 | AR44: =AB44/AA44-1 -> -0.19811557 | AS44: =AC44/AB44-1 -> -0.19518079 | AT44: =AD44/AC44-1 -> 0.25312974 | AU44: =AE44/AD44-1 -> -0.060176446 | AV44: =AVERAGE(AQ44:AU44) -> -0.099979342 | AW44: =(1+AV44)*AE44 -> 30057.657
B45: a. Jati | C45: Perhutani T.2.2.3 (hal.15) | D45: di estimasi data belum dapat | E45: Ha | F45: 2853.7 | G45: 4745.2 | H45: 3099.8 | I45: 3410.4 | J45: 2402.6 | K45: 4236.45 | M45: 9967 | N45: 14204 | O45: 26030 | P45: 38414 | Q45: 41603 | R45: 40191 | S45: 36400 | T45: 33914 | U45: 38905 | V45: 39184 | W45: 59231 | X45: 29450 | Y45: 16980 | Z45: 16980 | AA45: 27264 | AB45: 21975 | AC45: 13955 | AD45: 20402 | AE45: 17728.03 | AF45: =[2]Rekap!G22 -> 1617 | AG45: =[2]Rekap!H22 -> 4905.18 | AH45: =[2]Rekap!I22 -> 12043 | AI45: =[2]Rekap!J22 -> 14532 | AJ45: =[2]Rekap!K22 -> 13469 | AK45: =[2]Rekap!L22 -> 18537 | AL45: =[2]Rekap!M22 -> 9997 | AM45: =[2]Rekap!N22 -> 13258 | AN45: =[2]Rekap!O22 -> 10269 | AP45: =(AE45/AD45) -> 0.86893589 | AQ45: =AA45/Z45-1 -> 0.60565371 | AR45: =AB45/AA45-1 -> -0.19399208 | AS45: =AC45/AB45-1 -> -0.36496018 | AT45: =AD45/AC45-1 -> 0.46198495 | AU45: =AE45/AD45-1 -> -0.13106411 | AV45: =AVERAGE(AQ45:AU45) -> 0.075524458 | AW45: =(1+AV45)*AE45 -> 19066.93
B46: b. Rimba | E46: Ha | F46: 41234.93 | G46: 52860.21 | H46: 46573.85 | I46: 34265.7 | J46: 29751.3 | K46: 29772.49 | M46: 29214 | N46: 26318 | O46: 35230 | P46: 26984 | Q46: 31147 | R46: 40017 | S46: 28073 | T46: 29671 | U46: 39158 | V46: 54419 | W46: 100145 | X46: 65103 | Y46: 33972 | Z46: 45750 | AA46: 16675 | AB46: 13259 | AC46: 14402 | AD46: 15133 | AE46: 15668.6 | AF46: =[2]Rekap!G23 -> 3244 | AG46: =[2]Rekap!H23 -> 10365.644 | AH46: =[2]Rekap!I23 -> 6971 | AI46: =[2]Rekap!J23 -> 11525 | AJ46: =[2]Rekap!K23 -> 15520 | AK46: =[2]Rekap!L23 -> 17282 | AL46: =[2]Rekap!M23 -> 9992 | AM46: =[2]Rekap!N23 -> 7505 | AN46: =[2]Rekap!O23 -> 4337 | AP46: =(AE46/AD46) -> 1.0353929 | AQ46: =AA46/Z46-1 -> -0.63551913 | AR46: =AB46/AA46-1 -> -0.20485757 | AS46: =AC46/AB46-1 -> 0.086205596 | AT46: =AD46/AC46-1 -> 0.050756839 | AU46: =AE46/AD46-1 -> 0.03539285 | AV46: =AVERAGE(AQ46:AU46) -> -0.13360428 | AW46: =(1+AV46)*AE46 -> 13575.208
A47: 7 | B47: Luas Reboisasi: | C47: 5 + 6 | E47: Ha | F47: 55808.19 | G47: 71798.79 | H47: 59042.57 | I47: 47604.52 | J47: 42359.1 | K47: 43783.94 | M47: 48837 | N47: 49788 | O47: 71826 | P47: 75364 | Q47: 82515 | R47: 88978 | S47: 71574.2 | T47: 70588 | U47: 83312 | V47: 97260 | W47: 164422 | X47: 98475 | Y47: =+Y48+Y49 -> 54034 | Z47: =+Z48+Z49 -> 66922.63 | AA47: =+AA48+AA49 -> 47749 | AB47: =+AB48+AB49 -> 38407 | AC47: =+AC48+AC49 -> 31971.75 | AD47: =+AD48+AD49 -> 39719 | AE47: =+AE48+AE49 -> 37398.26 | AF47: =+AF48+AF49 -> 8652 | ... AN47: =+AN48+AN49 -> 20336 | AP47: =(AE47/AD47) -> 0.94157104 | AQ47: =AA47/Z47-1 -> -0.28650443 | AR47: =AB47/AA47-1 -> -0.19564808 | AS47: =AC47/AB47-1 -> -0.16755409 | AT47: =AD47/AC47-1 -> 0.24231548 | AU47: =AE47/AD47-1 -> -0.058428963 | AV47: =AVERAGE(AQ47:AU47) -> -0.093164016 | AW47: =(1+AV47)*AE47 -> 33914.088
B48: a. Jati | E48: Ha | F48: 9211.3 | G48: 10556.65 | H48: 8656.4 | I48: 8000.57 | J48: 8112.8 | K48: 9780.59 | M48: 14930 | N48: 18979 | O48: 31903 | P48: 44160 | Q48: 46587 | R48: 44869 | S48: 40748.6 | T48: 37619 | U48: 42964 | V48: 41622 | W48: 62605 | X48: 32016 | Y48: =Y42+Y45 -> 19150 | Z48: =Z42+Z45 -> 19324 | AA48: =AA42+AA45 -> 29868 | AB48: =AB42+AB45 -> 24529 | AC48: =AC42+AC45 -> 16232.75 | AD48: =AD42+AD45 -> 23340 | AE48: =AE42+AE45 -> 20328.37 | AF48: =AF42+AF45 -> 4480 | ... AN48: =AN42+AN45 -> 14076 | AP48: =(AE48/AD48) -> 0.87096701 | AQ48: =AA48/Z48-1 -> 0.54564272 | AR48: =AB48/AA48-1 -> -0.17875318 | AS48: =AC48/AB48-1 -> -0.3382221 | AT48: =AD48/AC48-1 -> 0.43783401 | AU48: =AE48/AD48-1 -> -0.12903299 | AV48: =AVERAGE(AQ48:AU48) -> 0.067493691 | AW48: =(1+AV48)*AE48 -> 21700.407
B49: b. Rimba | E49: Ha | F49: 46596.89 | G49: 61242.14 | H49: 50386.17 | I49: 39603.95 | J49: 34246.3 | K49: 34003.35 | M49: 33907 | N49: 30809 | O49: 39923 | P49: 31204 | Q49: 35928 | R49: 44109 | S49: 30825.6 | T49: 32969 | U49: 40348 | V49: 55638 | W49: 101817 | X49: 66459 | Y49: =Y43+Y46 -> 34884 | Z49: =Z43+Z46 -> 47598.63 | AA49: =AA43+AA46 -> 17881 | AB49: =AB43+AB46 -> 13878 | AC49: =AC43+AC46 -> 15739 | AD49: =AD43+AD46 -> 16379 | AE49: =AE43+AE46 -> 17069.89 | AF49: =AF43+AF46 -> 4172 | ... AN49: =AN43+AN46 -> 6260 | AP49: =(AE49/AD49) -> 1.0421815 | AQ49: =AA49/Z49-1 -> -0.62433793 | AR49: =AB49/AA49-1 -> -0.22386891 | AS49: =AC49/AB49-1 -> 0.13409713 | AT49: =AD49/AC49-1 -> 0.04066332 | AU49: =AE49/AD49-1 -> 0.042181452 | AV49: =AVERAGE(AQ49:AU49) -> -0.12625299 | AW49: =(1+AV49)*AE49 -> 14914.765
A50: 8 | B50: Produksi Kayu Pertukangan (Kayu Bulat) (000 m3) | E50: 000 M3 | F50: 1267.733 | G50: 1328.78 | H50: 1315.452 | I50: 1624.791 | J50: 1711.463 | K50: 1601.269 | M50: 1861.863 | N50: 1717.527 | O50: 1761.617 | P50: 1607.478 | Q50: 1455.54 | R50: 1484.891 | S50: 977.496 | T50: 923.631 | U50: 754.838 | V50: 875.603 | W50: 1153.165 | X50: 1082.923 | Y50: =+Y51+Y52 -> 979.39 | Z50: =+Z51+Z52 -> 889.461 | AA50: =+AA51+AA52 -> 969.2 | AB50: =+AB51+AB52 -> 928.922 | AC50: 955.58431 | AD50: 918.58701 | AE50: 791.24022 | AF50: =+AF51+AF52 -> 548.432 | AG50: =+AG51+AG52 -> 636.29236 | AH50: =+AH51+AH52 -> 809.934 | AI50: =+AI51+AI52 -> 783.52 | AJ50: =+AJ51+AJ52 -> 846.5056 | AK50: =+AK51+AK52 -> 986.183 | AL50: =+AL51+AL52 -> 925.767 | AM50: =+AM51+AM52 -> 916.108 | AN50: =+AN51+AN52 -> 803.637 | AP50: =(AE50/AD50) -> 0.86136666 | AQ50: =AA50/Z50-1 -> 0.089648675 | AR50: =AB50/AA50-1 -> -0.041557986 | AS50: =AC50/AB50-1 -> 0.028702419 | AT50: =AD50/AC50-1 -> -0.038716942 | AU50: =AE50/AD50-1 -> -0.13863334 | AV50: =AVERAGE(AQ50:AU50) -> -0.020111435 | AW50: =(1+AV50)*AE50 -> 775.32724
B51: a. Jati | C51: Perhutani T.1.5 (hal.12) | E51: 000 M3 | F51: 781.846 | G51: 757.646 | H51: 680.846 | I51: 834.074 | J51: 874.03 | K51: 661.071 | M51: 865.115 | N51: 760.753 | O51: 765.738 | P51: 694.242 | Q51: 654.939 | R51: 668.404 | S51: 427.847 | T51: 524.745 | U51: 361.152 | V51: 491.262 | W51: 521.069 | X51: 477.71 | Y51: 455.2 | Z51: 450.032 | AA51: 435.4 | AB51: 403.432 | AC51: 431.5166 | AD51: 455.99528 | AE51: 392.65651 | AF51: =[2]Rekap!G28/1000 -> 250.638 | AG51: =[2]Rekap!H28/1000 -> 306.21708 | AH51: =[2]Rekap!I28/1000 -> 400.112 | AI51: =[2]Rekap!J28/1000 -> 406.076 | AJ51: =[2]Rekap!K28/1000 -> 432.8173 | AK51: =[2]Rekap!L28/1000 -> 494.76 | AL51: =[2]Rekap!M28/1000 -> 500.476 | AM51: =[2]Rekap!N28/1000 -> 462.955 | AN51: =[2]Rekap!O28/1000 -> 395.508 | AP51: =(AE51/AD51) -> 0.86109777 | AQ51: =AA51/Z51-1 -> -0.032513244 | AR51: =AB51/AA51-1 -> -0.073422141 | AS51: =AC51/AB51-1 -> 0.069614205 | AT51: =AD51/AC51-1 -> 0.056727084 | AU51: =AE51/AD51-1 -> -0.13890223 | AV51: =AVERAGE(AQ51:AU51) -> -0.023699266 | AW51: =(1+AV51)*AE51 -> 383.35084
B52: b. Rimba | E52: 000 M3 | F52: 485.887 | G52: 571.134 | H52: 634.606 | I52: 790.717 | J52: 837.433 | K52: 940.198 | M52: 996.748 | N52: 956.774 | O52: 995.879 | P52: 913.236 | Q52: 800.601 | R52: 816.487 | S52: 549.649 | T52: 398.886 | U52: 393.686 | V52: 384.341 | W52: 632.096 | X52: 605.213 | Y52: 524.19 | Z52: 439.429 | AA52: 533.8 | AB52: 525.49 | AC52: 524.06771 | AD52: 462.59173 | AE52: 398.58371 | AF52: =[2]Rekap!G29/1000 -> 297.794 | AG52: =[2]Rekap!H29/1000 -> 330.07528 | AH52: =[2]Rekap!I29/1000 -> 409.822 | AI52: =[2]Rekap!J29/1000 -> 377.444 | AJ52: =[2]Rekap!K29/1000 -> 413.6883 | AK52: =[2]Rekap!L29/1000 -> 491.423 | AL52: =[2]Rekap!M29/1000 -> 425.291 | AM52: =[2]Rekap!N29/1000 -> 453.153 | AN52: =[2]Rekap!O29/1000 -> 408.129 | AP52: =(AE52/AD52) -> 0.86163172 | AQ52: =AA52/Z52-1 -> 0.21475824 | AR52: =AB52/AA52-1 -> -0.015567628 | AS52: =AC52/AB52-1 -> -0.0027065967 | AT52: =AD52/AC52-1 -> -0.11730542 | AU52: =AE52/AD52-1 -> -0.13836828 | AV52: =AVERAGE(AQ52:AU52) -> -0.011837936 | AW52: =(1+AV52)*AE52 -> 393.8653
A53: 9 | B53: Hasil Penjualan Kayu Bulat Dalam Negeri: | C53: Perhutani T.2.5.1 (hal.73) | E53: Miliar Rp | F53: 181468222 | G53: 198462749 | H53: 217966019 | I53: 294086536 | J53: 352609942 | K53: 400196667 | L53: 0 | M53: 488646168 | N53: 667703121 | O53: 812749938 | P53: 952932796 | Q53: 979158902 | R53: 1026223795 | S53: 960914414 | T53: 1070397593 | U53: 906586167 | V53: 933034215 | W53: 1316379764 | X53: 1369294702 | Y53: =+Y54+Y55 -> 1293158814 | Z53: =+Z54+Z55 -> 1348650057 | AA53: =+AA54+AA55 -> 1401262735 | AB53: =+AB54+AB55 -> 1522833352 | AC53: 1604.0784 | AD53: 1794.4218 | AE53: 1468.0676 | AF53: =+AF54+AF55 -> 1227.4102 | AG53: =+AG54+AG55 -> 1336.4822 | AH53: =+AH54+AH55 -> 1533.32 | AI53: =+AI54+AI55 -> 1482.2 | AJ53: =+AJ54+AJ55 -> 1636.5 | AK53: =+AK54+AK55 -> 1835.2 | AL53: =+AL54+AL55 -> 1807.527 | AM53: =+AM54+AM55 -> 1694 | AN53: =+AN54+AN55 -> 1513 | AP53: =(AE53/AD53) -> 0.8181285 | AQ53: =AA53/Z53-1 -> 0.039011364 | AR53: =AB53/AA53-1 -> 0.086757903 | AS53: =AC53/AB53-1 -> -0.99999895 | AT53: =AD53/AC53-1 -> 0.11866213 | AU53: =AE53/AD53-1 -> -0.1818715 | AV53: =AVERAGE(AQ53:AU53) -> -0.18748781 | AW53: =(1+AV53)*AE53 -> 1192.8228
B54: a. Jati | E54: Miliar Rp | F54: 155004065 | G54: 165745473 | H54: 180654219 | I54: 242615455 | J54: 289373384 | K54: 323336592 | M54: 392361233 | N54: 558490021 | O54: 662329199 | P54: 775922149 | Q54: 821638771 | R54: 848794590 | S54: 818455747 | T54: 943619324 | U54: 757769672 | V54: 758098225 | W54: 1038775770 | X54: 1062134047 | Y54: 1001177990 | Z54: 1100645245 | AA54: 1063191279 | AB54: 1115969382 | AC54: 1244.7 | AD54: 1491.6 | AE54: 1199.7313 | AF54: =[2]Rekap!G31 -> 984.20184 | AG54: =[2]Rekap!H31 -> 1041.5382 | AH54: =[2]Rekap!I31 -> 1225.62 | AI54: =[2]Rekap!J31 -> 1174.9 | AJ54: =[2]Rekap!K31 -> 1225.9 | AK54: =[2]Rekap!L31 -> 1424 | AL54: =[2]Rekap!M31 -> 1466.8 | AM54: =[2]Rekap!N31 -> 1329 | AN54: =[2]Rekap!O31 -> 1173 | AP54: =(AE54/AD54) -> 0.80432512 | AQ54: =AA54/Z54-1 -> -0.034029099 | AR54: =AB54/AA54-1 -> 0.049641211 | AS54: =AC54/AB54-1 -> -0.99999888 | AT54: =AD54/AC54-1 -> 0.19836105 | AU54: =AE54/AD54-1 -> -0.19567488 | AV54: =AVERAGE(AQ54:AU54) -> -0.19634012 | AW54: =(1+AV54)*AE54 -> 964.17595
B55: b. Rimba | E55: Miliar Rp | F55: 26464157 | G55: 32717276 | H55: 37311800 | I55: 51471081 | J55: 63236558 | K55: 76860075 | M55: 96284935 | N55: 109213100 | O55: 150420739 | P55: 177010647 | Q55: 157520131 | R55: 177429205 | S55: 142458667 | T55: 126778269 | U55: 148816495 | V55: 174935990 | W55: 277603994 | X55: 295545248 | Y55: 291980824 | Z55: 248004812 | AA55: 338071456 | AB55: 406863970 | AC55: 359.37842 | AD55: 302.82179 | AE55: 268.33626 | AF55: =[2]Rekap!G32 -> 243.20838 | AG55: =[2]Rekap!H32 -> 294.94394 | AH55: =[2]Rekap!I32 -> 307.7 | AI55: =[2]Rekap!J32 -> 307.3 | AJ55: =[2]Rekap!K32 -> 410.6 | AK55: =[2]Rekap!L32 -> 411.2 | AL55: =[2]Rekap!M32 -> 340.727 | AM55: =[2]Rekap!N32 -> 365 | AN55: =[2]Rekap!O32 -> 340 | AP55: =(AE55/AD55) -> 0.88611938 | AQ55: =AA55/Z55-1 -> 0.36316491 | AR55: =AB55/AA55-1 -> 0.20348513 | AS55: =AC55/AB55-1 -> -0.99999912 | AT55: =AD55/AC55-1 -> -0.15737348 | AU55: =AE55/AD55-1 -> -0.11388062 | AV55: =AVERAGE(AQ55:AU55) -> -0.14092064 | AW55: =(1+AV55)*AE55 -> 230.52214
A56: 10 | B56: Volume Penjualan Kayu Bulat Dalam Negeri: | E56: M3 | F56: 1061926 | G56: 1114594 | H56: 1301545 | I56: 1512946 | J56: 1540375 | K56: 1548254 | L56: 0 | M56: 1718967 | N56: 1716895 | O56: 1468395 | P56: 1593629 | Q56: 1419347 | R56: 1418641 | S56: 1155506 | T56: 890124 | U56: 790440 | V56: 708623 | W56: 1149679 | X56: 992484 | Y56: =+Y57+Y58 -> 900455 | Z56: =+Z57+Z58 -> 774137 | AA56: =+AA57+AA58 -> 915323 | AB56: =+AB57+AB58 -> 965518 | AC56: 831029.02 | AD56: 697010.92 | AE56: 614513.93 | AF56: =+AF57+AF58 -> 590115.31 | AG56: =+AG57+AG58 -> 557247.32 | AH56: =+AH57+AH58 -> 688107 | AI56: =+AI57+AI58 -> 751819 | AJ56: =+AJ57+AJ58 -> 811587 | AK56: =+AK57+AK58 -> 936397 | AL56: =+AL57+AL58 -> 860700 | AM56: =+AM57+AM58 -> 846359 | AN56: =+AN57+AN58 -> 790349 | AP56: =(AE56/AD56) -> 0.88164174 | AQ56: =AA56/Z56-1 -> 0.18237857 | AR56: =AB56/AA56-1 -> 0.054838565 | AS56: =AC56/AB56-1 -> -0.13929205 | AT56: =AD56/AC56-1 -> -0.16126765 | AU56: =AE56/AD56-1 -> -0.11835826 | AV56: =AVERAGE(AQ56:AU56) -> -0.036340164 | AW56: =(1+AV56)*AE56 -> 592182.39
B57: a. Jati | E57: M3 | F57: 584404 | G57: 556194 | H57: 683651 | I57: 709572 | J57: 742645 | K57: 699041 | M57: 807232 | N57: 732204 | O57: 577000 | P57: 743078 | Q57: 656477 | R57: 629078 | S57: 591401 | T57: 495863 | U57: 373046 | V57: 352879 | W57: 532155 | X57: 421758 | Y57: 377310 | Z57: 395359 | AA57: 394601 | AB57: 389636 | AC57: 376972.21 | AD57: 352909.68 | AE57: 303425 | AF57: =[2]Rekap!G34 -> 283789.06 | AG57: =[2]Rekap!H34 -> 257404.14 | AH57: =[2]Rekap!I34 -> 347201 | AI57: =[2]Rekap!J34 -> 407900 | AJ57: =[2]Rekap!K34 -> 423437 | AK57: =[2]Rekap!L34 -> 474554 | AL57: =[2]Rekap!M34 -> 472037 | AM57: =[2]Rekap!N34 -> 431517 | AN57: =[2]Rekap!O34 -> 399067 | AP57: =(AE57/AD57) -> 0.8597809 | AQ57: =AA57/Z57-1 -> -0.0019172448 | AR57: =AB57/AA57-1 -> -0.01258233 | AS57: =AC57/AB57-1 -> -0.032501585 | AT57: =AD57/AC57-1 -> -0.063831062 | AU57: =AE57/AD57-1 -> -0.1402191 | AV57: =AVERAGE(AQ57:AU57) -> -0.050210264 | AW57: =(1+AV57)*AE57 -> 288189.95
B58: b. Rimba | E58: M3 | F58: 477522 | G58: 558400 | H58: 617894 | I58: 803374 | J58: 797730 | K58: 849213 | M58: 911735 | N58: 984691 | O58: 891395 | P58: 850551 | Q58: 762870 | R58: 789563 | S58: 564105 | T58: 394261 | U58: 417394 | V58: 355744 | W58: 617524 | X58: 565817 | Y58: 523145 | Z58: 378778 | AA58: 520722 | AB58: 575882 | AC58: 454056.8 | AD58: 344101.25 | AE58: 311088.93 | AF58: =[2]Rekap!G35 -> 306326.24 | AG58: =[2]Rekap!H35 -> 299843.18 | AH58: =[2]Rekap!I35 -> 340906 | AI58: =[2]Rekap!J35 -> 343919 | AJ58: =[2]Rekap!K35 -> 388150 | AK58: =[2]Rekap!L35 -> 461843 | AL58: =[2]Rekap!M35 -> 388663 | AM58: =[2]Rekap!N35 -> 414842 | AN58: =[2]Rekap!O35 -> 391282 | AP58: =(AE58/AD58) -> 0.90406218 | AQ58: =AA58/Z58-1 -> 0.37474193 | AR58: =AB58/AA58-1 -> 0.10592984 | AS58: =AC58/AB58-1 -> -0.21154541 | AT58: =AD58/AC58-1 -> -0.24216256 | AU58: =AE58/AD58-1 -> -0.095937818 | AV58: =AVERAGE(AQ58:AU58) -> -0.013794802 | AW58: =(1+AV58)*AE58 -> 306797.51
A59: 11 | B59: Harga Rata-rata Kayu Bulat: | E59: 000Rp/m3 | F59: 170885.94 | G59: 178058.33 | H59: 167467.14 | I59: 194380.06 | J59: 228911.75 | K59: 258482.57 | L59: #DIV/0! | M59: 284267.33 | N59: 388901.55 | O59: 553495.44 | P59: 597964.02 | Q59: 689865.76 | R59: 723385.12 | S59: 831596.21 | T59: 1202526.4 | U59: 1146938.6 | V59: 1316686.3 | W59: 1144997.7 | X59: 1379664.3 | Y59: =(Y53*1000)/Y56 -> 1436117.1 | Z59: =(Z53*1000)/Z56 -> 1742133.6 | AA59: =(AA53*1000)/AA56 -> 1530894.3 | AB59: =(AB53*1000)/AB56 -> 1577219 | AC59: =AC53*1000000/AC56 -> 1930.2315 | AD59: =AD53*1000000/AD56 -> 2574.4529 | AE59: =AE53*1000000/AE56 -> 2388.99 | AF59: =AF53*1000000/AF56 -> 2079.9498 | AG59: =AG53*1000000/AG56 -> 2398.3645 | AH59: =AH53*1000000/AH56 -> 2228.3162 | AI59: =AI53*1000000/AI56 -> 1971.4852 | AJ59: =AJ53*1000000/AJ56 -> 2016.4197 | ... AN59: =AN53*1000000/AN56 -> 1914.3442 | AP59: =(AE59/AD59) -> 0.92796026 | AQ59: =AA59/Z59-1 -> -0.12125322 | AR59: =AB59/AA59-1 -> 0.030259927 | AS59: =AC59/AB59-1 -> -0.99877618 | AT59: =AD59/AC59-1 -> 0.3337534 | AU59: =AE59/AD59-1 -> -0.072039742 | AV59: =AVERAGE(AQ59:AU59) -> -0.16561116 | AW59: =(1+AV59)*AE59 -> 1993.3466
B60: a. Jati | E60: 000Rp/m3 | F60: 265234.44 | G60: 297999.39 | H60: 264249.18 | I60: 341918.02 | J60: 389652.37 | K60: 462543.1 | L60: #DIV/0! | M60: 486057.58 | N60: 762751.94 | O60: 1147884.2 | P60: 1044200.1 | Q60: 1251588.1 | R60: 1349267.6 | S60: 1383926.9 | T60: 1902983.9 | U60: 2031303.6 | V60: 2148323.4 | W60: 1952017.3 | X60: 2520208.6 | Y60: =(Y54*1000)/Y57 -> 2653462.6 | Z60: =(Z54*1000)/Z57 -> 2783913.5 | AA60: =(AA54*1000)/AA57 -> 2694345.1 | AB60: =(AB54*1000)/AB57 -> 2864133.1 | AC60: =AC54*1000000/AC57 -> 3301.8349 | AD60: =AD54*1000000/AD57 -> 4226.5772 | AE60: =AE54*1000000/AE57 -> 3953.9634 | AF60: =AF54*1000000/AF57 -> 3468.0753 | AG60: =AG54*1000000/AG57 -> 4046.315 | AH60: =AH54*1000000/AH57 -> 3530.0014 | AI60: =AI54*1000000/AI57 -> 2880.3628 | AJ60: =AJ54*1000000/AJ57 -> 2895.1178 | ... AN60: =AN54*1000000/AN57 -> 2939.356 | AP60: =(AE60/AD60) -> 0.9355001 | AQ60: =AA60/Z60-1 -> -0.032173539 | AR60: =AB60/AA60-1 -> 0.063016435 | AS60: =AC60/AB60-1 -> -0.99884718 | AT60: =AD60/AC60-1 -> 0.28006923 | AU60: =AE60/AD60-1 -> -0.064499903 | AV60: =AVERAGE(AQ60:AU60) -> -0.15048699 | AW60: =(1+AV60)*AE60 -> 3358.9434
B61: b. Rimba | E61: 000Rp/m3 | F61: 55419.765 | G61: 58591.11 | H61: 60385.438 | I61: 64068.642 | J61: 79270.628 | K61: 90507.417 | L61: #DIV/0! | M61: 105606.27 | N61: 110911.04 | O61: 168747.57 | P61: 208112.91 | Q61: 206483.58 | R61: 224718.24 | S61: 252539.27 | T61: 321559.24 | U61: 356537.22 | V61: 491746.85 | W61: 449543.65 | X61: 531417.75 | Y61: =(Y55*1000)/Y58 -> 558126 | Z61: =(Z55*1000)/Z58 -> 654749.78 | AA61: =(AA55*1000)/AA58 -> 649235.98 | AB61: =(AB55*1000)/AB58 -> 706505.79 | AC61: =AC55*1000000/AC58 -> 791.4834 | AD61: =AD55*1000000/AD58 -> 880.03688 | AE61: =AE55*1000000/AE58 -> 862.57091 | AF61: =AF55*1000000/AF58 -> 793.95215 | AG61: =AG55*1000000/AG58 -> 983.66066 | AH61: =AH55*1000000/AH58 -> 902.59485 | AI61: =AI55*1000000/AI58 -> 893.52435 | AJ61: =AJ55*1000000/AJ58 -> 1057.8385 | ... AN61: =AN55*1000000/AN58 -> 868.93851 | AP61: =(AE61/AD61) -> 0.98015313 | AQ61: =AA61/Z61-1 -> -0.0084212374 | AR61: =AB61/AA61-1 -> 0.088211098 | AS61: =AC61/AB61-1 -> -0.99887972 | AT61: =AD61/AC61-1 -> 0.11188293 | AU61: =AE61/AD61-1 -> -0.019846866 | AV61: =AVERAGE(AQ61:AU61) -> -0.16541076 | AW61: =(1+AV61)*AE61 -> 719.8924
U62: 10.877614 | V62: 37.923006 | W62: -8.582301 | X62: 18.212714 | Y62: =Y61/X61*100-100 -> 5.0258472 | Z62: =Z61/Y61*100-100 -> 17.312181 | AA62: =AA61/Z61*100-100 -> -0.84212374 | AB62: =AB61/AA61*100-100 -> 8.8211098 | AD62: =AD61/AC61*100-100 -> 11.188293 | AE62: =AE61/AD61*100-100 -> -1.9846866 | AF62: =AF61/AE61*100-100 -> -7.9551435 | AG62: =AG61/AF61*100-100 -> 23.894199 | AH62: =AH61/AG61*100-100 -> -8.2412374 | AI62: =AI61/AH61*100-100 -> -1.0049363 | AJ62: =AJ61/AI61*100-100 -> 18.389439 | AK62: =AK61/AJ61*100-100 -> -15.833477 | ... AN62: =AN61/AM61*100-100 -> -1.2404955 | AQ62: =AA62/Z62-1 -> -1.0486434 | AR62: =AB62/AA62-1 -> -11.474838 | AS62: =AC62/AB62-1 -> -1 | AT62: =AD62/AC62-1 -> #DIV/0! | AU62: =AE62/AD62-1 -> -1.1773896 | AV62: =AVERAGE(AQ62:AU62) -> #DIV/0! | AW62: =(1+AV62)*AE62 -> #DIV/0!
B63: Kerugian Gangguan Keamanan Hutan | F63: 2007 | G63: 2008 | H63: 2009 | I63: 2010 | J63: 2011 | K63: 2012 | L63: 2013 | M63: 2014 | N63: 2015 | AQ63: =AA63/Z63-1 -> #DIV/0! | AR63: =AB63/AA63-1 -> #DIV/0! | AS63: =AC63/AB63-1 -> #DIV/0! | AT63: =AD63/AC63-1 -> #DIV/0! | AU63: =AE63/AD63-1 -> #DIV/0! | AV63: =AVERAGE(AQ63:AU63) -> #DIV/0! | AW63: =(1+AV63)*AE63 -> #DIV/0!
B64: Pencuri pohon | C64: Perhutani T.2.9.1 (hal.149) | E64: 000 Rp | F64: 16918356 | G64: 12777434 | H64: 9718774 | I64: 8077904 | J64: 23932473 | K64: 40646372 | L64: 42237796 | M64: 29811174 | N64: 38158228 | W64: 16918356 | X64: 12777434 | Y64: 9718774 | Z64: 8077904 | AA64: 23932473 | AB64: 40646372 | AC64: 42237796 | AD64: 29708748 | AE64: 38158228 | AF64: =[2]Rekap!G37 -> 38456014 | AG64: =[2]Rekap!H37 -> 49292712 | AH64: =[2]Rekap!I37 -> 38304975 | AI64: =[2]Rekap!J37 -> 27329056 | AJ64: =[2]Rekap!K37 -> 23492087 | AK64: =[2]Rekap!L37 -> 15976261 | AL64: =[2]Rekap!M37 -> 20833308 | AM64: =[2]Rekap!N37 -> 17758449 | AN64: =[2]Rekap!O37 -> 16704952 | AP64: =(AE64/AD64) -> 1.2844105 | AQ64: =AA64/Z64-1 -> 1.9627083 | AR64: =AB64/AA64-1 -> 0.69837743 | AS64: =AC64/AB64-1 -> 0.039152916 | AT64: =AD64/AC64-1 -> -0.2966312 | AU64: =AE64/AD64-1 -> 0.2844105 | AV64: =AVERAGE(AQ64:AU64) -> 0.53760359 | AW64: =(1+AV64)*AE64 -> 58672228
B65: Bibrikan | E65: 000 Rp | F65: 272528 | G65: 271964 | H65: 192619 | I65: 28722 | J65: 339582 | K65: 367931 | L65: 975266 | M65: 1014200 | N65: 774572 | W65: 272528 | X65: 271964 | Y65: 192619 | Z65: 28722 | AA65: 339582 | AB65: 367931 | AC65: 975266 | AD65: 1014200 | AE65: 774572 | AF65: =[2]Rekap!G38 -> 305815 | AG65: =[2]Rekap!H38 -> 211048 | AH65: =[2]Rekap!I38 -> 84201 | AI65: =[2]Rekap!J38 -> 288541 | AJ65: =[2]Rekap!K38 -> 18531 | AK65: =[2]Rekap!L38 -> 44654 | AL65: =[2]Rekap!M38 -> 39049 | AM65: =[2]Rekap!N38 -> 318595 | AN65: =[2]Rekap!O38 -> 160309 | AP65: =(AE65/AD65) -> 0.76372708 | AQ65: =AA65/Z65-1 -> 10.823062 | AR65: =AB65/AA65-1 -> 0.083482046 | AS65: =AC65/AB65-1 -> 1.6506763 | AT65: =AD65/AC65-1 -> 0.039921416 | AU65: =AE65/AD65-1 -> -0.23627292 | AV65: =AVERAGE(AQ65:AU65) -> 2.4721739 | AW65: =(1+AV65)*AE65 -> 2689448.7
B66: Perusakan hutan | E66: 000 Rp | F66: 593150 | G66: 707604 | H66: 471534 | I66: 1292101 | J66: 1656549 | K66: 4638857 | L66: 1228118 | M66: 2328120 | N66: 1669381 | W66: 593150 | X66: 707604 | Y66: 471534 | Z66: 1292101 | AA66: 1656549 | AB66: 4638857 | AC66: 1228118 | AD66: 2328120 | AE66: 1669381 | AF66: =[2]Rekap!G39 -> 1120886 | AG66: =[2]Rekap!H39 -> 1702742 | AH66: =[2]Rekap!I39 -> 963923 | AI66: =[2]Rekap!J39 -> 4125921 | AJ66: =[2]Rekap!K39 -> 1804012 | AK66: =[2]Rekap!L39 -> 1142998 | AL66: =[2]Rekap!M39 -> 5017771 | AM66: =[2]Rekap!N39 -> 18942706 | AN66: =[2]Rekap!O39 -> 4577197 | AP66: =(AE66/AD66) -> 0.7170511 | AQ66: =AA66/Z66-1 -> 0.28205845 | AR66: =AB66/AA66-1 -> 1.8003138 | AS66: =AC66/AB66-1 -> -0.73525418 | AT66: =AD66/AC66-1 -> 0.89568103 | AU66: =AE66/AD66-1 -> -0.2829489 | AV66: =AVERAGE(AQ66:AU66) -> 0.39197004 | AW66: =(1+AV66)*AE66 -> 2323728.3
B67: Penggembalaan | E67: 000 Rp | F67: 89897 | G67: 79529 | H67: 29710 | I67: 34813 | J67: 233255 | K67: 131288 | L67: 236050 | M67: 182068 | N67: 43287 | W67: 89897 | X67: 79529 | Y67: 29710 | Z67: 34813 | AA67: 233255 | AB67: 131288 | AC67: 236050 | AD67: 182068 | AE67: 43287 | AF67: =[2]Rekap!G40 -> 107205 | AG67: =[2]Rekap!H40 -> 184927 | AH67: =[2]Rekap!I40 -> 18475 | AI67: =[2]Rekap!J40 -> 143100 | AJ67: =[2]Rekap!K40 -> 4500 | AK67: =[2]Rekap!L40 -> 15975 | AL67: =[2]Rekap!M40 -> 0 | AM67: =[2]Rekap!N40 -> 0 | AN67: =[2]Rekap!O40 -> 57285 | AP67: =(AE67/AD67) -> 0.23775183 | AQ67: =AA67/Z67-1 -> 5.7002269 | AR67: =AB67/AA67-1 -> -0.43714819 | AS67: =AC67/AB67-1 -> 0.79795564 | AT67: =AD67/AC67-1 -> -0.22868884 | AU67: =AE67/AD67-1 -> -0.76224817 | AV67: =AVERAGE(AQ67:AU67) -> 1.0140195 | AW67: =(1+AV67)*AE67 -> 87180.861
B68: Kebakaran | E68: 000 Rp | F68: 2345097 | G68: 1495144 | H68: 3822571 | I68: 54750 | J68: 22995049 | K68: 27925113 | L68: 7359556 | M68: 11046629 | N68: 12879190 | W68: 2345097 | X68: 1495144 | Y68: 3822571 | Z68: 54750 | AA68: 22995049 | AB68: 27925113 | AC68: 7359556 | AD68: 11046629 | AE68: 12879190 | AF68: =[2]Rekap!G41 -> 522062 | AG68: =[2]Rekap!H41 -> 6089975 | AH68: =[2]Rekap!I41 -> 8082052 | AI68: =[2]Rekap!J41 -> 7782911 | AJ68: =[2]Rekap!K41 -> 2712738 | AK68: =[2]Rekap!L41 -> 760082 | AL68: =[2]Rekap!M41 -> 456726 | AM68: =[2]Rekap!N41 -> 11577893 | AN68: =[2]Rekap!O41 -> 3822440 | AP68: =(AE68/AD68) -> 1.1658932 | AQ68: =AA68/Z68-1 -> 419.00089 | AR68: =AB68/AA68-1 -> 0.21439676 | AS68: =AC68/AB68-1 -> -0.73645385 | AT68: =AD68/AC68-1 -> 0.50099123 | AU68: =AE68/AD68-1 -> 0.16589323 | AV68: =AVERAGE(AQ68:AU68) -> 83.829144 | AW68: =(1+AV68)*AE68 -> 1.0925307e+09 | BJ68: =AH68/AG68*100-100 -> 32.710758
B69: Bencana alam | E69: 000 Rp | F69: 11530432 | G69: 11524867 | H69: 9678490 | I69: 26469493 | J69: 33628477 | K69: 136168967 | L69: 62017916 | M69: 40947442 | N69: 46678527 | W69: 11530432 | X69: 11524867 | Y69: 9678490 | Z69: 26469493 | AA69: 33628477 | AB69: 136168967 | AC69: 62017916 | AD69: 40947442 | AE69: 46678527 | AF69: =[2]Rekap!G42 -> 31763130 | AG69: =[2]Rekap!H42 -> 30855268 | AH69: =[2]Rekap!I42 -> 47480576 | AI69: =[2]Rekap!J42 -> 47764182 | AJ69: =[2]Rekap!K42 -> 45412984 | AK69: =[2]Rekap!L42 -> 24178170 | AL69: =[2]Rekap!M42 -> 25971685 | AM69: =[2]Rekap!N42 -> 22888350 | AN69: =[2]Rekap!O42 -> 30696326 | AP69: =(AE69/AD69) -> 1.139962 | AQ69: =AA69/Z69-1 -> 0.2704617 | AR69: =AB69/AA69-1 -> 3.049216 | AS69: =AC69/AB69-1 -> -0.54455176 | AT69: =AD69/AC69-1 -> -0.33974818 | AU69: =AE69/AD69-1 -> 0.13996198 | AV69: =AVERAGE(AQ69:AU69) -> 0.51506795 | AW69: =(1+AV69)*AE69 -> 70721140
B70: Total | E70: 000 Rp | F70: =SUM(F64:F69) -> 31749460 | G70: =SUM(G64:G69) -> 26856542 | H70: =SUM(H64:H69) -> 23913698 | I70: =SUM(I64:I69) -> 35957783 | J70: =SUM(J64:J69) -> 82785385 | K70: =SUM(K64:K69) -> 209878528 | L70: =SUM(L64:L69) -> 114054702 | M70: =SUM(M64:M69) -> 85329633 | N70: =SUM(N64:N69) -> 100203185 | W70: =SUM(W64:W69) -> 31749460 | X70: =SUM(X64:X69) -> 26856542 | Y70: =SUM(Y64:Y69) -> 23913698 | Z70: =SUM(Z64:Z69) -> 35957783 | AA70: =SUM(AA64:AA69) -> 82785385 | AB70: =SUM(AB64:AB69) -> 209878528 | AC70: =SUM(AC64:AC69) -> 114054702 | AD70: =SUM(AD64:AD69) -> 85227207 | ... AN70: =SUM(AN64:AN69) -> 56018509 | AP70: =(AE70/AD70) -> 1.1757183 | AQ70: =AA70/Z70-1 -> 1.3022939 | AR70: =AB70/AA70-1 -> 1.5352123 | AS70: =AC70/AB70-1 -> -0.45656803 | AT70: =AD70/AC70-1 -> -0.25275148 | AU70: =AE70/AD70-1 -> 0.17571828 | AV70: =AVERAGE(AQ70:AU70) -> 0.460781 | AW70: =(1+AV70)*AE70 -> 1.4637491e+08
B71: KONVERSI NILAI: | AQ71: =AA71/Z71-1 -> #DIV/0! | AR71: =AB71/AA71-1 -> #DIV/0! | AS71: =AC71/AB71-1 -> #DIV/0! | AT71: =AD71/AC71-1 -> #DIV/0! | AU71: =AE71/AD71-1 -> #DIV/0! | AV71: =AVERAGE(AQ71:AU71) -> #DIV/0! | AW71: =(1+AV71)*AE71 -> #DIV/0!
B72: Kerugian Gangguan Keamanan Hutan | F72: 2007 | G72: 2008 | H72: 2009 | I72: 2010 | J72: 2011 | K72: 2012 | L72: 2013 | M72: 2014 | N72: 2015 | AQ72: =AA72/Z72-1 -> #DIV/0! | AR72: =AB72/AA72-1 -> #DIV/0! | AS72: =AC72/AB72-1 -> #DIV/0! | AT72: =AD72/AC72-1 -> #DIV/0! | AU72: =AE72/AD72-1 -> #DIV/0! | AV72: =AVERAGE(AQ72:AU72) -> #DIV/0! | AW72: =(1+AV72)*AE72 -> #DIV/0!
B73: Pencuri pohon | E73: 000 M3 | F73: 16918356 | G73: 12777434 | H73: 9718774 | I73: 8077904 | J73: 23932473 | K73: 40646372 | L73: 42237796 | M73: 29811174 | N73: 38158228 | AQ73: =AA73/Z73-1 -> #DIV/0! | AR73: =AB73/AA73-1 -> #DIV/0! | AS73: =AC73/AB73-1 -> #DIV/0! | AT73: =AD73/AC73-1 -> #DIV/0! | AU73: =AE73/AD73-1 -> #DIV/0! | AV73: =AVERAGE(AQ73:AU73) -> #DIV/0! | AW73: =(1+AV73)*AE73 -> #DIV/0!
B74: Bibrikan | E74: 000 M3 | F74: 272528 | G74: 271964 | H74: 192619 | I74: 28722 | J74: 339582 | K74: 367931 | L74: 975266 | M74: 1014200 | N74: 774572 | AQ74: =AA74/Z74-1 -> #DIV/0! | AR74: =AB74/AA74-1 -> #DIV/0! | AS74: =AC74/AB74-1 -> #DIV/0! | AT74: =AD74/AC74-1 -> #DIV/0! | AU74: =AE74/AD74-1 -> #DIV/0! | AV74: =AVERAGE(AQ74:AU74) -> #DIV/0! | AW74: =(1+AV74)*AE74 -> #DIV/0!
B75: Perusakan hutan | E75: 000 M3 | F75: 593150 | G75: 707604 | H75: 471534 | I75: 1292101 | J75: 1656549 | K75: 4638857 | L75: 1228118 | M75: 2328120 | N75: 1669381 | AQ75: =AA75/Z75-1 -> #DIV/0! | AR75: =AB75/AA75-1 -> #DIV/0! | AS75: =AC75/AB75-1 -> #DIV/0! | AT75: =AD75/AC75-1 -> #DIV/0! | AU75: =AE75/AD75-1 -> #DIV/0! | AV75: =AVERAGE(AQ75:AU75) -> #DIV/0! | AW75: =(1+AV75)*AE75 -> #DIV/0!
B76: Penggembalaan | E76: 000 M3 | F76: 89897 | G76: 79529 | H76: 29710 | I76: 34813 | J76: 233255 | K76: 131288 | L76: 236050 | M76: 182068 | N76: 43287 | AQ76: =AA76/Z76-1 -> #DIV/0! | AR76: =AB76/AA76-1 -> #DIV/0! | AS76: =AC76/AB76-1 -> #DIV/0! | AT76: =AD76/AC76-1 -> #DIV/0! | AU76: =AE76/AD76-1 -> #DIV/0! | AV76: =AVERAGE(AQ76:AU76) -> #DIV/0! | AW76: =(1+AV76)*AE76 -> #DIV/0!
B77: Kebakaran | E77: 000 M3 | F77: 2345097 | G77: 1495144 | H77: 3822571 | I77: 54750 | J77: 22995049 | K77: 27925113 | L77: 7359556 | M77: 11046629 | N77: 12879190 | AQ77: =AA77/Z77-1 -> #DIV/0! | AR77: =AB77/AA77-1 -> #DIV/0! | AS77: =AC77/AB77-1 -> #DIV/0! | AT77: =AD77/AC77-1 -> #DIV/0! | AU77: =AE77/AD77-1 -> #DIV/0! | AV77: =AVERAGE(AQ77:AU77) -> #DIV/0! | AW77: =(1+AV77)*AE77 -> #DIV/0!
B78: Bencana alam | E78: 000 M3 | F78: 11530432 | G78: 11524867 | H78: 9678490 | I78: 26469493 | J78: 33628477 | K78: 136168967 | L78: 62017916 | M78: 40947442 | N78: 46678527 | AQ78: =AA78/Z78-1 -> #DIV/0! | AR78: =AB78/AA78-1 -> #DIV/0! | AS78: =AC78/AB78-1 -> #DIV/0! | AT78: =AD78/AC78-1 -> #DIV/0! | AU78: =AE78/AD78-1 -> #DIV/0! | AV78: =AVERAGE(AQ78:AU78) -> #DIV/0! | AW78: =(1+AV78)*AE78 -> #DIV/0!
B79: Total | E79: 000 M3 | F79: =SUM(F73:F78) -> 31749460 | G79: =SUM(G73:G78) -> 26856542 | H79: =SUM(H73:H78) -> 23913698 | I79: =SUM(I73:I78) -> 35957783 | J79: =SUM(J73:J78) -> 82785385 | K79: =SUM(K73:K78) -> 209878528 | L79: =SUM(L73:L78) -> 114054702 | M79: =SUM(M73:M78) -> 85329633 | N79: =SUM(N73:N78) -> 100203185 | AQ79: =AA79/Z79-1 -> #DIV/0! | AR79: =AB79/AA79-1 -> #DIV/0! | AS79: =AC79/AB79-1 -> #DIV/0! | AT79: =AD79/AC79-1 -> #DIV/0! | AU79: =AE79/AD79-1 -> #DIV/0! | AV79: =AVERAGE(AQ79:AU79) -> #DIV/0! | AW79: =(1+AV79)*AE79 -> #DIV/0!
B80: Luas Kebakaran Hutan dan lahan(total) | C80: Statistik KLHK | E80: Ha | AB80: ='1.luas kebakaran hutan'!D46 -> 8621.03 | AC80: ='1.luas kebakaran hutan'!E46 -> 4918.74 | AD80: ='1.luas kebakaran hutan'!F46 -> 44411.36 | AE80: 2611408 | AF80: 438364 | AG80: ='[1]1.luas kebakaran hutan'!$N$48+'[1]1.luas kebakaran hutan'!$O$48 -> 165484 | AH80: ='[1]1.luas kebakaran hutan'!P$46 -> 529266.64 | AI80: ='[1]1.luas kebakaran hutan'!Q$46 -> 1649258 | AJ80: ='[1]1.luas kebakaran hutan'!R$46 -> 296942 | AK80: ='[1]1.luas kebakaran hutan'!S$46 -> 358867 | AL80: ='[1]1.luas kebakaran hutan'!T$46 -> 204936 | AM80: 1161192.9 | AN80: 376805.05 | BJ80: =AH80/AG80*100-100 -> 219.82949
B81: Luas Kebakaran Hutan (luar jawa) | AB81: ='1.luas kebakaran hutan'!D47 -> 0 | AC81: ='1.luas kebakaran hutan'!E47 -> 3282.6 | AD81: ='1.luas kebakaran hutan'!F47 -> 38721.59 | AE81: ='[1]1.luas kebakaran hutan'!$J$49+'[1]1.luas kebakaran hutan'!$K$49 -> 2597833 | AF81: ='[1]1.luas kebakaran hutan'!$L$49+'[1]1.luas kebakaran hutan'!$M$49 -> 438364 | AG81: ='[1]1.luas kebakaran hutan'!$N$49+'[1]1.luas kebakaran hutan'!$O$49 -> 153692 | AH81: ='[1]1.luas kebakaran hutan'!P$49 -> 515944.07 | AI81: ='[1]1.luas kebakaran hutan'!Q$49 -> 1611260 | AJ81: ='[1]1.luas kebakaran hutan'!R$49 -> 267932 | AK81: ='[1]1.luas kebakaran hutan'!S$49 -> 341511 | AL81: ='[1]1.luas kebakaran hutan'!T$49 -> 200444 | AM81: =AM80-11524.8-9965.59-119.91-49498.32-1.01 -> 1090083.3 | AN81: =AN80-0.51-4548.58-3726.78-51.91-20957.17-362.83 -> 347157.27 | BJ81: =AH81/AG81*100-100 -> 235.70002
B82: Luas Reboisasi (total) | AA82: ='2.realisasi reboisasi'!D50 -> 0 | AB82: ='2.realisasi reboisasi'!E50 -> 100987 | AC82: ='2.realisasi reboisasi'!F50 -> 105655.63 | AD82: ='2.realisasi reboisasi'!G50 -> 26162 | AE82: ='2.realisasi reboisasi'!H50 -> 10508 | AF82: ='2.realisasi reboisasi'!I50 -> 7066.66 | AG82: ='[1]2.realisasi reboisasi'!K50 -> 35123 | AH82: ='[1]2.realisasi reboisasi'!L50 -> 25188 | AI82: ='[1]2.realisasi reboisasi'!M50 -> 206000 | AJ82: =AJ102 -> 69251.69 | AK82: =AK102 -> 69960.48 | AL82: =AVERAGE(AG82:AK82) -> 81104.634 | AM82: =AVERAGE(AH82:AL82) -> 90300.961 | AN82: =AVERAGE(AI82:AM82) -> 103323.55 | BJ82: =AH82/AG82*100-100 -> -28.286308
B83: Luas Reboisasi (luar jawa) | AA83: ='2.realisasi reboisasi'!D51 -> 0 | AB83: ='2.realisasi reboisasi'!E51 -> 95455 | AC83: ='2.realisasi reboisasi'!F51 -> 101200 | AD83: ='2.realisasi reboisasi'!G51 -> 25387 | AE83: ='2.realisasi reboisasi'!H51 -> 10508 | AF83: ='2.realisasi reboisasi'!I51 -> 7066.66 | AG83: ='[1]2.realisasi reboisasi'!K51 -> 13271 | AH83: ='[1]2.realisasi reboisasi'!L51 -> 17023 | AI83: ='[1]2.realisasi reboisasi'!M51 -> 156350 | AJ83: =AJ102-AJ97 -> 69251.69 | AK83: =AK102-AK97 -> 61177.55 | AL83: =AVERAGE(AG83:AK83) -> 63414.648 | AM83: =AVERAGE(AH83:AL83) -> 73443.378 | AN83: =AVERAGE(AI83:AM83) -> 84727.453 | BJ83: =AH83/AG83*100-100 -> 28.272172
B84: Luas kebakaran + luas konversi hutan | C84: NSDH | E84: Ha | Z84: =Z7+Z28+Z29 -> 3493.12 | AA84: =AA7+AA28+AA29 -> 547739.38 | AB84: =AB7+AB28+AB29 -> 659824.2 | AC84: =AC7+AC28+AC29 -> 178010.87 | AD84: =AD7+AD28+AD29 -> 380974.18 | AE84: =AE7+AE28+AE29 -> 1210580.4 | AF84: =AF7+AF28+AF29 -> 380545.35 | AG84: =AG7+AG28+AG29 -> 293794.27 | ... AN84: =AN7+AN28+AN29 -> 188239.93 | BJ84: =AH84/AG84*100-100 -> -14.482546
AE87: Angka Deforestasi Stat LH BPS
AE88: Hutan tetap | AF88: 255470.8 | AG88: 195730.2 | AH88: 369132 | AI88: 61655.6
AE89: Hutan yg dpt dikonversi | AF89: 41712.4 | AG89: 27593.6 | AH89: 6734.9 | AI89: 5340
AE90: area penggunaan lain | AF90: 182827.5 | AG90: 216115.2 | AH90: 86591.8 | AI90: 48464.1
AE91: total | AF91: =SUM(AF88:AF90) -> 480010.7 | AG91: =SUM(AG88:AG90) -> 439439 | AH91: =SUM(AH88:AH90) -> 462458.7 | AI91: =SUM(AI88:AI90) -> 115459.7
AE94: sumber: Status Lingkungan Hidup Indonesia klhk https://www.menlhk.go.id/cadmin/uploads/SLHI_2022_upload_final_77f9948571.pdf
AE95: luas kegiatan reboisasi per sub region (Ha)
AE96: sumatera | AG96: 5966 | AH96: =885+1047+1140+400+1130+550+675+125+350+200 -> 6502 | AI96: =14143+17207+1551+14749+1000+17629+771+16500+500+400 -> 84450 | AJ96: =60+500+1318.49+367.49 -> 2245.98 | AK96: =2010+3017+2152+1348+1100+3472+2000+2557+840+600 -> 19096
AE97: jawa | AG97: =13260+6577+145+675+555+640 -> 21852 | AH97: =2500+2005+1035+125+750+775+850+125 -> 8165 | AI97: =9740.51+8500.08+5000+3400.01+3657.38+4342.72+15000+9.49 -> 49650.19 | AJ97: 0 | AK97: =2528+1000+1000.68+820+280+1397.25+1035+722 -> 8782.93
AE98: bali nusra | AG98: 1306 | AH98: 2680 | AI98: 9850 | AJ98: =54361 -> 54361 | AK98: =750+1624+3665 -> 6039
AE99: kalimantan | AG99: 1576 | AH99: 2089 | AI99: 23400 | AJ99: 10022.19 | AK99: 12417.05
AE100: sulawesi maluku | AG100: =350+490+915+250+490+400+325+205 -> 3425 | AH100: =632+835+1375+485+425+300+400+275 -> 4727 | AI100: =400+200+19600+300+12300+2000+2050+500 -> 37350 | AJ100: =2.2+645+1119.02 -> 1766.22 | AK100: =1600+1250+6353+5037+2500+1250+1300+2229.5 -> 21519.5
AE101: papua | AG101: 998 | AH101: 1025 | AI101: 1300 | AJ101: 856.3 | AK101: 2106
AE102: total | AG102: =SUM(AG96:AG101) -> 35123 | AH102: =SUM(AH96:AH101) -> 25188 | AI102: =SUM(AI96:AI101) -> 206000.19 | AJ102: =SUM(AJ96:AJ101) -> 69251.69 | AK102: =SUM(AK96:AK101) -> 69960.48
AE103: Rehabilitasi Hutan dan Lahan | AF103: 198346.29 | AG103: =AG104+AG102+AG105 -> 200990.44 | AH103: =AH104+AH102+AH105 -> 188648 | AI103: =AI104+AI102+AI105 -> 395168.19 | AJ103: =AJ104+AJ102+AJ105 -> 147527.26 | AK103: =AK104+AK102+AK105 -> 151090.09
AE104: Rehabilitasi Lahan (ha) | AF104: 190782 | AG104: 164692 | AH104: 162500 | AI104: 188168 | AJ104: ='[1]3. rehabilitasi lahan'!$N$52 -> 78275.57 | AK104: ='[1]3. rehabilitasi lahan'!$O$52 -> 81129.61
...

Sheet 1.luas kebakaran hutan
A1: DATA LUAS KEBAKARAN HUTAN
A2: Sumber: | B2: Statistik perum perhutani 2012-2016, hal 142
A3: Satuan : | B3: Ha x Rp 1000
A4: Luas Kebakaran Hutan | B4: 2010 | C4: 2011 | D4: 2012 | E4: 2013 | F4: 2014 | G4: 2015 | H4: 2016 | I4: 2017
A5: ha | B5: 326 | C5: 9847 | D5: 12311 | E5: 2662 | F5: 4275 | G5: 11137 | H5: 352
A6: x Rp1000 | B6: 54750 | C6: 22995049 | D6: 27925113 | E6: 7359556 | F6: 11046629 | G6: 12879190 | H6: 522062
A8: Sumber | B8: Statistik KLHK 2016, hal 268
A9: Satuan | B9: Ha
A10: Provinsi | B10: Luas Kebakaran Hutan
B11: 2010 | C11: 2011 | D11: 2012 | E11: 2013 | F11: 2014 | G11: 2015 | H11: 2016 | I11: 2017
A12: Aceh | B12: 5 | D12: 13 | F12: 155.66 | I12: 797
A13: Bali | B13: 10.1 | D13: 250 | E13: 60.5 | F13: 30 | G13: 85 | I13: 3.5
A14: Kep. Bangka Belitung
A15: Banten | F15: 2
A16: Bengkulu | C16: 0.5 | F16: 5.25 | G16: 181
A17: DKI Jakarta
A18: Gorontalo | G18: 2082.74
A19: Jambi | B19: 2.5 | C19: 89 | D19: 11.25 | E19: 199.1 | F19: 3470.61 | G19: 19528 | H19: 36.8 | I19: 306.13
A20: Jawa Barat | C20: 1278.55 | D20: 1945.5 | E20: 252.8 | F20: 552.69 | G20: 3292.4 | I20: 6.44
A21: Jawa Tengah | C21: 712.24 | D21: 454 | E21: 31.2 | F21: 159.76 | G21: 6995.34
A22: Jawa Timur | B22: 204.9 | C22: 48.35 | D22: 2960.05 | E22: 1352.14 | F22: 4975.32 | G22: 975.95 | I22: 16
A23: Kalimantan Barat | D23: 577.4 | E23: 22.7 | F23: 3556.1 | G23: 3191.98 | H23: 1859.05 | I23: 761.33
A24: Kalimantan Selatan | D24: 60.5 | E24: 417.5 | F24: 341 | G24: 1714.89 | H24: 160 | I24: 1073.4
A25: Kalimantan Tengah | C25: 22 | D25: 55.15 | E25: 3.1 | F25: 4022.85 | G25: 122882.9 | H25: 912.89 | I25: 734.38
A26: Kalimantan Timur | C26: 148.8 | D26: 51.5 | F26: 325.19 | G26: 19179.86 | H26: 1197.2 | I26: 175.97
A27: Kalimantan Utara | H27: 3
A28: Kepulauan Riau | I28: 56.1
A29: Lampung | B29: 106 | C29: 31 | F29: 22.8 | G29: 19695.86 | I29: 4
A30: Maluku | F30: 179.83 | G30: 3394.48 | I30: 41
A31: Maluku Utara | B31: 10 | F31: 6.5 | G31: 60
A32: Nusa Tenggara Barat | B32: 2 | E32: 12 | F32: 3977.55 | G32: 1462.04 | I32: 103
A33: Nusa Tenggara Timur | B33: 95 | D33: 553.2 | E33: 649.9 | F33: 980.87 | G33: 372.43 | H33: 64.37 | I33: 159.83
A34: Papua | B34: 39 | F34: 300 | G34: 1792.44
A35: Papua Barat | B35: 1.12
A36: Riau | B36: 26 | C36: 74.5 | D36: 74.5 | E36: 1077.5 | F36: 6301.1 | G36: 4040.5 | H36: 1928.26 | I36: 1109.36
A37: Sulawesi Barat | I37: 20
A38: Sulawesi Selatan | B38: 28 | C38: 31.75 | D38: 45.3 | E38: 40.5 | F38: 483.1 | G38: 720.4 | H38: 18.91 | I38: 29.75
A39: Sulawesi Tengah | D39: 30.83 | E39: 1 | F39: 70.73
A40: Sulawesi Tenggara | B40: 16 | C40: 85.9 | D40: 346.1 | E40: 13 | F40: 2410.86 | G40: 57.82 | H40: 184.86 | I40: 1639.81
A41: Sulawesi Utara | D41: 1.8 | E41: 0.25 | F41: 236.06 | G41: 18268.93 | I41: 10.33
A42: Sumatera Barat | B42: 56 | D42: 3.5 | F42: 120.5 | I42: 5.33
A43: Sumatera Selatan | C43: 84.5 | E43: 484.15 | F43: 8504.86 | G43: 30984.98 | H43: 266.49 | I43: 2602.9
A44: Sumatera Utara | B44: 80 | C44: 5 | D44: 1181 | E44: 295.4 | F44: 3219.9 | G44: 177 | H44: 547.5 | I44: 1471.93
A45: Yogyakarta | B45: 2818.5 | D45: 6.45 | E45: 6 | F45: 0.27
A46: Total | B46: =SUM(B12:B45) -> 3500.12 | C46: =SUM(C12:C45) -> 2612.09 | D46: =SUM(D12:D45) -> 8621.03 | E46: =SUM(E12:E45) -> 4918.74 | F46: =SUM(F12:F45) -> 44411.36 | G46: =SUM(G12:G45) -> 261136.94 | H46: =SUM(H12:H45) -> 7179.33 | I46: =SUM(I12:I45) -> 11127.49
A47: Total Luar Jawa | E47: =E46-E22-E21-E20-E15 -> 3282.6 | F47: =F46-F22-F21-F20-F15 -> 38721.59 | G47: =G46-G22-G21-G20-G15 -> 249873.25 | H47: =H46-H22-H21-H20-H15 -> 7179.33 | I47: =I46-I22-I21-I20-I15 -> 11105.05
A49: Sumber | B49: NSDH
A50: Satuan | B50: Ha
A51: Tahun | B51: Luas Kebakaran Hutan
A52: 2010 | B52: 905.62
A53: 2011 | B53: 7089.58
A54: 2012 | B54: 8268.65
A55: 2013 | B55: 4918.75
A56: 2014 | B56: 32761.26
A57: 2015 | B57: 17025.51
A58: 2016 | B58: 3109.15
A59: 2017

Sheet 2.realisasi reboisasi
A1: Perkembangan Kegiatan Rehabilitasi Hutan (Reboisasi) Tahun 2012 s/d
A2: Sumber | B2: KLHK hal 144
A3: Satuan : | B3: Ha
A4: Provinsi | B4: Balai Pengelolaan Daerah Aliran Sungai dam Hutan Lindung | C4: Perkembangan Kegiatan Rehabilitasi Hutan (Reboisasi)
C5: 2010 (Ha) | D5: 2011 (Ha) | E5: 2012 (Ha) | F5: 2013 (Ha) | G5: 2014 (Ha) | H5: 2015 (Ha) | I5: 2016 (Ha) | J5: 2017 (Ha)
A6: Nanggroe Aceh Darussalam | B6: Krueng Aceh | E6: 5000 | F6: 500 | G6: 500 | H6: 900 | I6: 575 | J6: 460
A7: Sumatera Utara | B7: Wampu Sei Ular | E7: 3000 | F7: 5000 | G7: 800 | H7: - | I7: - | J7: 150
B8: Asahan Barumun | E8: 4005 | F8: 1500 | G8: 250 | H8: 800 | I8: - | J8: 1033
A9: Sumatera Barat | B9: Agam Kuantan | E9: 745 | F9: 1500 | G9: 200 | H9: 180 | I9: - | J9: 280
B10: Batanghari | E10: - | F10: - | G10: - | H10: 175 | I10: 50 | J10: 300
B11: Indragiri Rokan | E11: - | F11: - | G11: - | H11: 718 | I11: 400
A12: Riau | B12: Indragiri Rokan | E12: 2562 | F12: 1500 | G12: 850 | H12: 0 | I12: 375 | J12: 560
A13: Jambi | B13: Batanghari | E13: 7750 | F13: 6350 | G13: 800 | H13: 0 | I13: - | J13: 1000
A14: Sumatera Selatan | B14: Musi | E14: 5000 | F14: 3500 | G14: 400 | H14: 200 | I14: 107 | J14: 660
A15: Bengkulu | B15: Ketahun | E15: 5000 | F15: 6000 | G15: 2050 | H15: 200 | I15: 325 | J15: 295
A16: Lampung | B16: Way Seputih Sekampung | E16: 8800 | F16: 8300 | G16: 1750 | H16: 900 | I16: 604.04 | J16: 600
A17: Bangka Belitung | B17: Baturusa Cerucuk | E17: - | F17: - | G17: - | H17: - | I17: 150 | J17: 335
A18: Kepulauan Riau | B18: Kepulauan Riau (Sei Jang Duriangkang) | E18: - | F18: 850 | G18: 100 | H18: 200 | I18: 258 | J18: 293
A19: DKI Jakarta | B19: Citarum Ciliwung | E19: 270 | F19: 0 | G19: 0 | H19: 0 | I19: 0 | J19: 0
A20: Jawa Barat | B20: Citarum Ciliwung | E20: 1825 | F20: 1250 | G20: 175 | H20: 0 | I20: 0 | J20: 13260
B21: Cimanuk Citanduy | E21: 1124 | F21: 500 | G21: 175 | H21: 0 | I21: 0 | J21: 6577
A22: Jawa Tengah | B22: Cimanuk Citanduy | E22: 102 | F22: 100 | G22: 0 | H22: 0 | I22: 0 | J22: 0
B23: Pemali Jratun | E23: 533 | F23: 200 | G23: 0 | H23: 0 | I23: 0 | J23: 145
B24: Serayu Opak Progo | E24: 322 | F24: 320.88 | G24: 70 | H24: 0 | I24: 0 | J24: 675
B25: Solo | E25: 406 | F25: 200 | G25: 0 | H25: 0 | I25: 0 | J25: 555
A26: DI Yogyakarta | B26: Serayu Opak Progo | E26: 125 | F26: 134.75 | G26: 30 | H26: 0 | I26: 0 | J26: 0
A27: Jawa Timur | B27: Solo | E27: 0 | F27: 0 | G27: 0 | H27: 0 | I27: 0 | J27: 0
B28: Brantas (Brantas Sampean) | E28: 500 | F28: 200 | G28: 0 | H28: 0 | I28: 0 | J28: 640
B29: Sampean (Brantas Sampean) | E29: 150 | F29: 300 | G29: 100 | H29: 0 | I29: 0 | J29: 0
A30: Banten | B30: Citarum Ciliwung | E30: 175 | F30: 1250 | G30: 225 | H30: 0 | I30: 0 | J30: 0
A31: Bali | B31: Unda Anyar | E31: 200 | F31: 1000 | G31: 300 | H31: 300 | I31: 300 | J31: 250
A32: Nusa Tenggara Barat | B32: Dodokan Moyosari | E32: 3000 | F32: 4000 | G32: 550 | H32: 1125 | I32: 330 | J32: 606
A33: Nusa Tenggara Timur | B33: Benain Noelmina | E33: 4552 | F33: 3900 | G33: 700 | H33: 900 | I33: 350 | J33: 450
A34: Kalimantan Barat | B34: Kapuas | E34: 5000 | F34: 7000 | G34: 800 | H34: - | I34: - | J34: 650
A35: Kalimantan Tengah | B35: Kahayan | E35: 5000 | F35: 6000 | G35: 750 | H35: 900 | I35: 97 | J35: 254
A36: Kalimantan Selatan | B36: Barito | E36: 666 | F36: 1300 | G36: 500 | H36: 300 | I36: - | J36: 302
A37: Kalimantan Timur | B37: Mahakam Berau | E37: 2000 | F37: 2700 | G37: 800 | H37: 200 | I37: 400 | J37: 370
A38: Sulawesi Utara | B38: Tondano | E38: 1100 | F38: 1300 | G38: 700 | H38: - | I38: 252 | J38: 350
A39: Sulawesi Tengah | B39: Palu Poso | E39: 3000 | F39: 2750 | G39: 425 | H39: - | I39: 106 | J39: 490
A40: Sulawesi Selatan | B40: Jeneberang Walanae (Jeneberang Saddang) | E40: 5000 | F40: 5200 | G40: 2500 | H40: - | I40: - | J40: 915
B41: Saddang (Jeneberang Saddang) | E41: 1000 | F41: 5800 | G41: 3000 | H41: 150 | I41: -
A42: Sulawesi Tenggara | B42: Sampara | E42: 6425 | F42: 7000 | G42: 2000 | H42: 460 | I42: 400 | J42: 250
A43: Gorontalo | B43: Bone Bolango | E43: 2650 | F43: 2500 | G43: 500 | H43: 200 | I43: - | J43: 490
A44: Sulawesi Barat | B44: Lariang Mamasa | E44: 500 | F44: 6750 | G44: 2037 | H44: 800 | I44: 200 | J44: 400
B45: Saddang | E45: - | F45: - | G45: - | H45: 300 | I45: 344
A46: Maluku | B46: Waehapu Batu Merah | E46: 3000 | F46: 1500 | G46: 300 | H46: - | I46: 275 | J46: 325
A47: Maluku Utara | B47: Ake Malamo | E47: 500 | F47: 500 | G47: 250 | H47: - | I47: 218 | J47: 205
A48: Papua Barat | B48: Remu Ransiki | E48: 5000 | F48: 3000 | G48: 1000 | H48: 400 | I48: 400.62 | J48: 223
A49: Papua | B49: Membramo | E49: 5000 | F49: 4000 | G49: 575 | H49: 200 | I49: 550 | J49: 775
A50: Total | C50: =SUM(C6:C49) -> 0 | D50: =SUM(D6:D49) -> 0 | E50: =SUM(E6:E49) -> 100987 | F50: =SUM(F6:F49) -> 105655.63 | G50: =SUM(G6:G49) -> 26162 | H50: =SUM(H6:H49) -> 10508 | I50: =SUM(I6:I49) -> 7066.66 | J50: =SUM(J6:J49) -> 35123
A51: Total Luar Jawa | E51: =E50-E30-E29-E28-E27-E26-E25-E24-E23-E22-E21-E20-E19 -> 95455 | F51: =F50-F30-F29-F28-F27-F26-F25-F24-F23-F22-F21-F20-F19 -> 101200 | G51: =G50-G30-G29-G28-G27-G26-G25-G24-G23-G22-G21-G20-G19 -> 25387 | H51: =H50-H30-H29-H28-H27-H26-H25-H24-H23-H22-H21-H20-H19 -> 10508 | I51: =I50-I30-I29-I28-I27-I26-I25-I24-I23-I22-I21-I20-I19 -> 7066.66 | J51: =J50-J30-J29-J28-J27-J26-J25-J24-J23-J22-J21-J20-J19 -> 13271
A53: Rehabilitasi Hutan
A54: NSDH
A55: Tahun | B55: Luas Hutan (Ha)
A56: 2010 | B56: 100859
A57: 2011 | B57: 137924.48
A58: 2012 | B58: 100776.57
A59: 2013 | B59: 114459.53
A60: 2014 | B60: 204131.54
A61: 2015 | B61: 204131.54
A62: 2016 | B62: 204131.54
A63: 2017

Sheet Rent Perhutani
A1: Tabel E2. Perhitungan Harga Unit Rent Kayu Perhutani (Jati & Rimba) di Jawa
A3: Rincian | B3: 1990 | C3: 1991 | D3: 1992 | E3: 1993 | F3: 1994 | G3: 1995 | H3: 1996 | I3: 1997 | J3: 1998 | K3: 1999 | L3: 2000 | M3: 2001 | N3: 2002 | O3: 2003 | P3: 2004 | Q3: 2005 | R3: 2006 | S3: 2007 | T3: 2008 | U3: 2009 | V3: 2010 | W3: 2011 | X3: 2012 | Y3: 2013 | Z3: 2014 | AA3: 2015 | AB3: 2016 | AC3: 2017 | AD3: 2016
A4: a. Nilai Produksi (juta Rp) | B4: =B5 -> 231266 | C4: =C5 -> 228000 | D4: =D5 -> 256469 | E4: =E5 -> 333227 | F4: =F5 -> 404911 | G4: =G5 -> 442089 | H4: =H5 -> 504434 | I4: =I5 -> 638678 | ... Y4: =Y5 -> 3682245 | Z4: =Z5+427128.33 -> 2220128.3 | AA4: =AA5+313785 -> 1781785 | AB4: =AB5+AB6 -> 2396593 | AC4: =AC5+AC6 -> #REF! | AD4: 2396593 | AE4: " nilai penjualan DN+pendapatan lain | AI4: 2010
A5: Penjualan Dlm Negeri | B5: 231266 | C5: 228000 | D5: 256469 | E5: 333227 | F5: 404911 | G5: 442089 | H5: 504434 | I5: 638678 | J5: 843840 | K5: 1028020 | L5: 1302936 | M5: 1304709 | N5: 1206716 | O5: 1162926 | P5: 1297822 | Q5: 1200677 | R5: 1187721 | S5: 1623751 | T5: 1735239 | U5: 1756612 | V5: 1909300 | W5: 2035450 | X5: 2212915 | Y5: 3682245 | Z5: 1793000 | AA5: 1468000 | AB5: 1953942 | AC5: #REF! | AD5: 1953942 | AI5: =1073872.45+248004.81 -> 1321877.3
A6: Selisih Persediaan | C6: =C19-B19 -> 24594 | D6: =D19-C19 -> -5947 | E6: =E19-D19 -> 90870 | F6: =F19-E19 -> 52286 | G6: =G19-F19 -> 84267 | H6: =H19-G19 -> 71264 | I6: =I19-H19 -> 71384 | J6: =J19-I19 -> 381772 | ... AA6: =AA19-Z19 -> 353794 | AB6: 442651 | AC6: #REF! | AD6: 442651 | AE6: " aktiva t - aktiva (t-1)
A8: b. Beban Usaha (juta Rp) | B8: 147858 | C8: 180433 | D8: 198546 | E8: 229646 | F8: 253511 | G8: 277128 | H8: 340023.85 | I8: 368750.15 | J8: 531367.29 | K8: 674106.48 | L8: 872876.37 | M8: 866862.62 | N8: 875895.53 | O8: 885320.07 | P8: 932068.21 | Q8: 911822.96 | R8: 759522.29 | S8: 920536.47 | T8: 983759.48 | U8: =SUM(U9:U13) -> 1051330.8 | V8: =SUM(V9:V13) -> 1129638.9 | W8: =SUM(W9:W13) -> 1298394.9 | X8: =SUM(X9:X13) -> 1266785.9 | Y8: 873373 | Z8: 1346979 | AA8: 1283730 | AB8: 1306307 | AC8: #REF! | AD8: 1306307 | AE8: langsung ada di laporan manajemen | AF8: =SUM(V9:V13) -> 1129638.9 | AG8: =SUM(W9:W13) -> 1298394.9 | AH8: =SUM(X9:X13) -> 1266785.9 | AI8: =SUM(Y9:Y13) -> 2189713.6
A9: Biaya Umum (*c) | B9: 68579 | C9: 64813 | D9: 75399 | E9: 77697 | F9: 86595 | G9: 89796 | H9: 113640.91 | I9: 146577.63 | J9: 165385.35 | K9: 228149.78 | L9: 298183.77 | M9: 396826.28 | N9: 408491.64 | O9: 386824.61 | P9: 433029.74 | Q9: 411453.34 | R9: 255731 | S9: =+S5/S35*287755 -> 211677.19 | T9: =+T5/T35*322209 -> 236822.55 | U9: =+U5/U35*413641 -> 299546.29 | V9: =+V5/V35*472746 -> 323845.33 | W9: =+W5/W35*669465 -> 433373.69 | X9: =+X5/X35*535537 -> 333271.71 | Y9: =+Y5/Y35*615496 -> 586668.32 | AB9: 1085127 | AC9: #REF! | AD9: 1085127 | AE9: " penjualan DN / Total penjualan x biaya umum total | AI9: =AI8-Y8 -> 1316340.6
A10: Biaya Pemeliharaan | B10: 14916 | C10: 17647 | D10: 17837 | E10: 22907 | F10: 22298 | G10: 27242 | H10: 33374 | I10: 32863.074 | J10: 40286.439 | K10: 70880.47 | L10: 77903.109 | M10: 85959.396 | N10: 80132.011 | O10: 72452.312 | P10: 74292.601 | Q10: 76179.633 | R10: 78108.034 | S10: 89864 | T10: 82353.007 | U10: =22861+60761 -> 83622 | V10: =+V5/U5*U10 -> 90890.581 | W10: 77556 | X10: =+X5/W5*W10 -> 84317.883 | Y10: =+Y35/X5*X10 -> 147197.44 | AB10: 20330 | AC10: #REF! | AD10: 20330 | AE10: tdk ada datanya di lap. Keuangan
A11: Biaya Eksploitasi | B11: 47673 | C11: 79376 | D11: 82104 | E11: 105905 | F11: 118831 | G11: 133142 | H11: 161479 | I11: 160769.9 | J11: 297911.53 | K11: 336771.91 | L11: 445986.97 | M11: 327266.95 | N11: 324361.09 | O11: 370069.65 | P11: 370069.65 | Q11: 370069.65 | R11: 370069.65 | S11: 517448.84 | T11: 574785.89 | U11: =261627+304170 -> 565797 | V11: =+V5/U5*U11 -> 614977.13 | W11: =318266+354189 -> 672455 | X11: =+X5/W5*W11 -> 731084.41 | Y11: =+Y35/X5*X11 -> 1276286.2 | AB11: 1037951 | AC11: #REF! | AD11: 1037951 | AE11: tdk ada datanya di lap. Keuangan
A12: Biaya Pemasaran (*c) | B12: 10155 | C12: 8283 | D12: 7544 | E12: 10127 | F12: 11675 | G12: 10292 | H12: 12587.634 | I12: 16735.213 | J12: 17811.178 | K12: 27772.564 | L12: 37231.093 | M12: 46499.382 | N12: 46374.315 | O12: 40428.258 | P12: 37987.109 | Q12: 37136.115 | R12: 40849.811 | S12: =+S5/S35*117295 -> 86284.082 | T12: =+T5/T35*115701 -> 85039.853 | U12: =+U5/U35*120442 -> 87220.451 | V12: =+V5/V35*124957 -> 85599.331 | W12: =+W5/W35*139862 -> 90538.731 | X12: =+X5/X35*151992 -> 94586.617 | Y12: =+Y5/Y35*150582 -> 143529.27 | AB12: 221179 | AC12: #REF! | AD12: 221179 | AE12: " penjualan DN / Total penjualan x biaya pemasaran total
A13: Biaya Penyusutan (*c) | B13: 6535 | C13: 10314 | D13: 15662 | E13: 13010 | F13: 14112 | G13: 16656 | H13: 18942.31 | I13: 11804.34 | J13: 9972.7969 | K13: 10531.761 | L13: 13571.436 | M13: 10310.619 | N13: 16536.479 | O13: 15545.238 | P13: 16689.116 | Q13: 16984.222 | R13: 14763.795 | S13: 15384.472 | T13: 14887.751 | U13: =+U5/U35*((13493.560676+1959.789149)/(28746.157352+1315.716008+2801.200715)*44475.102118) -> 15145.087 | V13: =+V5/V35*((13493.560676+1959.789149)/(28746.157352+1315.716008+2801.200715)*44475.102118) -> 14326.536 | W13: =+W5/W35*(23594+13835+374) -> 24471.519 | X13: =(X5/W5)/(X35/W35)*W13 -> 23525.303 | Y13: =(Y5/X5)/(Y35/X35)*X13 -> 36032.44 | AB13: 130020 | AC13: #REF! | AD13: 130020 | AE13: tdk ada datanya di lap. Keuangan
AB14: =AB4-AB8 -> 1090286 | AD14: 1090286
A15: c. Laba Usaha (Juta Rp) | B15: =+B4-B8 -> 83408 | C15: =+C4-C8 -> 47567 | D15: =+D4-D8 -> 57923 | E15: =+E4-E8 -> 103581 | F15: =+F4-F8 -> 151400 | G15: =+G4-G8 -> 164961 | H15: =+H4-H8 -> 164410.15 | I15: =+I4-I8 -> 269927.85 | ... AA15: =+AA4-AA8 -> 498055 | AB15: -495271 | AC15: #REF! | AD15: -495271 | AE15: " niai produksi - beban usaha
A17: N.Aktiva Tetap (juta Rp) | B17: 63585 | C17: 78301 | D17: 90679 | E17: 90761 | F17: 92257 | G17: 98378 | H17: 133289 | I17: 152103 | J17: 175955 | K17: 228791.83 | L17: 249466.34 | M17: 319537 | N17: 296732 | O17: 278413 | P17: 257270 | Q17: 242251 | R17: 249135 | S17: 239792.63 | T17: 230263 | U17: 356732 | V17: 524013 | W17: 876148 | X17: 651836 | Y17: 772219.87 | Z17: 912793.93 | AA17: 1094942.6 | AB17: 819789 | AC17: #REF! | AD17: 819789
A18: Laba* stlh Pajak (jt Rp) | B18: 53875 | C18: 35769 | D18: 24108 | E18: 63713 | F18: 105572 | G18: 145144 | H18: 147300 | I18: 166965 | J18: 437954 | K18: 441898.55 | L18: 191542 | M18: 252171 | N18: 83644 | O18: 4954 | P18: 140704 | Q18: 92944 | R18: 100391 | S18: 84147.984 | T18: 164352 | U18: 158380 | V18: 275759 | W18: 389725 | X18: 197068 | Y18: 207564 | Z18: 373569 | AA18: 272672 | AB18: -357317 | AD18: -357317
A19: Total Aktiva (juta Rp) | B19: 268341 | C19: 292935 | D19: 286988 | E19: 377858 | F19: 430144 | G19: 514411 | H19: 585675 | I19: 657059 | J19: 1038831 | K19: 1247033.9 | L19: 1145884 | M19: 1093493 | N19: 1063592 | O19: 991742 | P19: 1211533 | Q19: 1276046 | R19: 1451656 | S19: 1518045.9 | T19: 1583531 | U19: 1800705 | V19: 2078948 | W19: 2549103 | X19: 2443861 | Y19: 3479696 | Z19: 4139504 | AA19: 4493298 | AB19: 3716315 | AC19: #REF! | AD19: 3716315
A20: R O I | B20: =B15/B19 -> 0.31082839 | C20: =C15/C19 -> 0.16238073 | D20: =D15/D19 -> 0.20183074 | E20: =E15/E19 -> 0.27412679 | F20: =F15/F19 -> 0.35197515 | G20: =G15/G19 -> 0.32067938 | H20: =H15/H19 -> 0.28071908 | I20: =I15/I19 -> 0.41081219 | ... AC20: =AC15/AC19 -> #REF! | AD20: -0.13326938 | AE20: " laba / total aktiva
A21: N.Akt TetapxROI (jt Rp) | B21: =+B20*B17 -> 19764.023 | C21: =+C20*C17 -> 12714.574 | D21: =+D20*D17 -> 18301.81 | E21: =+E20*E17 -> 24880.021 | F21: =+F20*F17 -> 32472.172 | G21: =+G20*G17 -> 31547.796 | H21: =+H20*H17 -> 37416.766 | I21: =+I20*I17 -> 62485.767 | ... AC21: =+AC20*AC17 -> #REF! | AD21: -109252.77 | AE21: " penyusutan kapital
A23: d. Economic Rent (jt Rp) | B23: 73074 | C23: 49497 | D23: 42840 | E23: 93608 | F23: 138113 | G23: 137199 | H23: 130887.34 | I23: 231277.02 | J23: 238292.99 | K23: 272838.91 | L23: 388359.7 | M23: 364157.78 | N23: 307484.59 | O23: 276215.19 | P23: 335875.18 | Q23: 271209.08 | R23: 410969.49 | S23: 689922.4 | T23: =+T15-T21 -> 642206.05 | U23: =+U15-U21 -> 565560.14 | V23: =+V15-V21 -> 583142.2 | W23: =+W15-W21 -> 483723.08 | X23: =+X15-X21 -> 693773.9 | Y23: =+Y15-Y21 -> 2185522.5 | Z23: =+Z15-Z21 -> 680612.88 | AA23: =+AA15-AA21 -> 376687.21 | ... AC23: =+AC15-AC21 -> #REF! | AD23: -386018.23 | AE23: " laba usaha - penyusutan
A24: Total Prod. Ky. (000m3) | B24: ='Data Penunjang'!F50 -> 1267.733 | C24: ='Data Penunjang'!G50 -> 1328.78 | D24: ='Data Penunjang'!H50 -> 1315.452 | E24: ='Data Penunjang'!I50 -> 1624.791 | F24: ='Data Penunjang'!J50 -> 1711.463 | G24: ='Data Penunjang'!K50 -> 1601.269 | H24: ='Data Penunjang'!L50 -> 0 | I24: ='Data Penunjang'!M50 -> 1861.863 | ... AC24: ='Data Penunjang'!AG50 -> 636.29236 | AD24: 548.432
A25: e. Unit Rent P.tani(Rp/m3) | B25: 57633.883 | C25: 37252.201 | D25: 32568.04 | E25: 57612.014 | F25: 80701.765 | G25: 74690.511 | H25: 71950.516 | I25: 124218.06 | J25: 138741.92 | K25: 154879.81 | L25: 241595.65 | M25: 250187.41 | N25: 207075.53 | O25: 282574.24 | P25: 363646.5 | Q25: 359294.42 | R25: 469355.96 | S25: 598285.93 | T25: =+T23/T24*1000 -> 593030.2 | U25: =+U23/U24*1000 -> 577461.62 | V25: =+V23/V24*1000 -> 655613.01 | W25: =W23/W24*1000 -> 499095.21 | X25: =X23/X24*1000 -> 746859.15 | Y25: =Y23/Y24*1000 -> 2287105.9 | Z25: =Z23/Z24*1000 -> 740934.58 | AA25: =AA23/AA24*1000 -> 476071.87 | AB25: =AB23/AB24*1000 -> -703857.96 | AC25: =AC23/AC24*1000 -> #REF! | AD25: -703857.96 | AE25: " economic rent / total prod
A27: Harga Kayu Perhutani | B27: =B4/B24*1000 -> 182424.85 | C27: =C4/C24*1000 -> 171585.97 | D27: =D4/D24*1000 -> 194966.44 | E27: =E4/E24*1000 -> 205089.15 | F27: =F4/F24*1000 -> 236587.64 | G27: =G4/G24*1000 -> 276086.65 | H27: =H4/H24*1000 -> #DIV/0! | I27: =I4/I24*1000 -> 343031.68 | ... AC27: =AC4/AC24*1000 -> #REF! | AD27: 4369900 | AE27: " nilai produksi / total produksi
A28: Rasio Harga (UR/P.tani) | B28: =+B25/B27 -> 0.3159322 | C28: =+C25/C27 -> 0.21710518 | D28: =+D25/D27 -> 0.16704433 | E28: =+E25/E27 -> 0.28091206 | F28: =+F25/F27 -> 0.34110727 | G28: =+G25/G27 -> 0.27053286 | H28: =+H25/H27 -> #DIV/0! | I28: =+I25/I27 -> 0.36211834 | ... AC28: =+AC25/AC27 -> #REF! | AD28: -0.16106958 | AE28: " unit rent / harga | AK28: Produksi | AM28: Pendapatan
AI29: 2009 | AJ29: 2010 | AK29: 2008 | AL29: 2009 | AM29: 2008 | AN29: 2009
A30: f Harga Kayu Jati (PDB) | B30: 187661.88 | C30: 222220.4 | D30: 249187.94 | E30: 264619.48 | F30: 301037.71 | G30: 349288.22 | H30: 427003.02 | I30: 461106.17 | J30: 1116884.9 | K30: 835084.09 | L30: 972609.96 | M30: 1030123.9 | N30: 1192170.1 | O30: 1216214.6 | P30: 1265699.7 | Q30: 1318183 | R30: 1428081.1 | S30: 1467401.9 | T30: 1547166 | U30: 1684962.3 | V30: 1747794.9 | W30: 1823437.2 | X30: 1919114.8 | Y30: 2259323 | Z30: 2544638.3 | AA30: 3116120.1 | AB30: 3340763.8 | AC30: 3380519.2 | AD30: 3340763.8 | AI30: 1684962.3 | AJ30: 1746812.4 | AK30: =477736+605213 -> 1082949 | AL30: =458263+524194 -> 982457 | AM30: 2362406 | AN30: 2425691
A31: g Hrg.Kayu "Rimba" PDB | B31: 50068.803 | C31: 53478.345 | D31: 57499.858 | E31: 63564.719 | F31: 76377.123 | G31: 80897.027 | H31: 88794.03 | I31: 90134.236 | J31: 113763.97 | K31: 140990.3 | L31: 147151.79 | M31: 149329.74 | N31: 152953.52 | O31: 161158.79 | P31: 174411.84 | Q31: 190438.65 | R31: 294552.43 | S31: 333639.1 | T31: 373185.1 | U31: 409613.35 | V31: 426135.04 | W31: 444987.93 | X31: 460953 | Y31: 475824 | Z31: 1830165.3 | AA31: 2267644.7 | AB31: 2308238.8 | AC31: 2325895.1 | AD31: 2308238.8 | AI31: 409613.35 | AJ31: 426068.91 | AM31: =+AM30/AK30*1000000 -> 2181456.4 | AN31: =+AN30/AL30*1000000 -> 2469004.8 | AO31: =+AN31/AM31 -> 1.1318149
AI32: 1036999.6 | AJ32: 1077646.9
A33: h. Unit Rent Jati (Rp/m3) | B33: =+B28*B30 -> 59288.429 | C33: =+C28*C30 -> 48245.199 | D33: =+D28*D30 -> 41625.434 | E33: =+E28*E30 -> 74334.803 | F33: =+F28*F30 -> 102686.15 | G33: =+G28*G30 -> 94493.941 | H33: =+H28*H30 -> #DIV/0! | I33: =+I28*I30 -> 166975 | ... AC33: =+AC28*AC30 -> #REF! | AD33: -538095.41 | AE33: " rasio harga x harga jati | AI33: =+AI31/AH31*100-100 -> #DIV/0!
A34: i. Unit Rent "Rimba Jawa" | B34: 12008 | C34: 9770 | D34: 9185 | E34: 18258 | F34: 25412 | G34: 26376 | H34: 22716.92 | I34: 0 | J34: 34771.363 | K34: 45203.574 | L34: 54060.244 | M34: 52948.228 | N34: 58596.72 | O34: 64064.611 | P34: 67100.189 | Q34: 74400.654 | R34: 94504.643 | S34: 102273.37 | T34: =+T28*T31 -> 138114.53 | U34: =+U28*U31 -> 131879.43 | V34: =+V28*V31 -> 130151.01 | W34: =+W28*W31 -> 105751.03 | X34: =+X28*X31 -> 144513.98 | Y34: =+Y28*Y31 -> 282415.77 | Z34: =+Z28*Z31 -> 561064 | AA34: =+AA28*AA31 -> 479402.83 | ... AC34: =+AC28*AC31 -> #REF! | AD34: -371787.05 | AE34: " rasio harga x harga rimba
A35: Penjualan (DN + LN) (juta Rp) | B35: 284046 | C35: 282459 | D35: 320465 | E35: 421433 | F35: 520808 | G35: 637485 | H35: 706947 | I35: 836109 | J35: 1371553 | K35: 1508423.1 | L35: 1877595.9 | M35: 1714691 | N35: 1690208 | O35: 1564538 | P35: 1626347 | Q35: 1478468 | R35: 1682472 | S35: 2207335 | T35: 2360880 | U35: 2425691 | V35: 2787176 | W35: 3144313 | X35: 3555951 | Y35: 3863183
A36: Angka Lama
A37: h. Unit Rent Jati (Rp/m3) | B37: 116920 | C37: 94438 | D37: 81830 | E37: 154495 | F37: 221715 | G37: 232725 | H37: 223287.47 | I37: 356614.85 | J37: 357190.88 | K37: 473090.98 | L37: 772191.34 | M37: 614622.87 | N37: 563542.91 | O37: 616585.64 | P37: 626110.64 | Q37: 668318.9 | R37: 706812.38 | S37: 790274.7 | AE37: =Y35-180938 -> 3682245 | AI37: 2007 | AJ37: 2008 | AK37: 2009 | AL37: 2010
A38: i. Unit Rent "Rimba Jawa" | B38: 12008 | C38: 9770 | D38: 9185 | E38: 18258 | F38: 25412 | G38: 26376 | H38: 22716.92 | I38: 34715.289 | J38: 34771.363 | K38: 45203.574 | L38: 54060.244 | M38: 52948.228 | N38: 58596.72 | O38: 64064.611 | P38: 67100.189 | Q38: 74400.654 | R38: 94504.643 | S38: 94775.716 | AI38: 1467401.9 | AJ38: 1547166 | AK38: 1684962.3 | AL38: 1746812.4
AI39: 333639.1 | AJ39: 373185.1 | AK39: 409613.35 | AL39: 426068.91
AI40: 839514.41 | AJ40: 949310.09 | AK40: 1036999.6 | AL40: 1077646.9

Sheet Rent Luar Jawa
A1: Tabel E1. Perhitungan Harga Unit Rent Kayu Rimba Di Luar Jawa
A2: (Data Suatu Perusahaan HPH di Kalimantan, Tahun 1992)
A3: Rincian | B3: Satuan | C3: 1992 | D3: 1993 | E3: 1994 | F3: 1995 | G3: 1996 | H3: 1997 | I3: 1998 | J3: 1999 | K3: 2000 | L3: 2001 | M3: 2002 | N3: 2003 | O3: 2004 | P3: 2005 | Q3: 2006 | R3: 2007 | S3: 2008 | T3: 2009 | U3: 2010 | V3: 2011 | W3: 2012 | X3: 2013 | Y3: 2014 | Z3: 2015 | AA3: 2016 | AB3: 2017
A4: a. Nilai Penjualan Kayu | B4: Juta Rp | C4: 4251.5
A5: Produksi Log | B5: m3 | C5: 23981
A6: Harga Log | B6: Rp/m3 | C6: 177300
A7: b. Laba Usaha*) | B7: juta Rp | C7: 368.7
A9: Nilai Aktiva Tetap | B9: juta Rp | C9: 2339.3
A10: Laba setelah Pajak | B10: juta Rp | C10: 241.3
A11: Total Aktiva | B11: juta Rp | C11: 7302.7
A12: Return On Investment | B12: % | C12: =C7/C11 -> 0.050488176 | AD12: " laba / total aktiva
A13: Nilai Aktiva Tetap x ROI | B13: juta Rp | C13: =C12*C9 -> 118.10699 | AD13: " penyusutan kapital
A15: c. Economic Rent Kayu Rimba | B15: juta Rp | C15: =C7-C13 -> 250.59301 | AD15: " laba usaha - penyusutan
A16: d. Unit Rent Kayu Rimba | B16: Rp/m3 | C16: =C15*1000000/C5 -> 10449.648 | AD16: " economic rent / total prod
A18: e. Rasio Harga (Unit rent/hrg log)** | B18: % | C18: =C16/C19 -> 0.072097652 | D18: =C18 -> 0.072097652 | E18: =D18 -> 0.072097652 | F18: =E18 -> 0.072097652 | G18: =F18 -> 0.072097652 | H18: =G18 -> 0.072097652 | I18: =H18 -> 0.072097652 | J18: =I18 -> 0.072097652 | K18: =J18 -> 0.072097652 | ... AC18: =AB18 -> 0.072097652 | AD18: " unit rent / harga
A19: f. Harga Ky. Log Rimba (LK PDB) | B19: Rp/m3 | C19: 144937.43 | D19: 158800.24 | E19: 191857.07 | F19: 207148.72 | G19: 224888.55 | H19: 228354.75 | I19: 290857.8 | J19: 356210.28 | K19: 371312.93 | L19: 375538.27 | M19: 384750.27 | N19: 407805.59 | O19: 441986.04 | P19: 508164.29 | Q19: 713040.22 | R19: 839514.41 | S19: 949310.09 | T19: 1036999.6 | U19: 1077646.9 | V19: 1126642.9 | W19: 1167378.6 | X19: 1981675.5 | Y19: 2082476.1 | Z19: 2264231.2 | AA19: 2307758.8 | AB19: 2328000.9 | AC19: 2405257.2
A21: g. Unit Rent Kayu log Rimba (PDB'92) | B21: Rp/m3 | C21: =C18*C19 -> 10449.648 | D21: =D18*D19 -> 11449.125 | E21: =E18*E19 -> 13832.444 | F21: =F18*F19 -> 14934.936 | G21: =G18*G19 -> 16213.937 | H21: =H18*H19 -> 16463.842 | I21: =I18*I19 -> 20970.165 | J21: =J18*J19 -> 25681.925 | ... AC21: =AC18*AC19 -> 173413.39
C22: =+C16/C6*100 -> 5.8937665
A23: Catatan: *) Laba Usaha: Hasil Pengurangan Nilai penjualan terhadap Biaya
A24: (produksi + penjualan + umum + finansial + penyusutan).
A25: **) Karena Keterbatasan data, maka rasio unit rent diatas digunakan
A26: Sebagai alokator untuk series harga kayu rimba PDB lainnya.

Sheet Jati Jawa
A1: Neraca Fisik dan Moneter
A2: Kayu Jati Jawa
A4: Perincian | B4: 1990 | C4: 1991 | D4: 1992 | E4: 1993 | F4: 1994 | G4: 1995 | H4: 1996 | I4: 1997 | J4: 1998 | K4: 1999 | L4: 2000 | M4: 2001 | N4: 2002 | O4: 2003 | P4: 2004 | Q4: 2005 | R4: 2006 | S4: 2007 | T4: 2008 | U4: 2009 | V4: 2010 | W4: 2011 | X4: 2012 | Y4: 2013 | Z4: 2014 | AA4: 2015 | AB4: 2016 | AC4: 2017 | AD4: 2018 | AE4: 2019 | AF4: 2020 | AG4: 2021 | AH4: 2022 | AI4: 2023 | AJ4: 2024 | AV4: 2004 | AW4: 2005 | AX4: 2006 | AY4: 2007 | AZ4: 2008 | BA4: 2009 | BB4: 2010 | BC4: 2011 | BD4: 2012 | BE4: 2013 | BF4: 2014 | BG4: 2015 | BH4: 2016 | BI4: 2017
A6: I. Neraca Fisik (000 M3) | AV6: Persentase pertumbuhan
A8: 1. Persediaan Awal | B8: 32304.3 | C8: =B14 -> 34013.5 | D8: =C14 -> 35879.6 | E8: =D14 -> 37930.4 | F8: =E14 -> 39907.9 | G8: =F14 -> 42030 | H8: =G14 -> 44303.5 | I8: =H14 -> 48155.34 | J8: =I14 -> 51768.635 | ... AJ8: =AI14 -> 143946.66 | AV8: =P8/O8*100-100 -> 5.3289197 | AW8: =Q8/P8*100-100 -> 4.9586234 | AX8: =R8/Q8*100-100 -> 5.137219 | AY8: =S8/R8*100-100 -> 4.8881098 | AZ8: =T8/S8*100-100 -> 4.6709881 | BA8: =U8/T8*100-100 -> 4.5119743 | BB8: =V8/U8*100-100 -> 4.3928757 | BC8: =W8/V8*100-100 -> 4.0841534 | ... BI8: =AC8/AB8*100-100 -> 2.7861282
A9: 2. Pertumbuhan | B9: 2580.4 | C9: 2716.5 | D9: 2865.5 | E9: 3029.3 | F9: 3187.2 | G9: 3356.7 | H9: 4882.73 | I9: 4650.13 | J9: 4716.25 | K9: 4547.8065 | L9: 4692.4008 | M9: 4660.876 | N9: 4510.2537 | O9: 4619.361 | P9: 4643.6453 | Q9: 4727.4685 | R9: 4732.2948 | S9: 4727.4302 | T9: 4732.2962 | U9: ='Data Penunjang'!Y37/'Data Penunjang'!X37*T9*1.005 -> 4755.9577 | V9: ='Data Penunjang'!Z37/'Data Penunjang'!Y37*U9*1.005 -> 4779.736 | W9: ='Data Penunjang'!AA37/'Data Penunjang'!Z37*V9*1.005 -> 4803.6347 | X9: ='Data Penunjang'!AB37/'Data Penunjang'!AA37*W9*1.005 -> 4827.6543 | Y9: ='Data Penunjang'!AC37/'Data Penunjang'!AB37*X9*1.005 -> 5459.4625 | Z9: ='Data Penunjang'!AD37/'Data Penunjang'!AC37*Y9*1.005 -> 4764.8739 | AA9: ='Data Penunjang'!AE37/'Data Penunjang'!AD37*Z9*1.005 -> 4794.9495 | AB9: ='Data Penunjang'!AF37/'Data Penunjang'!AE37*AA9*1.005 -> 4335.8832 | ... AJ9: ='Data Penunjang'!AN37/'Data Penunjang'!AM37*AI9*1.005 -> 5096.753 | AV9: =P9/O9*100-100 -> 0.52570698 | AW9: =Q9/P9*100-100 -> 1.8051154 | AX9: =R9/Q9*100-100 -> 0.102091 | AY9: =S9/R9*100-100 -> -0.10279558 | AZ9: =T9/S9*100-100 -> 0.10293138 | BA9: =U9/T9*100-100 -> 0.5 | BB9: =V9/U9*100-100 -> 0.49996986 | BC9: =W9/V9*100-100 -> 0.5 | ... BI9: =AC9/AB9*100-100 -> -0.10023061
A10: 3. Penanaman | B10: 18.8 | C10: 21.5 | D10: 17.6 | E10: 16.3 | F10: 16.5 | G10: 19.9 | H10: 10.5 | I10: 15.89 | J10: 14.43 | K10: 31.781 | L10: 44.16 | M10: 46.587 | N10: 44.869 | O10: 40.9 | P10: 37.619 | Q10: 42.0964 | R10: 41.622 | S10: 62.605 | T10: 32.016 | U10: ='Data Penunjang'!Y48/'Data Penunjang'!X48*T10 -> 19.15 | V10: ='Data Penunjang'!Z48/'Data Penunjang'!Y48*U10 -> 19.324 | W10: ='Data Penunjang'!AA48/'Data Penunjang'!Z48*V10 -> 29.868 | X10: ='Data Penunjang'!AB48/'Data Penunjang'!AA48*W10 -> 24.529 | Y10: ='Data Penunjang'!AC48/'Data Penunjang'!AB48*X10 -> 16.23275 | Z10: ='Data Penunjang'!AD48/'Data Penunjang'!AC48*Y10 -> 23.34 | AA10: ='Data Penunjang'!AE48/'Data Penunjang'!AD48*Z10 -> 20.32837 | AB10: ='Data Penunjang'!AF48/'Data Penunjang'!AE48*AA10 -> 4.48 | ... AJ10: ='Data Penunjang'!AN48/'Data Penunjang'!AM48*AI10 -> 14.076 | AV10: =P10/O10*100-100 -> -8.0220049 | AW10: =Q10/P10*100-100 -> 11.901964 | AX10: =R10/Q10*100-100 -> -1.1269372 | AY10: =S10/R10*100-100 -> 50.413243 | AZ10: =T10/S10*100-100 -> -48.860315 | BA10: =U10/T10*100-100 -> -40.186157 | BB10: =V10/U10*100-100 -> 0.90861619 | BC10: =W10/V10*100-100 -> 54.564272 | ... BI10: =AC10/AB10*100-100 -> 62.083929
A11: 4. Konversi & Kerusakan | B11: 112.7 | C11: 114.3 | D11: 151.5 | E11: 234 | F11: 207.6 | G11: 206.4 | H11: 208.87 | I11: 187.61 | J11: 534.95 | K11: 558.43809 | L11: 559.74385 | M11: 564.60888 | N11: 583.46428 | O11: 569.7 | P11: 566.7 | Q11: 504.88153 | R11: 377.6009 | S11: 354.96372 | T11: 329.24483 | U11: ='Rimba Jawa'!AP31/'Rimba Jawa'!AO31*T11 -> 293.16735 | V11: ='Rimba Jawa'!AQ31/'Rimba Jawa'!AP31*U11 -> 440.82049 | W11: ='Rimba Jawa'!AR31/'Rimba Jawa'!AQ31*V11 -> 1014.8983 | X11: ='Rimba Jawa'!AS31/'Rimba Jawa'!AR31*W11 -> 2572.9828 | Y11: ='Rimba Jawa'!AT31/'Rimba Jawa'!AS31*X11 -> 1398.2411 | Z11: ='Rimba Jawa'!AU31/'Rimba Jawa'!AT31*Y11 -> 1044.8336 | AA11: ='Rimba Jawa'!AV31/'Rimba Jawa'!AU31*Z11 -> 1228.4299 | AB11: ='Data Penunjang'!AF70/'Data Penunjang'!AE70*AA11 -> 886.0488 | AC11: ='Data Penunjang'!AG70/'Data Penunjang'!AF70*AB11 -> 1082.9537 | AD11: ='Data Penunjang'!AH70/'Data Penunjang'!AG70*AC11 -> 1163.8354 | AE11: ='Data Penunjang'!AI70/'Data Penunjang'!AH70*AD11 -> 1071.884 | AF11: ='Data Penunjang'!AJ70/'Data Penunjang'!AI70*AE11 -> 900.3891 | AG11: ='Data Penunjang'!AK70/'Data Penunjang'!AJ70*AF11 -> 516.34271 | AH11: ='Data Penunjang'!AL70/'Data Penunjang'!AK70*AG11 -> 641.39338 | AI11: ='Data Penunjang'!AM70/'Data Penunjang'!AL70*AH11 -> 876.37468 | AJ11: ='Data Penunjang'!AN70/'Data Penunjang'!AM70*AI11 -> 686.75276 | AV11: =P11/O11*100-100 -> -0.52659294 | AW11: =Q11/P11*100-100 -> -10.9085 | AX11: =R11/Q11*100-100 -> -25.21 | AY11: =S11/R11*100-100 -> -5.995 | AZ11: =T11/S11*100-100 -> -7.2454996 | BA11: =U11/T11*100-100 -> -10.957643 | BB11: =V11/U11*100-100 -> 50.364795 | BC11: =W11/V11*100-100 -> 130.22939 | ... BI11: =AC11/AB11*100-100 -> 22.222809
A12: 5. Penebangan | B12: 777.3 | C12: 757.6 | D12: 680.8 | E12: 834.1 | F12: 874 | G12: 896.7 | H12: 832.52 | I12: ='Data Penunjang'!M51 -> 865.115 | J12: ='Data Penunjang'!N51 -> 760.753 | K12: ='Data Penunjang'!O51 -> 765.738 | L12: ='Data Penunjang'!P51 -> 694.242 | M12: ='Data Penunjang'!Q51 -> 654.939 | N12: ='Data Penunjang'!R51 -> 668.404 | O12: ='Data Penunjang'!S51 -> 427.847 | P12: ='Data Penunjang'!T51 -> 524.745 | ... AJ12: ='Data Penunjang'!AN51 -> 395.508 | AV12: =P12/O12*100-100 -> 22.647816 | AW12: =Q12/P12*100-100 -> -31.175714 | AX12: =R12/Q12*100-100 -> 36.026382 | AY12: =S12/R12*100-100 -> 6.0674345 | AZ12: =T12/S12*100-100 -> -8.3211628 | BA12: =U12/T12*100-100 -> -4.7120638 | BB12: =V12/U12*100-100 -> -1.1353251 | BC12: =W12/V12*100-100 -> -3.2513244 | ... BI12: =AC12/AB12*100-100 -> 22.17504
A13: 6. Perubahan Neto | B13: =B14-B8 -> 1709.2 | C13: =C14-C8 -> 1866.1 | D13: =D14-D8 -> 2050.8 | E13: =E14-E8 -> 1977.5 | F13: =F14-F8 -> 2122.1 | G13: =G14-G8 -> 2273.5 | H13: =H14-H8 -> 3851.84 | I13: =I14-I8 -> 3613.295 | ... AJ13: =AJ14-AJ8 -> 4028.5683 | AV13: =P13/O13*100-100 -> -1.9901826 | AW13: =Q13/P13*100-100 -> 8.7389364 | AX13: =R13/Q13*100-100 -> 0.039004525 | AY13: =S13/R13*100-100 -> 0.22915391 | AZ13: =T13/S13*100-100 -> 1.1076872 | BA13: =U13/T13*100-100 -> 1.7532648 | BB13: =V13/U13*100-100 -> -2.9436411 | BC13: =W13/V13*100-100 -> -13.433349 | ... BI13: =AC13/AB13*100-100 -> -7.9299061
A14: 7. Persediaan Akhir | B14: =B8+B9+B10-B11-B12 -> 34013.5 | C14: =C8+C9+C10-C11-C12 -> 35879.6 | D14: =D8+D9+D10-D11-D12 -> 37930.4 | E14: =E8+E9+E10-E11-E12 -> 39907.9 | F14: =F8+F9+F10-F11-F12 -> 42030 | G14: =G8+G9+G10-G11-G12 -> 44303.5 | H14: =H8+H9+H10-H11-H12 -> 48155.34 | I14: =I8+I9+I10-I11-I12 -> 51768.635 | ... AJ14: =AJ8+AJ9+AJ10-AJ11-AJ12 -> 147975.23 | AV14: =P14/O14*100-100 -> 4.9586234 | AW14: =Q14/P14*100-100 -> 5.137219 | AX14: =R14/Q14*100-100 -> 4.8881098 | AY14: =S14/R14*100-100 -> 4.6709881 | AZ14: =T14/S14*100-100 -> 4.5119743 | BA14: =U14/T14*100-100 -> 4.3928757 | BB14: =V14/U14*100-100 -> 4.0841534 | BC14: =W14/V14*100-100 -> 3.3967849 | ... BI14: =AC14/AB14*100-100 -> 2.4956586
A15: Pertumbuhan | C15: =+C12/B12*100-100 -> -2.534414 | D15: =+D12/C12*100-100 -> -10.137276 | E15: =+E12/D12*100-100 -> 22.517626 | F15: =+F12/E12*100-100 -> 4.7835991 | G15: =+G12/F12*100-100 -> 2.597254 | H15: =+H12/G12*100-100 -> -7.1573547 | I15: =+I12/H12*100-100 -> 3.9152213 | J15: =+J12/I12*100-100 -> -12.063367 | ... AH15: =+AH12/AG12*100-100 -> 1.1553076
A16: II. Unit Rent | B16: 116920 | C16: 94638 | D16: 81830 | E16: 154495 | F16: 221715 | G16: 232725 | H16: 223287.47 | I16: 356614.85 | J16: 357190.88 | K16: 473090.98 | L16: 504505.32 | M16: ='Rent Perhutani'!M33 -> 287518.23 | N16: ='Rent Perhutani'!N33 -> 303778.14 | O16: ='Rent Perhutani'!O33 -> 288872.16 | P16: ='Rent Perhutani'!P33 -> 327561.95 | Q16: ='Rent Perhutani'!Q33 -> 297751.36 | R16: ='Rent Perhutani'!R33 -> 494137.71 | S16: ='Rent Perhutani'!S33 -> 623490.58 | T16: ='Rent Perhutani'!T33 -> 572600.87 | ... AH16: ='Rent Perhutani'!AH33 -> 0 | AV16: =P16/O16*100-100 -> 13.393392 | AW16: =Q16/P16*100-100 -> -9.1007473 | AX16: =R16/Q16*100-100 -> 65.956491 | AY16: =S16/R16*100-100 -> 26.177494 | AZ16: =T16/S16*100-100 -> -8.1620656 | BA16: =U16/T16*100-100 -> -5.2583096 | BB16: =V16/U16*100-100 -> -1.5994273 | BC16: =W16/V16*100-100 -> -18.822362 | ... BI16: =AC16/AB16*100-100 -> #REF!
T17: -1.1561291 | U17: =+U16/T16*100-100 -> -5.2583096 | V17: =+V16/U16*100-100 -> -1.5994273 | W17: =+W16/V16*100-100 -> -18.822362 | X17: =+X16/W16*100-100 -> 38.843962 | Y17: =+Y16/X16*100-100 -> 122.87777 | Z17: =+Z16/Y16*100-100 -> -41.826229 | AA17: =+AA16/Z16*100-100 -> -15.551562 | AB17: =+AB16/AA16*100-100 -> -181.68071 | ... AH17: =+AH16/AG16*100-100 -> #DIV/0!
A18: III. Neraca Moneter
A19: (Miliar Rp)
A21: 1. Persediaan Awal | B21: 3202.2 | C21: =B28 -> 3976.8397 | D21: =C28 -> 3395.5548 | E21: =D28 -> 3103.8259 | F21: =E28 -> 6165.5523 | G21: =F28 -> 9318.6627 | H21: =G28 -> 10310.513 | I21: =H28 -> 10752.465 | J21: =I28 -> 18461.445 | ... AH21: =AG28 -> #REF! | AV21: =P21/O21*100-100 -> 0.16057464 | AW21: =Q21/P21*100-100 -> 19.016161 | AX21: =R21/Q21*100-100 -> -4.4310569 | AY21: =S21/R21*100-100 -> 74.068685 | AZ21: =T21/S21*100-100 -> 32.071244 | BA21: =U21/T21*100-100 -> -4.018363 | BB21: =V21/U21*100-100 -> -1.0964253 | BC21: =W21/V21*100-100 -> 2.4194039 | ... BI21: =AC21/AB21*100-100 -> -183.95649
A22: 2. Pertumbuhan | B22: =B9*B16/1000000 -> 301.70037 | C22: =C9*C16/1000000 -> 257.08413 | D22: =D9*D16/1000000 -> 234.48387 | E22: =E9*E16/1000000 -> 468.0117 | F22: =F9*F16/1000000 -> 706.65005 | G22: =G9*G16/1000000 -> 781.18801 | H22: =H9*H16/1000000 -> 1090.2524 | I22: =I9*I16/1000000 -> 1658.3054 | ... AH22: =AH9*AH16/1000000 -> 0 | AV22: =P22/O22*100-100 -> 13.989509 | AW22: =Q22/P22*100-100 -> -7.4599108 | AX22: =R22/Q22*100-100 -> 66.125917 | AY22: =S22/R22*100-100 -> 26.047789 | AZ22: =T22/S22*100-100 -> -8.0675356 | BA22: =U22/T22*100-100 -> -4.7846012 | BB22: =V22/U22*100-100 -> -1.1074541 | BC22: =W22/V22*100-100 -> -18.416473 | ... BI22: =AC22/AB22*100-100 -> #REF!
A23: 3. Penanaman | B23: =B10*B16/1000000 -> 2.198096 | C23: =C10*C16/1000000 -> 2.034717 | D23: =D10*D16/1000000 -> 1.440208 | E23: =E10*E16/1000000 -> 2.5182685 | F23: =F10*F16/1000000 -> 3.6582975 | G23: =G10*G16/1000000 -> 4.6312275 | H23: =H10*H16/1000000 -> 2.3445184 | I23: =I10*I16/1000000 -> 5.66661 | ... AH23: =AH10*AH16/1000000 -> 0 | AV23: =P23/O23*100-100 -> 4.2969689 | AW23: =Q23/P23*100-100 -> 1.7180495 | AX23: =R23/Q23*100-100 -> 64.086265 | AY23: =S23/R23*100-100 -> 89.787661 | AZ23: =T23/S23*100-100 -> -53.034369 | BA23: =U23/T23*100-100 -> -43.331354 | BB23: =V23/U23*100-100 -> -0.70534375 | BC23: =W23/V23*100-100 -> 25.471626 | ... BI23: =AC23/AB23*100-100 -> #REF!
A24: 4. Konversi & Kerusakan | B24: =B11*B16/1000000 -> 13.176884 | C24: =C11*C16/1000000 -> 10.817123 | D24: =D11*D16/1000000 -> 12.397245 | E24: =E11*E16/1000000 -> 36.15183 | F24: =F11*F16/1000000 -> 46.028034 | G24: =G11*G16/1000000 -> 48.03444 | H24: =H11*H16/1000000 -> 46.638054 | I24: =I11*I16/1000000 -> 66.904512 | ... AH24: =AH11*AH16/1000000 -> 0 | AV24: =P24/O24*100-100 -> 12.796271 | AW24: =Q24/P24*100-100 -> -19.016492 | AX24: =R24/Q24*100-100 -> 24.118859 | AY24: =S24/R24*100-100 -> 18.613153 | AZ24: =T24/S24*100-100 -> -14.816183 | BA24: =U24/T24*100-100 -> -15.639766 | BB24: =V24/U24*100-100 -> 47.95982 | BC24: =W24/V24*100-100 -> 86.894783 | ... BI24: =AC24/AB24*100-100 -> #REF!
A25: 5. Penebangan | B25: =B12*B16/1000000 -> 90.881916 | C25: =C12*C16/1000000 -> 71.697749 | D25: =D12*D16/1000000 -> 55.709864 | E25: =E12*E16/1000000 -> 128.86428 | F25: =F12*F16/1000000 -> 193.77891 | G25: =G12*G16/1000000 -> 208.68451 | H25: =H12*H16/1000000 -> 185.89128 | I25: =I12*I16/1000000 -> 308.51286 | ... AH25: =AH12*AH16/1000000 -> 0 | AV25: =P25/O25*100-100 -> 39.074519 | AW25: =Q25/P25*100-100 -> -37.439238 | AX25: =R25/Q25*100-100 -> 125.74461 | AY25: =S25/R25*100-100 -> 33.833231 | AZ25: =T25/S25*100-100 -> -15.80405 | BA25: =U25/T25*100-100 -> -9.7225985 | BB25: =V25/U25*100-100 -> -2.7165937 | BC25: =W25/V25*100-100 -> -21.46171 | ... BI25: =AC25/AB25*100-100 -> #REF!
A26: 6. Perubahan Neto | B26: =B13*B16/1000000 -> 199.83966 | C26: =C13*C16/1000000 -> 176.60397 | D26: =D13*D16/1000000 -> 167.81696 | E26: =E13*E16/1000000 -> 305.51386 | F26: =F13*F16/1000000 -> 470.5014 | G26: =G13*G16/1000000 -> 529.10029 | H26: =H13*H16/1000000 -> 860.06761 | I26: =I13*I16/1000000 -> 1288.5547 | ... AH26: =AH13*AH16/1000000 -> 0 | AV26: =P26/O26*100-100 -> 11.136657 | AW26: =Q26/P26*100-100 -> -1.1571193 | AX26: =R26/Q26*100-100 -> 66.021221 | AY26: =S26/R26*100-100 -> 26.466635 | AZ26: =T26/S26*100-100 -> -7.1447886 | BA26: =U26/T26*100-100 -> -3.5972369 | BB26: =V26/U26*100-100 -> -4.495987 | BC26: =W26/V26*100-100 -> -29.727237 | ... BI26: =AC26/AB26*100-100 -> #REF!
A27: 7. Revaluasi | B27: 574.8 | C27: =C8*(C16-B16)/1000000 -> -757.88881 | D27: =D8*(D16-C16)/1000000 -> -459.54592 | E27: =E8*(E16-D16)/1000000 -> 2756.2125 | F27: =F8*(F16-E16)/1000000 -> 2682.609 | G27: =G8*(G16-F16)/1000000 -> 462.7503 | H27: =H8*(H16-G16)/1000000 -> -418.11561 | I27: =I8*(I16-H16)/1000000 -> 6420.4253 | J27: =J8*(J16-I16)/1000000 -> 29.820287 | ... AH27: =AH8*(AH16-AG16)/1000000 -> 0 | AV27: =P27/O27*100-100 -> -373.39056 | AW27: =Q27/P27*100-100 -> -180.87091 | AX27: =R27/Q27*100-100 -> -792.6236 | AY27: =S27/R27*100-100 -> -30.913844 | AZ27: =T27/S27*100-100 -> -141.17942 | BA27: =U27/T27*100-100 -> -38.165019 | BB27: =V27/U27*100-100 -> -69.916363 | BC27: =W27/V27*100-100 -> 1105.2908 | ... BI27: =AC27/AB27*100-100 -> #REF!
A28: 8. Persediaan Akhir | B28: =B21+B22+B23-B24-B25+B27 -> 3976.8397 | C28: =C21+C22+C23-C24-C25+C27 -> 3395.5548 | D28: =D21+D22+D23-D24-D25+D27 -> 3103.8259 | E28: =E21+E22+E23-E24-E25+E27 -> 6165.5523 | F28: =F21+F22+F23-F24-F25+F27 -> 9318.6627 | G28: =G21+G22+G23-G24-G25+G27 -> 10310.513 | H28: =H21+H22+H23-H24-H25+H27 -> 10752.465 | I28: =I21+I22+I23-I24-I25+I27 -> 18461.445 | ... AH28: =AH21+AH22+AH23-AH24-AH25+AH27 -> #REF! | AV28: =P28/O28*100-100 -> 19.016161 | AW28: =Q28/P28*100-100 -> -4.4310569 | AX28: =R28/Q28*100-100 -> 74.068685 | AY28: =S28/R28*100-100 -> 32.071244 | AZ28: =T28/S28*100-100 -> -4.018363 | BA28: =U28/T28*100-100 -> -1.0964253 | BB28: =V28/U28*100-100 -> 2.4194039 | BC28: =W28/V28*100-100 -> -16.064938 | ... BI28: =AC28/AB28*100-100 -> #REF!

Sheet Rimba Jawa
A1: Neraca Fisik dan Moneter
A2: Kayu Bulat Rimba Jawa
A4: Perincian | B4: 1990 | C4: 1991 | D4: 1992 | E4: 1993 | F4: 1994 | G4: 1995 | H4: 1996 | I4: 1997 | J4: 1998 | K4: 1999 | L4: 2000 | M4: 2001 | N4: 2002 | O4: 2003 | P4: 2004 | Q4: 2005 | R4: 2006 | S4: 2007 | T4: 2008 | U4: 2009 | V4: 2010 | W4: 2011 | X4: 2012 | Y4: 2013 | Z4: 2014 | AA4: 2015 | AB4: 2016 | AC4: 2017 | AD4: 2018 | AE4: 2019 | AF4: 2020 | AG4: 2021 | AH4: 2022 | AI4: 2023 | AJ4: 2024
A6: I. Neraca Fisik (000 M3)
A8: 1. Persediaan awal | B8: 68020.3 | C8: =B14 -> 76085.5 | D8: =C14 -> 85124.546 | E8: =D14 -> 95162.367 | F8: =E14 -> 106191.91 | G8: =F14 -> 118559.04 | H8: =G14 -> 132369.45 | I8: =H14 -> 147915.4 | J8: =I14 -> 165431.49 | ... AJ8: =AI14 -> 565494.79
A9: 2. Pertumbuhan | B9: 8502.5 | C9: 9510.6456 | D9: 10640.521 | E9: 11895.243 | F9: 13273.93 | G9: 14819.81 | H9: 16546.11 | I9: 18489.34 | J9: 20678.85 | K9: 23107.418 | L9: 20943.4 | M9: 20825.975 | N9: 20549.65 | O9: 17634.375 | P9: 21588.534 | Q9: 17388.258 | R9: 16669.276 | S9: 17317.458 | T9: 16669.278 | U9: =(683113*25)/1000 -> 17077.825 | V9: 16669.3 | W9: =+'Data Penunjang'!AA38/'Data Penunjang'!Z38*'Rimba Jawa'!V9*1.02 -> 17002.694 | X9: =+'Data Penunjang'!AB38/'Data Penunjang'!AA38*'Rimba Jawa'!W9 -> 18588.711 | Y9: =+'Data Penunjang'!AC38/'Data Penunjang'!AB38*'Rimba Jawa'!X9 -> 30769.212 | Z9: =+'Data Penunjang'!AD38/'Data Penunjang'!AC38*'Rimba Jawa'!Y9 -> 18645.347 | AA9: =+'Data Penunjang'!AE38/'Data Penunjang'!AD38*'Rimba Jawa'!Z9 -> 18669.687 | AB9: =+'Data Penunjang'!AF38/'Data Penunjang'!AE38*'Rimba Jawa'!AA9 -> 11115.135 | AC9: =+'Data Penunjang'!AG38/'Data Penunjang'!AF38*'Rimba Jawa'!AB9 -> 11264.08 | AD9: =+'Data Penunjang'!AH38/'Data Penunjang'!AG38*'Rimba Jawa'!AC9 -> 11671.29 | AE9: =+'Data Penunjang'!AI38/'Data Penunjang'!AH38*'Rimba Jawa'!AD9 -> 11477.648 | ... AJ9: =+'Data Penunjang'!AN38/'Data Penunjang'!AM38*'Rimba Jawa'!AI9 -> 18205.292
A10: 3. Penanaman | B10: 151.4 | C10: 199 | D10: 163.8 | E10: 128.7 | F10: 111.3 | G10: 110.5 | H10: 90.58 | I10: 112.97 | J10: 90.18 | K10: 127.88494 | L10: 101.413 | M10: 116.766 | N10: 143.35425 | O10: 99.68075 | P10: 107.14925 | Q10: 131.131 | R10: 180.8235 | S10: 231.63368 | T10: ='Data Penunjang'!X49/'Data Penunjang'!W49*'Rimba Jawa'!S10 -> 151.19423 | U10: ='Data Penunjang'!Y49/'Data Penunjang'!X49*'Rimba Jawa'!T10 -> 79.3611 | V10: ='Data Penunjang'!Z49/'Data Penunjang'!Y49*'Rimba Jawa'!U10 -> 108.28688 | W10: ='Data Penunjang'!AA49/'Data Penunjang'!Z49*'Rimba Jawa'!V10 -> 40.679275 | X10: ='Data Penunjang'!AB49/'Data Penunjang'!AA49*'Rimba Jawa'!W10 -> 31.57245 | Y10: ='Data Penunjang'!AC49/'Data Penunjang'!AB49*'Rimba Jawa'!X10 -> 35.806225 | Z10: ='Data Penunjang'!AD49/'Data Penunjang'!AC49*'Rimba Jawa'!Y10 -> 37.262225 | AA10: ='Data Penunjang'!AE49/'Data Penunjang'!AD49*'Rimba Jawa'!Z10 -> 38.834 | ... AJ10: ='Data Penunjang'!AN49/'Data Penunjang'!AM49*'Rimba Jawa'!AI10 -> 14.2415
A11: 4. Konversi & kerusakan | B11: 98.1 | C11: 99.5 | D11: 131.9 | E11: 203.7 | F11: 180.7 | G11: 179.7 | H11: 104.13 | I11: 89.47 | J11: 383.59 | K11: 362.17896 | L11: 365.46129 | M11: 361.32855 | N11: 366.18725 | O11: 426.749 | P11: 348.567 | Q11: 452.61338 | R11: 341.6309 | S11: 340.16397 | T11: =AO31/AN31*S11 -> 287.74121 | U11: =AP31/AO31*T11 -> 256.21155 | V11: =AQ31/AP31*U11 -> 385.25198 | W11: =AR31/AQ31*V11 -> 886.96329 | X11: =AS31/AR31*W11 -> 2248.6402 | Y11: =AT31/AS31*X11 -> 1221.983 | Z11: =AU31/AT31*Y11 -> 913.12499 | AA11: =AV31/AU31*Z11 -> 1073.5777 | AB11: ='Data Penunjang'!AF70/'Data Penunjang'!AE70*AA11 -> 774.35614 | AC11: ='Data Penunjang'!AG70/'Data Penunjang'!AF70*AB11 -> 946.43982 | AD11: ='Data Penunjang'!AH70/'Data Penunjang'!AG70*AC11 -> 1017.1258 | AE11: ='Data Penunjang'!AI70/'Data Penunjang'!AH70*AD11 -> 936.76549 | AF11: ='Data Penunjang'!AJ70/'Data Penunjang'!AI70*AE11 -> 786.88874 | AG11: ='Data Penunjang'!AK70/'Data Penunjang'!AJ70*AF11 -> 451.25409 | AH11: ='Data Penunjang'!AL70/'Data Penunjang'!AK70*AG11 -> 560.54125 | AI11: ='Data Penunjang'!AM70/'Data Penunjang'!AL70*AH11 -> 765.90151 | AJ11: ='Data Penunjang'!AN70/'Data Penunjang'!AM70*AI11 -> 600.18276
A12: 5. Penebangan | B12: 490.6 | C12: 571.1 | D12: 634.6 | E12: 790.7 | F12: 837.4 | G12: 940.2 | H12: 986.61 | I12: 996.75 | J12: 956.77 | K12: 995.879 | L12: 913.236 | M12: 800.601 | N12: 816.487 | O12: 549.649 | P12: 398.886 | Q12: 393.686 | R12: 384.341 | S12: 632.096 | T12: 605.213 | U12: ='Data Penunjang'!Y52 -> 524.19 | V12: ='Data Penunjang'!Z52 -> 439.429 | W12: ='Data Penunjang'!AA52 -> 533.8 | X12: ='Data Penunjang'!AB52 -> 525.49 | Y12: ='Data Penunjang'!AC52 -> 524.06771 | Z12: ='Data Penunjang'!AD52 -> 462.59173 | AA12: ='Data Penunjang'!AE52 -> 398.58371 | AB12: ='Data Penunjang'!AF52 -> 297.794 | ... AJ12: ='Data Penunjang'!AN52 -> 408.129
A13: 6. Perubahan Neto | B13: 8065.2 | C13: 9039.0456 | D13: 10037.821 | E13: 11029.543 | F13: 12367.13 | G13: 13810.41 | H13: 15545.95 | I13: 17516.09 | J13: 19428.67 | K13: 21877.245 | L13: 19766.116 | M13: 19780.811 | N13: 19510.33 | O13: 16757.658 | P13: 20948.23 | Q13: 16673.09 | R13: 16124.127 | S13: 16576.832 | T13: =T14-T8 -> 15927.518 | U13: =U14-U8 -> 16376.785 | V13: =V14-V8 -> 15952.906 | W13: =W14-W8 -> 15622.61 | X13: =X14-X8 -> 15846.153 | Y13: =Y14-Y8 -> 29058.967 | Z13: =Z14-Z8 -> 17306.892 | AA13: =AA14-AA8 -> 17236.359 | ... AJ13: =AJ14-AJ8 -> 17211.222
A14: 7. Persediaan akhir | B14: 76085.5 | C14: 85124.546 | D14: 95162.367 | E14: 106191.91 | F14: 118559.04 | G14: 132369.45 | H14: 147915.4 | I14: 165431.49 | J14: 184860.17 | K14: 206737.41 | L14: 226503.53 | M14: 246284.34 | N14: 265794.67 | O14: 282552.32 | P14: 303500.55 | Q14: 320173.64 | R14: 336297.77 | S14: 352874.6 | T14: =T8+T9+T10-T11-T12 -> 368802.12 | U14: =U8+U9+U10-U11-U12 -> 385178.91 | V14: =V8+V9+V10-V11-V12 -> 401131.81 | W14: =W8+W9+W10-W11-W12 -> 416754.42 | X14: =X8+X9+X10-X11-X12 -> 432600.57 | Y14: =Y8+Y9+Y10-Y11-Y12 -> 461659.54 | Z14: =Z8+Z9+Z10-Z11-Z12 -> 478966.43 | AA14: =AA8+AA9+AA10-AA11-AA12 -> 496202.79 | ... AJ14: =AJ8+AJ9+AJ10-AJ11-AJ12 -> 582706.01
A16: II. Unit Rent | B16: 12008 | C16: 9770 | D16: 9185 | E16: 18258 | F16: 25412 | G16: 26376 | H16: 22716.92 | I16: 34715.29 | J16: 34771.36 | K16: 45203.574 | L16: 43766.822 | M16: 55171.949 | N16: 58596.729 | O16: 64064.609 | P16: 67100.2 | Q16: 74400.654 | R16: 94504.643 | S16: 102273.37 | T16: 107249.51 | U16: ='Rent Perhutani'!U34 -> 131879.43 | V16: ='Rent Perhutani'!V34 -> 130151.01 | W16: ='Rent Perhutani'!W34 -> 105751.03 | X16: ='Rent Perhutani'!X34 -> 144513.98 | Y16: ='Rent Perhutani'!Y34 -> 282415.77 | Z16: ='Rent Perhutani'!Z34 -> 561064 | AA16: ='Rent Perhutani'!AA34 -> 479402.83 | AB16: ='Rent Perhutani'!AB34 -> -371787.05 | ... AH16: ='Rent Perhutani'!AH34 -> 0
T17: =T16/S16*100-100 -> 4.8655233 | U17: =U16/T16*100-100 -> 22.965063 | V17: =V16/U16*100-100 -> -1.310602 | W17: =W16/V16*100-100 -> -18.74744 | X17: =X16/W16*100-100 -> 36.654919 | Y17: =Y16/X16*100-100 -> 95.424528 | Z17: =Z16/Y16*100-100 -> 98.66596 | AA17: =AA16/Z16*100-100 -> -14.554698 | ... AH17: =AH16/AG16*100-100 -> #DIV/0!
A18: III. Neraca Moneter
A19: (miliar Rp)
A21: 1. Persediaan awal | B21: 674.2 | C21: =B28 -> 913.64692 | D21: =C28 -> 831.67905 | E21: =D28 -> 874.07858 | F21: =E28 -> 1938.8641 | G21: =F28 -> 3012.8346 | H21: =G28 -> 3491.3889 | I21: =H28 -> 3360.1946 | J21: =I28 -> 5743.0145 | ... AH21: =AG28 -> #REF!
A22: 2. Pertumbuhan | B22: =B9*B16/1000000 -> 102.09802 | C22: =C9*C16/1000000 -> 92.919007 | D22: =D9*D16/1000000 -> 97.733188 | E22: =E9*E16/1000000 -> 217.18335 | F22: =F9*F16/1000000 -> 337.31712 | G22: =G9*G16/1000000 -> 390.88731 | H22: =H9*H16/1000000 -> 375.87666 | I22: =I9*I16/1000000 -> 641.8628 | ... AH22: =AH9*AH16/1000000 -> 0
A23: 3. Penanaman | B23: =B10*B16/1000000 -> 1.8180112 | C23: =C10*C16/1000000 -> 1.94423 | D23: =D10*D16/1000000 -> 1.504503 | E23: =E10*E16/1000000 -> 2.3498046 | F23: =F10*F16/1000000 -> 2.8283556 | G23: =G10*G16/1000000 -> 2.914548 | H23: =H10*H16/1000000 -> 2.0576986 | I23: =I10*I16/1000000 -> 3.9217863 | ... AH23: =AH10*AH16/1000000 -> 0 | AL23: Kerugian Gangguan Keamanan Hutan | AN23: 2007 | AO23: 2008 | AP23: 2009 | AQ23: 2010 | AR23: 2011 | AS23: 2012 | AT23: 2013 | AU23: 2014 | AV23: 2015 | AW23: 2016 | AX23: 2017
A24: 4. Konversi & kerusakan | B24: =B11*B16/1000000 -> 1.1779848 | C24: =C11*C16/1000000 -> 0.972115 | D24: =D11*D16/1000000 -> 1.2115015 | E24: =E11*E16/1000000 -> 3.7191546 | F24: =F11*F16/1000000 -> 4.5919484 | G24: =G11*G16/1000000 -> 4.7397672 | H24: =H11*H16/1000000 -> 2.3655129 | I24: =I11*I16/1000000 -> 3.105977 | ... AH24: =AH11*AH16/1000000 -> 0
A25: 5. Penebangan | B25: =B12*B16/1000000 -> 5.8911248 | C25: =C12*C16/1000000 -> 5.579647 | D25: =D12*D16/1000000 -> 5.828801 | E25: =E12*E16/1000000 -> 14.436601 | F25: =F12*F16/1000000 -> 21.280009 | G25: =G12*G16/1000000 -> 24.798715 | H25: =H12*H16/1000000 -> 22.41274 | I25: =I12*I16/1000000 -> 34.602465 | ... AH25: =AH12*AH16/1000000 -> 0 | AL25: Pencuri pohon | AM25: 000 Rp | AN25: ='Data Penunjang'!W64 -> 16918356 | AO25: ='Data Penunjang'!X64 -> 12777434 | AP25: ='Data Penunjang'!Y64 -> 9718774 | AQ25: ='Data Penunjang'!Z64 -> 8077904 | AR25: ='Data Penunjang'!AA64 -> 23932473 | AS25: ='Data Penunjang'!AB64 -> 40646372 | AT25: ='Data Penunjang'!AC64 -> 42237796 | AU25: ='Data Penunjang'!AD64 -> 29708748 | ... AX25: ='Data Penunjang'!AG64 -> 49292712
A26: 6. Perubahan Neto | B26: =B13*B16/1000000 -> 96.846922 | C26: =C13*C16/1000000 -> 88.311475 | D26: =D13*D16/1000000 -> 92.197388 | E26: =E13*E16/1000000 -> 201.3774 | F26: =F13*F16/1000000 -> 314.27351 | G26: =G13*G16/1000000 -> 364.26337 | H26: =H13*H16/1000000 -> 353.1561 | I26: =I13*I16/1000000 -> 608.07614 | ... AH26: =AH13*AH16/1000000 -> 0 | AL26: Bibrikan | AM26: 000 Rp | AN26: ='Data Penunjang'!W65 -> 272528 | AO26: ='Data Penunjang'!X65 -> 271964 | AP26: ='Data Penunjang'!Y65 -> 192619 | AQ26: ='Data Penunjang'!Z65 -> 28722 | AR26: ='Data Penunjang'!AA65 -> 339582 | AS26: ='Data Penunjang'!AB65 -> 367931 | AT26: ='Data Penunjang'!AC65 -> 975266 | AU26: ='Data Penunjang'!AD65 -> 1014200 | ... AX26: ='Data Penunjang'!AG65 -> 211048
A27: 7. Revaluasi | B27: 142.6 | C27: =C8*(C16-B16)/1000000 -> -170.27935 | D27: =D8*(D16-C16)/1000000 -> -49.797859 | E27: =E8*(E16-D16)/1000000 -> 863.40815 | F27: =F8*(F16-E16)/1000000 -> 759.69693 | G27: =G8*(G16-F16)/1000000 -> 114.29091 | H27: =H8*(H16-G16)/1000000 -> -484.35041 | I27: =I8*(I16-H16)/1000000 -> 1774.7438 | J27: =J8*(J16-I16)/1000000 -> 9.2757439 | ... AH27: =AH8*(AH16-AG16)/1000000 -> 0 | AL27: Perusakan hutan | AM27: 000 Rp | AN27: ='Data Penunjang'!W66 -> 593150 | AO27: ='Data Penunjang'!X66 -> 707604 | AP27: ='Data Penunjang'!Y66 -> 471534 | AQ27: ='Data Penunjang'!Z66 -> 1292101 | AR27: ='Data Penunjang'!AA66 -> 1656549 | AS27: ='Data Penunjang'!AB66 -> 4638857 | AT27: ='Data Penunjang'!AC66 -> 1228118 | AU27: ='Data Penunjang'!AD66 -> 2328120 | ... AX27: ='Data Penunjang'!AG66 -> 1702742
A28: 8. Persediaan akhir | B28: =B21+B22+B23-B24-B25+B27 -> 913.64692 | C28: =C21+C22+C23-C24-C25+C27 -> 831.67905 | D28: =D21+D22+D23-D24-D25+D27 -> 874.07858 | E28: =E21+E22+E23-E24-E25+E27 -> 1938.8641 | F28: =F21+F22+F23-F24-F25+F27 -> 3012.8346 | G28: =G21+G22+G23-G24-G25+G27 -> 3491.3889 | H28: =H21+H22+H23-H24-H25+H27 -> 3360.1946 | I28: =I21+I22+I23-I24-I25+I27 -> 5743.0145 | ... AH28: =AH21+AH22+AH23-AH24-AH25+AH27 -> #REF! | AL28: Penggembalaan | AM28: 000 Rp | AN28: ='Data Penunjang'!W67 -> 89897 | AO28: ='Data Penunjang'!X67 -> 79529 | AP28: ='Data Penunjang'!Y67 -> 29710 | AQ28: ='Data Penunjang'!Z67 -> 34813 | AR28: ='Data Penunjang'!AA67 -> 233255 | AS28: ='Data Penunjang'!AB67 -> 131288 | AT28: ='Data Penunjang'!AC67 -> 236050 | AU28: ='Data Penunjang'!AD67 -> 182068 | ... AX28: ='Data Penunjang'!AG67 -> 184927
AL29: Kebakaran | AM29: 000 Rp | AN29: ='Data Penunjang'!W68 -> 2345097 | AO29: ='Data Penunjang'!X68 -> 1495144 | AP29: ='Data Penunjang'!Y68 -> 3822571 | AQ29: ='Data Penunjang'!Z68 -> 54750 | AR29: ='Data Penunjang'!AA68 -> 22995049 | AS29: ='Data Penunjang'!AB68 -> 27925113 | AT29: ='Data Penunjang'!AC68 -> 7359556 | AU29: ='Data Penunjang'!AD68 -> 11046629 | ... AX29: ='Data Penunjang'!AG68 -> 6089975
C30: =+C28/B28*100-100 -> -8.9715044 | D30: =+D28/C28*100-100 -> 5.0980639 | E30: =+E28/D28*100-100 -> 121.81806 | F30: =+F28/E28*100-100 -> 55.391733 | G30: =+G28/F28*100-100 -> 15.883855 | H30: =+H28/G28*100-100 -> -3.7576538 | I30: =+I28/H28*100-100 -> 70.913153 | J30: =+J28/I28*100-100 -> 11.924696 | ... Y30: =+Y28/X28*100-100 -> 108.55171 | AL30: Bencana alam | AM30: 000 Rp | AN30: ='Data Penunjang'!W69 -> 11530432 | AO30: ='Data Penunjang'!X69 -> 11524867 | AP30: ='Data Penunjang'!Y69 -> 9678490 | AQ30: ='Data Penunjang'!Z69 -> 26469493 | AR30: ='Data Penunjang'!AA69 -> 33628477 | AS30: ='Data Penunjang'!AB69 -> 136168967 | AT30: ='Data Penunjang'!AC69 -> 62017916 | AU30: ='Data Penunjang'!AD69 -> 40947442 | ... AX30: ='Data Penunjang'!AG69 -> 30855268
AL31: Total | AM31: 000 Rp | AN31: =SUM(AN25:AN30) -> 31749460 | AO31: =SUM(AO25:AO30) -> 26856542 | AP31: =SUM(AP25:AP30) -> 23913698 | AQ31: =SUM(AQ25:AQ30) -> 35957783 | AR31: =SUM(AR25:AR30) -> 82785385 | AS31: =SUM(AS25:AS30) -> 209878528 | AT31: =SUM(AT25:AT30) -> 114054702 | AU31: =SUM(AU25:AU30) -> 85227207 | ... AX31: =SUM(AX25:AX30) -> 88336672
AL33: Kerugian Gangguan Keamanan Hutan | AN33: 2007 | AO33: 2008 | AP33: 2009 | AQ33: 2010 | AR33: 2011 | AS33: 2012 | AT33: 2013 | AU33: 2014 | AV33: 2015 | AW33: 2016 | AX33: 2017
AL35: Pencuri pohon | AM35: % | AO35: =AO25/AN25*100-100 -> -24.475912 | AP35: =AP25/AO25*100-100 -> -23.937983 | AQ35: =AQ25/AP25*100-100 -> -16.883508 | AR35: =AR25/AQ25*100-100 -> 196.27083 | AS35: =AS25/AR25*100-100 -> 69.837743 | AT35: =AT25/AS25*100-100 -> 3.9152916 | AU35: =AU25/AT25*100-100 -> -29.66312 | AV35: =AV25/AU25*100-100 -> 28.44105 | ... AX35: =AX25/AW25*100-100 -> 28.179462
AL36: Bibrikan | AM36: % | AO36: =AO26/AN26*100-100 -> -0.20695121 | AP36: =AP26/AO26*100-100 -> -29.174817 | AQ36: =AQ26/AP26*100-100 -> -85.088698 | AR36: =AR26/AQ26*100-100 -> 1082.3062 | AS36: =AS26/AR26*100-100 -> 8.3482046 | AT36: =AT26/AS26*100-100 -> 165.06763 | AU36: =AU26/AT26*100-100 -> 3.9921416 | AV36: =AV26/AU26*100-100 -> -23.627292 | ... AX36: =AX26/AW26*100-100 -> -30.988343
AL37: Perusakan hutan | AM37: % | AO37: =AO27/AN27*100-100 -> 19.295962 | AP37: =AP27/AO27*100-100 -> -33.36188 | AQ37: =AQ27/AP27*100-100 -> 174.02075 | AR37: =AR27/AQ27*100-100 -> 28.205845 | AS37: =AS27/AR27*100-100 -> 180.03138 | AT37: =AT27/AS27*100-100 -> -73.525418 | AU37: =AU27/AT27*100-100 -> 89.568103 | AV37: =AV27/AU27*100-100 -> -28.29489 | ... AX37: =AX27/AW27*100-100 -> 51.910364
AL38: Penggembalaan | AM38: % | AO38: =AO28/AN28*100-100 -> -11.533199 | AP38: =AP28/AO28*100-100 -> -62.642558 | AQ38: =AQ28/AP28*100-100 -> 17.176035 | AR38: =AR28/AQ28*100-100 -> 570.02269 | AS38: =AS28/AR28*100-100 -> -43.714819 | AT38: =AT28/AS28*100-100 -> 79.795564 | AU38: =AU28/AT28*100-100 -> -22.868884 | AV38: =AV28/AU28*100-100 -> -76.224817 | ... AX38: =AX28/AW28*100-100 -> 72.498484
AL39: Kebakaran | AM39: % | AO39: =AO29/AN29*100-100 -> -36.243831 | AP39: =AP29/AO29*100-100 -> 155.66574 | AQ39: =AQ29/AP29*100-100 -> -98.567718 | AR39: =AR29/AQ29*100-100 -> 41900.089 | AS39: =AS29/AR29*100-100 -> 21.439676 | AT39: =AT29/AS29*100-100 -> -73.645385 | AU39: =AU29/AT29*100-100 -> 50.099123 | AV39: =AV29/AU29*100-100 -> 16.589323 | ... AX39: =AX29/AW29*100-100 -> 1066.5233
AL40: Bencana alam | AM40: % | AO40: =AO30/AN30*100-100 -> -0.048263586 | AP40: =AP30/AO30*100-100 -> -16.02081 | AQ40: =AQ30/AP30*100-100 -> 173.48784 | AR40: =AR30/AQ30*100-100 -> 27.04617 | AS40: =AS30/AR30*100-100 -> 304.9216 | AT40: =AT30/AS30*100-100 -> -54.455176 | AU40: =AU30/AT30*100-100 -> -33.974818 | AV40: =AV30/AU30*100-100 -> 13.996198 | ... AX40: =AX30/AW30*100-100 -> -2.8582259
AL41: Total | AM41: %

Sheet Rimba Luar Jawa
A1: Neraca Fisik dan Moneter
A2: Kayu Rimba Luar Jawa | W2: 276481.4 | X2: 303357.85 | Y2: 327010.6 | Z2: 699859.49 | AA2: 2223867.8 | AB2: 1604043.8 | AC2: 1960507.3
W3: 28564.609 | X3: 34409.832 | Y3: 9283.2669 | Z3: 19867.803 | AA3: 63131.77 | AB3: 19845.44 | AC3: 30697.099
A4: Perincian | B4: 1990 | C4: 1991 | D4: 1992 | E4: 1993 | F4: 1994 | G4: 1995 | H4: 1996 | I4: 1997 | J4: 1998 | K4: 1999 | L4: 2000 | M4: 2001 | N4: 2002 | O4: 2003 | P4: 2004 | Q4: 2005 | R4: 2006 | S4: 2007 | T4: 2008 | U4: 2009 | V4: 2010 | W4: 2011 | X4: 2012 | Y4: 2013 | Z4: 2014 | AA4: 2015 | AB4: 2016 | AC4: 2017 | AD4: 2018 | AE4: 2019 | AF4: 2020 | AG4: 2021 | AH4: 2022 | AI4: 2023 | AJ4: 2024 | BH4: Pertumbuhan
BH5: 1991 | BI5: =+BH5+1 -> 1992 | BJ5: =+BI5+1 -> 1993 | BK5: =+BJ5+1 -> 1994 | BL5: =+BK5+1 -> 1995 | BM5: =+BL5+1 -> 1996 | BN5: =+BM5+1 -> 1997 | BO5: =+BN5+1 -> 1998 | BP5: =+BO5+1 -> 1999 | ... BX5: =+BW5+1 -> 2007 | BY5: 2008 | BZ5: 2009 | CA5: 2010 | CB5: 2011 | CC5: 2012 | CD5: 2013 | CE5: 2014 | CF5: 2015
A6: I. Neraca Fisik (000 M3)
A8: 1. Persediaan awal | B8: 8544100 | C8: =+B14 -> 8532878.8 | D8: =+C14 -> 8519248.6 | E8: =+D14 -> 8485914.4 | F8: =+E14 -> 8442976.2 | G8: =+F14 -> 8408592.9 | H8: =+G14 -> 8372034.7 | I8: =+H14 -> 8339545.6 | J8: =+I14 -> 8261234.1 | ... AJ8: =+AI14 -> 2815937.8 | BH8: =C8/B8*100-100 -> -0.13133273 | BI8: =D8/C8*100-100 -> -0.15973741 | BJ8: =E8/D8*100-100 -> -0.39128099 | BK8: =F8/E8*100-100 -> -0.50599379 | BL8: =G8/F8*100-100 -> -0.40724194 | BM8: =H8/G8*100-100 -> -0.43477191 | BN8: =I8/H8*100-100 -> -0.38806696 | BO8: =J8/I8*100-100 -> -0.93903738 | ... CC8: =X8/W8*100-100 -> -5.0593783 | CE8: =SUM(BX8:CB8)/5 -> -4.102061
A9: 2. Pertumbuhan | B9: 30900 | C9: 30861 | D9: 30814 | E9: 30694 | F9: 30542 | G9: 30419 | H9: 32997.62 | I9: 31893.09 | J9: 31366.37 | K9: 33107.012 | L9: 32276.026 | M9: 32279.899 | N9: 32293.457 | O9: 32244.403 | P9: 32163.849 | Q9: 31726.62 | R9: 30730.92 | S9: 29735.238 | T9: 28768.843 | U9: ='Data Penunjang'!Y14/'Data Penunjang'!X14*T9 -> 29427.551 | V9: ='Data Penunjang'!Z14/'Data Penunjang'!Y14*U9 -> 29417.615 | W9: ='Data Penunjang'!AA14/'Data Penunjang'!Z14*V9 -> 29641.821 | X9: ='Data Penunjang'!AB14/'Data Penunjang'!AA14*W9 -> 29470.768 | Y9: ='Data Penunjang'!AC14/'Data Penunjang'!AB14*X9 -> 22422.401 | Z9: ='Data Penunjang'!AD14/'Data Penunjang'!AC14*Y9 -> 23276.945 | AA9: ='Data Penunjang'!AE14/'Data Penunjang'!AD14*Z9 -> 23334.934 | AB9: ='Data Penunjang'!AF14/'Data Penunjang'!AE14*AA9 -> 23679.321 | ... AJ9: ='Data Penunjang'!AN14/'Data Penunjang'!AM14*AI9 -> 23297.342 | BH9: =C9/B9*100-100 -> -0.12621359 | BI9: =D9/C9*100-100 -> -0.15229578 | BJ9: =E9/D9*100-100 -> -0.38943337 | BK9: =F9/E9*100-100 -> -0.49521079 | BL9: =G9/F9*100-100 -> -0.40272412 | BM9: =H9/G9*100-100 -> 8.4770045 | BN9: =I9/H9*100-100 -> -3.347302 | BO9: =J9/I9*100-100 -> -1.6515176 | ... CC9: =X9/W9*100-100 -> -0.57706777 | CE9: =AVERAGE(BT9:CC9) -> -0.89485018
A10: 3. Penanaman | B10: 619.8 | C10: 931.8 | D10: 949.8 | E10: 1456.8 | F10: 1239.66 | G10: 1543.8 | H10: 2552.95 | I10: 2137.73 | J10: 1576.88 | K10: 1279.5338 | L10: 3339.4118 | M10: 1242.9956 | N10: 4865.3544 | O10: 5830.756 | P10: 5525.549 | Q10: 5407.211 | R10: 7042.8923 | S10: 6178.7294 | T10: 7954.0144 | U10: =('Data Penunjang'!Y10/'Data Penunjang'!X10*'Rimba Luar Jawa'!T10) -> 6050.4458 | V10: =('Data Penunjang'!Z10/'Data Penunjang'!Y10*'Rimba Luar Jawa'!U10) -> 4452.6684 | W10: =('Data Penunjang'!AA10/'Data Penunjang'!Z10*'Rimba Luar Jawa'!V10) -> 4825.0458 | X10: =('Data Penunjang'!AB10/'Data Penunjang'!AA10*'Rimba Luar Jawa'!W10) -> 6148.3529 | Y10: =('Data Penunjang'!AC10/'Data Penunjang'!AB10*'Rimba Luar Jawa'!X10) -> 11054.912 | Z10: =('Data Penunjang'!AD10/'Data Penunjang'!AC10*'Rimba Luar Jawa'!Y10) -> 11134.353 | AA10: =('Data Penunjang'!AE10/'Data Penunjang'!AD10*'Rimba Luar Jawa'!Z10) -> 15628.694 | AB10: =('Data Penunjang'!AF10/'Data Penunjang'!AE10*'Rimba Luar Jawa'!AA10) -> 17100.811 | ... AJ10: =('Data Penunjang'!AN10/'Data Penunjang'!AM10*'Rimba Luar Jawa'!AI10) -> 7699.2765 | BH10: =C10/B10*100-100 -> 50.338819 | BI10: =D10/C10*100-100 -> 1.931745 | BJ10: =E10/D10*100-100 -> 53.379659 | BK10: =F10/E10*100-100 -> -14.905272 | BL10: =G10/F10*100-100 -> 24.534146 | BM10: =H10/G10*100-100 -> 65.367923 | BN10: =I10/H10*100-100 -> -16.264322 | BO10: =J10/I10*100-100 -> -26.235773 | ... CC10: =X10/W10*100-100 -> 27.425794 | CE10: =AVERAGE(BT10:CC10) -> 4.4627525
A11: 4. Konversi & kerusakan | B11: 15455 | C11: 18612 | D11: 37724 | E11: 47160 | F11: 38175 | G11: 40691 | H11: 39765.83 | I11: 79973.9 | J11: 92320.84 | K11: 108270.54 | L11: 97333.105 | M11: 122921.98 | N11: 158520.18 | O11: 179191.22 | P11: 210549.65 | Q11: 252743.8 | R11: 303393.66 | S11: 292592.84 | T11: 206743.81 | U11: =(100+BZ11)/100*T11 -> 227447.89 | V11: =(100+CA11)/100*U11 -> 248573.61 | W11: =(100+CB11)/100*V11 -> 276481.4 | X11: =('Data Penunjang'!AB35/'Data Penunjang'!AA35)*'Rimba Luar Jawa'!W11 -> 333058.25 | Y11: =('Data Penunjang'!AC35/'Data Penunjang'!AB35)*'Rimba Luar Jawa'!X11 -> 89854.22 | Z11: =('Data Penunjang'!AD35/'Data Penunjang'!AC35)*'Rimba Luar Jawa'!Y11 -> 192303.64 | AA11: =('Data Penunjang'!AE35/'Data Penunjang'!AD35)*'Rimba Luar Jawa'!Z11 -> 611062.47 | AB11: =('Data Penunjang'!AF35/'Data Penunjang'!AE35)*'Rimba Luar Jawa'!AA11 -> 192087.18 | AC11: =('Data Penunjang'!AG35/'Data Penunjang'!AF35)*'Rimba Luar Jawa'!AB11 -> 148297.99 | AD11: =('Data Penunjang'!AH35/'Data Penunjang'!AG35)*'Rimba Luar Jawa'!AC11 -> 126820.67 | AE11: =('Data Penunjang'!AI35/'Data Penunjang'!AH35)*'Rimba Luar Jawa'!AD11 -> 323896.69 | ... AJ11: =('Data Penunjang'!AN35/'Data Penunjang'!AM35)*'Rimba Luar Jawa'!AI11 -> 95017.524 | BH11: =C11/B11*100-100 -> 20.427046 | BI11: =D11/C11*100-100 -> 102.68644 | BJ11: =E11/D11*100-100 -> 25.013254 | BK11: =F11/E11*100-100 -> -19.052163 | BL11: =G11/F11*100-100 -> 6.5907007 | BM11: =H11/G11*100-100 -> -2.2736477 | BN11: =I11/H11*100-100 -> 101.11211 | BO11: =J11/I11*100-100 -> 15.438712 | ... BY11: =T11/S11*100-100 -> -29.340784 | BZ11: =AVERAGE(BP11:BY11) -> 10.014363 | CA11: =AVERAGE(BQ11:BZ11) -> 9.2881618 | CB11: =AVERAGE(BR11:CA11) -> 11.227173 | CC11: =AVERAGE(BS11:CB11) -> 9.7208898 | CD11: =AVERAGE(BT11:CC11) -> 7.7969788 | CE11: =AVERAGE(BT11:CD11) -> 7.7969788 | CF11: =AVERAGE(BU11:CE11) -> 7.3203405 | CG11: =AVERAGE(BV11:CF11) -> 6.3949183
A12: 5. Penebangan | B12: 27286 | C12: 26811 | D12: 27374 | E12: 27929 | F12: 27990 | G12: 27830 | H12: 28273.84 | I12: 32368.37 | J12: 23815.22 | K12: 23978.395 | L12: 24654.585 | M12: 24622.535 | N12: 24006.971 | O12: 23166.727 | P12: 23616.156 | Q12: ='Data Penunjang'!U12/'Data Penunjang'!T12*'Rimba Luar Jawa'!P12 -> 42222.259 | R12: ='Data Penunjang'!V12/'Data Penunjang'!U12*'Rimba Luar Jawa'!Q12 -> 37985.345 | S12: ='Data Penunjang'!W12/'Data Penunjang'!V12*'Rimba Luar Jawa'!R12 -> 54892.393 | T12: ='Data Penunjang'!X12/'Data Penunjang'!W12*'Rimba Luar Jawa'!S12 -> 48522.631 | U12: ='Data Penunjang'!Y12/'Data Penunjang'!X12*'Rimba Luar Jawa'!T12 -> 50911.031 | V12: ='Data Penunjang'!Z12/'Data Penunjang'!Y12*'Rimba Luar Jawa'!U12 -> 53550.936 | W12: ='Data Penunjang'!AA12/'Data Penunjang'!Z12*'Rimba Luar Jawa'!V12 -> 49960.669 | X12: ='Data Penunjang'!AB12/'Data Penunjang'!AA12*'Rimba Luar Jawa'!W12 -> 49014.219 | ... AJ12: ='Data Penunjang'!AN12/'Data Penunjang'!AM12*'Rimba Luar Jawa'!AI12 -> 54503.682 | BH12: =C12/B12*100-100 -> -1.7408195 | BI12: =D12/C12*100-100 -> 2.0998844 | BJ12: =E12/D12*100-100 -> 2.0274713 | BK12: =F12/E12*100-100 -> 0.21841097 | BL12: =G12/F12*100-100 -> -0.57163273 | BM12: =H12/G12*100-100 -> 1.5948257 | BN12: =I12/H12*100-100 -> 14.48169 | BO12: =J12/I12*100-100 -> -26.424408 | ... CC12: =X12/W12*100-100 -> -1.8943909 | CE12: =AVERAGE(BT12:CC12) -> 10.160476
A13: 6. Perubahan Neto | B13: =B14-B8 -> -11221.2 | C13: =C14-C8 -> -13630.2 | D13: =D14-D8 -> -33334.2 | E13: =E14-E8 -> -42938.2 | F13: =F14-F8 -> -34383.34 | G13: =G14-G8 -> -36558.2 | H13: =H14-H8 -> -32489.1 | I13: =I14-I8 -> -78311.45 | ... AJ13: =AJ14-AJ8 -> -118524.59 | BH13: =C13/B13*100-100 -> 21.468292 | BI13: =D13/C13*100-100 -> 144.56134 | BJ13: =E13/D13*100-100 -> 28.811251 | BK13: =F13/E13*100-100 -> -19.923658 | BL13: =G13/F13*100-100 -> 6.3253308 | BM13: =H13/G13*100-100 -> -11.130471 | BN13: =I13/H13*100-100 -> 141.03915 | BO13: =J13/I13*100-100 -> 6.2332647 | ... CC13: =X13/W13*100-100 -> 18.658483 | CE13: =AVERAGE(BT13:CC13) -> 10.343934
A14: 7. Persediaan akhir | B14: =B8+B9+B10-B11-B12 -> 8532878.8 | C14: =C8+C9+C10-C11-C12 -> 8519248.6 | D14: =D8+D9+D10-D11-D12 -> 8485914.4 | E14: =E8+E9+E10-E11-E12 -> 8442976.2 | F14: =F8+F9+F10-F11-F12 -> 8408592.9 | G14: =G8+G9+G10-G11-G12 -> 8372034.7 | H14: =H8+H9+H10-H11-H12 -> 8339545.6 | I14: =I8+I9+I10-I11-I12 -> 8261234.1 | ... AJ14: =AJ8+AJ9+AJ10-AJ11-AJ12 -> 2697413.2 | BH14: =C14/B14*100-100 -> -0.15973741 | BI14: =D14/C14*100-100 -> -0.39128099 | BJ14: =E14/D14*100-100 -> -0.50599379 | BK14: =F14/E14*100-100 -> -0.40724194 | BL14: =G14/F14*100-100 -> -0.43477191 | BM14: =H14/G14*100-100 -> -0.38806696 | BN14: =I14/H14*100-100 -> -0.93903738 | BO14: =J14/I14*100-100 -> -1.0070264 | ... CC14: =X14/W14*100-100 -> -6.3233012 | CE14: =AVERAGE(BT14:CC14) -> -4.0109115
C15: =+C14/B14*100-100 -> -0.15973741 | D15: =+D14/C14*100-100 -> -0.39128099 | E15: =+E14/D14*100-100 -> -0.50599379 | F15: =+F14/E14*100-100 -> -0.40724194 | G15: =+G14/F14*100-100 -> -0.43477191 | H15: =+H14/G14*100-100 -> -0.38806696 | I15: =+I14/H14*100-100 -> -0.93903738 | J15: =+J14/I14*100-100 -> -1.0070264 | ... AJ15: =+AJ14/AI14*100-100 -> -4.2090627 | CE15: =SUM(BX15:CB15)/5 -> 0
A16: II. Unit Rent | B16: 9248 | C16: 10892 | D16: ='Rent Luar Jawa'!C21 -> 10449.648 | E16: ='Rent Luar Jawa'!D21 -> 11449.125 | F16: ='Rent Luar Jawa'!E21 -> 13832.444 | G16: ='Rent Luar Jawa'!F21 -> 14934.936 | H16: ='Rent Luar Jawa'!G21 -> 16213.937 | I16: ='Rent Luar Jawa'!H21 -> 16463.842 | J16: ='Rent Luar Jawa'!I21 -> 20970.165 | K16: ='Rent Luar Jawa'!J21 -> 25681.925 | ... AJ16: ='Rent Luar Jawa'!AI21 -> 0 | BH16: =C16/B16*100-100 -> 17.776817 | BI16: =D16/C16*100-100 -> -4.0612552 | BJ16: =E16/D16*100-100 -> 9.5646906 | BK16: =F16/E16*100-100 -> 20.816609 | BL16: =G16/F16*100-100 -> 7.9703354 | BM16: =H16/G16*100-100 -> 8.5638155 | BN16: =I16/H16*100-100 -> 1.5412969 | BO16: =J16/I16*100-100 -> 27.37103 | ... CC16: =X16/W16*100-100 -> 3.615673 | CE16: =SUM(BX16:CB16)/5 -> 9.7038494
A17: Pertumbuhan Unit Rent | C17: =+C16/B16*100-100 -> 17.776817 | D17: =+D16/C16*100-100 -> -4.0612552 | E17: =+E16/D16*100-100 -> 9.5646906 | F17: =+F16/E16*100-100 -> 20.816609 | G17: =+G16/F16*100-100 -> 7.9703354 | H17: =+H16/G16*100-100 -> 8.5638155 | I17: =+I16/H16*100-100 -> 1.5412969 | J17: =+J16/I16*100-100 -> 27.37103 | ... AJ17: =+AJ16/AI16*100-100 -> #DIV/0!
A18: III. Neraca Moneter
A19: (miliar Rp)
A21: 1. Persediaan awal | B21: 70232.502 | C21: =B28 -> 78912.063 | D21: =C28 -> 92791.656 | E21: =D28 -> 88674.819 | F21: =E28 -> 96664.686 | G21: =F28 -> 116311.39 | H21: =G28 -> 125035.8 | I21: =H28 -> 135216.86 | J21: =I28 -> 136011.65 | ... AJ21: =AI28 -> 0
A22: 2. Pertumbuhan | B22: =B9*B16/1000000 -> 285.7632 | C22: =C9*C16/1000000 -> 336.13801 | D22: =D9*D16/1000000 -> 321.99546 | E22: =E9*E16/1000000 -> 351.41943 | F22: =F9*F16/1000000 -> 422.47051 | G22: =G9*G16/1000000 -> 454.30583 | H22: =H9*H16/1000000 -> 535.02132 | I22: =I9*I16/1000000 -> 525.08278 | ... AJ22: =AJ9*AJ16/1000000 -> 0
A23: 3. Penanaman | B23: =B10*B16/1000000 -> 5.7319104 | C23: =C10*C16/1000000 -> 10.149166 | D23: =D10*D16/1000000 -> 9.9250758 | E23: =E10*E16/1000000 -> 16.679085 | F23: =F10*F16/1000000 -> 17.147528 | G23: =G10*G16/1000000 -> 23.056555 | H23: =H10*H16/1000000 -> 41.39337 | I23: =I10*I16/1000000 -> 35.195248 | ... AJ23: =AJ10*AJ16/1000000 -> 0
A24: 4. Konversi & kerusakan | B24: =B11*B16/1000000 -> 142.92784 | C24: =C11*C16/1000000 -> 202.7219 | D24: =D11*D16/1000000 -> 394.20252 | E24: =E11*E16/1000000 -> 539.94072 | F24: =F11*F16/1000000 -> 528.05355 | G24: =G11*G16/1000000 -> 607.71749 | H24: =H11*H16/1000000 -> 644.76065 | I24: =I11*I16/1000000 -> 1316.6776 | ... AJ24: =AJ11*AJ16/1000000 -> 0
A25: 5. Penebangan | B25: =B12*B16/1000000 -> 252.34093 | C25: =C12*C16/1000000 -> 292.02541 | D25: =D12*D16/1000000 -> 286.04867 | E25: =E12*E16/1000000 -> 319.7626 | F25: =F12*F16/1000000 -> 387.17011 | G25: =G12*G16/1000000 -> 415.63928 | H25: =H12*H16/1000000 -> 458.43025 | I25: =I12*I16/1000000 -> 532.90771 | ... AJ25: =AJ12*AJ16/1000000 -> 0
A26: 6. Perubahan Neto | B26: =B13*B16/1000000 -> -103.77366 | C26: =C13*C16/1000000 -> -148.46014 | D26: =D13*D16/1000000 -> -348.33066 | E26: =E13*E16/1000000 -> -491.6048 | F26: =F13*F16/1000000 -> -475.60563 | G26: =G13*G16/1000000 -> -545.99439 | H26: =H13*H16/1000000 -> -526.77621 | I26: =I13*I16/1000000 -> -1289.3073 | ... AJ26: =AJ13*AJ16/1000000 -> 0
A27: 7. Revaluasi | B27: 8783.3348 | C27: =C8*(C16-B16)/1000000 -> 14028.053 | D27: =D8*(D16-C16)/1000000 -> -3768.5059 | E27: =E8*(E16-D16)/1000000 -> 8481.4721 | F27: =F8*(F16-E16)/1000000 -> 20122.31 | G27: =G8*(G16-F16)/1000000 -> 9270.4079 | H27: =H8*(H16-G16)/1000000 -> 10707.836 | I27: =I8*(I16-H16)/1000000 -> 2084.0933 | J27: =J8*(J16-I16)/1000000 -> 37227.789 | ... AJ27: =AJ8*(AJ16-AI16)/1000000 -> 0
A28: 8. Persediaan akhir | B28: =B21+B22+B23-B24-B25+B27 -> 78912.063 | C28: =C21+C22+C23-C24-C25+C27 -> 92791.656 | D28: =D21+D22+D23-D24-D25+D27 -> 88674.819 | E28: =E21+E22+E23-E24-E25+E27 -> 96664.686 | F28: =F21+F22+F23-F24-F25+F27 -> 116311.39 | G28: =G21+G22+G23-G24-G25+G27 -> 125035.8 | H28: =H21+H22+H23-H24-H25+H27 -> 135216.86 | I28: =I21+I22+I23-I24-I25+I27 -> 136011.65 | ... AJ28: =AJ21+AJ22+AJ23-AJ24-AJ25+AJ27 -> 0 | BR28: =M28/L28*100-100 -> -0.30466023 | BS28: =N28/M28*100-100 -> 0.56293283 | BT28: =O28/N28*100-100 -> 3.7409536 | BU28: =P28/O28*100-100 -> 5.5686036 | BV28: =Q28/P28*100-100 -> 10.952708 | BW28: =R28/Q28*100-100 -> 34.330082 | BX28: =S28/R28*100-100 -> 12.352351 | BY28: =T28/S28*100-100 -> 9.2769194 | ... CC28: =X28/W28*100-100 -> -2.9362582 | CE28: =SUM(BX28:CB28)/5 -> 5.0407961
C30: =+C28/B28*100-100 -> 17.588683 | D30: =+D28/C28*100-100 -> -4.4366452 | E30: =+E28/D28*100-100 -> 9.0103 | F30: =+F28/E28*100-100 -> 20.324593 | G30: =+G28/F28*100-100 -> 7.5009107 | H30: =+H28/G28*100-100 -> 8.1425152 | I30: =+I28/H28*100-100 -> 0.58778615 | J30: =+J28/I28*100-100 -> 26.08837 | ... Y30: =+Y28/X28*100-100 -> 66.565532
A32: Pertumbuhan (metode lama) | T32: =T9 -> 28768.843 | U32: =(100-3.2)/100*T32 -> 27848.24 | V32: =(100-3.2)/100*U32 -> 26957.096 | W32: =(100-3.2)/100*V32 -> 26094.469 | X32: =(100-3.22)/100*W32 -> 25254.227 | Y32: =(100-3.22)/100*X32 -> 24441.041 | Z32: =(100-3.22)/100*Y32 -> 23654.04 | AA32: =(100-3.22)/100*Z32 -> 22892.38 | AB32: =(100-3.22)/100*AA32 -> 22155.245 | AC32: =(100-3.22)/100*AB32 -> 21441.846 | AD32: =(100-3.22)/100*AC32 -> 20751.419 | AE32: =(100-3.22)/100*AD32 -> 20083.223 | ... AJ32: =(100-3.22)/100*AI32 -> 17051.457
A33: metode baru --> menggunakan luas hutan produksi luar jawa | T33: ='Data Penunjang'!X14/'Data Penunjang'!W14*S9 -> 28948.205 | U33: ='Data Penunjang'!Y14/'Data Penunjang'!X14*T9 -> 29427.551 | V33: ='Data Penunjang'!Z14/'Data Penunjang'!Y14*U9 -> 29417.615 | W33: ='Data Penunjang'!AA14/'Data Penunjang'!Z14*V9 -> 29641.821 | X33: ='Data Penunjang'!AB14/'Data Penunjang'!AA14*W9 -> 29470.768 | Y33: ='Data Penunjang'!AC14/'Data Penunjang'!AB14*X9 -> 22422.401 | Z33: ='Data Penunjang'!AD14/'Data Penunjang'!AC14*Y9 -> 23276.945 | AA33: ='Data Penunjang'!AE14/'Data Penunjang'!AD14*Z9 -> 23334.934 | ... AJ33: ='Data Penunjang'!AN14/'Data Penunjang'!AM14*AI9 -> 23297.342
T34: =T9-T33 -> -179.36238 | U34: =U9-U33 -> 0 | V34: =V9-V33 -> 0 | W34: =W9-W33 -> 0 | X34: =X9-X33 -> 0 | Y34: =Y9-Y33 -> 0 | Z34: =Z9-Z33 -> 0 | AA34: =AA9-AA33 -> 0 | ... AJ34: =AJ9-AJ33 -> 0

Sheet Indonesia
A1: Neraca Fisik dan Moneter
A2: Indonesia | W2: 276481.4 | X2: 303357.85 | Y2: 327010.6 | Z2: 699859.49
W3: 28564.609 | X3: 34409.832 | Y3: 9283.2669 | Z3: 19867.803
A4: Perincian | B4: 1990 | C4: 1991 | D4: 1992 | E4: 1993 | F4: 1994 | G4: 1995 | H4: 1996 | I4: 1997 | J4: 1998 | K4: 1999 | L4: 2000 | M4: 2001 | N4: 2002 | O4: 2003 | P4: 2004 | Q4: 2005 | R4: 2006 | S4: 2007 | T4: 2008 | U4: 2009 | V4: 2010 | W4: 2011 | X4: 2012 | Y4: 2013 | Z4: 2014 | AA4: 2015 | AB4: 2016 | AC4: 2017 | AD4: 2018 | AE4: 2019 | AF4: 2020 | AG4: 2021 | AH4: 2022 | AI4: 2023 | AJ4: 2024 | BH4: Pertumbuhan
BH5: 1991 | BI5: =+BH5+1 -> 1992 | BJ5: =+BI5+1 -> 1993 | BK5: =+BJ5+1 -> 1994 | BL5: =+BK5+1 -> 1995 | BM5: =+BL5+1 -> 1996 | BN5: =+BM5+1 -> 1997 | BO5: =+BN5+1 -> 1998 | BP5: =+BO5+1 -> 1999 | ... BX5: =+BW5+1 -> 2007 | BY5: 2008 | BZ5: 2009 | CA5: 2010 | CB5: 2011 | CC5: 2012 | CD5: 2013 | CE5: 2014 | CF5: 2015
A6: I. Neraca Fisik (000 M3)
A8: 1. Persediaan awal | B8: 8544100 | C8: =+B14 -> 8532878.8 | D8: =+C14 -> 8519248.6 | E8: =+D14 -> 8485914.4 | F8: =+E14 -> 8442976.2 | G8: =+F14 -> 8408592.9 | H8: =+G14 -> 8372034.7 | I8: =+H14 -> 8339545.6 | J8: =+I14 -> 8261234.1 | ... X8: =+W14 -> 5478994.8 | AA8: ='Jati Jawa'!AA8+'Rimba Luar Jawa'!AA8+'Rimba Jawa'!AA8 -> 5423882.4 | AB8: ='Jati Jawa'!AB8+'Rimba Luar Jawa'!AB8+'Rimba Jawa'!AB8 -> 4827604.5 | AC8: ='Jati Jawa'!AC8+'Rimba Luar Jawa'!AC8+'Rimba Jawa'!AC8 -> 4644893.8 | AD8: ='Jati Jawa'!AD8+'Rimba Luar Jawa'!AD8+'Rimba Jawa'!AD8 -> 4493898.5 | AE8: ='Jati Jawa'!AE8+'Rimba Luar Jawa'!AE8+'Rimba Jawa'!AE8 -> 4366432.4 | AF8: ='Jati Jawa'!AF8+'Rimba Luar Jawa'!AF8+'Rimba Jawa'!AF8 -> 4043705.7 | AG8: ='Jati Jawa'!AG8+'Rimba Luar Jawa'!AG8+'Rimba Jawa'!AG8 -> 3968297.7 | AH8: ='Jati Jawa'!AH8+'Rimba Luar Jawa'!AH8+'Rimba Jawa'!AH8 -> 3842760.9 | ... AJ8: ='Jati Jawa'!AJ8+'Rimba Luar Jawa'!AJ8+'Rimba Jawa'!AJ8 -> 3525379.2 | BH8: =C8/B8*100-100 -> -0.13133273 | BI8: =D8/C8*100-100 -> -0.15973741 | BJ8: =E8/D8*100-100 -> -0.39128099 | BK8: =F8/E8*100-100 -> -0.50599379 | BL8: =G8/F8*100-100 -> -0.40724194 | BM8: =H8/G8*100-100 -> -0.43477191 | BN8: =I8/H8*100-100 -> -0.38806696 | BO8: =J8/I8*100-100 -> -0.93903738 | ... CC8: =X8/W8*100-100 -> -5.0593783 | CE8: =SUM(BX8:CB8)/5 -> -4.102061
A9: 2. Pertumbuhan | B9: 30900 | C9: 30861 | D9: 30814 | E9: 30694 | F9: 30542 | G9: 30419 | H9: 32997.62 | I9: 31893.09 | J9: 31366.37 | K9: 33107.012 | L9: 32276.026 | M9: 32279.899 | N9: 32293.457 | O9: 32244.403 | P9: 32163.849 | Q9: 31726.62 | R9: 30730.92 | S9: 29735.238 | T9: 28768.843 | U9: ='Data Penunjang'!Y14/'Data Penunjang'!X14*T9 -> 29427.551 | V9: ='Data Penunjang'!Z14/'Data Penunjang'!Y14*U9 -> 29417.615 | W9: ='Data Penunjang'!AA14/'Data Penunjang'!Z14*V9 -> 29641.821 | X9: ='Data Penunjang'!AB14/'Data Penunjang'!AA14*W9 -> 29470.768 | AA9: ='Jati Jawa'!AA9+'Rimba Luar Jawa'!AA9+'Rimba Jawa'!AA9 -> 46799.571 | AB9: ='Jati Jawa'!AB9+'Rimba Luar Jawa'!AB9+'Rimba Jawa'!AB9 -> 39130.339 | AC9: ='Jati Jawa'!AC9+'Rimba Luar Jawa'!AC9+'Rimba Jawa'!AC9 -> 39323.955 | AD9: ='Jati Jawa'!AD9+'Rimba Luar Jawa'!AD9+'Rimba Jawa'!AD9 -> 39685.752 | AE9: ='Jati Jawa'!AE9+'Rimba Luar Jawa'!AE9+'Rimba Jawa'!AE9 -> 39539.545 | AF9: ='Jati Jawa'!AF9+'Rimba Luar Jawa'!AF9+'Rimba Jawa'!AF9 -> 34282.649 | AG9: ='Jati Jawa'!AG9+'Rimba Luar Jawa'!AG9+'Rimba Jawa'!AG9 -> 34157.553 | AH9: ='Jati Jawa'!AH9+'Rimba Luar Jawa'!AH9+'Rimba Jawa'!AH9 -> 33987.37 | ... AJ9: ='Jati Jawa'!AJ9+'Rimba Luar Jawa'!AJ9+'Rimba Jawa'!AJ9 -> 46599.387 | BH9: =C9/B9*100-100 -> -0.12621359 | BI9: =D9/C9*100-100 -> -0.15229578 | BJ9: =E9/D9*100-100 -> -0.38943337 | BK9: =F9/E9*100-100 -> -0.49521079 | BL9: =G9/F9*100-100 -> -0.40272412 | BM9: =H9/G9*100-100 -> 8.4770045 | BN9: =I9/H9*100-100 -> -3.347302 | BO9: =J9/I9*100-100 -> -1.6515176 | ... CC9: =X9/W9*100-100 -> -0.57706777 | CE9: =AVERAGE(BT9:CC9) -> -0.89485018
A10: 3. Penanaman | B10: 619.8 | C10: 931.8 | D10: 949.8 | E10: 1456.8 | F10: 1239.66 | G10: 1543.8 | H10: 2552.95 | I10: 2137.73 | J10: 1576.88 | K10: 1279.5338 | L10: 3339.4118 | M10: 1242.9956 | N10: 4865.3544 | O10: 5830.756 | P10: 5525.549 | Q10: 5407.211 | R10: 7042.8923 | S10: 6178.7294 | T10: 7954.0144 | U10: =('Data Penunjang'!Y10/'Data Penunjang'!X10*Indonesia!T10) -> 6050.4458 | V10: =('Data Penunjang'!Z10/'Data Penunjang'!Y10*Indonesia!U10) -> 4452.6684 | W10: =('Data Penunjang'!AA10/'Data Penunjang'!Z10*Indonesia!V10) -> 4825.0458 | X10: =('Data Penunjang'!AB10/'Data Penunjang'!AA10*Indonesia!W10) -> 6148.3529 | AA10: ='Jati Jawa'!AA10+'Rimba Luar Jawa'!AA10+'Rimba Jawa'!AA10 -> 15687.856 | AB10: ='Jati Jawa'!AB10+'Rimba Luar Jawa'!AB10+'Rimba Jawa'!AB10 -> 17114.782 | AC10: ='Jati Jawa'!AC10+'Rimba Luar Jawa'!AC10+'Rimba Jawa'!AC10 -> 7358.6198 | AD10: ='Jati Jawa'!AD10+'Rimba Luar Jawa'!AD10+'Rimba Jawa'!AD10 -> 9119.8912 | AE10: ='Jati Jawa'!AE10+'Rimba Luar Jawa'!AE10+'Rimba Jawa'!AE10 -> 13004.311 | AF10: ='Jati Jawa'!AF10+'Rimba Luar Jawa'!AF10+'Rimba Jawa'!AF10 -> 10760.199 | AG10: ='Jati Jawa'!AG10+'Rimba Luar Jawa'!AG10+'Rimba Jawa'!AG10 -> 4748.4949 | AH10: ='Jati Jawa'!AH10+'Rimba Luar Jawa'!AH10+'Rimba Jawa'!AH10 -> 6631.7194 | ... AJ10: ='Jati Jawa'!AJ10+'Rimba Luar Jawa'!AJ10+'Rimba Jawa'!AJ10 -> 7727.594 | BH10: =C10/B10*100-100 -> 50.338819 | BI10: =D10/C10*100-100 -> 1.931745 | BJ10: =E10/D10*100-100 -> 53.379659 | BK10: =F10/E10*100-100 -> -14.905272 | BL10: =G10/F10*100-100 -> 24.534146 | BM10: =H10/G10*100-100 -> 65.367923 | BN10: =I10/H10*100-100 -> -16.264322 | BO10: =J10/I10*100-100 -> -26.235773 | ... CC10: =X10/W10*100-100 -> 27.425794 | CE10: =AVERAGE(BT10:CC10) -> 4.4627525
A11: 4. Konversi & kerusakan | B11: 15455 | C11: 18612 | D11: 37724 | E11: 47160 | F11: 38175 | G11: 40691 | H11: 39765.83 | I11: 79973.9 | J11: 92320.84 | K11: 108270.54 | L11: 97333.105 | M11: 122921.98 | N11: 158520.18 | O11: 179191.22 | P11: 210549.65 | Q11: 252743.8 | R11: 303393.66 | S11: 292592.84 | T11: 206743.81 | U11: =(100+BZ11)/100*T11 -> 227447.89 | V11: =(100+CA11)/100*U11 -> 248573.61 | W11: =(100+CB11)/100*V11 -> 276481.4 | X11: =('Data Penunjang'!AB35/'Data Penunjang'!AA35)*Indonesia!W11 -> 333058.25 | AA11: ='Jati Jawa'!AA11+'Rimba Luar Jawa'!AA11+'Rimba Jawa'!AA11 -> 613364.48 | AB11: ='Jati Jawa'!AB11+'Rimba Luar Jawa'!AB11+'Rimba Jawa'!AB11 -> 193747.58 | AC11: ='Jati Jawa'!AC11+'Rimba Luar Jawa'!AC11+'Rimba Jawa'!AC11 -> 150327.39 | AD11: ='Jati Jawa'!AD11+'Rimba Luar Jawa'!AD11+'Rimba Jawa'!AD11 -> 129001.63 | AE11: ='Jati Jawa'!AE11+'Rimba Luar Jawa'!AE11+'Rimba Jawa'!AE11 -> 325905.34 | AF11: ='Jati Jawa'!AF11+'Rimba Luar Jawa'!AF11+'Rimba Jawa'!AF11 -> 68470.12 | AG11: ='Jati Jawa'!AG11+'Rimba Luar Jawa'!AG11+'Rimba Jawa'!AG11 -> 109629.58 | AH11: ='Jati Jawa'!AH11+'Rimba Luar Jawa'!AH11+'Rimba Jawa'!AH11 -> 55997.21 | ... AJ11: ='Jati Jawa'!AJ11+'Rimba Luar Jawa'!AJ11+'Rimba Jawa'!AJ11 -> 96304.46 | BH11: =C11/B11*100-100 -> 20.427046 | BI11: =D11/C11*100-100 -> 102.68644 | BJ11: =E11/D11*100-100 -> 25.013254 | BK11: =F11/E11*100-100 -> -19.052163 | BL11: =G11/F11*100-100 -> 6.5907007 | BM11: =H11/G11*100-100 -> -2.2736477 | BN11: =I11/H11*100-100 -> 101.11211 | BO11: =J11/I11*100-100 -> 15.438712 | ... BY11: =T11/S11*100-100 -> -29.340784 | BZ11: =AVERAGE(BP11:BY11) -> 10.014363 | CA11: =AVERAGE(BQ11:BZ11) -> 9.2881618 | CB11: =AVERAGE(BR11:CA11) -> 11.227173 | CC11: =AVERAGE(BS11:CB11) -> 9.7208898 | CD11: =AVERAGE(BT11:CC11) -> 7.7969788 | CE11: =AVERAGE(BT11:CD11) -> 7.7969788 | CF11: =AVERAGE(BU11:CE11) -> 7.3203405 | CG11: =AVERAGE(BV11:CF11) -> 6.3949183
A12: 5. Penebangan | B12: 27286 | C12: 26811 | D12: 27374 | E12: 27929 | F12: 27990 | G12: 27830 | H12: 28273.84 | I12: 32368.37 | J12: 23815.22 | K12: 23978.395 | L12: 24654.585 | M12: 24622.535 | N12: 24006.971 | O12: 23166.727 | P12: 23616.156 | Q12: ='Data Penunjang'!U12/'Data Penunjang'!T12*Indonesia!P12 -> 42222.259 | R12: ='Data Penunjang'!V12/'Data Penunjang'!U12*Indonesia!Q12 -> 37985.345 | S12: ='Data Penunjang'!W12/'Data Penunjang'!V12*Indonesia!R12 -> 54892.393 | T12: ='Data Penunjang'!X12/'Data Penunjang'!W12*Indonesia!S12 -> 48522.631 | U12: ='Data Penunjang'!Y12/'Data Penunjang'!X12*Indonesia!T12 -> 50911.031 | V12: ='Data Penunjang'!Z12/'Data Penunjang'!Y12*Indonesia!U12 -> 53550.936 | W12: ='Data Penunjang'!AA12/'Data Penunjang'!Z12*Indonesia!V12 -> 49960.669 | X12: ='Data Penunjang'!AB12/'Data Penunjang'!AA12*Indonesia!W12 -> 49014.219 | AA12: ='Jati Jawa'!AA12+'Rimba Luar Jawa'!AA12+'Rimba Jawa'!AA12 -> 45400.908 | AB12: ='Jati Jawa'!AB12+'Rimba Luar Jawa'!AB12+'Rimba Jawa'!AB12 -> 45208.181 | AC12: ='Jati Jawa'!AC12+'Rimba Luar Jawa'!AC12+'Rimba Jawa'!AC12 -> 47350.504 | AD12: ='Jati Jawa'!AD12+'Rimba Luar Jawa'!AD12+'Rimba Jawa'!AD12 -> 47270.063 | AE12: ='Jati Jawa'!AE12+'Rimba Luar Jawa'!AE12+'Rimba Jawa'!AE12 -> 49365.234 | AF12: ='Jati Jawa'!AF12+'Rimba Luar Jawa'!AF12+'Rimba Jawa'!AF12 -> 51980.746 | AG12: ='Jati Jawa'!AG12+'Rimba Luar Jawa'!AG12+'Rimba Jawa'!AG12 -> 54813.235 | AH12: ='Jati Jawa'!AH12+'Rimba Luar Jawa'!AH12+'Rimba Jawa'!AH12 -> 55055.541 | ... AJ12: ='Jati Jawa'!AJ12+'Rimba Luar Jawa'!AJ12+'Rimba Jawa'!AJ12 -> 55307.319 | BH12: =C12/B12*100-100 -> -1.7408195 | BI12: =D12/C12*100-100 -> 2.0998844 | BJ12: =E12/D12*100-100 -> 2.0274713 | BK12: =F12/E12*100-100 -> 0.21841097 | BL12: =G12/F12*100-100 -> -0.57163273 | BM12: =H12/G12*100-100 -> 1.5948257 | BN12: =I12/H12*100-100 -> 14.48169 | BO12: =J12/I12*100-100 -> -26.424408 | ... CC12: =X12/W12*100-100 -> -1.8943909 | CE12: =AVERAGE(BT12:CC12) -> 10.160476
A13: 6. Perubahan Neto | B13: =B14-B8 -> -11221.2 | C13: =C14-C8 -> -13630.2 | D13: =D14-D8 -> -33334.2 | E13: =E14-E8 -> -42938.2 | F13: =F14-F8 -> -34383.34 | G13: =G14-G8 -> -36558.2 | H13: =H14-H8 -> -32489.1 | I13: =I14-I8 -> -78311.45 | ... X13: =X14-X8 -> -346453.35 | AA13: ='Jati Jawa'!AA13+'Rimba Luar Jawa'!AA13+'Rimba Jawa'!AA13 -> -596277.96 | AB13: ='Jati Jawa'!AB13+'Rimba Luar Jawa'!AB13+'Rimba Jawa'!AB13 -> -182710.64 | AC13: ='Jati Jawa'!AC13+'Rimba Luar Jawa'!AC13+'Rimba Jawa'!AC13 -> -150995.32 | AD13: ='Jati Jawa'!AD13+'Rimba Luar Jawa'!AD13+'Rimba Jawa'!AD13 -> -127466.05 | AE13: ='Jati Jawa'!AE13+'Rimba Luar Jawa'!AE13+'Rimba Jawa'!AE13 -> -322726.72 | AF13: ='Jati Jawa'!AF13+'Rimba Luar Jawa'!AF13+'Rimba Jawa'!AF13 -> -75408.019 | AG13: ='Jati Jawa'!AG13+'Rimba Luar Jawa'!AG13+'Rimba Jawa'!AG13 -> -125536.77 | AH13: ='Jati Jawa'!AH13+'Rimba Luar Jawa'!AH13+'Rimba Jawa'!AH13 -> -70433.661 | ... AJ13: ='Jati Jawa'!AJ13+'Rimba Luar Jawa'!AJ13+'Rimba Jawa'!AJ13 -> -97284.797 | BH13: =C13/B13*100-100 -> 21.468292 | BI13: =D13/C13*100-100 -> 144.56134 | BJ13: =E13/D13*100-100 -> 28.811251 | BK13: =F13/E13*100-100 -> -19.923658 | BL13: =G13/F13*100-100 -> 6.3253308 | BM13: =H13/G13*100-100 -> -11.130471 | BN13: =I13/H13*100-100 -> 141.03915 | BO13: =J13/I13*100-100 -> 6.2332647 | ... CC13: =X13/W13*100-100 -> 18.658483 | CE13: =AVERAGE(BT13:CC13) -> 10.343934
A14: 7. Persediaan akhir | B14: =B8+B9+B10-B11-B12 -> 8532878.8 | C14: =C8+C9+C10-C11-C12 -> 8519248.6 | D14: =D8+D9+D10-D11-D12 -> 8485914.4 | E14: =E8+E9+E10-E11-E12 -> 8442976.2 | F14: =F8+F9+F10-F11-F12 -> 8408592.9 | G14: =G8+G9+G10-G11-G12 -> 8372034.7 | H14: =H8+H9+H10-H11-H12 -> 8339545.6 | I14: =I8+I9+I10-I11-I12 -> 8261234.1 | ... X14: =X8+X9+X10-X11-X12 -> 5132541.5 | AA14: ='Jati Jawa'!AA14+'Rimba Luar Jawa'!AA14+'Rimba Jawa'!AA14 -> 4827604.5 | AB14: ='Jati Jawa'!AB14+'Rimba Luar Jawa'!AB14+'Rimba Jawa'!AB14 -> 4644893.8 | AC14: ='Jati Jawa'!AC14+'Rimba Luar Jawa'!AC14+'Rimba Jawa'!AC14 -> 4493898.5 | AD14: ='Jati Jawa'!AD14+'Rimba Luar Jawa'!AD14+'Rimba Jawa'!AD14 -> 4366432.4 | AE14: ='Jati Jawa'!AE14+'Rimba Luar Jawa'!AE14+'Rimba Jawa'!AE14 -> 4043705.7 | AF14: ='Jati Jawa'!AF14+'Rimba Luar Jawa'!AF14+'Rimba Jawa'!AF14 -> 3968297.7 | AG14: ='Jati Jawa'!AG14+'Rimba Luar Jawa'!AG14+'Rimba Jawa'!AG14 -> 3842760.9 | AH14: ='Jati Jawa'!AH14+'Rimba Luar Jawa'!AH14+'Rimba Jawa'!AH14 -> 3772327.3 | ... AJ14: ='Jati Jawa'!AJ14+'Rimba Luar Jawa'!AJ14+'Rimba Jawa'!AJ14 -> 3428094.4 | BH14: =C14/B14*100-100 -> -0.15973741 | BI14: =D14/C14*100-100 -> -0.39128099 | BJ14: =E14/D14*100-100 -> -0.50599379 | BK14: =F14/E14*100-100 -> -0.40724194 | BL14: =G14/F14*100-100 -> -0.43477191 | BM14: =H14/G14*100-100 -> -0.38806696 | BN14: =I14/H14*100-100 -> -0.93903738 | BO14: =J14/I14*100-100 -> -1.0070264 | ... CC14: =X14/W14*100-100 -> -6.3233012 | CE14: =AVERAGE(BT14:CC14) -> -4.0109115
C15: =+C14/B14*100-100 -> -0.15973741 | D15: =+D14/C14*100-100 -> -0.39128099 | E15: =+E14/D14*100-100 -> -0.50599379 | F15: =+F14/E14*100-100 -> -0.40724194 | G15: =+G14/F14*100-100 -> -0.43477191 | H15: =+H14/G14*100-100 -> -0.38806696 | I15: =+I14/H14*100-100 -> -0.93903738 | J15: =+J14/I14*100-100 -> -1.0070264 | ... X15: =+X14/W14*100-100 -> -6.3233012 | CE15: =SUM(BX15:CB15)/5 -> 0
A16: II. Unit Rent | B16: 9248 | C16: 10892 | D16: ='Rent Luar Jawa'!C21 -> 10449.648 | E16: ='Rent Luar Jawa'!D21 -> 11449.125 | F16: ='Rent Luar Jawa'!E21 -> 13832.444 | G16: ='Rent Luar Jawa'!F21 -> 14934.936 | H16: ='Rent Luar Jawa'!G21 -> 16213.937 | I16: ='Rent Luar Jawa'!H21 -> 16463.842 | J16: ='Rent Luar Jawa'!I21 -> 20970.165 | K16: ='Rent Luar Jawa'!J21 -> 25681.925 | ... X16: ='Rent Luar Jawa'!W21 -> 84165.257 | BH16: =C16/B16*100-100 -> 17.776817 | BI16: =D16/C16*100-100 -> -4.0612552 | BJ16: =E16/D16*100-100 -> 9.5646906 | BK16: =F16/E16*100-100 -> 20.816609 | BL16: =G16/F16*100-100 -> 7.9703354 | BM16: =H16/G16*100-100 -> 8.5638155 | BN16: =I16/H16*100-100 -> 1.5412969 | BO16: =J16/I16*100-100 -> 27.37103 | ... CC16: =X16/W16*100-100 -> 3.615673 | CE16: =SUM(BX16:CB16)/5 -> 9.7038494
A17: Pertumbuhan Unit Rent | C17: =+C16/B16*100-100 -> 17.776817 | D17: =+D16/C16*100-100 -> -4.0612552 | E17: =+E16/D16*100-100 -> 9.5646906 | F17: =+F16/E16*100-100 -> 20.816609 | G17: =+G16/F16*100-100 -> 7.9703354 | H17: =+H16/G16*100-100 -> 8.5638155 | I17: =+I16/H16*100-100 -> 1.5412969 | J17: =+J16/I16*100-100 -> 27.37103 | ... X17: =+X16/W16*100-100 -> 3.615673
A18: III. Neraca Moneter
A19: (miliar Rp)
A21: 1. Persediaan awal | B21: 70232.502 | C21: =B28 -> 78912.063 | D21: =C28 -> 92791.656 | E21: =D28 -> 88674.819 | F21: =E28 -> 96664.686 | G21: =F28 -> 116311.39 | H21: =G28 -> 125035.8 | I21: =H28 -> 135216.86 | J21: =I28 -> 136011.65 | ... X21: =W28 -> 445049.48
A22: 2. Pertumbuhan | B22: =B9*B16/1000000 -> 285.7632 | C22: =C9*C16/1000000 -> 336.13801 | D22: =D9*D16/1000000 -> 321.99546 | E22: =E9*E16/1000000 -> 351.41943 | F22: =F9*F16/1000000 -> 422.47051 | G22: =G9*G16/1000000 -> 454.30583 | H22: =H9*H16/1000000 -> 535.02132 | I22: =I9*I16/1000000 -> 525.08278 | ... X22: =X9*X16/1000000 -> 2480.4148
A23: 3. Penanaman | B23: =B10*B16/1000000 -> 5.7319104 | C23: =C10*C16/1000000 -> 10.149166 | D23: =D10*D16/1000000 -> 9.9250758 | E23: =E10*E16/1000000 -> 16.679085 | F23: =F10*F16/1000000 -> 17.147528 | G23: =G10*G16/1000000 -> 23.056555 | H23: =H10*H16/1000000 -> 41.39337 | I23: =I10*I16/1000000 -> 35.195248 | ... X23: =X10*X16/1000000 -> 517.47771
A24: 4. Konversi & kerusakan | B24: =B11*B16/1000000 -> 142.92784 | C24: =C11*C16/1000000 -> 202.7219 | D24: =D11*D16/1000000 -> 394.20252 | E24: =E11*E16/1000000 -> 539.94072 | F24: =F11*F16/1000000 -> 528.05355 | G24: =G11*G16/1000000 -> 607.71749 | H24: =H11*H16/1000000 -> 644.76065 | I24: =I11*I16/1000000 -> 1316.6776 | ... X24: =X11*X16/1000000 -> 28031.933
A25: 5. Penebangan | B25: =B12*B16/1000000 -> 252.34093 | C25: =C12*C16/1000000 -> 292.02541 | D25: =D12*D16/1000000 -> 286.04867 | E25: =E12*E16/1000000 -> 319.7626 | F25: =F12*F16/1000000 -> 387.17011 | G25: =G12*G16/1000000 -> 415.63928 | H25: =H12*H16/1000000 -> 458.43025 | I25: =I12*I16/1000000 -> 532.90771 | ... X25: =X12*X16/1000000 -> 4125.2943
A26: 6. Perubahan Neto | B26: =B13*B16/1000000 -> -103.77366 | C26: =C13*C16/1000000 -> -148.46014 | D26: =D13*D16/1000000 -> -348.33066 | E26: =E13*E16/1000000 -> -491.6048 | F26: =F13*F16/1000000 -> -475.60563 | G26: =G13*G16/1000000 -> -545.99439 | H26: =H13*H16/1000000 -> -526.77621 | I26: =I13*I16/1000000 -> -1289.3073 | ... X26: =X13*X16/1000000 -> -29159.335
A27: 7. Revaluasi | B27: 8783.3348 | C27: =C8*(C16-B16)/1000000 -> 14028.053 | D27: =D8*(D16-C16)/1000000 -> -3768.5059 | E27: =E8*(E16-D16)/1000000 -> 8481.4721 | F27: =F8*(F16-E16)/1000000 -> 20122.31 | G27: =G8*(G16-F16)/1000000 -> 9270.4079 | H27: =H8*(H16-G16)/1000000 -> 10707.836 | I27: =I8*(I16-H16)/1000000 -> 2084.0933 | J27: =J8*(J16-I16)/1000000 -> 37227.789 | ... X27: =X8*(X16-W16)/1000000 -> 16091.534
A28: 8. Persediaan akhir | B28: =B21+B22+B23-B24-B25+B27 -> 78912.063 | C28: =C21+C22+C23-C24-C25+C27 -> 92791.656 | D28: =D21+D22+D23-D24-D25+D27 -> 88674.819 | E28: =E21+E22+E23-E24-E25+E27 -> 96664.686 | F28: =F21+F22+F23-F24-F25+F27 -> 116311.39 | G28: =G21+G22+G23-G24-G25+G27 -> 125035.8 | H28: =H21+H22+H23-H24-H25+H27 -> 135216.86 | I28: =I21+I22+I23-I24-I25+I27 -> 136011.65 | ... X28: =X21+X22+X23-X24-X25+X27 -> 431981.67 | BR28: =M28/L28*100-100 -> -0.30466023 | BS28: =N28/M28*100-100 -> 0.56293283 | BT28: =O28/N28*100-100 -> 3.7409536 | BU28: =P28/O28*100-100 -> 5.5686036 | BV28: =Q28/P28*100-100 -> 10.952708 | BW28: =R28/Q28*100-100 -> 34.330082 | BX28: =S28/R28*100-100 -> 12.352351 | BY28: =T28/S28*100-100 -> 9.2769194 | ... CC28: =X28/W28*100-100 -> -2.9362582 | CE28: =SUM(BX28:CB28)/5 -> 5.0407961
C30: =+C28/B28*100-100 -> 17.588683 | D30: =+D28/C28*100-100 -> -4.4366452 | E30: =+E28/D28*100-100 -> 9.0103 | F30: =+F28/E28*100-100 -> 20.324593 | G30: =+G28/F28*100-100 -> 7.5009107 | H30: =+H28/G28*100-100 -> 8.1425152 | I30: =+I28/H28*100-100 -> 0.58778615 | J30: =+J28/I28*100-100 -> 26.08837 | ... X30: =+X28/W28*100-100 -> -2.9362582
T32: =T9-#REF! -> #REF! | U32: =U9-#REF! -> #REF! | V32: =V9-#REF! -> #REF! | W32: =W9-#REF! -> #REF! | X32: =X9-#REF! -> #REF!

Sheet Sheet1
B2: IHP | C2: 2010 | D2: 2011 | E2: 2012 | F2: 2013 | G2: 2014 | I2: 2015 | J2: 2016
B3: Kayu Jati | C3: 100 | D3: 107.32331 | E3: 113.42951 | F3: 130.3457 | G3: 149.29271 | I3: 179.47327 | J3: 191.17344
B4: Kayu Rimba Lainnya | C4: 100 | D4: 107.12745 | E4: 112.45625 | F4: 118.01152 | G4: 124.02711 | I4: 134.52492 | J4: 137.3588
B16: Tabel 1. Data Harga Kayu | I16: Tabel 2. Data Harga dan Produksi Kayu Jati dan Rimba
B17: Jenis Data | C17: 2013 | D17: =C17+1 -> 2014 | E17: =D17+1 -> 2015 | F17: =E17+1 -> 2016 | G17: =F17+1 -> 2017 | I17: Tahun | J17: Jati Jawa | L17: Rimba Jawa | N17: Rimba Luar Jawa
B18: Harga Kayu Jati (PDB) | J18: Harga | K18: Produksi (000 m3) | L18: Harga | M18: Produksi (000 m3) | N18: Harga | O18: Produksi (000 m3)
B19: Hrg.Kayu "Rimba" PDB | I19: 2013
B20: Harga Ky. Log Rimba (LK PDB) (Rp/m3) | I20: 2014
I21: 2015*
I22: 2016**
I23: 2017***

Sheet Jati Jawa Ha
B1: NERACA ASET FISIK UNTUK HUTAN DAN LAHAN BERHUTAN LAINNYA (HEKTAR)
B2: JATI JAWA
A4: No. | B4: Uraian | C4: 2007 | D4: 2008 | E4: 2009 | F4: 2010 | G4: 2011 | H4: 2012 | I4: 2013 | J4: 2014 | K4: 2015 | L4: 2016 | M4: 2017
A5: 1 | B5: Stok awal hutan dan lahan berhutan lain | C5: ='Data Penunjang'!W37 -> 1099402.4 | D5: =C14 -> 1118135.4 | E5: =D14 -> 1077401 | F5: =E14 -> 1062957 | G5: =F14 -> 1051725 | H5: =G14 -> 1051334 | I5: =H14 -> 1058626 | J5: =I14 -> 1074858.8 | K5: =J14 -> 1098198.8 | ... M5: =L14 -> 1123007.1
A6: 2 | B6: Penambahan stok
B7: Afforestasi | C7: ='Data Penunjang'!W48 -> 62605 | D7: ='Data Penunjang'!X48 -> 32016 | E7: ='Data Penunjang'!Y48 -> 19150 | F7: ='Data Penunjang'!Z48 -> 19324 | G7: ='Data Penunjang'!AA48 -> 29868 | H7: ='Data Penunjang'!AB48 -> 24529 | I7: ='Data Penunjang'!AC48 -> 16232.75 | J7: ='Data Penunjang'!AD48 -> 23340 | ... M7: ='Data Penunjang'!AG48 -> 7261.36
B8: Ekspansi alam | D8: ='Data Penunjang'!X39 -> 1131.63 | E8: ='Data Penunjang'!Y39 -> 0 | F8: ='Data Penunjang'!Z39 -> -0.33 | G8: ='Data Penunjang'!AA39 -> 0 | H8: ='Data Penunjang'!AB39 -> 0.33 | I8: ='Data Penunjang'!AC39 -> 137838 | J8: ='Data Penunjang'!AD39 -> -162931 | K8: ='Data Penunjang'!AE39 -> 1403.8957 | ... M8: ='Data Penunjang'!AG39 -> -5786.7231
B9: Total penambahan stok | C9: =C8+C7 -> 62605 | D9: =D8+D7 -> 33147.63 | E9: =E8+E7 -> 19150 | F9: =F8+F7 -> 19323.67 | G9: =G8+G7 -> 29868 | H9: =H8+H7 -> 24529.33 | I9: =I8+I7 -> 154070.75 | J9: =J8+J7 -> -139591 | ... M9: =M8+M7 -> 1474.6369
A10: 3 | B10: Pengurangan stok
B11: Deforestasi | C11: =39708+3033 -> 42741 | D11: =70890+2992 -> 73882 | E11: =31029+2565 -> 33594 | F11: =28054+2502 -> 30556 | G11: =27622+2637 -> 30259 | H11: =14622+2615 -> 17237
B12: Regresi alam | C12: 1131 | E12: ='Data Penunjang'!Y39 -> 0 | F12: ='Data Penunjang'!Z39 -> -0.33 | G12: ='Data Penunjang'!AA39 -> 0 | H12: ='Data Penunjang'!AB39 -> 0.33 | I12: ='Data Penunjang'!AC39 -> 137838 | J12: ='Data Penunjang'!AD39 -> -162931 | K12: ='Data Penunjang'!AE39 -> 1403.8957 | L12: ='Data Penunjang'!AF39 -> -107941.17 | M12: ='Data Penunjang'!AG39 -> -5786.7231
B13: Total pengurangan stok | C13: =C12+C11 -> 43872 | D13: =D12+D11 -> 73882 | E13: =E12+E11 -> 33594 | F13: =F12+F11 -> 30555.67 | G13: =G12+G11 -> 30259 | H13: =H12+H11 -> 17237.33 | I13: =I12+I11 -> 137838 | J13: =J12+J11 -> -162931 | ... M13: =M12+M11 -> -5786.7231
A14: 4 | B14: Stok akhir hutan dan lahan berhutan lain | C14: =C5+C9-C13 -> 1118135.4 | D14: =D5+D9-D13 -> 1077401 | E14: =E5+E9-E13 -> 1062957 | F14: =F5+F9-F13 -> 1051725 | G14: =G5+G9-G13 -> 1051334 | H14: =H5+H9-H13 -> 1058626 | I14: =I5+I9-I13 -> 1074858.8 | J14: =J5+J9-J13 -> 1098198.8 | ... M14: =M5+M9-M13 -> 1130268.5
D15: =D14/C14*100-100 -> -3.6430625 | E15: =E14/D14*100-100 -> -1.3406336 | F15: =F14/E14*100-100 -> -1.0566749 | G15: =G14/F14*100-100 -> -0.037177019 | H15: =H14/G14*100-100 -> 0.69359499 | I15: =I14/H14*100-100 -> 1.5333791 | J15: =J14/I14*100-100 -> 2.1714481 | K15: =K14/J14*100-100 -> 1.8510648 | ... M15: =M14/L14*100-100 -> 0.64659964

Sheet Rimba Jawa Ha
A1: NERACA ASET FISIK UNTUK HUTAN DAN LAHAN BERHUTAN LAINNYA (HEKTAR)
A2: RIMBA JAWA
A4: No. | B4: Uraian | C4: 2007 | D4: 2008 | E4: 2009 | F4: 2010 | G4: 2011 | H4: 2012 | I4: 2013 | J4: 2014 | K4: 2015 | L4: 2016 | M4: 2017
