Workbook

Sheet READ ME
A1: Data yang di-update saat penulisan Publikasi Sisnerling 2020 - 2024 (18 November 2025)
A2: Sheet Penyediaan: mengalami revisi pada Rasio NTB terhadap Output yang dihitung dari tabel SUT menggunakan SUT 2020 untuk Tahun 2020, SUT 2021 untuk 2021 sd sekarang
A3: Sheet Stok Kapital: Data stok kapital hanya dirilis oleh DNPeng setiap 5 tahun sekali. Data terakhir sampai dengan 2022. Untuk 2023 - 2024, estimasi dilakukan sendiri karena dari pihak DNPeng tidak bersedia mengestimasi
A4: Kesimpulan: Neraca Terintegrasi 2020 - 2024 tidak ada angka tetap karena perubahan data produksi neraca aset mineral. Oleh karena itu, dilakukan pula update rasio penyediaan untuk tahun 2020 - 2024 (meskipun ini tidak beda jauh)
A6: PETUNJUK WARNA SHEET
B7: Meminta dengan mengirimkan format ke DNPeng (PDB ADHB dan Penyusutan) atau ke PJ Neraca (Aset Moneter, ingat angka tetap tidak boleh berubah)
B8: Perhitungan dengan Sheet "SUT (Rasio Penyediaan)" sebagai sheet bantu, SUT Nas bisa meminta ke KNPN
B9: Perhitungan dan meminta nilai Stok Akhir tahun berjalan ke DNPeng (Stok Kapital) dan jumlah penduduk ke PJ PDRB DAU
B10: Sheet bantu
B11: Full Perhitungan

Sheet PDB ADHB
B1: =C1-1 -> 2014 | C1: 2015 | D1: =C1+1 -> 2016 | E1: =C1+2 -> 2017 | F1: 2018 | G1: 2019 | H1: 2020 | I1: 2021 | J1: 2022 | K1: 2023* | L1: 2024**
A2: PDB Penggunaan (Seri 2010) | B2: =B1 -> 2014 | C2: =C1 -> 2015 | D2: =D1 -> 2016 | E2: =E1 -> 2017 | F2: =F1 -> 2018 | G2: =G1 -> 2019 | H2: =H1 -> 2020 | I2: =I1 -> 2021 | ... L2: =L1 -> 2024**
A6: 1. Pengeluaran Konsumsi Rumahtangga | B6: 5915194.2 | C6: 6490929.7 | D6: 7027023.5 | E6: 7623056.1 | F6: 8274214.4 | G6: 8965837.4 | H6: 8899917.6 | I6: 9236049.1 | J6: 10161713 | K6: 11109566 | L6: 11964947
A7: a. Makanan dan Minuman, Selain Restoran | B7: 2247450.6 | C7: 2495433.4 | D7: 2759335 | E7: 2986882 | F7: 3255945.9 | G7: 3529891.7 | H7: 3669993.5 | I7: 3803853.4 | J7: 4174005.2 | K7: 4542099.3 | L7: 4925152.2
A8: b. Pakaian, Alas Kaki dan Jasa Perawatannya | B8: 221633.2 | C8: 239644.36 | D8: 256951.35 | E8: 273621.29 | F8: 296092.19 | G8: 321705.24 | H8: 316446.6 | I8: 319886.33 | J8: 339007.54 | K8: 358339.99 | L8: 370749.13
A9: c. Perumahan dan Perlengkapan Rumahtangga | B9: 774867.36 | C9: 849310.41 | D9: 902678.59 | E9: 980387.89 | F9: 1060517 | G9: 1144776.7 | H9: 1186900 | I9: 1223129.7 | J9: 1296548 | K9: 1375977.7 | L9: 1445425.7
A10: d. Kesehatan dan Pendidikan | B10: 394267.5 | C10: 433073.01 | D10: 473136.67 | E10: 515134.08 | F10: 558969.26 | G10: 616504.64 | H10: 652831.63 | I10: 677159.59 | J10: 708941.91 | K10: 755651.11 | L10: 801067.94
A11: e. Transportasi dan Komunikasi | B11: 1420289.1 | C11: 1518754.7 | D11: 1597642.8 | E11: 1748905.2 | F11: 1894012.6 | G11: 2042268.5 | H11: 1796642.8 | I11: 1861337.4 | J11: 2165432.5 | K11: 2469012.4 | L11: 2673353
A12: f. Restoran dan Hotel | B12: 570464.73 | C12: 636959.26 | D12: 695938.8 | E12: 755577.03 | F12: 826225.85 | G12: 903979.63 | H12: 853216.32 | I12: 909182.31 | J12: 1006405.8 | K12: 1104034.4 | L12: 1201577.6
A13: g. Lainnya | B13: 286221.7 | C13: 317754.5 | D13: 341340.32 | E13: 362548.57 | F13: 382451.64 | G13: 406711.02 | H13: 423886.75 | I13: 441500.39 | J13: 471372.49 | K13: 504451.18 | L13: 547621.01
A14: 2. Pengeluaran Konsumsi LNPRT | B14: 124242 | C14: 130950.57 | D14: 144499.38 | E14: 160594.43 | F14: 180893.25 | G14: 206094.49 | H14: 201451.56 | I14: 207916.21 | J14: 228999.01 | K14: 261210.19 | L14: 300080.4
A15: 3. Pengeluaran Konsumsi Pemerintah | B15: 996197.44 | C15: 1123749.9 | D15: 1181613.1 | E15: 1239469.7 | F15: 1338638.6 | G15: 1394615.1 | H15: 1491171.7 | I15: 1569830.3 | J15: 1506284.8 | K15: 1557495.6 | L15: 1711550.8
A16: a. Konsumsi Kolektif | B16: 622774.29 | C16: 691754.84 | D16: 731393.32 | E16: 761297.46 | F16: 821700.18 | G16: 868092.34 | H16: 897223.32 | I16: 902552.44 | J16: 904343.88 | K16: 963842.56 | L16: 1076657.1
A17: b. Konsumsi Individu | B17: 373423.15 | C17: 431995.03 | D17: 450219.82 | E17: 478172.26 | F17: 516938.4 | G17: 526522.72 | H17: 593948.34 | I17: 667277.85 | J17: 601940.9 | K17: 593653.01 | L17: 634893.75
... A37: 8. PRODUK DOMESTIK BRUTO | B37: 10569705 | C37: 11526333 | D37: 12401728 | E37: 13589826 | F37: 14838756 | G37: 15832657 | H37: 15443353 | I37: 16976751 | J37: 19588460 | K37: 20892348 | L37: 22138964

Sheet Penyusutan
A1: National Income (Billion Rp) | B1: PENDAPATAN NASIONAL
A3: English | B3: Indonesia | C3: ='PDB ADHB'!C1-1 -> 2014 | I3: ='PDB ADHB'!C1 -> 2015 | O3: ='PDB ADHB'!D1 -> 2016 | U3: ='PDB ADHB'!E1 -> 2017 | AA3: ='PDB ADHB'!F1 -> 2018 | AG3: ='PDB ADHB'!G1 -> 2019 | AM3: ='PDB ADHB'!H1 -> 2020 | AS3: 2021 | AY3: 2022 | BE3: 2023* | BK3: 2024**
C4: Q1 | D4: Q2 | E4: Q3 | F4: Q4 | G4: Total | I4: Q1 | J4: Q2 | K4: Q3 | L4: Q4 | M4: Total | O4: Q1 | P4: Q2 | Q4: Q3 | R4: Q4 | S4: Total | U4: Q1 | V4: Q2 | W4: Q3 | X4: Q4 | Y4: Total | AA4: Q1 | AB4: Q2 | AC4: Q3 | AD4: Q4 | AE4: Total | AG4: Q1 | AH4: Q2 | AI4: Q3 | AJ4: Q4 | AK4: Total | AM4: Q1 | AN4: Q2 | AO4: Q3 | AP4: Q4 | AQ4: Total | AS4: Q1 | AT4: Q2 | AU4: Q3 | AV4: Q4 | AW4: Total | AY4: Q1 | AZ4: Q2 | BA4: Q3 | BB4: Q4 | BC4: Total | BE4: Q1 | BF4: Q2 | BG4: Q3 | BH4: Q4 | BI4: Total | BK4: Q1 | BL4: Q2 | BM4: Q3 | BN4: Q4 | BO4: Total
A6: GDP | B6: 1. PRODUK DOMESTIK BRUTO | C6: 2506300.2 | D6: 2618947.3 | E6: 2746762.4 | F6: 2697695.4 | G6: 10569705 | I6: 2728180.7 | J6: 2867948.4 | K6: 2990645 | L6: 2939558.7 | M6: 11526333 | O6: 2929269 | P6: 3073536.7 | Q6: 3205019 | R6: 3193903.8 | S6: 12401728 | U6: 3228172.2 | V6: 3366787.3 | W6: 3504138.5 | X6: 3490727.7 | Y6: 13589826 | AA6: 3510363.1 | AB6: 3686836.4 | AC6: 3842343 | AD6: 3799213.5 | AE6: 14838756 | AG6: 3782618.3 | AH6: 3964074.7 | AI6: 4067358 | AJ6: 4018606.2 | AK6: 15832657 | AM6: 3923347.9 | AN6: 3690742.2 | AO6: 3897851.9 | AP6: 3931411.2 | AQ6: 15443353 | AS6: 3972933 | AT6: 4178022 | AU6: 4327383.9 | AV6: 4498412.5 | AW6: =SUM(AS6:AV6) -> 16976751 | AY6: 4508662.5 | AZ6: 4898031.8 | BA6: 5066968.2 | BB6: 5114797.4 | BC6: 19588460 | BE6: 5071497.2 | BF6: 5223290.3 | BG6: 5294903.3 | BH6: 5302657.7 | BI6: 20892348 | BK6: 5288576.6 | BL6: 5536588.5 | BM6: 5638869.1 | BN6: 5674929.8 | BO6: 22138964
A8: Net factor income | B8: 2. Pendapatan Neto Terhadap Luar Negeri
A9: from abroad | B9: Atas Faktor Produksi | C9: -86145.715 | D9: -92461.23 | E9: -86577.572 | F9: -89208.618 | G9: -354393.14 | I9: -91603.357 | J9: -95751.318 | K9: -103974.82 | L9: -91010.272 | M9: -382339.77 | O9: -99190.519 | P9: -106805.68 | Q9: -107404.25 | R9: -83612.608 | S9: -397013.05 | U9: -102445.14 | V9: -109472.77 | W9: -114620.47 | X9: -104067.4 | Y9: -430605.78 | AA9: -100730.17 | AB9: -113256.13 | AC9: -117186.93 | AD9: -111010.51 | AE9: -442183.75 | AG9: -115717.82 | AH9: -127792.47 | AI9: -119846.92 | AJ9: -117963.85 | AK9: -481321.06 | AM9: -113407.13 | AN9: -93393.279 | AO9: -109659.96 | AP9: -107586.99 | AQ9: -424047.35 | AS9: -96526.974 | AT9: -116435.92 | AU9: -119892.38 | AV9: -128041.58 | AW9: =SUM(AS9:AV9) -> -460896.85 | AY9: -111721.79 | AZ9: -132028.69 | BA9: -134333.94 | BB9: -151014.22 | BC9: -529098.63 | BE9: -136751.88 | BF9: -139543.11 | BG9: -132769.2 | BH9: -143253.48 | BI9: -552317.67 | BK9: -141117.02 | BL9: -156980.77 | BM9: -141388.25 | BN9: -144953.23 | BO9: -584439.26
A10: from | B10: a. Pendapatan Dari Luar Negeri | C10: 4604.8268 | D10: 7875.6713 | E10: 7424.1909 | F10: 5161.8559 | G10: 25066.545 | I10: 5958.7541 | J10: 9442.5882 | K10: 9730.7274 | L10: 12695.067 | M10: 37827.136 | O10: 9587.2088 | P10: 11408.314 | Q10: 15377.927 | R10: 17122.502 | S10: 53495.952 | U10: 15681.845 | V10: 18258.631 | W10: 18585.816 | X10: 21321.601 | Y10: 73847.894 | AA10: 27586.277 | AB10: 35214.297 | AC10: 25664.595 | AD10: 43608.678 | AE10: 132073.85 | AG10: 20187.837 | AH10: 32791.125 | AI10: 23347.515 | AJ10: 27521.726 | AK10: 103848.2 | AM10: 14664.763 | AN10: 20952.244 | AO10: 18316.767 | AP10: 21911.369 | AQ10: 75845.143 | AS10: 19071.262 | AT10: 25445.701 | AU10: 25820.734 | AV10: 25677.041 | AW10: =SUM(AS10:AV10) -> 96014.739 | AY10: 22030.733 | AZ10: 29125.885 | BA10: 29614.395 | BB10: 30686.797 | BC10: 111457.81 | BE10: 27174.938 | BF10: 29515.954 | BG10: 29528.135 | BH10: 33067.895 | BI10: 119286.92 | BK10: 35849.136 | BL10: 36286.224 | BM10: 39933.412 | BN10: 35817.653 | BO10: 147886.42
A11: to | B11: b. Pendapatan Ke Luar Negeri | C11: 90750.542 | D11: 100336.9 | E11: 94001.763 | F11: 94370.474 | G11: 379459.68 | I11: 97562.111 | J11: 105193.91 | K11: 113705.55 | L11: 103705.34 | M11: 420166.9 | O11: 108777.73 | P11: 118213.99 | Q11: 122782.17 | R11: 100735.11 | S11: 450509 | U11: 118126.98 | V11: 127731.4 | W11: 133206.28 | X11: 125389 | Y11: 504453.67 | AA11: 128316.44 | AB11: 148470.43 | AC11: 142851.53 | AD11: 154619.19 | AE11: 574257.59 | AG11: 135905.65 | AH11: 160583.59 | AI11: 143194.44 | AJ11: 145485.57 | AK11: 585169.26 | AM11: 128071.89 | AN11: 114345.52 | AO11: 127976.72 | AP11: 129498.36 | AQ11: 499892.5 | AS11: 115598.24 | AT11: 141881.62 | AU11: 145713.11 | AV11: 153718.62 | AW11: =SUM(AS11:AV11) -> 556911.59 | AY11: 133752.52 | AZ11: 161154.58 | BA11: 163948.33 | BB11: 181701.01 | BC11: 640556.44 | BE11: 163926.81 | BF11: 169059.07 | BG11: 162297.34 | BH11: 176321.37 | BI11: 671604.59 | BK11: 176966.15 | BL11: 193266.99 | BM11: 181321.66 | BN11: 180770.88 | BO11: 732325.68
A13: GNP | B13: 3. PRODUK NASIONAL BRUTO | C13: 2420154.5 | D13: 2526486.1 | E13: 2660184.8 | F13: 2608486.8 | G13: 10215312 | I13: 2636577.3 | J13: 2772197.1 | K13: 2886670.2 | L13: 2848548.4 | M13: 11143993 | O13: 2830078.5 | P13: 2966731 | Q13: 3097614.8 | R13: 3110291.2 | S13: 12004715 | U13: 3125727.1 | V13: 3257314.5 | W13: 3389518 | X13: 3386660.3 | Y13: 13159220 | AA13: 3409632.9 | AB13: 3573580.3 | AC13: 3725156.1 | AD13: 3688203 | AE13: 14396572 | AG13: 3666900.5 | AH13: 3836282.2 | AI13: 3947511.1 | AJ13: 3900642.4 | AK13: 15351336 | AM13: 3809940.8 | AN13: 3597348.9 | AO13: 3788191.9 | AP13: 3823824.2 | AQ13: 15019306 | AS13: 3876406 | AT13: 4061586.1 | AU13: 4207491.5 | AV13: 4370370.9 | AW13: =SUM(AS13:AV13) -> 16515855 | AY13: 4396940.7 | AZ13: 4766003.1 | BA13: 4932634.3 | BB13: 4963783.2 | BC13: 19059361 | BE13: 4934745.3 | BF13: 5083747.2 | BG13: 5162134.1 | BH13: 5159404.2 | BI13: 20340031 | BK13: 5147459.6 | BL13: 5379607.7 | BM13: 5497480.9 | BN13: 5529976.6 | BO13: 21554525
A15: Less indirect taxes (nett) | B15: 4. Dikurangi Pajak Tidak Langsung Neto (a-b) | C15: 102291.54 | D15: 30486.585 | E15: 83121.49 | F15: 116960.94 | G15: 332860.55 | I15: 87674.862 | J15: 129367.32 | K15: 145472.35 | L15: 232456.28 | M15: 594970.82 | O15: 88610.864 | P15: 120509.61 | Q15: 163777.57 | R15: 167038.13 | S15: 539936.16 | U15: 110813 | V15: 135702.91 | W15: 176178.35 | X15: 263268.69 | Y15: 685962.96 | AA15: 121744.84 | AB15: 179969.29 | AC15: 191443.81 | AD15: 237495.09 | AE15: 730653.03 | AG15: 134804.3 | AH15: 183741.32 | AI15: 212345.07 | AJ15: 260169.68 | AK15: 791060.36 | AM15: 138860.55 | AN15: 145731.52 | AO15: 153926.77 | AP15: 218501.36 | AQ15: 657020.2 | AS15: 162844.79 | AT15: 183303.47 | AU15: 198876.38 | AV15: 253834.98 | AW15: =SUM(AS15:AV15) -> 798859.62 | AY15: 206463.61 | AZ15: 264152.96 | BA15: 265377.68 | BB15: 243520.28 | BC15: 979514.52 | BE15: 274752.32 | BF15: 237863.59 | BG15: 263335.17 | BH15: 275147.55 | BI15: 1051098.6 | BK15: 242061.23 | BL15: 233823.44 | BM15: 289341.5 | BN15: 263467.92 | BO15: 1028694.1
A16: Indirect taxes | B16: a. Pajak Tidak Langsung | C16: 141907.81 | D16: 166338.54 | E16: 177874.9 | F16: 212593.64 | G16: 698714.88 | I16: 135782.99 | J16: 161525.13 | K16: 194205.36 | L16: 257925.69 | M16: 749439.17 | O16: 109436.5 | P16: 163089.5 | Q16: 188182.12 | R16: 218646.85 | S16: 679354.97 | U16: 124395.43 | V16: 171580.15 | W16: 205100.13 | X16: 318727.77 | Y16: 819803.48 | AA16: 137841.53 | AB16: 216441.44 | AC16: 232450 | AD16: 320995.89 | AE16: 907728.86 | AG16: 155109.49 | AH16: 231657.21 | AI16: 256785.25 | AJ16: 326196.27 | AK16: 969748.22 | AM16: 158451.32 | AN16: 187237.86 | AO16: 187918.26 | AP16: 272304.62 | AQ16: 805912.05 | AS16: 183883.98 | AT16: 223141.84 | AU16: 239722.41 | AV16: 321309.54 | AW16: =SUM(AS16:AV16) -> 968057.77 | AY16: 240691.4 | AZ16: 313744.97 | BA16: 323981.14 | BB16: 315737.33 | BC16: 1194154.8 | BE16: 299666.98 | BF16: 290233.21 | BG16: 307731.95 | BH16: 370981.28 | BI16: 1268613.4 | BK16: 270183.61 | BL16: 286649.14 | BM16: 359032.46 | BN16: 347947.34 | BO16: 1263812.6
A17: Subsidy | B17: b. Subsidi | C17: 39616.27 | D17: 135851.95 | E17: 94753.411 | F17: 95632.699 | G17: 365854.33 | I17: 48108.131 | J17: 32157.807 | K17: 48733.009 | L17: 25469.41 | M17: 154468.36 | O17: 20825.636 | P17: 42579.898 | Q17: 24404.548 | R17: 51608.727 | S17: 139418.81 | U17: 13582.43 | V17: 35877.233 | W17: 28921.773 | X17: 55459.08 | Y17: 133840.52 | AA17: 16096.691 | AB17: 36472.147 | AC17: 41006.189 | AD17: 83500.804 | AE17: 177075.83 | AG17: 20305.194 | AH17: 47915.887 | AI17: 44440.187 | AJ17: 66026.594 | AK17: 178687.86 | AM17: 19590.767 | AN17: 41506.34 | AO17: 33991.485 | AP17: 53803.263 | AQ17: 148891.85 | AS17: 21039.188 | AT17: 39838.373 | AU17: 40846.031 | AV17: 67474.562 | AW17: =SUM(AS17:AV17) -> 169198.15 | AY17: 34227.791 | AZ17: 49592.01 | BA17: 58603.463 | BB17: 72217.059 | BC17: 214640.32 | BE17: 24914.654 | BF17: 52369.627 | BG17: 44396.78 | BH17: 95833.736 | BI17: 217514.8 | BK17: 28122.374 | BL17: 52825.705 | BM17: 69690.962 | BN17: 84479.419 | BO17: 235118.46
A19: Less depreciation | B19: 5. Dikurangi Penyusutan | C19: 492629.85 | D19: 492629.85 | E19: 492629.85 | F19: 492629.85 | G19: 1970519.4 | I19: 532359.55 | J19: 532359.55 | K19: 532359.55 | L19: 532359.55 | M19: 2129438.2 | O19: 537503.12 | P19: 493457.11 | Q19: 508494.71 | R19: 496234.45 | S19: 2035689.4 | U19: 544279.01 | V19: 603991.19 | W19: 631021.23 | X19: 651646 | Y19: 2430937.4 | AA19: 632063.02 | AB19: 680456.15 | AC19: 733280.71 | AD19: 754230.33 | AE19: 2800030.2 | AG19: 755612.38 | AH19: 773271.26 | AI19: 820470.28 | AJ19: 818747.21 | AK19: 3168101.1 | AM19: 847342.33 | AN19: 677857.62 | AO19: 700337.84 | AP19: 718267.21 | AQ19: 2943805 | AS19: 766637.78 | AT19: 758413.02 | AU19: 785163.52 | AV19: 836194.78 | AW19: =SUM(AS19:AV19) -> 3146409.1 | AY19: 884430.52 | AZ19: 900088.01 | BA19: 915489.23 | BB19: 986036.62 | BC19: 3686044.4 | BE19: 1015112.3 | BF19: 1029237.1 | BG19: 1023909.2 | BH19: 1070046.1 | BI19: 4138304.5 | BK19: 1078127.5 | BL19: 1096673.1 | BM19: 1103853.4 | BN19: 1147605.2 | BO19: 4426259.2
A21: National Income | B21: 6. PENDAPATAN NASIONAL | C21: 1825233.1 | D21: 2003369.6 | E21: 2084433.5 | F21: 1998896 | G21: 7911932.2 | I21: 2016542.9 | J21: 2110470.2 | K21: 2208838.3 | L21: 2083732.6 | M21: 8419584 | O21: 2203964.5 | P21: 2352764.3 | Q21: 2425342.5 | R21: 2447018.6 | S21: 9429089.9 | U21: 2470635 | V21: 2517620.4 | W21: 2582318.4 | X21: 2471745.6 | Y21: 10042320 | AA21: 2655825.1 | AB21: 2713154.8 | AC21: 2800431.5 | AD21: 2696477.6 | AE21: 10865889 | AG21: 2776483.8 | AH21: 2879269.7 | AI21: 2914695.7 | AJ21: 2821725.5 | AK21: 11392175 | AM21: 2823737.9 | AN21: 2773759.8 | AO21: 2933927.3 | AP21: 2887055.6 | AQ21: 11418481 | AS21: 2946923.5 | AT21: 3119869.6 | AU21: 3223451.6 | AV21: 3280341.2 | AW21: =SUM(AS21:AV21) -> 12570586 | AY21: 3306046.6 | AZ21: 3601762.1 | BA21: 3751767.4 | BB21: 3734226.3 | BC21: 14393802 | BE21: 3644880.7 | BF21: 3816646.5 | BG21: 3874889.8 | BH21: 3814210.6 | BI21: 15150628 | BK21: 3827270.9 | BL21: 4049111.2 | BM21: 4104286 | BN21: 4118903.5 | BO21: 16099571

Sheet SUT (Rasio Penyediaan)
A1: SUT | B1: 2010 | C1: 2016 | D1: 2019 | E1: 2020 | F1: 2021
A2: PDB (P) -> Total NTB | B2: 6683679717 | C2: 1.2171368e+10 | D2: 1.5346957e+10 | E2: 1.5049222e+10 | F2: 1.6342833e+10
A3: TOP SOP | B3: 180453318 | C3: 4.7445005e+08 | D3: 6.3746209e+08 | E3: 5.7129477e+08 | F3: 7.1906341e+08
A4: Output domestik | B4: 13109120481 | C4: 2.3230338e+10 | D4: 2.9585178e+10 | E4: 2.8700251e+10 | F4: 3.1335746e+10
A5: Rasio Output | B5: =B4/(B2+B3) -> 1.9097999 | C5: =C4/(C2+C3) -> 1.8369977 | D5: =D4/(D2+D3) -> 1.850876 | E5: =E4/(E2+E3) -> 1.8373432 | F5: =F4/(F2+F3) -> 1.8365922

Sheet Penyediaan
A2: Kegiatan Ekonomi | B2: =E2-1 -> 2014 | E2: ='PDB ADHB'!C1 -> 2015 | H2: ='PDB ADHB'!D1 -> 2016 | K2: ='PDB ADHB'!E1 -> 2017 | N2: ='PDB ADHB'!F1 -> 2018 | Q2: ='PDB ADHB'!G1 -> 2019 | T2: ='PDB ADHB'!H1 -> 2020 | W2: ='PDB ADHB'!I1 -> 2021 | Z2: ='PDB ADHB'!J1 -> 2022 | AC2: ='PDB ADHB'!K1 -> 2023* | AF2: ='PDB ADHB'!L1 -> 2024**
B3: Total Penyediaan | C3: Total Penggunaan | D3: Produk Domestik Bruto | E3: Total Penyediaan | F3: Total Penggunaan | G3: Produk Domestik Bruto | H3: Total Penyediaan | I3: Total Penggunaan | J3: Produk Domestik Bruto | K3: Total Penyediaan | L3: Total Penggunaan | M3: Produk Domestik Bruto | N3: Total Penyediaan | O3: Total Penggunaan | P3: Produk Domestik Bruto | Q3: Total Penyediaan | R3: Total Penggunaan | S3: Produk Domestik Bruto | T3: Total Penyediaan | U3: Total Penggunaan | V3: Produk Domestik Bruto | W3: Total Penyediaan | X3: Total Penggunaan | Y3: Produk Domestik Bruto | Z3: Total Penyediaan | AA3: Total Penggunaan | AB3: Produk Domestik Bruto | AC3: Total Penyediaan | AD3: Total Penggunaan | AE3: Produk Domestik Bruto | AF3: Total Penyediaan | AG3: Total Penggunaan | AH3: Produk Domestik Bruto
A4: Industri | B4: ='SUT (Rasio Penyediaan)'!$B$5*D4 -> 20186022 | C4: =B4-D4 -> 9616316.7 | D4: ='PDB ADHB'!B37 -> 10569705 | E4: ='SUT (Rasio Penyediaan)'!$B$5*G4 -> 22012989 | F4: =E4-G4 -> 10486656 | G4: ='PDB ADHB'!C37 -> 11526333 | H4: ='SUT (Rasio Penyediaan)'!$C$5*J4 -> 22781947 | I4: =H4-J4 -> 10380218 | J4: ='PDB ADHB'!D37 -> 12401728 | K4: ='SUT (Rasio Penyediaan)'!$C$5*M4 -> 24964479 | L4: =K4-M4 -> 11374653 | M4: ='PDB ADHB'!E37 -> 13589826 | N4: ='SUT (Rasio Penyediaan)'!$C$5*P4 -> 27258761 | O4: =N4-P4 -> 12420005 | P4: ='PDB ADHB'!F37 -> 14838756 | Q4: ='SUT (Rasio Penyediaan)'!$D$5*S4 -> 29304285 | R4: =Q4-S4 -> 13471628 | S4: ='PDB ADHB'!G37 -> 15832657 | T4: ='SUT (Rasio Penyediaan)'!$E$5*V4 -> 28374740 | U4: =T4-V4 -> 12931387 | V4: ='PDB ADHB'!H37 -> 15443353 | W4: ='SUT (Rasio Penyediaan)'!$F$5*Y4 -> 31179368 | X4: =W4-Y4 -> 14202617 | Y4: ='PDB ADHB'!I37 -> 16976751 | Z4: ='SUT (Rasio Penyediaan)'!$F$5*AB4 -> 35976012 | AA4: =Z4-AB4 -> 16387552 | AB4: ='PDB ADHB'!J37 -> 19588460 | AC4: ='SUT (Rasio Penyediaan)'!$F$5*AE4 -> 38370723 | AD4: =AC4-AE4 -> 17478375 | AE4: ='PDB ADHB'!K37 -> 20892348 | AF4: ='SUT (Rasio Penyediaan)'!$F$5*AH4 -> 40660248 | AG4: =AF4-AH4 -> 18521284 | AH4: ='PDB ADHB'!L37 -> 22138964
A5: Konsumsi Akhir | C5: ='PDB ADHB'!B6+'PDB ADHB'!B14+'PDB ADHB'!B15 -> 7035633.7 | F5: ='PDB ADHB'!C6+'PDB ADHB'!C14+'PDB ADHB'!C15 -> 7745630.1 | I5: ='PDB ADHB'!D6+'PDB ADHB'!D14+'PDB ADHB'!D15 -> 8353136 | L5: ='PDB ADHB'!E6+'PDB ADHB'!E14+'PDB ADHB'!E15 -> 9023120.3 | O5: ='PDB ADHB'!F6+'PDB ADHB'!F14+'PDB ADHB'!F15 -> 9793746.3 | R5: ='PDB ADHB'!G6+'PDB ADHB'!G14+'PDB ADHB'!G15 -> 10566547 | U5: ='PDB ADHB'!H6+'PDB ADHB'!H14+'PDB ADHB'!H15 -> 10592541 | X5: ='PDB ADHB'!I6+'PDB ADHB'!I14+'PDB ADHB'!I15 -> 11013796 | AA5: ='PDB ADHB'!J6+'PDB ADHB'!J14+'PDB ADHB'!J15 -> 11896997 | AD5: ='PDB ADHB'!K6+'PDB ADHB'!K14+'PDB ADHB'!K15 -> 12928272 | AG5: ='PDB ADHB'!L6+'PDB ADHB'!L14+'PDB ADHB'!L15 -> 13976578
A6: Akumulasi | C6: ='PDB ADHB'!B18+'PDB ADHB'!B25+'PDB ADHB'!B36 -> 3613154.8 | F6: ='PDB ADHB'!C18+'PDB ADHB'!C25+'PDB ADHB'!C36 -> 3736589.3 | I6: ='PDB ADHB'!D18+'PDB ADHB'!D25+'PDB ADHB'!D36 -> 3954755.4 | L6: ='PDB ADHB'!E18+'PDB ADHB'!E25+'PDB ADHB'!E36 -> 4430927.9 | O6: ='PDB ADHB'!F18+'PDB ADHB'!F25+'PDB ADHB'!F36 -> 5203608.7 | R6: ='PDB ADHB'!G18+'PDB ADHB'!G25+'PDB ADHB'!G36 -> 5336521.6 | U6: ='PDB ADHB'!H18+'PDB ADHB'!H25+'PDB ADHB'!H36 -> 4589794.8 | X6: ='PDB ADHB'!I18+'PDB ADHB'!I25+'PDB ADHB'!I36 -> 5516746.8 | AA6: ='PDB ADHB'!J18+'PDB ADHB'!J25+'PDB ADHB'!J36 -> 6997805.3 | AD6: ='PDB ADHB'!K18+'PDB ADHB'!K25+'PDB ADHB'!K36 -> 7510418.7 | AG6: ='PDB ADHB'!L18+'PDB ADHB'!L25+'PDB ADHB'!L36 -> 7765217.9
A7: Luar Negeri | B7: ='PDB ADHB'!B31 -> 2580508 | C7: ='PDB ADHB'!B26 -> 2501424.8 | E7: ='PDB ADHB'!C31 -> 2394879.3 | F7: ='PDB ADHB'!C26 -> 2438992.7 | H7: ='PDB ADHB'!D31 -> 2273528 | I7: ='PDB ADHB'!D26 -> 2367365.2 | K7: ='PDB ADHB'!E31 -> 2606283 | L7: ='PDB ADHB'!E26 -> 2742060.5 | N7: ='PDB ADHB'!F31 -> 3275145.3 | O7: ='PDB ADHB'!F26 -> 3116546.3 | Q7: ='PDB ADHB'!G31 -> 3013944.2 | R7: ='PDB ADHB'!G26 -> 2943532.9 | T7: ='PDB ADHB'!H31 -> 2415496 | U7: ='PDB ADHB'!H26 -> 2676513.5 | W7: ='PDB ADHB'!I31 -> 3189626.5 | X7: ='PDB ADHB'!I26 -> 3635835.4 | Z7: ='PDB ADHB'!J31 -> 4106085.7 | AA7: ='PDB ADHB'!J26 -> 4799743 | AC7: ='PDB ADHB'!K31 -> 4091231.5 | AD7: ='PDB ADHB'!K26 -> 4544889.6 | AF7: ='PDB ADHB'!L31 -> 4513987.4 | AG7: ='PDB ADHB'!L26 -> 4911155.7
A8: Total | B8: =SUM(B4:B7) -> 22766530 | C8: =SUM(C4:C7) -> 22766530 | E8: =SUM(E4:E7) -> 24407868 | F8: =SUM(F4:F7) -> 24407868 | H8: =SUM(H4:H7) -> 25055475 | I8: =SUM(I4:I7) -> 25055475 | K8: =SUM(K4:K7) -> 27570762 | L8: =SUM(L4:L7) -> 27570762 | N8: =SUM(N4:N7) -> 30533906 | O8: =SUM(O4:O7) -> 30533906 | Q8: =SUM(Q4:Q7) -> 32318229 | R8: =SUM(R4:R7) -> 32318229 | T8: =SUM(T4:T7) -> 30790236 | U8: =SUM(U4:U7) -> 30790236 | W8: =SUM(W4:W7) -> 34368995 | X8: =SUM(X4:X7) -> 34368995 | Z8: =SUM(Z4:Z7) -> 40082097 | AA8: =SUM(AA4:AA7) -> 40082097 | AC8: =SUM(AC4:AC7) -> 42461955 | AD8: =SUM(AD4:AD7) -> 42461955 | AF8: =SUM(AF4:AF7) -> 45174235 | AG8: =SUM(AG4:AG7) -> 45174235
A11: *LK Stok Kapital untuk based tahun 2005

Sheet Stok Kapital
A2: Kegiatan Ekonomi | B2: =J2-1 -> 2014 | J2: ='PDB ADHB'!C1 -> 2015 | R2: ='PDB ADHB'!D1 -> 2016 | Z2: ='PDB ADHB'!E1 -> 2017 | AH2: ='PDB ADHB'!F1 -> 2018 | AP2: ='PDB ADHB'!G1 -> 2019 | AX2: ='PDB ADHB'!H1 -> 2020 | BF2: ='PDB ADHB'!I1 -> 2021 | BN2: ='PDB ADHB'!J1 -> 2022 | BV2: ='PDB ADHB'!K1 -> 2023* | CD2: ='PDB ADHB'!L1 -> 2024**
B3: 1. Stok Awal | C3: 2. Total penyediaan | D3: 3. Total Penggunaan | E3: 4. Produk Domestik Bruto | F3: 5. Penyusutan | G3: 6. Produksi Domestik Neto | H3: 7. Revaluasi | I3: 8. Stok Akhir | J3: 1. Stok Awal | K3: 2. Total penyediaan | L3: 3. Total Penggunaan | M3: 4. Produk Domestik Bruto | N3: 5. Penyusutan | O3: 6. Produksi Domestik Neto | P3: 7. Revaluasi | Q3: 8. Stok Akhir | R3: 1. Stok Awal | S3: 2. Total penyediaan | T3: 3. Total Penggunaan | U3: 4. Produk Domestik Bruto | V3: 5. Penyusutan | W3: 6. Produksi Domestik Neto | X3: 7. Revaluasi | Y3: 8. Stok Akhir | Z3: 1. Stok Awal | AA3: 2. Total penyediaan | AB3: 3. Total Penggunaan | AC3: 4. Produk Domestik Bruto | AD3: 5. Penyusutan | AE3: 6. Produksi Domestik Neto | AF3: 7. Revaluasi | AG3: 8. Stok Akhir | AH3: 1. Stok Awal | AI3: 2. Total penyediaan | AJ3: 3. Total Penggunaan | AK3: 4. Produk Domestik Bruto | AL3: 5. Penyusutan | AM3: 6. Produksi Domestik Neto | AN3: 7. Revaluasi | AO3: 8. Stok Akhir | AP3: 1. Stok Awal | AQ3: 2. Total penyediaan | AR3: 3. Total Penggunaan | AS3: 4. Produk Domestik Bruto | AT3: 5. Penyusutan | AU3: 6. Produksi Domestik Neto | AV3: 7. Revaluasi | AW3: 8. Stok Akhir | AX3: 1. Stok Awal | AY3: 2. Total penyediaan | AZ3: 3. Total Penggunaan | BA3: 4. Produk Domestik Bruto | BB3: 5. Penyusutan | BC3: 6. Produksi Domestik Neto | BD3: 7. Revaluasi | BE3: 8. Stok Akhir | BF3: 1. Stok Awal | BG3: 2. Total penyediaan | BH3: 3. Total Penggunaan | BI3: 4. Produk Domestik Bruto | BJ3: 5. Penyusutan | BK3: 6. Produksi Domestik Neto | BL3: 7. Revaluasi | BM3: 8. Stok Akhir | BN3: 1. Stok Awal | BO3: 2. Total penyediaan | BP3: 3. Total Penggunaan | BQ3: 4. Produk Domestik Bruto | BR3: 5. Penyusutan | BS3: 6. Produksi Domestik Neto | BT3: 7. Revaluasi | BU3: 8. Stok Akhir | BV3: 1. Stok Awal | BW3: 2. Total penyediaan | BX3: 3. Total Penggunaan | BY3: 4. Produk Domestik Bruto | BZ3: 5. Penyusutan | CA3: 6. Produksi Domestik Neto | CB3: 7. Revaluasi | CC3: 8. Stok Akhir | CD3: 1. Stok Awal | CE3: 2. Total penyediaan | CF3: 3. Total Penggunaan | CG3: 4. Produk Domestik Bruto | CH3: 5. Penyusutan | CI3: 6. Produksi Domestik Neto | CJ3: 7. Revaluasi | CK3: 8. Stok Akhir
B4: Barang Modal | I4: Barang Modal | J4: Barang Modal | Q4: Barang Modal | R4: Barang Modal | Y4: Barang Modal | Z4: Barang Modal | AG4: Barang Modal | AH4: Barang Modal | AO4: Barang Modal | AP4: Barang Modal | AW4: Barang Modal | AX4: Barang Modal | BE4: Barang Modal | BF4: Barang Modal | BM4: Barang Modal | BN4: Barang Modal | BU4: Barang Modal | BV4: Barang Modal | CC4: Barang Modal | CD4: Barang Modal | CK4: Barang Modal
A5: Industri | C5: =Penyediaan!B4 -> 20186022 | D5: =Penyediaan!C4 -> 9616316.7 | E5: =Penyediaan!D4 -> 10569705 | F5: =Penyusutan!G19 -> 1970519.4 | G5: =E5-F5 -> 8599185.9 | K5: =Penyediaan!E4 -> 22012989 | L5: =Penyediaan!F4 -> 10486656 | M5: =Penyediaan!G4 -> 11526333 | N5: =Penyusutan!M19 -> 2129438.2 | O5: =M5-N5 -> 9396894.6 | S5: =Penyediaan!H4 -> 22781947 | T5: =Penyediaan!I4 -> 10380218 | U5: =Penyediaan!J4 -> 12401728 | V5: =Penyusutan!S19 -> 2035689.4 | W5: =U5-V5 -> 10366039 | AA5: =Penyediaan!K4 -> 24964479 | AB5: =Penyediaan!L4 -> 11374653 | AC5: =Penyediaan!M4 -> 13589826 | AD5: =Penyusutan!Y19 -> 2430937.4 | AE5: =AC5-AD5 -> 11158888 | AI5: =Penyediaan!N4 -> 27258761 | AJ5: =Penyediaan!O4 -> 12420005 | AK5: =Penyediaan!P4 -> 14838756 | AL5: =Penyusutan!AE19 -> 2800030.2 | AM5: =AK5-AL5 -> 12038726 | AQ5: =Penyediaan!Q4 -> 29304285 | AR5: =Penyediaan!R4 -> 13471628 | AS5: =Penyediaan!S4 -> 15832657 | AT5: =Penyusutan!AK19 -> 3168101.1 | AU5: =AS5-AT5 -> 12664556 | AY5: =Penyediaan!T4 -> 28374740 | AZ5: =Penyediaan!U4 -> 12931387 | BA5: =Penyediaan!V4 -> 15443353 | BB5: =Penyusutan!AQ19 -> 2943805 | BC5: =BA5-BB5 -> 12499548 | BG5: =Penyediaan!W4 -> 31179368 | BH5: =Penyediaan!X4 -> 14202617 | BI5: =Penyediaan!Y4 -> 16976751 | BJ5: =Penyusutan!AW19 -> 3146409.1 | BK5: =BI5-BJ5 -> 13830342 | BO5: =Penyediaan!Z4 -> 35976012 | BP5: =Penyediaan!AA4 -> 16387552 | BQ5: =Penyediaan!AB4 -> 19588460 | BR5: =Penyusutan!BC19 -> 3686044.4 | BS5: =BQ5-BR5 -> 15902416 | BW5: =Penyediaan!AC4 -> 38370723 | BX5: =Penyediaan!AD4 -> 17478375 | BY5: =Penyediaan!AE4 -> 20892348 | BZ5: =Penyusutan!BI19 -> 4138304.5 | CA5: =BY5-BZ5 -> 16754044 | CE5: =Penyediaan!AF4 -> 40660248 | CF5: =Penyediaan!AG4 -> 18521284 | CG5: =Penyediaan!AH4 -> 22138964 | CH5: =Penyusutan!BO19 -> 4426259.2 | CI5: =CG5-CH5 -> 17712705
A6: Konsumsi Akhir | D6: =Penyediaan!C5 -> 7035633.7 | L6: =Penyediaan!F5 -> 7745630.1 | T6: =Penyediaan!I5 -> 8353136 | AB6: =Penyediaan!L5 -> 9023120.3 | AJ6: =Penyediaan!O5 -> 9793746.3 | AR6: =Penyediaan!R5 -> 10566547 | AZ6: =Penyediaan!U5 -> 10592541 | BH6: =Penyediaan!X5 -> 11013796 | BP6: =Penyediaan!AA5 -> 11896997 | BX6: =Penyediaan!AD5 -> 12928272 | CF6: =Penyediaan!AG5 -> 13976578
A7: Akumulasi Kapital yang Diproduksi | B7: 33313961 | D7: =Penyediaan!C6 -> 3613154.8 | F7: =-F5 -> -1970519.4 | G7: =D7+F7 -> 1642635.4 | H7: =I7-B7-G7 -> 3145856.7 | I7: 38102453 | J7: =I7 -> 38102453 | L7: =Penyediaan!F6 -> 3736589.3 | N7: =-N5 -> -2129438.2 | O7: =L7+N7 -> 1607151.1 | P7: =Q7-J7-O7 -> 1914113.9 | Q7: 41623718 | R7: =Q7 -> 41623718 | T7: =Penyediaan!I6 -> 3954755.4 | V7: =-V5 -> -2035689.4 | W7: =T7+V7 -> 1919066 | X7: =Y7-R7-W7 -> 1318339.4 | Y7: 44861123 | Z7: =Y7 -> 44861123 | AB7: =Penyediaan!L6 -> 4430927.9 | AD7: =-AD5 -> -2430937.4 | AE7: =AB7+AD7 -> 1999990.5 | AF7: =AG7-Z7-AE7 -> 2311045.3 | AG7: 49172159 | AH7: =AG7 -> 49172159 | AJ7: =Penyediaan!O6 -> 5203608.7 | AL7: =-AL5 -> -2800030.2 | AM7: =AJ7+AL7 -> 2403578.5 | AN7: =AO7-AH7-AM7 -> 2816519.2 | AO7: 54392257 | AP7: =AO7 -> 54392257 | AR7: =Penyediaan!R6 -> 5336521.6 | AT7: =-AT5 -> -3168101.1 | AU7: =AR7+AT7 -> 2168420.4 | AV7: =AW7-AP7-AU7 -> 1617443.7 | AW7: 58178121 | AX7: =AW7 -> 58178121 | AZ7: =Penyediaan!U6 -> 4589794.8 | BB7: =-BB5 -> -2943805 | BC7: =AZ7+BB7 -> 1645989.8 | BD7: =BE7-AX7-BC7 -> 1842694.6 | BE7: 61666805 | BF7: =BE7 -> 61666805 | BH7: =Penyediaan!X6 -> 5516746.8 | BJ7: =-BJ5 -> -3146409.1 | BK7: =BH7+BJ7 -> 2370337.7 | BL7: =BM7-BF7-BK7 -> 3659416.5 | BM7: 67696559 | BN7: =BM7 -> 67696559 | BP7: =Penyediaan!AA6 -> 6997805.3 | BR7: =-BR5 -> -3686044.4 | BS7: =BP7+BR7 -> 3311760.9 | BT7: =BU7-BN7-BS7 -> 3334636.5 | BU7: 74342957 | BV7: =BU7 -> 74342957 | BX7: =Penyediaan!AD6 -> 7510418.7 | BZ7: =-BZ5 -> -4138304.5 | CA7: =BX7+BZ7 -> 3372114.2 | CB7: =CC7-BV7-CA7 -> 2718562.5 | CC7: =BV7+'PDB ADHB'!K18 -> 80433633 | CD7: =CC7 -> 80433633 | CF7: =Penyediaan!AG6 -> 7765217.9 | CH7: =-CH5 -> -4426259.2 | CI7: =CF7+CH7 -> 3338958.7 | CJ7: =CK7-CD7-CI7 -> 3113572 | CK7: =CD7+'PDB ADHB'!L18 -> 86886164
A8: Luar Negeri | C8: =Penyediaan!B7 -> 2580508 | D8: =Penyediaan!C7 -> 2501424.8 | K8: =Penyediaan!E7 -> 2394879.3 | L8: =Penyediaan!F7 -> 2438992.7 | S8: =Penyediaan!H7 -> 2273528 | T8: =Penyediaan!I7 -> 2367365.2 | AA8: =Penyediaan!K7 -> 2606283 | AB8: =Penyediaan!L7 -> 2742060.5 | AI8: =Penyediaan!N7 -> 3275145.3 | AJ8: =Penyediaan!O7 -> 3116546.3 | AQ8: =Penyediaan!Q7 -> 3013944.2 | AR8: =Penyediaan!R7 -> 2943532.9 | AY8: =Penyediaan!T7 -> 2415496 | AZ8: =Penyediaan!U7 -> 2676513.5 | BG8: =Penyediaan!W7 -> 3189626.5 | BH8: =Penyediaan!X7 -> 3635835.4 | BO8: =Penyediaan!Z7 -> 4106085.7 | BP8: =Penyediaan!AA7 -> 4799743 | BW8: =Penyediaan!AC7 -> 4091231.5 | BX8: =Penyediaan!AD7 -> 4544889.6 | CE8: =Penyediaan!AF7 -> 4513987.4 | CF8: =Penyediaan!AG7 -> 4911155.7
A9: Total | C9: =Penyediaan!B8 -> 22766530 | D9: =Penyediaan!C8 -> 22766530 | K9: =Penyediaan!E8 -> 24407868 | L9: =Penyediaan!F8 -> 24407868 | S9: =Penyediaan!H8 -> 25055475 | T9: =Penyediaan!I8 -> 25055475 | AA9: =Penyediaan!K8 -> 27570762 | AB9: =Penyediaan!L8 -> 27570762 | AI9: =Penyediaan!N8 -> 30533906 | AJ9: =Penyediaan!O8 -> 30533906 | AQ9: =Penyediaan!Q8 -> 32318229 | AR9: =Penyediaan!R8 -> 32318229 | AY9: =Penyediaan!T8 -> 30790236 | AZ9: =Penyediaan!U8 -> 30790236 | BG9: =Penyediaan!W8 -> 34368995 | BH9: =Penyediaan!X8 -> 34368995 | BO9: =Penyediaan!Z8 -> 40082097 | BP9: =Penyediaan!AA8 -> 40082097 | BW9: =Penyediaan!AC8 -> 42461955 | BX9: =Penyediaan!AD8 -> 42461955 | CE9: =Penyediaan!AF8 -> 45174235 | CF9: =Penyediaan!AG8 -> 45174235
I10: =B7+'PDB ADHB'!B18 -> 36750884 | Q10: =J7+'PDB ADHB'!C18 -> 41884465 | Y10: =R7+'PDB ADHB'!D18 -> 45663919
A12: Sumber Data :
A13: 1. Stok Awal | CC13: =CC7+'PDB ADHB'!L18 -> 86886164 | CK13: =CK7+'PDB ADHB'!T18 -> 86886164
A14: - Barang Modal | D14: S. Akhir Thn sblmnya | BW14: =BU7-BN7 -> 6646397.4 | CE14: =CC7-BV7 -> 6090676.7
A15: 2. Total penyediaan | B15: Output PDB | E15: Impor
A16: 3. Total Penggunaan | B16: Penyedia - PDB | C16: Konsumsi RT + Pem | D16: PMTB + P. Stok+Deskrepancy | E16: Ekspor
A17: 4. Produk Domestik Bruto | B17: PDB
A18: 5. Penyusutan | B18: PDB(Penyusutan) | D18: - Penyusutan
A19: 6. Produksi Domestik Neto | B19: PDB - Penyusut | D19: Penggunaan + Penyusut
A20: 7. Revaluasi | D20: S.Akhir-S.Awal-PDN
A21: 8. Stok Akhir
A22: - Barang Modal | D22: S. Awal + PMTB
A24: Sumber Data :
A25: 1. Stok Awal
A26: - Barang Modal | D26: S. Akhir Thn sblmnya
A27: 2. Total penyediaan | B27: Output PDB | E27: Impor
A28: 3. Total Penggunaan | B28: Penyedia - PDB | C28: Konsumsi RT + Pem | D28: PMTB + P. Stok+Deskrepancy | E28: Ekspor
A29: 4. Produk Domestik Bruto | B29: PDB
A30: 5. Penyusutan | B30: PDB(Penyusutan) | D30: - Penyusutan
A31: 6. Produksi Domestik Neto | B31: PDB - Penyusut | D31: Penggunaan + Penyusut
A32: 7. Revaluasi | D32: S.Akhir-S.Awal-PDN | F32: Merupakan item balancing yang menunjukkan adanya perubahan harga barang modal di awal dan akhir tahun
A33: 8. Stok Akhir
A34: - Barang Modal | D34: S. Awal + PMTB | F34: Update: dihitungkan dan diberikan secara value oleh DNPeng, tapi karena 2023 belum tersedia makanya estimasi

Sheet Aset Moneter
A1: Aset Moneter dalam satuan miliar rupiah
A2: Hasil Hutan
A3: Rincian/Detail | D3: Tahun / Year
D4: =E4-1 -> 2014 | E4: ='PDB ADHB'!C1 -> 2015 | F4: ='PDB ADHB'!D1 -> 2016 | G4: ='PDB ADHB'!E1 -> 2017 | H4: ='PDB ADHB'!F1 -> 2018 | I4: ='PDB ADHB'!G1 -> 2019 | J4: ='PDB ADHB'!H1 -> 2020 | K4: ='PDB ADHB'!I1 -> 2021 | L4: ='PDB ADHB'!J1 -> 2022 | ... N4: ='PDB ADHB'!L1 -> 2024**
A5: -1 | D5: =A5-1 -> -2 | E5: =D5-1 -> -3 | F5: =E5-1 -> -4 | G5: =F5-1 -> -5 | H5: =G5-1 -> -6 | I5: =H5-1 -> -7 | J5: =I5-1 -> -8 | K5: =J5-1 -> -9 | L5: =J5-1 -> -9 | M5: =K5-1 -> -10 | N5: =L5-1 -> -10
A6: Stok awal tahun/Opening stock | D6: 701661.76 | E6: 719985.09 | F6: 628834.11 | G6: 681499.89 | H6: 749533.49 | I6: 740284 | J6: 818198.38 | K6: 952915.52 | L6: 1100095.7 | M6: 1173971.8 | N6: 1390349.6
A7: Penambahan stok/Additions to stock
A8: Pertumbuhan alami/Natural growth | D8: 4013.4808 | E8: 3927.0238 | F8: 4254.0726 | G8: 4901.6472 | H8: 5087.0422 | I8: 6109.567 | J8: 7281.4543 | K8: 7365.4623 | L8: 9402.4752 | M8: 12119.482 | N8: 11982.625
A9: Reklasifikasi/Reclassifications | D9: 1626.2872 | E9: 2284.5052 | F9: 2856.7213 | G9: 1401.2454 | H9: 1773.0106 | I9: 3075.1912 | J9: 3032.543 | K9: 1343.8434 | L9: 2447.6811 | M9: 2087.0909 | N9: 3715.5351
A10: Total penambahan/Total additions to stock | D10: 5639.768 | E10: 6211.529 | F10: 7110.7939 | G10: 6302.8926 | H10: 6860.0527 | I10: 9184.7582 | J10: 10313.997 | K10: 8709.3058 | L10: 11850.156 | M10: 14206.573 | N10: 15698.16
A11: Pengurangan stok/Reductions in stock
A12: Penebangan/Removals | D12: 6621.4561 | E12: 6545.6817 | F12: 7473.951 | G12: 8951.9533 | H12: 9094.5459 | I12: 11560.738 | J12: 14524.238 | K12: 15185.369 | L12: 20145.685 | M12: 27656.299 | N12: 26332.756
A13: Kerusakan dan Reklasifikasi/Losses and Reclassifiations | D13: 28141.491 | E13: 89344.514 | F13: 32133.043 | G13: 28424.101 | H13: 24829.202 | I13: 76926.656 | J13: 19002.634 | K13: 22902.56 | L13: 20409.484 | M13: 114856.7 | N13: 45836.176
A14: Total pengurangan/Total reductions in stock | D14: 34762.947 | E14: 95890.196 | F14: 39606.994 | G14: 37376.054 | H14: 33923.748 | I14: 88487.394 | J14: 33526.873 | K14: 38087.928 | L14: 40555.169 | M14: 142513 | N14: 72168.932
A15: Revaluasi/Revaluations | D15: 47446.501 | E15: -1472.309 | F15: 85161.98 | G15: 99106.76 | H15: 17814.209 | I15: 157217.01 | J15: 157930.02 | K15: 176558.81 | L15: 102581.11 | M15: 344684.22 | N15: -3840.5881
A16: Stok akhir tahun/Closing stock | D16: 719985.09 | E16: 628834.11 | F16: 681499.89 | G16: 749533.49 | H16: 740284 | I16: 818198.38 | J16: 952915.52 | K16: 1100095.7 | L16: 1173971.8 | M16: 1390349.6 | N16: 1330038.2
A18: Minyak Bumi
A19: Uraian Description | D19: Tahun / Year
D20: =E20-1 -> 2014 | E20: =E4 -> 2015 | F20: =F4 -> 2016 | G20: =G4 -> 2017 | H20: =H4 -> 2018 | I20: =I4 -> 2019 | J20: =J4 -> 2020 | K20: =K4 -> 2021 | L20: =L4 -> 2022 | ... N20: =N4 -> 2024**
A21: -1 | D21: =A21-1 -> -2 | E21: =D21-1 -> -3 | F21: =E21-1 -> -4 | G21: =F21-1 -> -5 | H21: =G21-1 -> -6 | I21: =H21-1 -> -7 | J21: =I21-1 -> -8 | K21: =J21-1 -> -9 | L21: =J21-1 -> -9 | M21: =K21-1 -> -10 | N21: =L21-1 -> -10
A22: Stok awal tahun Opening stock | D22: 2131738 | E22: 1936674 | F22: 1128616.9 | G22: 1038776.4 | H22: 1442786.8 | I22: 1827895.4 | J22: 1650482.1 | K22: 1232797.1 | L22: 1759477.5 | M22: 2275538.7 | N22: 1904383.6
A23: Ekstraksi Extraction | D23: -78448.958 | E23: -59816.752 | F23: -45283.89 | G23: -48952.527 | H23: -61277.109 | I23: -92568.191 | J23: -95012.345 | K23: -89111.472 | L23: -110761.69 | M23: -105018.04 | N23: -89462.611
A24: Perubahan lainnya Other changes in stock | D24: 30720.524 | E24: 45297.101 | F24: 37257.867 | G24: 95647.459 | H24: 57406.243 | I24: -1179312.2 | J24: 239454.88 | K24: 6989.5507 | L24: 223266.08 | M24: 354946.17 | N24: -74368.112
A25: Revaluasi Revaluation | D25: -147335.56 | E25: -793537.46 | F25: -81814.455 | G25: 357315.45 | H25: 388979.48 | I25: 1094467.2 | J25: -562127.59 | K25: 608802.28 | L25: 403556.83 | M25: -621083.24 | N25: 145800.33
A26: Stok akhir tahun Closing stock | D26: 1936674 | E26: 1128616.9 | F26: 1038776.4 | G26: 1442786.8 | H26: 1827895.4 | I26: 1650482.1 | J26: 1232797.1 | K26: 1759477.5 | L26: 2275538.7 | M26: 1904383.6 | N26: 1886353.2
A28: Gas Alam
A29: Uraian Description | D29: Tahun / Year
D30: =D20 -> 2014 | E30: =E20 -> 2015 | F30: =F20 -> 2016 | G30: =G20 -> 2017 | H30: =H20 -> 2018 | I30: =I20 -> 2019 | J30: =J20 -> 2020 | K30: =K20 -> 2021 | ... N30: =N20 -> 2024**
A31: -1 | D31: =A31-1 -> -2 | E31: =D31-1 -> -3 | F31: =E31-1 -> -4 | G31: =F31-1 -> -5 | H31: =G31-1 -> -6 | I31: =H31-1 -> -7 | J31: =I31-1 -> -8 | K31: =J31-1 -> -9 | L31: =J31-1 -> -9 | M31: =K31-1 -> -10 | N31: =L31-1 -> -10
A32: Stok awal tahun Opening stock | D32: 2209651.2 | E32: 1929560.4 | F32: 2092742.2 | G32: 2099174 | H32: 2081924.9 | I32: 1985652.1 | J32: 2088004.1 | K32: 2190729.9 | L32: 2571830.7 | M32: 3019060 | N32: 2672571.9
A33: Ekstraksi Extraction | D33: -43852.885 | E33: -41683.345 | F33: -43598.192 | G33: -40547.829 | H33: -43807.745 | I33: -58529.829 | J33: -75883.739 | K33: -94344.79 | L33: -115553.86 | M33: -125788.22 | N33: -123062.42
A34: Perubahan lainnya Other changes in stock | D34: 28780.916 | E34: 68857.884 | F34: -59637.711 | G34: 21011.296 | H34: -61004.503 | I34: -1155065.3 | J34: -387042.26 | K34: 25415.894 | L34: -166293.53 | M34: 122131.58 | N34: -14280.855
A35: Revaluasi Revaluation | D35: -265018.81 | E35: 136007.26 | F35: 109667.72 | G35: 2287.3592 | H35: 8539.4995 | I35: 1315947.1 | J35: 565651.8 | K35: 450029.71 | L35: 729076.67 | M35: -342831.44 | N35: 67246.415
A36: Stok akhir tahun Closing stock | D36: 1929560.4 | E36: 2092742.2 | F36: 2099174 | G36: 2081924.9 | H36: 1985652.1 | I36: 2088004.1 | J36: 2190729.9 | K36: 2571830.7 | L36: 3019060 | M36: 2672571.9 | N36: 2602475
A38: Batubara
A39: Uraian Description | D39: Tahun / Year
D40: =D30 -> 2014 | E40: =E30 -> 2015 | F40: =F30 -> 2016 | G40: =G30 -> 2017 | H40: =H30 -> 2018 | I40: =I30 -> 2019 | J40: =J30 -> 2020 | K40: =K30 -> 2021 | ... N40: =N30 -> 2024**
A41: -1 | D41: =A41-1 -> -2 | E41: =D41-1 -> -3 | F41: =E41-1 -> -4 | G41: =F41-1 -> -5 | H41: =G41-1 -> -6 | I41: =H41-1 -> -7 | J41: =I41-1 -> -8 | K41: =J41-1 -> -9 | L41: =J41-1 -> -9 | M41: =K41-1 -> -10 | N41: =L41-1 -> -10
A42: Stok awal tahun Opening stock | D42: 3124469.7 | E42: 2374378.3 | F42: 2534793.4 | G42: 2860161.4 | H42: 4126241.8 | I42: 4338434.3 | J42: 4057943.9 | K42: 3608155.4 | L42: 7098820.3 | M42: 15178689 | N42: 13539562
A43: Ekstraksi Extraction | D43: -39616.02 | E43: -35051.958 | F43: -40846.113 | G43: -62437.308 | H43: -79361.018 | I43: -68470.663 | J43: -56624.031 | K43: -88615.492 | L43: -216088.03 | M43: -333305.22 | N43: -306796.88
A44: Perubahan lainnya Other changes in stock | D44: 128481.76 | E44: 25858.496 | F44: -299962.97 | G44: -508445.66 | H44: 2029137.7 | I44: 30809.29 | J44: 177240.6 | K44: -276046.24 | L44: -168905.02 | M44: -1103022.6 | N44: 395572.41
A45: Revaluasi Revaluation | D45: -838957.18 | E45: 169608.56 | F45: 666177.16 | G45: 1836963.3 | H45: -1737584.1 | I45: -242829.04 | J45: -570405.06 | K45: 3855326.6 | L45: 8464861.7 | M45: -202799.1 | N45: -3820771.9
A46: Stok akhir tahun Closing stock | D46: 2374378.3 | E46: 2534793.4 | F46: 2860161.4 | G46: 4126241.8 | H46: 4338434.3 | I46: 4057943.9 | J46: 3608155.4 | K46: 7098820.3 | L46: 15178689 | M46: 13539562 | N46: 9807565.6
A48: Emas
A49: Uraian Description | D49: Tahun / Year
D50: =D40 -> 2014 | E50: =E40 -> 2015 | F50: =F40 -> 2016 | G50: =G40 -> 2017 | H50: =H40 -> 2018 | I50: =I40 -> 2019 | J50: =J40 -> 2020 | K50: =K40 -> 2021 | ... N50: =N40 -> 2024**
A51: -1 | D51: =A51-1 -> -2 | E51: =D51-1 -> -3 | F51: =E51-1 -> -4 | G51: =F51-1 -> -5 | H51: =G51-1 -> -6 | I51: =H51-1 -> -7 | J51: =I51-1 -> -8 | K51: =J51-1 -> -9 | L51: =J51-1 -> -9 | M51: =K51-1 -> -10 | N51: =L51-1 -> -10
A52: Stok awal tahun Opening stock | D52: 193839.94 | E52: 200366.45 | F52: 311024.64 | G52: 330729.39 | H52: 376606.06 | I52: 177537.95 | J52: 111404.04 | K52: 181971.97 | L52: 236975.2 | M52: 313647.4 | N52: 372761.02
A53: Ekstraksi Extraction | D53: -5059.7905 | E53: -9273.2681 | F53: -10760.668 | G53: -11196.82 | H53: -11043.246 | I53: -4937.9047 | J53: -3478.345 | K53: -7950.6586 | L53: -11260.468 | M53: -10682.966 | N53: -7392.9116
A54: Perubahan lainnya Other changes in stock | D54: -16505.264 | E54: 27233.919 | F54: -22.83822 | G54: 145291.44 | H54: -89672.462 | I54: 96748.804 | J54: -125099.91 | K54: -17200.765 | L54: 154066.26 | M54: 20270.474 | N54: 10521.526
A55: Revaluasi Revaluation | D55: 28091.564 | E55: 92697.544 | F55: 30488.252 | G55: -88217.946 | H55: -98352.408 | I55: -157944.8 | J55: 199146.18 | K55: 80154.659 | L55: -66133.6 | M55: 49526.108 | N55: 86041.101
A56: Stok akhir tahun Closing stock | D56: 200366.45 | E56: 311024.64 | F56: 330729.39 | G56: 376606.06 | H56: 177537.95 | I56: 111404.04 | J56: 181971.97 | K56: 236975.2 | L56: 313647.4 | M56: 372761.02 | N56: 461930.73
A58: Perak
A59: Uraian Description | D59: Tahun / Year
D60: =D50 -> 2014 | E60: =E50 -> 2015 | F60: =F50 -> 2016 | G60: =G50 -> 2017 | H60: =H50 -> 2018 | I60: =I50 -> 2019 | J60: =J50 -> 2020 | K60: =K50 -> 2021 | ... N60: =N50 -> 2024**
A61: -1 | D61: =A61-1 -> -2 | E61: =D61-1 -> -3 | F61: =E61-1 -> -4 | G61: =F61-1 -> -5 | H61: =G61-1 -> -6 | I61: =H61-1 -> -7 | J61: =I61-1 -> -8 | K61: =J61-1 -> -9 | L61: =J61-1 -> -9 | M61: =K61-1 -> -10 | N61: =L61-1 -> -10
A62: Stok awal tahun Opening stock | D62: 14354.02 | E62: 13473.768 | F62: 14780.666 | G62: 17318.011 | H62: 12622.997 | I62: 4957.2855 | J62: 5269.9371 | K62: 5627.0929 | L62: 5993.334 | M62: 5023.8836 | N62: 6092.4315
A63: Ekstraksi Extraction | D63: -250.22465 | E63: -334.54615 | F63: -385.03321 | G63: -571.09266 | H63: -400.903 | I63: -189.63674 | J63: -154.80963 | K63: -194.87779 | L63: -144.34519 | M63: -38.460002 | N63: -97.735409
A64: Perubahan lainnya Other changes in stock | D64: 241.21712 | E64: -731.03787 | F64: 1337.6063 | G64: -13578.289 | H64: 10139.075 | I64: 170.35248 | J64: -591.78401 | K64: 236.99735 | L64: 10505.26 | M64: -170.29361 | N64: 86.15016
A65: Revaluasi Revaluation | D65: -871.24425 | E65: 2372.482 | F65: 1584.7716 | G65: 9454.3675 | H65: -17403.883 | I65: 331.93582 | J65: 1103.7495 | K65: 324.12151 | L65: -11330.365 | M65: 1277.3015 | N65: 3164.2239
A66: Stok akhir tahun Closing stock | D66: 13473.768 | E66: 14780.666 | F66: 17318.011 | G66: 12622.997 | H66: 4957.2855 | I66: 5269.9371 | J66: 5627.0929 | K66: 5993.334 | L66: 5023.8836 | M66: 6092.4315 | N66: 9245.0701
A68: Tembaga
A69: Uraian Description | D69: Tahun / Year
D70: =D60 -> 2014 | E70: =E60 -> 2015 | F70: =F60 -> 2016 | G70: =G60 -> 2017 | H70: =H60 -> 2018 | I70: =I60 -> 2019 | J70: =J60 -> 2020 | K70: =K60 -> 2021 | ... N70: =N60 -> 2024**
A71: -1 | D71: =A71-1 -> -2 | E71: =D71-1 -> -3 | F71: =E71-1 -> -4 | G71: =F71-1 -> -5 | H71: =G71-1 -> -6 | I71: =H71-1 -> -7 | J71: =I71-1 -> -8 | K71: =J71-1 -> -9 | L71: =J71-1 -> -9 | M71: =K71-1 -> -10 | N71: =L71-1 -> -10
A72: Stok awal tahun Opening stock | D72: 369717.06 | E72: 220254.27 | F72: 172752.29 | G72: 195241.87 | H72: 228644.7 | I72: 243466.58 | J72: 182470.54 | K72: 603209.49 | L72: 925405.54 | M72: 1018188.9 | N72: 1137311.4
A73: Ekstraksi Extraction | D73: -11086.795 | E73: -6631.2044 | F73: -6970.8953 | G73: -7788.1186 | H73: -7258.6491 | I73: -4866.3659 | J73: -10871.394 | K73: -28116.166 | L73: -66743.604 | M73: -68937.059 | N73: -81347.171
A74: Perubahan lainnya Other changes in stock | D74: 5068.6222 | E74: 66.508588 | F74: 16245.212 | G74: -32152.036 | H74: -7186.1077 | I74: 14163.968 | J74: 17497.747 | K74: -124011.67 | L74: 83889.044 | M74: 126764.04 | N74: 76571.361
A75: Revaluasi Revaluation | D75: -143444.61 | E75: -40937.29 | F75: 13215.261 | G75: 73342.992 | H75: 29266.635 | I75: -70293.646 | J75: 414112.6 | K75: 474323.88 | L75: 75637.958 | M75: 61295.529 | N75: 131958.55
A76: Stok akhir tahun Closing stock | D76: 220254.27 | E76: 172752.29 | F76: 195241.87 | G76: 228644.7 | H76: 243466.58 | I76: 182470.54 | J76: 603209.49 | K76: 925405.54 | L76: 1018188.9 | M76: 1137311.4 | N76: 1264494.2
A78: Timah
A79: Uraian Description | D79: Tahun / Year
D80: =D70 -> 2014 | E80: =E70 -> 2015 | F80: =F70 -> 2016 | G80: =G70 -> 2017 | H80: =H70 -> 2018 | I80: =I70 -> 2019 | J80: =J70 -> 2020 | K80: =K70 -> 2021 | ... N80: =N70 -> 2024**
A81: -1 | D81: =A81-1 -> -2 | E81: =D81-1 -> -3 | F81: =E81-1 -> -4 | G81: =F81-1 -> -5 | H81: =G81-1 -> -6 | I81: =H81-1 -> -7 | J81: =I81-1 -> -8 | K81: =J81-1 -> -9 | L81: =J81-1 -> -9 | M81: =K81-1 -> -10 | N81: =L81-1 -> -10
A82: Stok awal tahun Opening stock | D82: 73799.752 | E82: 33762.4 | F82: 50123.665 | G82: 75206.158 | H82: 78627.703 | I82: 115623.7 | J82: 128560.7 | K82: 185956.97 | L82: 300256.29 | M82: 378436.44 | N82: 436324.54
A83: Ekstraksi Extraction | D83: -11714.077 | E83: -7263.6783 | F83: -5407.5495 | G83: -7830.3711 | H83: -6773.7646 | I83: -3994.7881 | J83: -3417.0025 | K83: -3599.1709 | L83: -8616.7529 | M83: -17415.351 | N83: -13740.702
A84: Perubahan lainnya Other changes in stock | D84: 13491.352 | E84: 37365.684 | F84: 32792.605 | G84: -13629.008 | H84: 152190.17 | I84: -7813.5355 | J84: 34080.104 | K84: -53761.498 | L84: 21071.259 | M84: -196962.04 | N84: 38299.817
A85: Revaluasi Revaluation | D85: -41814.627 | E85: -13740.74 | F85: -2302.5638 | G85: 24880.925 | H85: -108420.41 | I85: 24745.321 | J85: 26733.172 | K85: 171659.99 | L85: 65725.64 | M85: 272265.49 | N85: 73116.428
A86: Stok akhir tahun Closing stock | D86: 33762.4 | E86: 50123.665 | F86: 75206.158 | G86: 78627.703 | H86: 115623.7 | I86: 128560.7 | J86: 185956.97 | K86: 300256.29 | L86: 378436.44 | M86: 436324.54 | N86: 534000.08
A88: Nikel
A89: Uraian Description | D89: Tahun / Year
D90: =D80 -> 2014 | E90: =E80 -> 2015 | F90: =F80 -> 2016 | G90: =G80 -> 2017 | H90: =H80 -> 2018 | I90: =I80 -> 2019 | J90: =J80 -> 2020 | K90: =K80 -> 2021 | ... N90: =N80 -> 2024**
A91: -1 | D91: =A91-1 -> -2 | E91: =D91-1 -> -3 | F91: =E91-1 -> -4 | G91: =F91-1 -> -5 | H91: =G91-1 -> -6 | I91: =H91-1 -> -7 | J91: =I91-1 -> -8 | K91: =J91-1 -> -9 | L91: =J91-1 -> -9 | M91: =K91-1 -> -10 | N91: =L91-1 -> -10
A92: Stok awal tahun Opening stock | D92: 72154.565 | E92: 97741.009 | F92: 151551.61 | G92: 307466.41 | H92: 282952.63 | I92: 42142.188 | J92: 42808.066 | K92: 113056.09 | L92: 169831.81 | M92: 172030.87 | N92: 181377.43
A93: Ekstraksi Extraction | D93: -672.84247 | E93: -405.97464 | F93: -713.28495 | G93: -1253.0937 | H93: -1547.1992 | I93: -844.89467 | J93: -2044.0283 | K93: -4341.6139 | L93: -6415.4283 | M93: -11822.489 | N93: -12341.886
A94: Perubahan lainnya Other changes in stock | D94: 2.7599683 | E94: 111761.09 | F94: -10028.796 | G94: 76170.173 | H94: 38105.138 | I94: -1861.715 | J94: -30795.565 | K94: 25024.272 | L94: 170.97837 | M94: 15170.048 | N94: 31710.237
A95: Revaluasi Revaluation | D95: 26256.526 | E95: -57544.122 | F95: 166656.64 | G95: -99430.858 | H95: -277368.38 | I95: 3372.4877 | J95: 103087.62 | K95: 36093.058 | L95: 8443.5155 | M95: 5998.9982 | N95: 5153.4136
A96: Stok akhir tahun Closing stock | D96: 97741.009 | E96: 151552 | F96: 307466.17 | G96: 282952.63 | H96: 42142.188 | I96: 42808.066 | J96: 113056.09 | K96: 169831.81 | L96: 172030.87 | M96: 181377.43 | N96: 205899.19
A98: Bauksit
A99: Uraian Description | D99: Tahun / Year
D100: =D90 -> 2014 | E100: =E90 -> 2015 | F100: =F90 -> 2016 | G100: =G90 -> 2017 | H100: =H90 -> 2018 | I100: =I90 -> 2019 | J100: =J90 -> 2020 | K100: =K90 -> 2021 | ... N100: =N90 -> 2024**
A101: -1 | D101: =A101-1 -> -2 | E101: =D101-1 -> -3 | F101: =E101-1 -> -4 | G101: =F101-1 -> -5 | H101: =G101-1 -> -6 | I101: =H101-1 -> -7 | J101: =I101-1 -> -8 | K101: =J101-1 -> -9 | L101: =J101-1 -> -9 | M101: =K101-1 -> -10 | N101: =L101-1 -> -10
A102: Stok awal tahun Opening stock | D102: 48504.103 | E102: 7070.8202 | F102: 2508.8634 | G102: 16142.363 | H102: 51927.4 | I102: 81961.192 | J102: 119374.6 | K102: 92499.539 | L102: 132212.83 | M102: 161189.47 | N102: 189178.53
A103: Ekstraksi Extraction | D103: -68.394418 | E103: -1.225978 | F103: -7.1481691 | G103: -56.796367 | H103: -303.94609 | I103: -583.34299 | J103: -795.98646 | K103: -1063.7068 | L103: -1675.6729 | M103: -897.18193 | N103: -610.19653
A104: Perubahan lainnya Other changes in stock | D104: 68.394418 | E104: 5623.3098 | F104: 500.20427 | G104: 6373.3805 | H104: 1341.7766 | I104: 124.65003 | J104: 27554.453 | K104: -73936.256 | L104: 5405.1374 | M104: 85.313697 | N104: 8641.0762
A105: Revaluasi Revaluation | D105: -41433.283 | E105: -10184.041 | F105: 13140.444 | G105: 29468.452 | H105: 28995.962 | I105: 37872.097 | J105: -53633.524 | K105: 114713.25 | L105: 25247.178 | M105: 28800.923 | N105: 30921.679
A106: Stok akhir tahun Closing stock | D106: 7070.8202 | E106: 2508.8634 | F106: 16142.363 | G106: 51927.4 | H106: 81961.192 | I106: 119374.6 | J106: 92499.539 | K106: 132212.83 | L106: 161189.47 | M106: 189178.53 | N106: 228131.09

Sheet Neraca Terpadu
A2: Komponen Neraca | C2: =I2-1 -> 2014 | I2: ='PDB ADHB'!C1 -> 2015 | O2: ='PDB ADHB'!D1 -> 2016 | U2: ='PDB ADHB'!E1 -> 2017 | AA2: ='PDB ADHB'!F1 -> 2018 | AG2: ='PDB ADHB'!G1 -> 2019 | AM2: ='PDB ADHB'!H1 -> 2020 | AS2: ='PDB ADHB'!I1 -> 2021 | AY2: ='PDB ADHB'!J1 -> 2022 | BE2: ='PDB ADHB'!K1 -> 2023* | BK2: ='PDB ADHB'!L1 -> 2024**
C3: Kegiatan Ekonomi | H3: Kapital Lingkungan yang Tidak diproduksi | I3: Kegiatan Ekonomi | N3: Kapital Lingkungan yang Tidak diproduksi | O3: Kegiatan Ekonomi | T3: Kapital Lingkungan yang Tidak diproduksi | U3: Kegiatan Ekonomi | Z3: Kapital Lingkungan yang Tidak diproduksi | AA3: Kegiatan Ekonomi | AF3: Kapital Lingkungan yang Tidak diproduksi | AG3: Kegiatan Ekonomi | AL3: Kapital Lingkungan yang Tidak diproduksi | AM3: Kegiatan Ekonomi | AR3: Kapital Lingkungan yang Tidak diproduksi | AS3: Kegiatan Ekonomi | AX3: Kapital Lingkungan yang Tidak diproduksi | AY3: Kegiatan Ekonomi | BD3: Kapital Lingkungan yang Tidak diproduksi | BE3: Kegiatan Ekonomi | BJ3: Kapital Lingkungan yang Tidak diproduksi | BK3: Kegiatan Ekonomi | BP3: Kapital Lingkungan yang Tidak diproduksi
C4: Industri | D4: Konsumsi akhir | E4: Kapital | G4: Luar Negeri | I4: Industri | J4: Konsumsi akhir | K4: Kapital | M4: Luar Negeri | O4: Industri | P4: Konsumsi akhir | Q4: Kapital | S4: Luar Negeri | U4: Industri | V4: Konsumsi akhir | W4: Kapital | Y4: Luar Negeri | AA4: Industri | AB4: Konsumsi akhir | AC4: Kapital | AE4: Luar Negeri | AG4: Industri | AH4: Konsumsi akhir | AI4: Kapital | AK4: Luar Negeri | AM4: Industri | AN4: Konsumsi akhir | AO4: Kapital | AQ4: Luar Negeri | AS4: Industri | AT4: Konsumsi akhir | AU4: Kapital | AW4: Luar Negeri | AY4: Industri | AZ4: Konsumsi akhir | BA4: Kapital | BC4: Luar Negeri | BE4: Industri | BF4: Konsumsi akhir | BG4: Kapital | BI4: Luar Negeri | BK4: Industri | BL4: Konsumsi akhir | BM4: Kapital | BO4: Luar Negeri
E5: Diproduksi (Produced Assets) | F5: Buatan Alam (Non-Produced) | K5: Diproduksi (Produced Assets) | L5: Buatan Alam (Non-Produced) | Q5: Diproduksi (Produced Assets) | R5: Buatan Alam (Non-Produced) | W5: Diproduksi (Produced Assets) | X5: Buatan Alam (Non-Produced) | AC5: Diproduksi (Produced Assets) | AD5: Buatan Alam (Non-Produced) | AI5: Diproduksi (Produced Assets) | AJ5: Buatan Alam (Non-Produced) | AO5: Diproduksi (Produced Assets) | AP5: Buatan Alam (Non-Produced) | AU5: Diproduksi (Produced Assets) | AV5: Buatan Alam (Non-Produced) | BA5: Diproduksi (Produced Assets) | BB5: Buatan Alam (Non-Produced) | BG5: Diproduksi (Produced Assets) | BH5: Buatan Alam (Non-Produced) | BM5: Diproduksi (Produced Assets) | BN5: Buatan Alam (Non-Produced)
A6: (1) | C6: (2) | D6: (4) | E6: (5) | F6: (6) | G6: (3) | H6: (7) | I6: (2) | J6: (4) | K6: (5) | L6: (6) | M6: (3) | N6: (7) | O6: (2) | P6: (4) | Q6: (5) | R6: (6) | S6: (3) | T6: (7) | U6: (2) | V6: (4) | W6: (5) | X6: (6) | Y6: (3) | Z6: (7) | AA6: (2) | AB6: (4) | AC6: (5) | AD6: (6) | AE6: (3) | AF6: (7) | AG6: (2) | AH6: (4) | AI6: (5) | AJ6: (6) | AK6: (3) | AL6: (7) | AM6: (2) | AN6: (4) | AO6: (5) | AP6: (6) | AQ6: (3) | AR6: (7) | AS6: (2) | AT6: (4) | AU6: (5) | AV6: (6) | AW6: (3) | AX6: (7) | AY6: (2) | AZ6: (4) | BA6: (5) | BB6: (6) | BC6: (3) | BD6: (7) | BE6: (2) | BF6: (4) | BG6: (5) | BH6: (6) | BI6: (3) | BJ6: (7) | BK6: (2) | BL6: (4) | BM6: (5) | BN6: (6) | BO6: (3) | BP6: (7)
A8: 1 | B8: Stok Awal
B9: Barang Modal | E9: ='Stok Kapital'!B7 -> 33313961 | K9: ='Stok Kapital'!J7 -> 38102453 | Q9: =K60 -> 41623718 | W9: =Q60 -> 44861123 | AC9: =W60 -> 49172159 | AI9: =AC60 -> 54392257 | AO9: =AI60 -> 58178121 | AU9: =AO60 -> 61666805 | BA9: =AU60 -> 67696559 | BG9: =BA60 -> 74342957 | BM9: =BG60 -> 80433633
B10: a. Hasil Hutan | F10: ='Aset Moneter'!D6 -> 701661.76 | L10: ='Aset Moneter'!E6 -> 719985.09 | R10: ='Aset Moneter'!F6 -> 628834.11 | X10: ='Aset Moneter'!G6 -> 681499.89 | AD10: ='Aset Moneter'!H6 -> 749533.49 | AJ10: ='Aset Moneter'!I6 -> 740284 | AP10: ='Aset Moneter'!J6 -> 818198.38 | AV10: ='Aset Moneter'!K6 -> 952915.52 | BB10: ='Aset Moneter'!L6 -> 1100095.7 | BH10: ='Aset Moneter'!M6 -> 1173971.8 | BN10: ='Aset Moneter'!N6 -> 1390349.6
B11: b. Minyak Bumi | F11: ='Aset Moneter'!D22 -> 2131738 | L11: ='Aset Moneter'!E22 -> 1936674 | R11: ='Aset Moneter'!F22 -> 1128616.9 | X11: ='Aset Moneter'!G22 -> 1038776.4 | AD11: ='Aset Moneter'!H22 -> 1442786.8 | AJ11: ='Aset Moneter'!I22 -> 1827895.4 | AP11: ='Aset Moneter'!J22 -> 1650482.1 | AV11: ='Aset Moneter'!K22 -> 1232797.1 | BB11: ='Aset Moneter'!L22 -> 1759477.5 | BH11: ='Aset Moneter'!M22 -> 2275538.7 | BN11: ='Aset Moneter'!N22 -> 1904383.6
B12: c. Gas Alam | F12: ='Aset Moneter'!D32 -> 2209651.2 | L12: ='Aset Moneter'!E32 -> 1929560.4 | R12: ='Aset Moneter'!F32 -> 2092742.2 | X12: ='Aset Moneter'!G32 -> 2099174 | AD12: ='Aset Moneter'!H32 -> 2081924.9 | AJ12: ='Aset Moneter'!I32 -> 1985652.1 | AP12: ='Aset Moneter'!J32 -> 2088004.1 | AV12: ='Aset Moneter'!K32 -> 2190729.9 | BB12: ='Aset Moneter'!L32 -> 2571830.7 | BH12: ='Aset Moneter'!M32 -> 3019060 | BN12: ='Aset Moneter'!N32 -> 2672571.9
B13: d. Batubara | F13: ='Aset Moneter'!D42 -> 3124469.7 | L13: ='Aset Moneter'!E42 -> 2374378.3 | R13: ='Aset Moneter'!F42 -> 2534793.4 | X13: ='Aset Moneter'!G42 -> 2860161.4 | AD13: ='Aset Moneter'!H42 -> 4126241.8 | AJ13: ='Aset Moneter'!I42 -> 4338434.3 | AP13: ='Aset Moneter'!J42 -> 4057943.9 | AV13: ='Aset Moneter'!K42 -> 3608155.4 | BB13: ='Aset Moneter'!L42 -> 7098820.3 | BH13: ='Aset Moneter'!M42 -> 15178689 | BN13: ='Aset Moneter'!N42 -> 13539562
B14: e. Emas | F14: ='Aset Moneter'!D52 -> 193839.94 | L14: ='Aset Moneter'!E52 -> 200366.45 | R14: ='Aset Moneter'!F52 -> 311024.64 | X14: ='Aset Moneter'!G52 -> 330729.39 | AD14: ='Aset Moneter'!H52 -> 376606.06 | AJ14: ='Aset Moneter'!I52 -> 177537.95 | AP14: ='Aset Moneter'!J52 -> 111404.04 | AV14: ='Aset Moneter'!K52 -> 181971.97 | BB14: ='Aset Moneter'!L52 -> 236975.2 | BH14: ='Aset Moneter'!M52 -> 313647.4 | BN14: ='Aset Moneter'!N52 -> 372761.02
B15: f. Perak | F15: ='Aset Moneter'!D62 -> 14354.02 | L15: ='Aset Moneter'!E62 -> 13473.768 | R15: ='Aset Moneter'!F62 -> 14780.666 | X15: ='Aset Moneter'!G62 -> 17318.011 | AD15: ='Aset Moneter'!H62 -> 12622.997 | AJ15: ='Aset Moneter'!I62 -> 4957.2855 | AP15: ='Aset Moneter'!J62 -> 5269.9371 | AV15: ='Aset Moneter'!K62 -> 5627.0929 | BB15: ='Aset Moneter'!L62 -> 5993.334 | BH15: ='Aset Moneter'!M62 -> 5023.8836 | BN15: ='Aset Moneter'!N62 -> 6092.4315
B16: g. Tembaga | F16: ='Aset Moneter'!D72 -> 369717.06 | L16: ='Aset Moneter'!E72 -> 220254.27 | R16: ='Aset Moneter'!F72 -> 172752.29 | X16: ='Aset Moneter'!G72 -> 195241.87 | AD16: ='Aset Moneter'!H72 -> 228644.7 | AJ16: ='Aset Moneter'!I72 -> 243466.58 | AP16: ='Aset Moneter'!J72 -> 182470.54 | AV16: ='Aset Moneter'!K72 -> 603209.49 | BB16: ='Aset Moneter'!L72 -> 925405.54 | BH16: ='Aset Moneter'!M72 -> 1018188.9 | BN16: ='Aset Moneter'!N72 -> 1137311.4
B17: h. Timah | F17: ='Aset Moneter'!D82 -> 73799.752 | L17: ='Aset Moneter'!E82 -> 33762.4 | R17: ='Aset Moneter'!F82 -> 50123.665 | X17: ='Aset Moneter'!G82 -> 75206.158 | AD17: ='Aset Moneter'!H82 -> 78627.703 | AJ17: ='Aset Moneter'!I82 -> 115623.7 | AP17: ='Aset Moneter'!J82 -> 128560.7 | AV17: ='Aset Moneter'!K82 -> 185956.97 | BB17: ='Aset Moneter'!L82 -> 300256.29 | BH17: ='Aset Moneter'!M82 -> 378436.44 | BN17: ='Aset Moneter'!N82 -> 436324.54
B18: i. Nikel | F18: ='Aset Moneter'!D92 -> 72154.565 | L18: ='Aset Moneter'!E92 -> 97741.009 | R18: ='Aset Moneter'!F92 -> 151551.61 | X18: ='Aset Moneter'!G92 -> 307466.41 | AD18: ='Aset Moneter'!H92 -> 282952.63 | AJ18: ='Aset Moneter'!I92 -> 42142.188 | AP18: ='Aset Moneter'!J92 -> 42808.066 | AV18: ='Aset Moneter'!K92 -> 113056.09 | BB18: ='Aset Moneter'!L92 -> 169831.81 | BH18: ='Aset Moneter'!M92 -> 172030.87 | BN18: ='Aset Moneter'!N92 -> 181377.43
B19: j. Bauksit | F19: ='Aset Moneter'!D102 -> 48504.103 | L19: ='Aset Moneter'!E102 -> 7070.8202 | R19: ='Aset Moneter'!F102 -> 2508.8634 | X19: ='Aset Moneter'!G102 -> 16142.363 | AD19: ='Aset Moneter'!H102 -> 51927.4 | AJ19: ='Aset Moneter'!I102 -> 81961.192 | AP19: ='Aset Moneter'!J102 -> 119374.6 | AV19: ='Aset Moneter'!K102 -> 92499.539 | BB19: ='Aset Moneter'!L102 -> 132212.83 | BH19: ='Aset Moneter'!M102 -> 161189.47 | BN19: ='Aset Moneter'!N102 -> 189178.53
A20: 2 | B20: Penyediaan | C20: ='Stok Kapital'!C5 -> 20186022 | G20: ='Stok Kapital'!C8 -> 2580508 | I20: ='Stok Kapital'!K5 -> 22012989 | M20: ='Stok Kapital'!K8 -> 2394879.3 | O20: ='Stok Kapital'!S5 -> 22781947 | S20: ='Stok Kapital'!S8 -> 2273528 | U20: ='Stok Kapital'!AA5 -> 24964479 | Y20: ='Stok Kapital'!AA8 -> 2606283 | AA20: ='Stok Kapital'!AI5 -> 27258761 | AE20: ='Stok Kapital'!AI8 -> 3275145.3 | AG20: ='Stok Kapital'!AQ5 -> 29304285 | AK20: ='Stok Kapital'!AQ8 -> 3013944.2 | AM20: ='Stok Kapital'!AY5 -> 28374740 | AQ20: ='Stok Kapital'!AY8 -> 2415496 | AS20: ='Stok Kapital'!BG5 -> 31179368 | AW20: ='Stok Kapital'!BG8 -> 3189626.5 | AY20: ='Stok Kapital'!BO5 -> 35976012 | BC20: ='Stok Kapital'!BO8 -> 4106085.7 | BE20: ='Stok Kapital'!BW5 -> 38370723 | BI20: ='Stok Kapital'!BW8 -> 4091231.5 | BK20: ='Stok Kapital'!CE5 -> 40660248 | BO20: ='Stok Kapital'!CE8 -> 4513987.4
A21: 3 | B21: Penggunaan | C21: ='Stok Kapital'!D5 -> 9616316.7 | D21: ='Stok Kapital'!D6 -> 7035633.7 | E21: ='Stok Kapital'!D7 -> 3613154.8 | G21: ='Stok Kapital'!D8 -> 2501424.8 | I21: ='Stok Kapital'!L5 -> 10486656 | J21: ='Stok Kapital'!L6 -> 7745630.1 | K21: ='Stok Kapital'!L7 -> 3736589.3 | M21: ='Stok Kapital'!L8 -> 2438992.7 | O21: ='Stok Kapital'!T5 -> 10380218 | P21: ='Stok Kapital'!T6 -> 8353136 | Q21: ='Stok Kapital'!T7 -> 3954755.4 | S21: ='Stok Kapital'!T8 -> 2367365.2 | U21: ='Stok Kapital'!AB5 -> 11374653 | V21: ='Stok Kapital'!AB6 -> 9023120.3 | W21: ='Stok Kapital'!AB7 -> 4430927.9 | Y21: ='Stok Kapital'!AB8 -> 2742060.5 | AA21: ='Stok Kapital'!AJ5 -> 12420005 | AB21: ='Stok Kapital'!AJ6 -> 9793746.3 | AC21: ='Stok Kapital'!AJ7 -> 5203608.7 | AE21: ='Stok Kapital'!AJ8 -> 3116546.3 | AG21: ='Stok Kapital'!AR5 -> 13471628 | AH21: ='Stok Kapital'!AR6 -> 10566547 | AI21: ='Stok Kapital'!AR7 -> 5336521.6 | AK21: ='Stok Kapital'!AR8 -> 2943532.9 | AM21: ='Stok Kapital'!AZ5 -> 12931387 | AN21: ='Stok Kapital'!AZ6 -> 10592541 | AO21: ='Stok Kapital'!AZ7 -> 4589794.8 | AQ21: ='Stok Kapital'!AZ8 -> 2676513.5 | AS21: ='Stok Kapital'!BH5 -> 14202617 | AT21: ='Stok Kapital'!BH6 -> 11013796 | AU21: ='Stok Kapital'!BH7 -> 5516746.8 | AW21: ='Stok Kapital'!BH8 -> 3635835.4 | AY21: ='Stok Kapital'!BP5 -> 16387552 | AZ21: ='Stok Kapital'!BP6 -> 11896997 | BA21: ='Stok Kapital'!BP7 -> 6997805.3 | BC21: ='Stok Kapital'!BP8 -> 4799743 | BE21: ='Stok Kapital'!BX5 -> 17478375 | BF21: ='Stok Kapital'!BX6 -> 12928272 | BG21: ='Stok Kapital'!BX7 -> 7510418.7 | BI21: ='Stok Kapital'!BX8 -> 4544889.6 | BK21: ='Stok Kapital'!CF5 -> 18521284 | BL21: ='Stok Kapital'!CF6 -> 13976578 | BM21: ='Stok Kapital'!CF7 -> 7765217.9 | BO21: ='Stok Kapital'!CF8 -> 4911155.7
A22: 4 | B22: Penyusutan | C22: ='Stok Kapital'!F5 -> 1970519.4 | E22: =0-C22 -> -1970519.4 | I22: ='Stok Kapital'!N5 -> 2129438.2 | K22: =0-I22 -> -2129438.2 | O22: ='Stok Kapital'!V5 -> 2035689.4 | Q22: =0-O22 -> -2035689.4 | U22: ='Stok Kapital'!AD5 -> 2430937.4 | W22: =0-U22 -> -2430937.4 | AA22: ='Stok Kapital'!AL5 -> 2800030.2 | AC22: =0-AA22 -> -2800030.2 | AG22: ='Stok Kapital'!AT5 -> 3168101.1 | AI22: =0-AG22 -> -3168101.1 | AM22: ='Stok Kapital'!BB5 -> 2943805 | AO22: =0-AM22 -> -2943805 | AS22: ='Stok Kapital'!BJ5 -> 3146409.1 | AU22: =0-AS22 -> -3146409.1 | AY22: ='Stok Kapital'!BR5 -> 3686044.4 | BA22: =0-AY22 -> -3686044.4 | BE22: ='Stok Kapital'!BZ5 -> 4138304.5 | BG22: =0-BE22 -> -4138304.5 | BK22: ='Stok Kapital'!CH5 -> 4426259.2 | BM22: =0-BK22 -> -4426259.2
A23: 5 | B23: PDN | C23: =C20-C21-C22 -> 8599185.9 | D23: =D21 -> 7035633.7 | E23: =E21+E22 -> 1642635.4 | G23: =G21-G20 -> -79083.211 | I23: =I20-I21-I22 -> 9396894.6 | J23: =J21 -> 7745630.1 | K23: =K21+K22 -> 1607151.1 | M23: =M21-M20 -> 44113.382 | O23: =O20-O21-O22 -> 10366039 | P23: =P21 -> 8353136 | Q23: =Q21+Q22 -> 1919066 | S23: =S21-S20 -> 93837.171 | U23: =U20-U21-U22 -> 11158888 | V23: =V21 -> 9023120.3 | W23: =W21+W22 -> 1999990.5 | Y23: =Y21-Y20 -> 135777.55 | AA23: =AA20-AA21-AA22 -> 12038726 | AB23: =AB21 -> 9793746.3 | AC23: =AC21+AC22 -> 2403578.5 | AE23: =AE21-AE20 -> -158598.99 | AG23: =AG20-AG21-AG22 -> 12664556 | AH23: =AH21 -> 10566547 | AI23: =AI21+AI22 -> 2168420.4 | AK23: =AK21-AK20 -> -70411.3 | AM23: =AM20-AM21-AM22 -> 12499548 | AN23: =AN21 -> 10592541 | AO23: =AO21+AO22 -> 1645989.8 | AQ23: =AQ21-AQ20 -> 261017.56 | AS23: =AS20-AS21-AS22 -> 13830342 | AT23: =AT21 -> 11013796 | AU23: =AU21+AU22 -> 2370337.7 | AW23: =AW21-AW20 -> 446208.96 | AY23: =AY20-AY21-AY22 -> 15902416 | AZ23: =AZ21 -> 11896997 | BA23: =BA21+BA22 -> 3311760.9 | BC23: =BC21-BC20 -> 693657.37 | BE23: =BE20-BE21-BE22 -> 16754044 | BF23: =BF21 -> 12928272 | BG23: =BG21+BG22 -> 3372114.2 | BI23: =BI21-BI20 -> 453658.03 | BK23: =BK20-BK21-BK22 -> 17712705 | BL23: =BL21 -> 13976578 | BM23: =BM21+BM22 -> 3338958.7 | BO23: =BO21-BO20 -> 397168.24
A24: 6 | B24: Deplesi | C24: =SUM(C25:C34) -> 225532.93 | F24: =0-C24 -> -225532.93 | I24: =SUM(I25:I34) -> 256352.15 | L24: =0-I24 -> -256352.15 | O24: =SUM(O25:O34) -> 193579.77 | R24: =0-O24 -> -193579.77 | U24: =SUM(U25:U34) -> 218010.01 | X24: =0-U24 -> -218010.01 | AA24: =SUM(AA25:AA34) -> 245697.33 | AD24: =0-AA24 -> -245697.33 | AG24: =SUM(AG25:AG34) -> 323473.01 | AJ24: =0-AG24 -> -323473.01 | AM24: =SUM(AM25:AM34) -> 281808.55 | AP24: =0-AM24 -> -281808.55 | AS24: =SUM(AS25:AS34) -> 355425.88 | AV24: =0-AS24 -> -355425.88 | AY24: =SUM(AY25:AY34) -> 577815.02 | BB24: =0-AY24 -> -577815.02 | BE24: =SUM(BE25:BE34) -> 816417.99 | BH24: =0-BE24 -> -816417.99 | BK24: =SUM(BK25:BK34) -> 707021.45 | BN24: =0-BK24 -> -707021.45
B25: a. Hasil Hutan | C25: ='Aset Moneter'!D14 -> 34762.947 | F25: =0-C25 -> -34762.947 | I25: ='Aset Moneter'!E14 -> 95890.196 | L25: =0-I25 -> -95890.196 | O25: ='Aset Moneter'!F14 -> 39606.994 | R25: =0-O25 -> -39606.994 | U25: ='Aset Moneter'!G14 -> 37376.054 | X25: =0-U25 -> -37376.054 | AA25: ='Aset Moneter'!H14 -> 33923.748 | AD25: =0-AA25 -> -33923.748 | AG25: ='Aset Moneter'!I14 -> 88487.394 | AJ25: =0-AG25 -> -88487.394 | AM25: ='Aset Moneter'!J14 -> 33526.873 | AP25: =0-AM25 -> -33526.873 | AS25: ='Aset Moneter'!K14 -> 38087.928 | AV25: =0-AS25 -> -38087.928 | AY25: ='Aset Moneter'!L14 -> 40555.169 | BB25: =0-AY25 -> -40555.169 | BE25: ='Aset Moneter'!M14 -> 142513 | BH25: =0-BE25 -> -142513 | BK25: ='Aset Moneter'!N14 -> 72168.932 | BN25: =0-BK25 -> -72168.932
B26: b. Minyak Bumi | C26: =-'Aset Moneter'!D23 -> 78448.958 | F26: =0-C26 -> -78448.958 | I26: =-'Aset Moneter'!E23 -> 59816.752 | L26: =0-I26 -> -59816.752 | O26: =-'Aset Moneter'!F23 -> 45283.89 | R26: =0-O26 -> -45283.89 | U26: =-'Aset Moneter'!G23 -> 48952.527 | X26: =0-U26 -> -48952.527 | AA26: =-'Aset Moneter'!H23 -> 61277.109 | AD26: =0-AA26 -> -61277.109 | AG26: =-'Aset Moneter'!I23 -> 92568.191 | AJ26: =0-AG26 -> -92568.191 | AM26: =-'Aset Moneter'!J23 -> 95012.345 | AP26: =0-AM26 -> -95012.345 | AS26: =-'Aset Moneter'!K23 -> 89111.472 | AV26: =0-AS26 -> -89111.472 | AY26: =-'Aset Moneter'!L23 -> 110761.69 | BB26: =0-AY26 -> -110761.69 | BE26: =-'Aset Moneter'!M23 -> 105018.04 | BH26: =0-BE26 -> -105018.04 | BK26: =-'Aset Moneter'!N23 -> 89462.611 | BN26: =0-BK26 -> -89462.611
B27: c. Gas Alam | C27: =-'Aset Moneter'!D33 -> 43852.885 | F27: =0-C27 -> -43852.885 | I27: =-'Aset Moneter'!E33 -> 41683.345 | L27: =0-I27 -> -41683.345 | O27: =-'Aset Moneter'!F33 -> 43598.192 | R27: =0-O27 -> -43598.192 | U27: =-'Aset Moneter'!G33 -> 40547.829 | X27: =0-U27 -> -40547.829 | AA27: =-'Aset Moneter'!H33 -> 43807.745 | AD27: =0-AA27 -> -43807.745 | AG27: =-'Aset Moneter'!I33 -> 58529.829 | AJ27: =0-AG27 -> -58529.829 | AM27: =-'Aset Moneter'!J33 -> 75883.739 | AP27: =0-AM27 -> -75883.739 | AS27: =-'Aset Moneter'!K33 -> 94344.79 | AV27: =0-AS27 -> -94344.79 | AY27: =-'Aset Moneter'!L33 -> 115553.86 | BB27: =0-AY27 -> -115553.86 | BE27: =-'Aset Moneter'!M33 -> 125788.22 | BH27: =0-BE27 -> -125788.22 | BK27: =-'Aset Moneter'!N33 -> 123062.42 | BN27: =0-BK27 -> -123062.42
B28: d. Batubara | C28: =-'Aset Moneter'!D43 -> 39616.02 | F28: =0-C28 -> -39616.02 | I28: =-'Aset Moneter'!E43 -> 35051.958 | L28: =0-I28 -> -35051.958 | O28: =-'Aset Moneter'!F43 -> 40846.113 | R28: =0-O28 -> -40846.113 | U28: =-'Aset Moneter'!G43 -> 62437.308 | X28: =0-U28 -> -62437.308 | AA28: =-'Aset Moneter'!H43 -> 79361.018 | AD28: =0-AA28 -> -79361.018 | AG28: =-'Aset Moneter'!I43 -> 68470.663 | AJ28: =0-AG28 -> -68470.663 | AM28: =-'Aset Moneter'!J43 -> 56624.031 | AP28: =0-AM28 -> -56624.031 | AS28: =-'Aset Moneter'!K43 -> 88615.492 | AV28: =0-AS28 -> -88615.492 | AY28: =-'Aset Moneter'!L43 -> 216088.03 | BB28: =0-AY28 -> -216088.03 | BE28: =-'Aset Moneter'!M43 -> 333305.22 | BH28: =0-BE28 -> -333305.22 | BK28: =-'Aset Moneter'!N43 -> 306796.88 | BN28: =0-BK28 -> -306796.88
B29: e. Emas | C29: =-'Aset Moneter'!D53 -> 5059.7905 | F29: =0-C29 -> -5059.7905 | I29: =-'Aset Moneter'!E53 -> 9273.2681 | L29: =0-I29 -> -9273.2681 | O29: =-'Aset Moneter'!F53 -> 10760.668 | R29: =0-O29 -> -10760.668 | U29: =-'Aset Moneter'!G53 -> 11196.82 | X29: =0-U29 -> -11196.82 | AA29: =-'Aset Moneter'!H53 -> 11043.246 | AD29: =0-AA29 -> -11043.246 | AG29: =-'Aset Moneter'!I53 -> 4937.9047 | AJ29: =0-AG29 -> -4937.9047 | AM29: =-'Aset Moneter'!J53 -> 3478.345 | AP29: =0-AM29 -> -3478.345 | AS29: =-'Aset Moneter'!K53 -> 7950.6586 | AV29: =0-AS29 -> -7950.6586 | AY29: =-'Aset Moneter'!L53 -> 11260.468 | BB29: =0-AY29 -> -11260.468 | BE29: =-'Aset Moneter'!M53 -> 10682.966 | BH29: =0-BE29 -> -10682.966 | BK29: =-'Aset Moneter'!N53 -> 7392.9116 | BN29: =0-BK29 -> -7392.9116
B30: f. Perak | C30: =-'Aset Moneter'!D63 -> 250.22465 | F30: =0-C30 -> -250.22465 | I30: =-'Aset Moneter'!E63 -> 334.54615 | L30: =0-I30 -> -334.54615 | O30: =-'Aset Moneter'!F63 -> 385.03321 | R30: =0-O30 -> -385.03321 | U30: =-'Aset Moneter'!G63 -> 571.09266 | X30: =0-U30 -> -571.09266 | AA30: =-'Aset Moneter'!H63 -> 400.903 | AD30: =0-AA30 -> -400.903 | AG30: =-'Aset Moneter'!I63 -> 189.63674 | AJ30: =0-AG30 -> -189.63674 | AM30: =-'Aset Moneter'!J63 -> 154.80963 | AP30: =0-AM30 -> -154.80963 | AS30: =-'Aset Moneter'!K63 -> 194.87779 | AV30: =0-AS30 -> -194.87779 | AY30: =-'Aset Moneter'!L63 -> 144.34519 | BB30: =0-AY30 -> -144.34519 | BE30: =-'Aset Moneter'!M63 -> 38.460002 | BH30: =0-BE30 -> -38.460002 | BK30: =-'Aset Moneter'!N63 -> 97.735409 | BN30: =0-BK30 -> -97.735409
B31: g. Tembaga | C31: =-'Aset Moneter'!D73 -> 11086.795 | F31: =0-C31 -> -11086.795 | I31: =-'Aset Moneter'!E73 -> 6631.2044 | L31: =0-I31 -> -6631.2044 | O31: =-'Aset Moneter'!F73 -> 6970.8953 | R31: =0-O31 -> -6970.8953 | U31: =-'Aset Moneter'!G73 -> 7788.1186 | X31: =0-U31 -> -7788.1186 | AA31: =-'Aset Moneter'!H73 -> 7258.6491 | AD31: =0-AA31 -> -7258.6491 | AG31: =-'Aset Moneter'!I73 -> 4866.3659 | AJ31: =0-AG31 -> -4866.3659 | AM31: =-'Aset Moneter'!J73 -> 10871.394 | AP31: =0-AM31 -> -10871.394 | AS31: =-'Aset Moneter'!K73 -> 28116.166 | AV31: =0-AS31 -> -28116.166 | AY31: =-'Aset Moneter'!L73 -> 66743.604 | BB31: =0-AY31 -> -66743.604 | BE31: =-'Aset Moneter'!M73 -> 68937.059 | BH31: =0-BE31 -> -68937.059 | BK31: =-'Aset Moneter'!N73 -> 81347.171 | BN31: =0-BK31 -> -81347.171
B32: h. Timah | C32: =-'Aset Moneter'!D83 -> 11714.077 | F32: =0-C32 -> -11714.077 | I32: =-'Aset Moneter'!E83 -> 7263.6783 | L32: =0-I32 -> -7263.6783 | O32: =-'Aset Moneter'!F83 -> 5407.5495 | R32: =0-O32 -> -5407.5495 | U32: =-'Aset Moneter'!G83 -> 7830.3711 | X32: =0-U32 -> -7830.3711 | AA32: =-'Aset Moneter'!H83 -> 6773.7646 | AD32: =0-AA32 -> -6773.7646 | AG32: =-'Aset Moneter'!I83 -> 3994.7881 | AJ32: =0-AG32 -> -3994.7881 | AM32: =-'Aset Moneter'!J83 -> 3417.0025 | AP32: =0-AM32 -> -3417.0025 | AS32: =-'Aset Moneter'!K83 -> 3599.1709 | AV32: =0-AS32 -> -3599.1709 | AY32: =-'Aset Moneter'!L83 -> 8616.7529 | BB32: =0-AY32 -> -8616.7529 | BE32: =-'Aset Moneter'!M83 -> 17415.351 | BH32: =0-BE32 -> -17415.351 | BK32: =-'Aset Moneter'!N83 -> 13740.702 | BN32: =0-BK32 -> -13740.702
B33: i. Nikel | C33: =-'Aset Moneter'!D93 -> 672.84247 | F33: =0-C33 -> -672.84247 | I33: =-'Aset Moneter'!E93 -> 405.97464 | L33: =0-I33 -> -405.97464 | O33: =-'Aset Moneter'!F93 -> 713.28495 | R33: =0-O33 -> -713.28495 | U33: =-'Aset Moneter'!G93 -> 1253.0937 | X33: =0-U33 -> -1253.0937 | AA33: =-'Aset Moneter'!H93 -> 1547.1992 | AD33: =0-AA33 -> -1547.1992 | AG33: =-'Aset Moneter'!I93 -> 844.89467 | AJ33: =0-AG33 -> -844.89467 | AM33: =-'Aset Moneter'!J93 -> 2044.0283 | AP33: =0-AM33 -> -2044.0283 | AS33: =-'Aset Moneter'!K93 -> 4341.6139 | AV33: =0-AS33 -> -4341.6139 | AY33: =-'Aset Moneter'!L93 -> 6415.4283 | BB33: =0-AY33 -> -6415.4283 | BE33: =-'Aset Moneter'!M93 -> 11822.489 | BH33: =0-BE33 -> -11822.489 | BK33: =-'Aset Moneter'!N93 -> 12341.886 | BN33: =0-BK33 -> -12341.886
B34: j. Bauksit | C34: =-'Aset Moneter'!D103 -> 68.394418 | F34: =0-C34 -> -68.394418 | I34: =-'Aset Moneter'!E103 -> 1.225978 | L34: =0-I34 -> -1.225978 | O34: =-'Aset Moneter'!F103 -> 7.1481691 | R34: =0-O34 -> -7.1481691 | U34: =-'Aset Moneter'!G103 -> 56.796367 | X34: =0-U34 -> -56.796367 | AA34: =-'Aset Moneter'!H103 -> 303.94609 | AD34: =0-AA34 -> -303.94609 | AG34: =-'Aset Moneter'!I103 -> 583.34299 | AJ34: =0-AG34 -> -583.34299 | AM34: =-'Aset Moneter'!J103 -> 795.98646 | AP34: =0-AM34 -> -795.98646 | AS34: =-'Aset Moneter'!K103 -> 1063.7068 | AV34: =0-AS34 -> -1063.7068 | AY34: =-'Aset Moneter'!L103 -> 1675.6729 | BB34: =0-AY34 -> -1675.6729 | BE34: =-'Aset Moneter'!M103 -> 897.18193 | BH34: =0-BE34 -> -897.18193 | BK34: =-'Aset Moneter'!N103 -> 610.19653 | BN34: =0-BK34 -> -610.19653
A35: 7 | B35: Perubahan lainnya | F35: =SUM(F36:F45) -> 195990.05 | H35: =0-F35 -> -195990.05 | L35: =SUM(L36:L45) -> 327544.48 | N35: =0-L35 -> -327544.48 | R35: =SUM(R36:R45) -> -274408.03 | T35: =0-R35 -> 274408.03 | X35: =SUM(X36:X45) -> -217008.35 | Z35: =0-X35 -> 217008.35 | AD35: =SUM(AD36:AD45) -> 2137317.1 | AF35: =0-AD35 -> -2137317.1 | AJ35: =SUM(AJ36:AJ45) -> -2192851 | AL35: =0-AJ35 -> 2192851 | AP35: =SUM(AP36:AP45) -> -37387.736 | AR35: =0-AP35 -> 37387.736 | AV35: =SUM(AV36:AV45) -> -478580.41 | AX35: =0-AV35 -> 478580.41 | BB35: =SUM(BB36:BB45) -> 175025.62 | BD35: =0-BB35 -> -175025.62 | BH35: =SUM(BH36:BH45) -> -646580.77 | BJ35: =0-BH35 -> 646580.77 | BN35: =SUM(BN36:BN45) -> 488451.77 | BP35: =0-BN35 -> -488451.77
B36: a. Hasil Hutan | F36: ='Aset Moneter'!D10 -> 5639.768 | H36: =0-F36 -> -5639.768 | L36: ='Aset Moneter'!E10 -> 6211.529 | N36: =0-L36 -> -6211.529 | R36: ='Aset Moneter'!F10 -> 7110.7939 | T36: =0-R36 -> -7110.7939 | X36: ='Aset Moneter'!G10 -> 6302.8926 | Z36: =0-X36 -> -6302.8926 | AD36: ='Aset Moneter'!H10 -> 6860.0527 | AF36: =0-AD36 -> -6860.0527 | AJ36: ='Aset Moneter'!I10 -> 9184.7582 | AL36: =0-AJ36 -> -9184.7582 | AP36: ='Aset Moneter'!J10 -> 10313.997 | AR36: =0-AP36 -> -10313.997 | AV36: ='Aset Moneter'!K10 -> 8709.3058 | AX36: =0-AV36 -> -8709.3058 | BB36: ='Aset Moneter'!L10 -> 11850.156 | BD36: =0-BB36 -> -11850.156 | BH36: ='Aset Moneter'!M10 -> 14206.573 | BJ36: =0-BH36 -> -14206.573 | BN36: ='Aset Moneter'!N10 -> 15698.16 | BP36: =0-BN36 -> -15698.16
B37: b. Minyak Bumi | F37: ='Aset Moneter'!D24 -> 30720.524 | H37: =0-F37 -> -30720.524 | L37: ='Aset Moneter'!E24 -> 45297.101 | N37: =0-L37 -> -45297.101 | R37: ='Aset Moneter'!F24 -> 37257.867 | T37: =0-R37 -> -37257.867 | X37: ='Aset Moneter'!G24 -> 95647.459 | Z37: =0-X37 -> -95647.459 | AD37: ='Aset Moneter'!H24 -> 57406.243 | AF37: =0-AD37 -> -57406.243 | AJ37: ='Aset Moneter'!I24 -> -1179312.2 | AL37: =0-AJ37 -> 1179312.2 | AP37: ='Aset Moneter'!J24 -> 239454.88 | AR37: =0-AP37 -> -239454.88 | AV37: ='Aset Moneter'!K24 -> 6989.5507 | AX37: =0-AV37 -> -6989.5507 | BB37: ='Aset Moneter'!L24 -> 223266.08 | BD37: =0-BB37 -> -223266.08 | BH37: ='Aset Moneter'!M24 -> 354946.17 | BJ37: =0-BH37 -> -354946.17 | BN37: ='Aset Moneter'!N24 -> -74368.112 | BP37: =0-BN37 -> 74368.112
B38: c. Gas Alam | F38: ='Aset Moneter'!D34 -> 28780.916 | H38: =0-F38 -> -28780.916 | L38: ='Aset Moneter'!E34 -> 68857.884 | N38: =0-L38 -> -68857.884 | R38: ='Aset Moneter'!F34 -> -59637.711 | T38: =0-R38 -> 59637.711 | X38: ='Aset Moneter'!G34 -> 21011.296 | Z38: =0-X38 -> -21011.296 | AD38: ='Aset Moneter'!H34 -> -61004.503 | AF38: =0-AD38 -> 61004.503 | AJ38: ='Aset Moneter'!I34 -> -1155065.3 | AL38: =0-AJ38 -> 1155065.3 | AP38: ='Aset Moneter'!J34 -> -387042.26 | AR38: =0-AP38 -> 387042.26 | AV38: ='Aset Moneter'!K34 -> 25415.894 | AX38: =0-AV38 -> -25415.894 | BB38: ='Aset Moneter'!L34 -> -166293.53 | BD38: =0-BB38 -> 166293.53 | BH38: ='Aset Moneter'!M34 -> 122131.58 | BJ38: =0-BH38 -> -122131.58 | BN38: ='Aset Moneter'!N34 -> -14280.855 | BP38: =0-BN38 -> 14280.855
B39: d. Batubara | F39: ='Aset Moneter'!D44 -> 128481.76 | H39: =0-F39 -> -128481.76 | L39: ='Aset Moneter'!E44 -> 25858.496 | N39: =0-L39 -> -25858.496 | R39: ='Aset Moneter'!F44 -> -299962.97 | T39: =0-R39 -> 299962.97 | X39: ='Aset Moneter'!G44 -> -508445.66 | Z39: =0-X39 -> 508445.66 | AD39: ='Aset Moneter'!H44 -> 2029137.7 | AF39: =0-AD39 -> -2029137.7 | AJ39: ='Aset Moneter'!I44 -> 30809.29 | AL39: =0-AJ39 -> -30809.29 | AP39: ='Aset Moneter'!J44 -> 177240.6 | AR39: =0-AP39 -> -177240.6 | AV39: ='Aset Moneter'!K44 -> -276046.24 | AX39: =0-AV39 -> 276046.24 | BB39: ='Aset Moneter'!L44 -> -168905.02 | BD39: =0-BB39 -> 168905.02 | BH39: ='Aset Moneter'!M44 -> -1103022.6 | BJ39: =0-BH39 -> 1103022.6 | BN39: ='Aset Moneter'!N44 -> 395572.41 | BP39: =0-BN39 -> -395572.41
B40: e. Emas | F40: ='Aset Moneter'!D54 -> -16505.264 | H40: =0-F40 -> 16505.264 | L40: ='Aset Moneter'!E54 -> 27233.919 | N40: =0-L40 -> -27233.919 | R40: ='Aset Moneter'!F54 -> -22.83822 | T40: =0-R40 -> 22.83822 | X40: ='Aset Moneter'!G54 -> 145291.44 | Z40: =0-X40 -> -145291.44 | AD40: ='Aset Moneter'!H54 -> -89672.462 | AF40: =0-AD40 -> 89672.462 | AJ40: ='Aset Moneter'!I54 -> 96748.804 | AL40: =0-AJ40 -> -96748.804 | AP40: ='Aset Moneter'!J54 -> -125099.91 | AR40: =0-AP40 -> 125099.91 | AV40: ='Aset Moneter'!K54 -> -17200.765 | AX40: =0-AV40 -> 17200.765 | BB40: ='Aset Moneter'!L54 -> 154066.26 | BD40: =0-BB40 -> -154066.26 | BH40: ='Aset Moneter'!M54 -> 20270.474 | BJ40: =0-BH40 -> -20270.474 | BN40: ='Aset Moneter'!N54 -> 10521.526 | BP40: =0-BN40 -> -10521.526
B41: f. Perak | F41: ='Aset Moneter'!D64 -> 241.21712 | H41: =0-F41 -> -241.21712 | L41: ='Aset Moneter'!E64 -> -731.03787 | N41: =0-L41 -> 731.03787 | R41: ='Aset Moneter'!F64 -> 1337.6063 | T41: =0-R41 -> -1337.6063 | X41: ='Aset Moneter'!G64 -> -13578.289 | Z41: =0-X41 -> 13578.289 | AD41: ='Aset Moneter'!H64 -> 10139.075 | AF41: =0-AD41 -> -10139.075 | AJ41: ='Aset Moneter'!I64 -> 170.35248 | AL41: =0-AJ41 -> -170.35248 | AP41: ='Aset Moneter'!J64 -> -591.78401 | AR41: =0-AP41 -> 591.78401 | AV41: ='Aset Moneter'!K64 -> 236.99735 | AX41: =0-AV41 -> -236.99735 | BB41: ='Aset Moneter'!L64 -> 10505.26 | BD41: =0-BB41 -> -10505.26 | BH41: ='Aset Moneter'!M64 -> -170.29361 | BJ41: =0-BH41 -> 170.29361 | BN41: ='Aset Moneter'!N64 -> 86.15016 | BP41: =0-BN41 -> -86.15016
B42: g. Tembaga | F42: ='Aset Moneter'!D74 -> 5068.6222 | H42: =0-F42 -> -5068.6222 | L42: ='Aset Moneter'!E74 -> 66.508588 | N42: =0-L42 -> -66.508588 | R42: ='Aset Moneter'!F74 -> 16245.212 | T42: =0-R42 -> -16245.212 | X42: ='Aset Moneter'!G74 -> -32152.036 | Z42: =0-X42 -> 32152.036 | AD42: ='Aset Moneter'!H74 -> -7186.1077 | AF42: =0-AD42 -> 7186.1077 | AJ42: ='Aset Moneter'!I74 -> 14163.968 | AL42: =0-AJ42 -> -14163.968 | AP42: ='Aset Moneter'!J74 -> 17497.747 | AR42: =0-AP42 -> -17497.747 | AV42: ='Aset Moneter'!K74 -> -124011.67 | AX42: =0-AV42 -> 124011.67 | BB42: ='Aset Moneter'!L74 -> 83889.044 | BD42: =0-BB42 -> -83889.044 | BH42: ='Aset Moneter'!M74 -> 126764.04 | BJ42: =0-BH42 -> -126764.04 | BN42: ='Aset Moneter'!N74 -> 76571.361 | BP42: =0-BN42 -> -76571.361
B43: h. Timah | F43: ='Aset Moneter'!D84 -> 13491.352 | H43: =0-F43 -> -13491.352 | L43: ='Aset Moneter'!E84 -> 37365.684 | N43: =0-L43 -> -37365.684 | R43: ='Aset Moneter'!F84 -> 32792.605 | T43: =0-R43 -> -32792.605 | X43: ='Aset Moneter'!G84 -> -13629.008 | Z43: =0-X43 -> 13629.008 | AD43: ='Aset Moneter'!H84 -> 152190.17 | AF43: =0-AD43 -> -152190.17 | AJ43: ='Aset Moneter'!I84 -> -7813.5355 | AL43: =0-AJ43 -> 7813.5355 | AP43: ='Aset Moneter'!J84 -> 34080.104 | AR43: =0-AP43 -> -34080.104 | AV43: ='Aset Moneter'!K84 -> -53761.498 | AX43: =0-AV43 -> 53761.498 | BB43: ='Aset Moneter'!L84 -> 21071.259 | BD43: =0-BB43 -> -21071.259 | BH43: ='Aset Moneter'!M84 -> -196962.04 | BJ43: =0-BH43 -> 196962.04 | BN43: ='Aset Moneter'!N84 -> 38299.817 | BP43: =0-BN43 -> -38299.817
B44: i. Nikel | F44: ='Aset Moneter'!D94 -> 2.7599683 | H44: =0-F44 -> -2.7599683 | L44: ='Aset Moneter'!E94 -> 111761.09 | N44: =0-L44 -> -111761.09 | R44: ='Aset Moneter'!F94 -> -10028.796 | T44: =0-R44 -> 10028.796 | X44: ='Aset Moneter'!G94 -> 76170.173 | Z44: =0-X44 -> -76170.173 | AD44: ='Aset Moneter'!H94 -> 38105.138 | AF44: =0-AD44 -> -38105.138 | AJ44: ='Aset Moneter'!I94 -> -1861.715 | AL44: =0-AJ44 -> 1861.715 | AP44: ='Aset Moneter'!J94 -> -30795.565 | AR44: =0-AP44 -> 30795.565 | AV44: ='Aset Moneter'!K94 -> 25024.272 | AX44: =0-AV44 -> -25024.272 | BB44: ='Aset Moneter'!L94 -> 170.97837 | BD44: =0-BB44 -> -170.97837 | BH44: ='Aset Moneter'!M94 -> 15170.048 | BJ44: =0-BH44 -> -15170.048 | BN44: ='Aset Moneter'!N94 -> 31710.237 | BP44: =0-BN44 -> -31710.237
B45: j. Bauksit | F45: ='Aset Moneter'!D104 -> 68.394418 | H45: =0-F45 -> -68.394418 | L45: ='Aset Moneter'!E104 -> 5623.3098 | N45: =0-L45 -> -5623.3098 | R45: ='Aset Moneter'!F104 -> 500.20427 | T45: =0-R45 -> -500.20427 | X45: ='Aset Moneter'!G104 -> 6373.3805 | Z45: =0-X45 -> -6373.3805 | AD45: ='Aset Moneter'!H104 -> 1341.7766 | AF45: =0-AD45 -> -1341.7766 | AJ45: ='Aset Moneter'!I104 -> 124.65003 | AL45: =0-AJ45 -> -124.65003 | AP45: ='Aset Moneter'!J104 -> 27554.453 | AR45: =0-AP45 -> -27554.453 | AV45: ='Aset Moneter'!K104 -> -73936.256 | AX45: =0-AV45 -> 73936.256 | BB45: ='Aset Moneter'!L104 -> 5405.1374 | BD45: =0-BB45 -> -5405.1374 | BH45: ='Aset Moneter'!M104 -> 85.313697 | BJ45: =0-BH45 -> -85.313697 | BN45: ='Aset Moneter'!N104 -> 8641.0762 | BP45: =0-BN45 -> -8641.0762
A46: 8 | B46: PDN 1 | C46: =C23-C24 -> 8373652.9 | D46: =D23 -> 7035633.7 | E46: =E23 -> 1642635.4 | F46: =F35+F24-F36 -> -35182.648 | G46: =G23 -> -79083.211 | H46: =H35 -> -195990.05 | I46: =I23-I24 -> 9140542.4 | J46: =J23 -> 7745630.1 | K46: =K23 -> 1607151.1 | L46: =L35+L24-L36 -> 64980.805 | M46: =M23 -> 44113.382 | N46: =N35 -> -327544.48 | O46: =O23-O24 -> 10172459 | P46: =P23 -> 8353136 | Q46: =Q23 -> 1919066 | R46: =R35+R24-R36 -> -475098.59 | S46: =S23 -> 93837.171 | T46: =T35 -> 274408.03 | U46: =U23-U24 -> 10940878 | V46: =V23 -> 9023120.3 | W46: =W23 -> 1999990.5 | X46: =X35+X24-X36 -> -441321.25 | Y46: =Y23 -> 135777.55 | Z46: =Z35 -> 217008.35 | AA46: =AA23-AA24 -> 11793028 | AB46: =AB23 -> 9793746.3 | AC46: =AC23 -> 2403578.5 | AD46: =AD35+AD24-AD36 -> 1884759.7 | AE46: =AE23 -> -158598.99 | AF46: =AF35 -> -2137317.1 | AG46: =AG23-AG24 -> 12341083 | AH46: =AH23 -> 10566547 | AI46: =AI23 -> 2168420.4 | AJ46: =AJ35+AJ24-AJ36 -> -2525508.8 | AK46: =AK23 -> -70411.3 | AL46: =AL35 -> 2192851 | AM46: =AM23-AM24 -> 12217740 | AN46: =AN23 -> 10592541 | AO46: =AO23 -> 1645989.8 | AP46: =AP35+AP24-AP36 -> -329510.29 | AQ46: =AQ23 -> 261017.56 | AR46: =AR35 -> 37387.736 | AS46: =AS23-AS24 -> 13474916 | AT46: =AT23 -> 11013796 | AU46: =AU23 -> 2370337.7 | AV46: =AV35+AV24-AV36 -> -842715.59 | AW46: =AW23 -> 446208.96 | AX46: =AX35 -> 478580.41 | AY46: =AY23-AY24 -> 15324601 | AZ46: =AZ23 -> 11896997 | BA46: =BA23 -> 3311760.9 | BB46: =BB35+BB24-BB36 -> -414639.55 | BC46: =BC23 -> 693657.37 | BD46: =BD35 -> -175025.62 | BE46: =BE23-BE24 -> 15937626 | BF46: =BF23 -> 12928272 | BG46: =BG23 -> 3372114.2 | BH46: =BH35+BH24-BH36 -> -1477205.3 | BI46: =BI23 -> 453658.03 | BJ46: =BJ35 -> 646580.77 | BK46: =BK23-BK24 -> 17005683 | BL46: =BL23 -> 13976578 | BM46: =BM23 -> 3338958.7 | BN46: =BN35+BN24-BN36 -> -234267.84 | BO46: =BO23 -> 397168.24 | BP46: =BP35 -> -488451.77
A47: 9 | B47: Revaluasi
B48: Barang Modal | E48: =E60-E46-E9 -> 3145856.7 | K48: =K60-K46-K9 -> 1914113.9 | Q48: =Q60-Q46-Q9 -> 1318339.4 | W48: =W60-W46-W9 -> 2311045.3 | AC48: =AC60-AC46-AC9 -> 2816519.2 | AI48: =AI60-AI46-AI9 -> 1617443.7 | AO48: =AO60-AO46-AO9 -> 1842694.6 | AU48: =AU60-AU46-AU9 -> 3659416.5 | BA48: =BA60-BA46-BA9 -> 3334636.5 | BG48: =BG60-BG46-BG9 -> 2718562.5 | BM48: =BM60-BM46-BM9 -> 3113572
B49: a. Hasil Hutan | F49: ='Aset Moneter'!D15 -> 47446.501 | L49: ='Aset Moneter'!E15 -> -1472.309 | R49: ='Aset Moneter'!F15 -> 85161.98 | X49: ='Aset Moneter'!G15 -> 99106.76 | AD49: ='Aset Moneter'!H15 -> 17814.209 | AJ49: ='Aset Moneter'!I15 -> 157217.01 | AP49: ='Aset Moneter'!J15 -> 157930.02 | AV49: ='Aset Moneter'!K15 -> 176558.81 | BB49: ='Aset Moneter'!L15 -> 102581.11 | BH49: ='Aset Moneter'!M15 -> 344684.22 | BN49: ='Aset Moneter'!N15 -> -3840.5881
B50: b. Minyak Bumi | F50: ='Aset Moneter'!D25 -> -147335.56 | L50: ='Aset Moneter'!E25 -> -793537.46 | R50: ='Aset Moneter'!F25 -> -81814.455 | X50: ='Aset Moneter'!G25 -> 357315.45 | AD50: ='Aset Moneter'!H25 -> 388979.48 | AJ50: ='Aset Moneter'!I25 -> 1094467.2 | AP50: ='Aset Moneter'!J25 -> -562127.59 | AV50: ='Aset Moneter'!K25 -> 608802.28 | BB50: ='Aset Moneter'!L25 -> 403556.83 | BH50: ='Aset Moneter'!M25 -> -621083.24 | BN50: ='Aset Moneter'!N25 -> 145800.33
B51: c. Gas Alam | F51: ='Aset Moneter'!D35 -> -265018.81 | L51: ='Aset Moneter'!E35 -> 136007.26 | R51: ='Aset Moneter'!F35 -> 109667.72 | X51: ='Aset Moneter'!G35 -> 2287.3592 | AD51: ='Aset Moneter'!H35 -> 8539.4995 | AJ51: ='Aset Moneter'!I35 -> 1315947.1 | AP51: ='Aset Moneter'!J35 -> 565651.8 | AV51: ='Aset Moneter'!K35 -> 450029.71 | BB51: ='Aset Moneter'!L35 -> 729076.67 | BH51: ='Aset Moneter'!M35 -> -342831.44 | BN51: ='Aset Moneter'!N35 -> 67246.415
B52: d. Batubara | F52: ='Aset Moneter'!D45 -> -838957.18 | L52: ='Aset Moneter'!E45 -> 169608.56 | R52: ='Aset Moneter'!F45 -> 666177.16 | X52: ='Aset Moneter'!G45 -> 1836963.3 | AD52: ='Aset Moneter'!H45 -> -1737584.1 | AJ52: ='Aset Moneter'!I45 -> -242829.04 | AP52: ='Aset Moneter'!J45 -> -570405.06 | AV52: ='Aset Moneter'!K45 -> 3855326.6 | BB52: ='Aset Moneter'!L45 -> 8464861.7 | BH52: ='Aset Moneter'!M45 -> -202799.1 | BN52: ='Aset Moneter'!N45 -> -3820771.9
B53: e. Emas | F53: ='Aset Moneter'!D55 -> 28091.564 | L53: ='Aset Moneter'!E55 -> 92697.544 | R53: ='Aset Moneter'!F55 -> 30488.252 | X53: ='Aset Moneter'!G55 -> -88217.946 | AD53: ='Aset Moneter'!H55 -> -98352.408 | AJ53: ='Aset Moneter'!I55 -> -157944.8 | AP53: ='Aset Moneter'!J55 -> 199146.18 | AV53: ='Aset Moneter'!K55 -> 80154.659 | BB53: ='Aset Moneter'!L55 -> -66133.6 | BH53: ='Aset Moneter'!M55 -> 49526.108 | BN53: ='Aset Moneter'!N55 -> 86041.101
B54: f. Perak | F54: ='Aset Moneter'!D65 -> -871.24425 | L54: ='Aset Moneter'!E65 -> 2372.482 | R54: ='Aset Moneter'!F65 -> 1584.7716 | X54: ='Aset Moneter'!G65 -> 9454.3675 | AD54: ='Aset Moneter'!H65 -> -17403.883 | AJ54: ='Aset Moneter'!I65 -> 331.93582 | AP54: ='Aset Moneter'!J65 -> 1103.7495 | AV54: ='Aset Moneter'!K65 -> 324.12151 | BB54: ='Aset Moneter'!L65 -> -11330.365 | BH54: ='Aset Moneter'!M65 -> 1277.3015 | BN54: ='Aset Moneter'!N65 -> 3164.2239
B55: g. Tembaga | F55: ='Aset Moneter'!D75 -> -143444.61 | L55: ='Aset Moneter'!E75 -> -40937.29 | R55: ='Aset Moneter'!F75 -> 13215.261 | X55: ='Aset Moneter'!G75 -> 73342.992 | AD55: ='Aset Moneter'!H75 -> 29266.635 | AJ55: ='Aset Moneter'!I75 -> -70293.646 | AP55: ='Aset Moneter'!J75 -> 414112.6 | AV55: ='Aset Moneter'!K75 -> 474323.88 | BB55: ='Aset Moneter'!L75 -> 75637.958 | BH55: ='Aset Moneter'!M75 -> 61295.529 | BN55: ='Aset Moneter'!N75 -> 131958.55
B56: h. Timah | F56: ='Aset Moneter'!D85 -> -41814.627 | L56: ='Aset Moneter'!E85 -> -13740.74 | R56: ='Aset Moneter'!F85 -> -2302.5638 | X56: ='Aset Moneter'!G85 -> 24880.925 | AD56: ='Aset Moneter'!H85 -> -108420.41 | AJ56: ='Aset Moneter'!I85 -> 24745.321 | AP56: ='Aset Moneter'!J85 -> 26733.172 | AV56: ='Aset Moneter'!K85 -> 171659.99 | BB56: ='Aset Moneter'!L85 -> 65725.64 | BH56: ='Aset Moneter'!M85 -> 272265.49 | BN56: ='Aset Moneter'!N85 -> 73116.428
B57: i. Nikel | F57: ='Aset Moneter'!D95 -> 26256.526 | L57: ='Aset Moneter'!E95 -> -57544.122 | R57: ='Aset Moneter'!F95 -> 166656.64 | X57: ='Aset Moneter'!G95 -> -99430.858 | AD57: ='Aset Moneter'!H95 -> -277368.38 | AJ57: ='Aset Moneter'!I95 -> 3372.4877 | AP57: ='Aset Moneter'!J95 -> 103087.62 | AV57: ='Aset Moneter'!K95 -> 36093.058 | BB57: ='Aset Moneter'!L95 -> 8443.5155 | BH57: ='Aset Moneter'!M95 -> 5998.9982 | BN57: ='Aset Moneter'!N95 -> 5153.4136
B58: j. Bauksit | F58: ='Aset Moneter'!D105 -> -41433.283 | L58: ='Aset Moneter'!E105 -> -10184.041 | R58: ='Aset Moneter'!F105 -> 13140.444 | X58: ='Aset Moneter'!G105 -> 29468.452 | AD58: ='Aset Moneter'!H105 -> 28995.962 | AJ58: ='Aset Moneter'!I105 -> 37872.097 | AP58: ='Aset Moneter'!J105 -> -53633.524 | AV58: ='Aset Moneter'!K105 -> 114713.25 | BB58: ='Aset Moneter'!L105 -> 25247.178 | BH58: ='Aset Moneter'!M105 -> 28800.923 | BN58: ='Aset Moneter'!N105 -> 30921.679
A59: 10 | B59: Stok Akhir
B60: Barang Modal | E60: ='Stok Kapital'!J7 -> 38102453 | K60: ='Stok Kapital'!Q7 -> 41623718 | Q60: ='Stok Kapital'!Y7 -> 44861123 | R60: =SUM(R61:R70) -> 7621715.7 | W60: ='Stok Kapital'!AG7 -> 49172159 | X60: =SUM(X61:X70) -> 9431868.4 | AC60: ='Stok Kapital'!AO7 -> 54392257 | AD60: =SUM(AD61:AD70) -> 9557954.7 | AI60: ='Stok Kapital'!AW7 -> 58178121 | AJ60: =SUM(AJ61:AJ70) -> 9204516.4 | AO60: ='Stok Kapital'!BE7 -> 61666805 | AP60: =SUM(AP61:AP70) -> 9166919 | AU60: ='Stok Kapital'!BM7 -> 67696559 | AV60: =SUM(AV61:AV70) -> 14300899 | BA60: ='Stok Kapital'!BU7 -> 74342957 | BB60: =SUM(BB61:BB70) -> 23695776 | BG60: ='Stok Kapital'!CC7 -> 80433633 | BH60: =SUM(BH61:BH70) -> 21829912 | BM60: ='Stok Kapital'!CK7 -> 86886164 | BN60: =SUM(BN61:BN70) -> 18330132
B61: a. Hasil Hutan | F61: ='Aset Moneter'!D16 -> 719985.09 | L61: ='Aset Moneter'!E16 -> 628834.11 | R61: ='Aset Moneter'!F16 -> 681499.89 | X61: ='Aset Moneter'!G16 -> 749533.49 | AD61: ='Aset Moneter'!H16 -> 740284 | AJ61: ='Aset Moneter'!I16 -> 818198.38 | AP61: ='Aset Moneter'!J16 -> 952915.52 | AV61: ='Aset Moneter'!K16 -> 1100095.7 | BB61: ='Aset Moneter'!L16 -> 1173971.8 | BH61: ='Aset Moneter'!M16 -> 1390349.6 | BN61: ='Aset Moneter'!N16 -> 1330038.2
B62: b. Minyak Bumi | F62: ='Aset Moneter'!D26 -> 1936674 | L62: ='Aset Moneter'!E26 -> 1128616.9 | R62: ='Aset Moneter'!F26 -> 1038776.4 | X62: ='Aset Moneter'!G26 -> 1442786.8 | AD62: ='Aset Moneter'!H26 -> 1827895.4 | AJ62: ='Aset Moneter'!I26 -> 1650482.1 | AP62: ='Aset Moneter'!J26 -> 1232797.1 | AV62: ='Aset Moneter'!K26 -> 1759477.5 | BB62: ='Aset Moneter'!L26 -> 2275538.7 | BH62: ='Aset Moneter'!M26 -> 1904383.6 | BN62: ='Aset Moneter'!N26 -> 1886353.2
B63: c. Gas Alam | F63: ='Aset Moneter'!D36 -> 1929560.4 | L63: ='Aset Moneter'!E36 -> 2092742.2 | R63: ='Aset Moneter'!F36 -> 2099174 | X63: ='Aset Moneter'!G36 -> 2081924.9 | AD63: ='Aset Moneter'!H36 -> 1985652.1 | AJ63: ='Aset Moneter'!I36 -> 2088004.1 | AP63: ='Aset Moneter'!J36 -> 2190729.9 | AV63: ='Aset Moneter'!K36 -> 2571830.7 | BB63: ='Aset Moneter'!L36 -> 3019060 | BH63: ='Aset Moneter'!M36 -> 2672571.9 | BN63: ='Aset Moneter'!N36 -> 2602475
B64: d. Batubara | F64: ='Aset Moneter'!D46 -> 2374378.3 | L64: ='Aset Moneter'!E46 -> 2534793.4 | R64: ='Aset Moneter'!F46 -> 2860161.4 | X64: ='Aset Moneter'!G46 -> 4126241.8 | AD64: ='Aset Moneter'!H46 -> 4338434.3 | AJ64: ='Aset Moneter'!I46 -> 4057943.9 | AP64: ='Aset Moneter'!J46 -> 3608155.4 | AV64: ='Aset Moneter'!K46 -> 7098820.3 | BB64: ='Aset Moneter'!L46 -> 15178689 | BH64: ='Aset Moneter'!M46 -> 13539562 | BN64: ='Aset Moneter'!N46 -> 9807565.6
B65: e. Emas | F65: ='Aset Moneter'!D56 -> 200366.45 | L65: ='Aset Moneter'!E56 -> 311024.64 | R65: ='Aset Moneter'!F56 -> 330729.39 | X65: ='Aset Moneter'!G56 -> 376606.06 | AD65: ='Aset Moneter'!H56 -> 177537.95 | AJ65: ='Aset Moneter'!I56 -> 111404.04 | AP65: ='Aset Moneter'!J56 -> 181971.97 | AV65: ='Aset Moneter'!K56 -> 236975.2 | BB65: ='Aset Moneter'!L56 -> 313647.4 | BH65: ='Aset Moneter'!M56 -> 372761.02 | BN65: ='Aset Moneter'!N56 -> 461930.73
B66: f. Perak | F66: ='Aset Moneter'!D66 -> 13473.768 | L66: ='Aset Moneter'!E66 -> 14780.666 | R66: ='Aset Moneter'!F66 -> 17318.011 | X66: ='Aset Moneter'!G66 -> 12622.997 | AD66: ='Aset Moneter'!H66 -> 4957.2855 | AJ66: ='Aset Moneter'!I66 -> 5269.9371 | AP66: ='Aset Moneter'!J66 -> 5627.0929 | AV66: ='Aset Moneter'!K66 -> 5993.334 | BB66: ='Aset Moneter'!L66 -> 5023.8836 | BH66: ='Aset Moneter'!M66 -> 6092.4315 | BN66: ='Aset Moneter'!N66 -> 9245.0701
B67: g. Tembaga | F67: ='Aset Moneter'!D76 -> 220254.27 | L67: ='Aset Moneter'!E76 -> 172752.29 | R67: ='Aset Moneter'!F76 -> 195241.87 | X67: ='Aset Moneter'!G76 -> 228644.7 | AD67: ='Aset Moneter'!H76 -> 243466.58 | AJ67: ='Aset Moneter'!I76 -> 182470.54 | AP67: ='Aset Moneter'!J76 -> 603209.49 | AV67: ='Aset Moneter'!K76 -> 925405.54 | BB67: ='Aset Moneter'!L76 -> 1018188.9 | BH67: ='Aset Moneter'!M76 -> 1137311.4 | BN67: ='Aset Moneter'!N76 -> 1264494.2
B68: h. Timah | F68: ='Aset Moneter'!D86 -> 33762.4 | L68: ='Aset Moneter'!E86 -> 50123.665 | R68: ='Aset Moneter'!F86 -> 75206.158 | X68: ='Aset Moneter'!G86 -> 78627.703 | AD68: ='Aset Moneter'!H86 -> 115623.7 | AJ68: ='Aset Moneter'!I86 -> 128560.7 | AP68: ='Aset Moneter'!J86 -> 185956.97 | AV68: ='Aset Moneter'!K86 -> 300256.29 | BB68: ='Aset Moneter'!L86 -> 378436.44 | BH68: ='Aset Moneter'!M86 -> 436324.54 | BN68: ='Aset Moneter'!N86 -> 534000.08
B69: i. Nikel | F69: ='Aset Moneter'!D96 -> 97741.009 | L69: ='Aset Moneter'!E96 -> 151552 | R69: ='Aset Moneter'!F96 -> 307466.17 | X69: ='Aset Moneter'!G96 -> 282952.63 | AD69: ='Aset Moneter'!H96 -> 42142.188 | AJ69: ='Aset Moneter'!I96 -> 42808.066 | AP69: ='Aset Moneter'!J96 -> 113056.09 | AV69: ='Aset Moneter'!K96 -> 169831.81 | BB69: ='Aset Moneter'!L96 -> 172030.87 | BH69: ='Aset Moneter'!M96 -> 181377.43 | BN69: ='Aset Moneter'!N96 -> 205899.19
B70: j. Bauksit | F70: ='Aset Moneter'!D106 -> 7070.8202 | L70: ='Aset Moneter'!E106 -> 2508.8634 | R70: ='Aset Moneter'!F106 -> 16142.363 | X70: ='Aset Moneter'!G106 -> 51927.4 | AD70: ='Aset Moneter'!H106 -> 81961.192 | AJ70: ='Aset Moneter'!I106 -> 119374.6 | AP70: ='Aset Moneter'!J106 -> 92499.539 | AV70: ='Aset Moneter'!K106 -> 132212.83 | BB70: ='Aset Moneter'!L106 -> 161189.47 | BH70: ='Aset Moneter'!M106 -> 189178.53 | BN70: ='Aset Moneter'!N106 -> 228131.09
Q73: =Q60/(Q60+R60)*100 -> 85.477699 | R73: =R60/(Q60+R60)*100 -> 14.522301 | W73: =W60/(W60+X60)*100 -> 83.905767 | X73: =X60/(W60+X60)*100 -> 16.094233 | AC73: =AC60/(AC60+AD60)*100 -> 85.054069 | AD73: =AD60/(AC60+AD60)*100 -> 14.945931 | AI73: =AI60/(AI60+AJ60)*100 -> 86.339929 | AJ73: =AJ60/(AI60+AJ60)*100 -> 13.660071 | AO73: =AO60/(AO60+AP60)*100 -> 87.058539 | AP73: =AP60/(AO60+AP60)*100 -> 12.941461 | AU73: =AU60/(AU60+AV60)*100 -> 82.559339 | AV73: =AV60/(AU60+AV60)*100 -> 17.440661 | BA73: =BA60/(BA60+BB60)*100 -> 75.830189 | BB73: =BB60/(BA60+BB60)*100 -> 24.169811 | BG73: =BG60/(BG60+BH60)*100 -> 78.65328 | BH73: =BH60/(BG60+BH60)*100 -> 21.34672 | BM73: =BM60/(BM60+BN60)*100 -> 82.578619 | BN73: =BN60/(BM60+BN60)*100 -> 17.421381
O77: =O22/I22*100-100 -> -4.4025142 | P77: =O24/I24*100-100 -> -24.486778 | U77: =U22/O22*100-100 -> 19.415931 | V77: =U24/O24*100-100 -> 12.620245 | AA77: =AA22/U22*100-100 -> 15.183146 | AB77: =AA24/U24*100-100 -> 12.700022 | AG77: =AG22/AA22*100-100 -> 13.145248 | AH77: =AG24/AA24*100-100 -> 31.655079 | AM77: =AM22/AG22*100-100 -> -7.0798284 | AN77: =AM24/AG24*100-100 -> -12.88035 | AS77: =AS22/AM22*100-100 -> 6.8823883 | AT77: =AS24/AM24*100-100 -> 26.123169 | AY77: =AY22/AS22*100-100 -> 17.15083 | AZ77: =AY24/AS24*100-100 -> 62.569767 | BE77: =BE22/AY22*100-100 -> 12.269526 | BF77: =BE24/AY24*100-100 -> 41.294005 | BK77: =BK22/BE22*100-100 -> 6.9582751 | BL77: =BK24/BE24*100-100 -> -13.399575

Sheet PDB vs PDN1
A3: Komponen | C3: =G3-1 -> 2014 | G3: ='PDB ADHB'!C1 -> 2015 | K3: ='PDB ADHB'!D1 -> 2016 | O3: ='PDB ADHB'!E1 -> 2017 | S3: ='PDB ADHB'!F1 -> 2018 | W3: ='PDB ADHB'!G1 -> 2019 | AA3: ='PDB ADHB'!H1 -> 2020 | AE3: ='PDB ADHB'!I1 -> 2021 | AI3: ='PDB ADHB'!J1 -> 2022 | AM3: ='PDB ADHB'!K1 -> 2023* | AQ3: ='PDB ADHB'!L1 -> 2024**
C4: 1. Konsumsi Akhir | D4: 2. Akumulasi Kapital, neto | E4: 3. Ekspor Neto | F4: 4. Jumlah | G4: 1. Konsumsi Akhir | H4: 2. Akumulasi Kapital, neto | I4: 3. Ekspor Neto | J4: 4. Jumlah | K4: 1. Konsumsi Akhir | L4: 2. Akumulasi Kapital, neto | M4: 3. Ekspor Neto | N4: 4. Jumlah | O4: 1. Konsumsi Akhir | P4: 2. Akumulasi Kapital, neto | Q4: 3. Ekspor Neto | R4: 4. Jumlah | S4: 1. Konsumsi Akhir | T4: 2. Akumulasi Kapital, neto | U4: 3. Ekspor Neto | V4: 4. Jumlah | W4: 1. Konsumsi Akhir | X4: 2. Akumulasi Kapital, neto | Y4: 3. Ekspor Neto | Z4: 4. Jumlah | AA4: 1. Konsumsi Akhir | AB4: 2. Akumulasi Kapital, neto | AC4: 3. Ekspor Neto | AD4: 4. Jumlah | AE4: 1. Konsumsi Akhir | AF4: 2. Akumulasi Kapital, neto | AG4: 3. Ekspor Neto | AH4: 4. Jumlah | AI4: 1. Konsumsi Akhir | AJ4: 2. Akumulasi Kapital, neto | AK4: 3. Ekspor Neto | AL4: 4. Jumlah | AM4: 1. Konsumsi Akhir | AN4: 2. Akumulasi Kapital, neto | AO4: 3. Ekspor Neto | AP4: 4. Jumlah | AQ4: 1. Konsumsi Akhir | AR4: 2. Akumulasi Kapital, neto | AS4: 3. Ekspor Neto | AT4: 4. Jumlah
A5: PDN | B5: Nilai (Milliar RP) | C5: ='Neraca Terpadu'!D23 -> 7035633.7 | D5: ='Neraca Terpadu'!E23 -> 1642635.4 | E5: ='Neraca Terpadu'!G23 -> -79083.211 | F5: =SUM(C5:E5) -> 8599185.9 | G5: ='Neraca Terpadu'!J23 -> 7745630.1 | H5: ='Neraca Terpadu'!K23 -> 1607151.1 | I5: ='Neraca Terpadu'!M23 -> 44113.382 | J5: =SUM(G5:I5) -> 9396894.6 | K5: ='Neraca Terpadu'!P23 -> 8353136 | L5: ='Neraca Terpadu'!Q23 -> 1919066 | M5: ='Neraca Terpadu'!S23 -> 93837.171 | N5: =SUM(K5:M5) -> 10366039 | O5: ='Neraca Terpadu'!V23 -> 9023120.3 | P5: ='Neraca Terpadu'!W23 -> 1999990.5 | Q5: ='Neraca Terpadu'!Y23 -> 135777.55 | R5: =SUM(O5:Q5) -> 11158888 | S5: ='Neraca Terpadu'!AB23 -> 9793746.3 | T5: ='Neraca Terpadu'!AC23 -> 2403578.5 | U5: ='Neraca Terpadu'!AE23 -> -158598.99 | V5: =SUM(S5:U5) -> 12038726 | W5: ='Neraca Terpadu'!AH23 -> 10566547 | X5: ='Neraca Terpadu'!AI23 -> 2168420.4 | Y5: ='Neraca Terpadu'!AK23 -> -70411.3 | Z5: =SUM(W5:Y5) -> 12664556 | AA5: ='Neraca Terpadu'!AN23 -> 10592541 | AB5: ='Neraca Terpadu'!AO23 -> 1645989.8 | AC5: ='Neraca Terpadu'!AQ23 -> 261017.56 | AD5: =SUM(AA5:AC5) -> 12499548 | AE5: ='Neraca Terpadu'!AT23 -> 11013796 | AF5: ='Neraca Terpadu'!AU23 -> 2370337.7 | AG5: ='Neraca Terpadu'!AW23 -> 446208.96 | AH5: =SUM(AE5:AG5) -> 13830342 | AI5: ='Neraca Terpadu'!AZ23 -> 11896997 | AJ5: ='Neraca Terpadu'!BA23 -> 3311760.9 | AK5: ='Neraca Terpadu'!BC23 -> 693657.37 | AL5: =SUM(AI5:AK5) -> 15902416 | AM5: ='Neraca Terpadu'!BF23 -> 12928272 | AN5: ='Neraca Terpadu'!BG23 -> 3372114.2 | AO5: ='Neraca Terpadu'!BI23 -> 453658.03 | AP5: =SUM(AM5:AO5) -> 16754044 | AQ5: ='Neraca Terpadu'!BL23 -> 13976578 | AR5: ='Neraca Terpadu'!BM23 -> 3338958.7 | AS5: ='Neraca Terpadu'!BO23 -> 397168.24 | AT5: =SUM(AQ5:AS5) -> 17712705
B6: Distribusi (%) | C6: =C5/$F$5*100 -> 81.817439 | D6: =D5/$F$5*100 -> 19.10222 | E6: =E5/$F$5*100 -> -0.91965928 | F6: =SUM(C6:E6) -> 100 | G6: =G5/$J$5*100 -> 82.427552 | H6: =H5/$J$5*100 -> 17.103002 | I6: =I5/$J$5*100 -> 0.46944639 | J6: =SUM(G6:I6) -> 100 | K6: =K5/$N$5*100 -> 80.581752 | L6: =L5/$N$5*100 -> 18.513011 | M6: =M5/$N$5*100 -> 0.90523651 | N6: =SUM(K6:M6) -> 100 | O6: =O5/$R$5*100 -> 80.860387 | P6: =P5/$R$5*100 -> 17.922847 | Q6: =Q5/$R$5*100 -> 1.2167659 | R6: =SUM(O6:Q6) -> 100 | S6: =S5/$V$5*100 -> 81.352017 | T6: =T5/$V$5*100 -> 19.96539 | U6: =U5/$V$5*100 -> -1.3174068 | V6: =SUM(S6:U6) -> 100 | W6: =W5/$Z$5*100 -> 83.43401 | X6: =X5/$Z$5*100 -> 17.121962 | Y6: =Y5/$Z$5*100 -> -0.55597133 | Z6: =SUM(W6:Y6) -> 100 | AA6: =AA5/$AD$5*100 -> 84.743389 | AB6: =AB5/$AD$5*100 -> 13.168395 | AC6: =AC5/$AD$5*100 -> 2.088216 | AD6: =SUM(AA6:AC6) -> 100 | AE6: =AE5/$AH$5*100 -> 79.635018 | AF6: =AF5/$AH$5*100 -> 17.138677 | AG6: =AG5/$AH$5*100 -> 3.2263045 | AH6: =SUM(AE6:AG6) -> 100 | AI6: =AI5/$AL$5*100 -> 74.812517 | AJ6: =AJ5/$AL$5*100 -> 20.825521 | AK6: =AK5/$AL$5*100 -> 4.3619623 | AL6: =SUM(AI6:AK6) -> 100 | AM6: =AM5/$AP$5*100 -> 77.165082 | AN6: =AN5/$AP$5*100 -> 20.127166 | AO6: =AO5/$AP$5*100 -> 2.7077524 | AP6: =SUM(AM6:AO6) -> 100 | AQ6: =AQ5/$AT$5*100 -> 78.907078 | AR6: =AR5/$AT$5*100 -> 18.850643 | AS6: =AS5/$AT$5*100 -> 2.2422789 | AT6: =SUM(AQ6:AS6) -> 100
A7: PDN1 | B7: Nilai (Milliar RP) | C7: ='Neraca Terpadu'!D46 -> 7035633.7 | D7: =F7-C7-E7 -> 1417102.5 | E7: ='Neraca Terpadu'!G46 -> -79083.211 | F7: ='Neraca Terpadu'!C46 -> 8373652.9 | G7: ='Neraca Terpadu'!J46 -> 7745630.1 | H7: =J7-G7-I7 -> 1350798.9 | I7: ='Neraca Terpadu'!M46 -> 44113.382 | J7: ='Neraca Terpadu'!I46 -> 9140542.4 | K7: ='Neraca Terpadu'!P46 -> 8353136 | L7: =N7-K7-M7 -> 1725486.2 | M7: ='Neraca Terpadu'!S46 -> 93837.171 | N7: ='Neraca Terpadu'!O46 -> 10172459 | O7: ='Neraca Terpadu'!V46 -> 9023120.3 | P7: =R7-O7-Q7 -> 1781980.4 | Q7: ='Neraca Terpadu'!Y46 -> 135777.55 | R7: ='Neraca Terpadu'!U46 -> 10940878 | S7: ='Neraca Terpadu'!AB46 -> 9793746.3 | T7: =V7-S7-U7 -> 2157881.2 | U7: ='Neraca Terpadu'!AE46 -> -158598.99 | V7: ='Neraca Terpadu'!AA46 -> 11793028 | W7: ='Neraca Terpadu'!AH46 -> 10566547 | X7: =Z7-W7-Y7 -> 1844947.4 | Y7: ='Neraca Terpadu'!AK46 -> -70411.3 | Z7: ='Neraca Terpadu'!AG46 -> 12341083 | AA7: ='Neraca Terpadu'!AN46 -> 10592541 | AB7: =AD7-AA7-AC7 -> 1364181.3 | AC7: ='Neraca Terpadu'!AQ46 -> 261017.56 | AD7: ='Neraca Terpadu'!AM46 -> 12217740 | AE7: ='Neraca Terpadu'!AT46 -> 11013796 | AF7: =AH7-AE7-AG7 -> 2014911.9 | AG7: ='Neraca Terpadu'!AW46 -> 446208.96 | AH7: ='Neraca Terpadu'!AS46 -> 13474916 | AI7: ='Neraca Terpadu'!AZ46 -> 11896997 | AJ7: =AL7-AI7-AK7 -> 2733945.9 | AK7: ='Neraca Terpadu'!BC46 -> 693657.37 | AL7: ='Neraca Terpadu'!AY46 -> 15324601 | AM7: ='Neraca Terpadu'!BF46 -> 12928272 | AN7: =AP7-AM7-AO7 -> 2555696.2 | AO7: ='Neraca Terpadu'!BI46 -> 453658.03 | AP7: ='Neraca Terpadu'!BE46 -> 15937626 | AQ7: ='Neraca Terpadu'!BL46 -> 13976578 | AR7: =AT7-AQ7-AS7 -> 2631937.3 | AS7: ='Neraca Terpadu'!BO46 -> 397168.24 | AT7: ='Neraca Terpadu'!BK46 -> 17005683
B8: Distribusi (%) | C8: =C7/$F$7*100 -> 84.02108 | D8: =D7/$F$7*100 -> 16.923349 | E8: =E7/$F$7*100 -> -0.94442905 | F8: =SUM(C8:E8) -> 100 | G8: =G7/$J$7*100 -> 84.739283 | H8: =H7/$J$7*100 -> 14.778105 | I8: =I7/$J$7*100 -> 0.4826123 | J8: =SUM(G8:I8) -> 100 | K8: =K7/$N$7*100 -> 82.115206 | L8: =L7/$N$7*100 -> 16.962331 | M8: =M7/$N$7*100 -> 0.92246297 | N8: =SUM(K8:M8) -> 100 | O8: =O7/$R$7*100 -> 82.471627 | P8: =P7/$R$7*100 -> 16.287362 | Q8: =Q7/$R$7*100 -> 1.2410115 | R8: =SUM(O8:Q8) -> 100 | S8: =S7/$V$7*100 -> 83.046914 | T8: =T7/$V$7*100 -> 18.297939 | U8: =U7/$V$7*100 -> -1.3448538 | V8: =SUM(S8:U8) -> 100 | W8: =W7/$Z$7*100 -> 85.620904 | X8: =X7/$Z$7*100 -> 14.949639 | Y8: =Y7/$Z$7*100 -> -0.57054393 | Z8: =SUM(W8:Y8) -> 100 | AA8: =AA7/$AD$7*100 -> 86.69804 | AB8: =AB7/$AD$7*100 -> 11.165578 | AC8: =AC7/$AD$7*100 -> 2.1363817 | AD8: =SUM(AA8:AC8) -> 100 | AE8: =AE7/$AH$7*100 -> 81.735539 | AF8: =AF7/$AH$7*100 -> 14.953056 | AG8: =AG7/$AH$7*100 -> 3.3114043 | AH8: =SUM(AE8:AG8) -> 100 | AI8: =AI7/$AL$7*100 -> 77.633327 | AJ8: =AJ7/$AL$7*100 -> 17.840243 | AK8: =AK7/$AL$7*100 -> 4.5264303 | AL8: =SUM(AI8:AK8) -> 100 | AM8: =AM7/$AP$7*100 -> 81.117927 | AN8: =AN7/$AP$7*100 -> 16.035614 | AO8: =AO7/$AP$7*100 -> 2.8464593 | AP8: =SUM(AM8:AO8) -> 100 | AQ8: =AQ7/$AT$7*100 -> 82.187687 | AR8: =AR7/$AT$7*100 -> 15.47681 | AS8: =AS7/$AT$7*100 -> 2.335503 | AT8: =SUM(AQ8:AS8) -> 100
A12: Sumber Data :
A13: 1. Konsumsi Akhir | B13: Sheet Stokkap | D13: Idem PDN
A14: 2. Akumulasi Kapital, neto | B14: Sheet Stokkap = PDN | D14: File T-padu = buatan man+alam + lingk
A15: 3. Ekspor Neto | B15: Sheet Stokkap | D15: Idem PDN
A16: 4. Jumlah
A19: Komponen | C19: PDN | E19: PDN1
C20: Nilai (Milliar RP) | D20: Distribusi (%) | E20: Nilai (Milliar RP) | F20: Distribusi (%)
A21: =C3 -> 2014 | B21: 1. Konsumsi Akhir | C21: {=TRANSPOSE(C5:Z8)} -> 7035633.7 | D21: 81.817439 | E21: 7035633.7 | F21: 84.02108
B22: 2. Akumulasi Kapital, neto | C22: 1642635.4 | D22: 19.10222 | E22: 1417102.5 | F22: 16.923349
B23: 3. Ekspor Neto | C23: -79083.211 | D23: -0.91965928 | E23: -79083.211 | F23: -0.94442905
B24: 4. Jumlah | C24: 8599185.9 | D24: 100 | E24: 8373652.9 | F24: 100
A25: =A21+1 -> 2015 | B25: 1. Konsumsi Akhir | C25: 7745630.1 | D25: 82.427552 | E25: 7745630.1 | F25: 84.739283
B26: 2. Akumulasi Kapital, neto | C26: 1607151.1 | D26: 17.103002 | E26: 1350798.9 | F26: 14.778105
B27: 3. Ekspor Neto | C27: 44113.382 | D27: 0.46944639 | E27: 44113.382 | F27: 0.4826123
B28: 4. Jumlah | C28: 9396894.6 | D28: 100 | E28: 9140542.4 | F28: 100
A29: =A25+1 -> 2016 | B29: 1. Konsumsi Akhir | C29: 8353136 | D29: 80.581752 | E29: 8353136 | F29: 82.115206
B30: 2. Akumulasi Kapital, neto | C30: 1919066 | D30: 18.513011 | E30: 1725486.2 | F30: 16.962331
B31: 3. Ekspor Neto | C31: 93837.171 | D31: 0.90523651 | E31: 93837.171 | F31: 0.92246297
B32: 4. Jumlah | C32: 10366039 | D32: 100 | E32: 10172459 | F32: 100
A33: =A29+1 -> 2017 | B33: 1. Konsumsi Akhir | C33: 9023120.3 | D33: 80.860387 | E33: 9023120.3 | F33: 82.471627
B34: 2. Akumulasi Kapital, neto | C34: 1999990.5 | D34: 17.922847 | E34: 1781980.4 | F34: 16.287362
B35: 3. Ekspor Neto | C35: 135777.55 | D35: 1.2167659 | E35: 135777.55 | F35: 1.2410115
B36: 4. Jumlah | C36: 11158888 | D36: 100 | E36: 10940878 | F36: 100
A37: =S3 -> 2018 | B37: 1. Konsumsi Akhir | C37: 9793746.3 | D37: 81.352017 | E37: 9793746.3 | F37: 83.046914
B38: 2. Akumulasi Kapital, neto | C38: 2403578.5 | D38: 19.96539 | E38: 2157881.2 | F38: 18.297939
B39: 3. Ekspor Neto | C39: -158598.99 | D39: -1.3174068 | E39: -158598.99 | F39: -1.3448538
B40: 4. Jumlah | C40: 12038726 | D40: 100 | E40: 11793028 | F40: 100
A41: =W3 -> 2019 | B41: 1. Konsumsi Akhir | C41: 10566547 | D41: 83.43401 | E41: 10566547 | F41: 85.620904
B42: 2. Akumulasi Kapital, neto | C42: 2168420.4 | D42: 17.121962 | E42: 1844947.4 | F42: 14.949639
B43: 3. Ekspor Neto | C43: -70411.3 | D43: -0.55597133 | E43: -70411.3 | F43: -0.57054393
B44: 4. Jumlah | C44: 12664556 | D44: 100 | E44: 12341083 | F44: 100
A45: =AA3 -> 2020 | B45: 1. Konsumsi Akhir | C45: {=TRANSPOSE(AA5:AD8)} -> 10592541 | D45: 84.743389 | E45: 10592541 | F45: 86.69804
B46: 2. Akumulasi Kapital, neto | C46: 1645989.8 | D46: 13.168395 | E46: 1364181.3 | F46: 11.165578
B47: 3. Ekspor Neto | C47: 261017.56 | D47: 2.088216 | E47: 261017.56 | F47: 2.1363817
B48: 4. Jumlah | C48: 12499548 | D48: 100 | E48: 12217740 | F48: 100
A49: =AE3 -> 2021 | B49: 1. Konsumsi Akhir | C49: {=TRANSPOSE(AE5:AH8)} -> 11013796 | D49: 79.635018 | E49: 11013796 | F49: 81.735539
B50: 2. Akumulasi Kapital, neto | C50: 2370337.7 | D50: 17.138677 | E50: 2014911.9 | F50: 14.953056
B51: 3. Ekspor Neto | C51: 446208.96 | D51: 3.2263045 | E51: 446208.96 | F51: 3.3114043
B52: 4. Jumlah | C52: 13830342 | D52: 100 | E52: 13474916 | F52: 100
A53: =AI3 -> 2022 | B53: 1. Konsumsi Akhir | C53: {=TRANSPOSE(AI5:AL8)} -> 11896997 | D53: 74.812517 | E53: 11896997 | F53: 77.633327
B54: 2. Akumulasi Kapital, neto | C54: 3311760.9 | D54: 20.825521 | E54: 2733945.9 | F54: 17.840243
B55: 3. Ekspor Neto | C55: 693657.37 | D55: 4.3619623 | E55: 693657.37 | F55: 4.5264303
B56: 4. Jumlah | C56: 15902416 | D56: 100 | E56: 15324601 | F56: 100
A57: =AM3 -> 2023* | B57: 1. Konsumsi Akhir | C57: {=TRANSPOSE(AM5:AP8)} -> 12928272 | D57: 77.165082 | E57: 12928272 | F57: 81.117927
B58: 2. Akumulasi Kapital, neto | C58: 3372114.2 | D58: 20.127166 | E58: 2555696.2 | F58: 16.035614
B59: 3. Ekspor Neto | C59: 453658.03 | D59: 2.7077524 | E59: 453658.03 | F59: 2.8464593
B60: 4. Jumlah | C60: 16754044 | D60: 100 | E60: 15937626 | F60: 100
A61: {=TRANSPOSE(AQ3:AT8)} -> 2024** | B61: 1. Konsumsi Akhir | C61: 13976578 | D61: 78.907078 | E61: 13976578 | F61: 82.187687
A62: 0 | B62: 2. Akumulasi Kapital, neto | C62: 3338958.7 | D62: 18.850643 | E62: 2631937.3 | F62: 15.47681
A63: 0 | B63: 3. Ekspor Neto | C63: 397168.24 | D63: 2.2422789 | E63: 397168.24 | F63: 2.335503
A64: 0 | B64: 4. Jumlah | C64: 17712705 | D64: 100 | E64: 17005683 | F64: 100

Sheet Studi PDB
A3: Rincian | B3: =C3-1 -> 2014 | C3: ='PDB ADHB'!C1 -> 2015 | D3: ='PDB ADHB'!D1 -> 2016 | E3: ='PDB ADHB'!E1 -> 2017 | F3: ='PDB ADHB'!F1 -> 2018 | G3: ='PDB ADHB'!G1 -> 2019 | H3: ='PDB ADHB'!H1 -> 2020 | I3: ='PDB ADHB'!I1 -> 2021 | J3: ='PDB ADHB'!J1 -> 2022 | ... L3: ='PDB ADHB'!L1 -> 2024**
A4: 1. PDB | B4: ='Stok Kapital'!E5 -> 10569705 | C4: ='Stok Kapital'!M5 -> 11526333 | D4: ='Stok Kapital'!U5 -> 12401728 | E4: ='Stok Kapital'!AC5 -> 13589826 | F4: ='Stok Kapital'!AK5 -> 14838756 | G4: ='Stok Kapital'!AS5 -> 15832657 | H4: ='Stok Kapital'!BA5 -> 15443353 | I4: ='Stok Kapital'!BI5 -> 16976751 | J4: ='Stok Kapital'!BQ5 -> 19588460 | K4: ='Stok Kapital'!BY5 -> 20892348 | L4: ='Stok Kapital'!CG5 -> 22138964
A6: 2. PDN | B6: ='Stok Kapital'!G5 -> 8599185.9 | C6: ='Stok Kapital'!O5 -> 9396894.6 | D6: ='Stok Kapital'!W5 -> 10366039 | E6: ='Stok Kapital'!AE5 -> 11158888 | F6: ='Stok Kapital'!AM5 -> 12038726 | G6: ='Stok Kapital'!AU5 -> 12664556 | H6: ='Stok Kapital'!BC5 -> 12499548 | I6: ='Stok Kapital'!BK5 -> 13830342 | J6: ='Stok Kapital'!BS5 -> 15902416 | K6: ='Stok Kapital'!CA5 -> 16754044 | L6: ='Stok Kapital'!CI5 -> 17712705
A8: 3. PDN 1 | B8: ='PDB vs PDN1'!F7 -> 8373652.9 | C8: ='PDB vs PDN1'!J7 -> 9140542.4 | D8: ='PDB vs PDN1'!N7 -> 10172459 | E8: ='PDB vs PDN1'!R7 -> 10940878 | F8: ='PDB vs PDN1'!V7 -> 11793028 | G8: ='PDB vs PDN1'!Z7 -> 12341083 | H8: ='PDB vs PDN1'!AD7 -> 12217740 | I8: ='PDB vs PDN1'!AH7 -> 13474916 | J8: ='PDB vs PDN1'!AL7 -> 15324601 | K8: ='PDB vs PDN1'!AP7 -> 15937626 | L8: ='PDB vs PDN1'!AT7 -> 17005683
A10: 4. PDN x 100 | B10: =B6/B4*100 -> 81.356912 | C10: =C6/C4*100 -> 81.525449 | D10: =D6/D4*100 -> 83.585438 | E10: =E6/E4*100 -> 82.112078 | F10: =F6/F4*100 -> 81.13029 | G10: =G6/G4*100 -> 79.990086 | H10: =H6/H4*100 -> 80.938045 | I10: =I6/I4*100 -> 81.466365 | ... L10: =L6/L4*100 -> 80.006927 | M10: =100-L10 -> 19.993073
A11: PDB
N12: =M13-M10 -> 3.1935616
A13: 5. PDN1 x 100 | B13: =B8/B4*100 -> 79.223145 | C13: =C8/C4*100 -> 79.301393 | D13: =D8/D4*100 -> 82.024529 | E13: =E8/E4*100 -> 80.507863 | F13: =F8/F4*100 -> 79.474509 | G13: =G8/G4*100 -> 77.947011 | H13: =H8/H4*100 -> 79.113257 | I13: =I8/I4*100 -> 79.372762 | ... L13: =L8/L4*100 -> 76.813366 | M13: =100-L13 -> 23.186634
A14: PDB
A16: 6. PDN1 x 100 | B16: =B8/B6*100 -> 97.377276 | C16: =C8/C6*100 -> 97.271948 | D16: =D8/D6*100 -> 98.132558 | E16: =E8/E6*100 -> 98.046311 | F16: =F8/F6*100 -> 97.959109 | G16: =G8/G6*100 -> 97.44584 | H16: =H8/H6*100 -> 97.74545 | I16: =I8/I6*100 -> 97.430101 | ... L16: =L8/L6*100 -> 96.008394
A17: PDN
A20: Catatan:
A21: PDB | B21: : | C21: Produk Domestik Bruto
A22: PDN | B22: : | C22: Produk Domestik Neto (PDB dikurangi penyusutan)
A23: PDN1 | B23: : | C23: Produk Domestik Neto yang disesuaikan (PDN dikurangi deplesi sumber daya alam)

Sheet Penduduk
A3: Tahun | B3: PDB Atas Dasar Harga Berlaku (Miliar Rp) | C3: Penduduk Pertengahan Tahun (Ribu Orang) | D3: PDB Per Kapita (Rp) | E3: Kurs Dollar AS | F3: PDB Atas Dasar Harga Berlaku (Juta USD) | G3: PDB Per Kapita (USD) | J3: CATATAN
J4: 45979 | K4: Update data terakhir
A5: ='Studi PDB'!B3 -> 2014 | B5: ='PDB ADHB'!B37 -> 10569705 | C5: =252164786/1000 -> 252164.79 | D5: =+B5/C5*1000000 -> 41915866 | E5: 10431.21 | F5: =+B5/E5*1000 -> 1013277 | G5: =+F5/C5*1000 -> 4018.3129
A6: ='Studi PDB'!C3 -> 2015 | B6: ='PDB ADHB'!C37 -> 11526333 | C6: 255461.69 | D6: =+B6/C6*1000000 -> 45119615 | E6: 11838.95 | F6: =+B6/E6*1000 -> 973594.18 | G6: =+F6/C6*1000 -> 3811.1162
A7: ='Studi PDB'!D3 -> 2016 | B7: ='PDB ADHB'!D37 -> 12401728 | C7: 258704.99 | D7: =+B7/C7*1000000 -> 47937725
A8: ='Studi PDB'!E3 -> 2017 | B8: ='PDB ADHB'!E37 -> 13589826 | C8: 261890.87 | D8: =+B8/C8*1000000 -> 51891177
A9: ='Studi PDB'!F3 -> 2018 | B9: ='PDB ADHB'!F37 -> 14838756 | C9: 265015.31 | D9: =+B9/C9*1000000 -> 55992070
A10: ='Studi PDB'!G3 -> 2019 | B10: ='PDB ADHB'!G37 -> 15832657 | C10: =266911905/1000 -> 266911.91 | D10: =+B10/C10*1000000 -> 59317913
A11: ='Studi PDB'!H3 -> 2020 | B11: ='PDB ADHB'!H37 -> 15443353 | C11: =269566470/1000 -> 269566.47 | D11: =+B11/C11*1000000 -> 57289592
A12: ='Studi PDB'!I3 -> 2021 | B12: ='PDB ADHB'!I37 -> 16976751 | C12: =272679153/1000 -> 272679.15 | D12: =+B12/C12*1000000 -> 62259073
A13: ='Studi PDB'!J3 -> 2022 | B13: ='PDB ADHB'!J37 -> 19588460 | C13: =275719905/1000 -> 275719.91 | D13: =+B13/C13*1000000 -> 71044780
A14: ='Studi PDB'!K3 -> 2023* | B14: ='PDB ADHB'!K37 -> 20892348 | C14: =278696193/1000 -> 278696.19 | D14: =+B14/C14*1000000 -> 74964600
A15: ='Studi PDB'!L3 -> 2024** | B15: ='PDB ADHB'!L37 -> 22138964 | C15: =281603799/1000 -> 281603.8 | D15: =+B15/C15*1000000 -> 78617420

Sheet National Wealth
A3: Tahun | B3: Nilai Aset di Akhir Tahun (Miliar Rp) | D3: Total | E3: Persentase (%)
B4: Aset yang Diproduksi (Produced Assets) | C4: Aset Alam (Non-Produced Assets) | E4: Aset yang Diproduksi (Produced Assets) | F4: Aset Alam (Non-Produced Assets)
A5: =A6-1 -> 2014 | B5: ='Neraca Terpadu'!E60 -> 38102453 | C5: =SUM('Neraca Terpadu'!F61:F70) -> 7533266.5 | D5: =B5+C5 -> 45635719 | E5: =B5/D5 -> 0.83492609 | F5: =1-E5 -> 0.16507391
A6: ='Studi PDB'!C3 -> 2015 | B6: ='Neraca Terpadu'!K60 -> 41623718 | C6: =SUM('Neraca Terpadu'!L61:L70) -> 7087728.7 | D6: =B6+C6 -> 48711446 | E6: =B6/D6 -> 0.85449562 | F6: =1-E6 -> 0.14550438
A7: ='Studi PDB'!D3 -> 2016 | B7: ='Neraca Terpadu'!Q60 -> 44861123 | C7: =SUM('Neraca Terpadu'!R61:R70) -> 7621715.7 | D7: =B7+C7 -> 52482839 | E7: =B7/D7 -> 0.85477699 | F7: =1-E7 -> 0.14522301
A8: ='Studi PDB'!E3 -> 2017 | B8: ='Neraca Terpadu'!W60 -> 49172159 | C8: =SUM('Neraca Terpadu'!X61:X70) -> 9431868.4 | D8: =B8+C8 -> 58604027 | E8: =B8/D8 -> 0.83905767 | F8: =1-E8 -> 0.16094233
A9: ='Studi PDB'!F3 -> 2018 | B9: ='Neraca Terpadu'!AC60 -> 54392257 | C9: =SUM('Neraca Terpadu'!AD61:AD70) -> 9557954.7 | D9: =B9+C9 -> 63950211 | E9: =B9/D9 -> 0.85054069 | F9: =1-E9 -> 0.14945931
A10: ='Studi PDB'!G3 -> 2019 | B10: ='Neraca Terpadu'!AI60 -> 58178121 | C10: =SUM('Neraca Terpadu'!AJ61:AJ70) -> 9204516.4 | D10: =B10+C10 -> 67382637 | E10: =B10/D10 -> 0.86339929 | F10: =1-E10 -> 0.13660071
A11: ='Studi PDB'!H3 -> 2020 | B11: ='Neraca Terpadu'!AO60 -> 61666805 | C11: =SUM('Neraca Terpadu'!AP61:AP70) -> 9166919 | D11: =B11+C11 -> 70833724 | E11: =B11/D11 -> 0.87058539 | F11: =1-E11 -> 0.12941461
A12: ='Studi PDB'!I3 -> 2021 | B12: ='Neraca Terpadu'!AU60 -> 67696559 | C12: =SUM('Neraca Terpadu'!AV61:AV70) -> 14300899 | D12: =B12+C12 -> 81997458 | E12: =B12/D12 -> 0.82559339 | F12: =1-E12 -> 0.17440661
A13: ='Studi PDB'!J3 -> 2022 | B13: ='Neraca Terpadu'!BA60 -> 74342957 | C13: =SUM('Neraca Terpadu'!BB61:BB70) -> 23695776 | D13: =B13+C13 -> 98038733 | E13: =B13/D13 -> 0.75830189 | F13: =1-E13 -> 0.24169811
A14: ='Studi PDB'!K3 -> 2023* | B14: ='Neraca Terpadu'!BG60 -> 80433633 | C14: =SUM('Neraca Terpadu'!BH61:BH70) -> 21829912 | D14: =B14+C14 -> 1.0226355e+08 | E14: =B14/D14 -> 0.7865328 | F14: =1-E14 -> 0.2134672
A15: ='Studi PDB'!L3 -> 2024** | B15: ='Neraca Terpadu'!BM60 -> 86886164 | C15: =SUM('Neraca Terpadu'!BN61:BN70) -> 18330132 | D15: =B15+C15 -> 1.052163e+08 | E15: =B15/D15 -> 0.82578619 | F15: =1-E15 -> 0.17421381
A17: Tahun | B17: Nilai Aset per Kapita (Ribu Rp) | E17: Pertumbuhan (%)
B18: Aset yang Diproduksi (Produced Assets) | C18: Aset Alam (Non-Produced Assets) | D18: Total | E18: Aset yang Diproduksi (Produced Assets) | F18: Aset Alam (Non-Produced Assets) | G18: Total | M18: 1000000000 | N18: 9
A19: =A5 -> 2014 | B19: =B5/Penduduk!C5*1000 -> 151101.4 | C19: =C5/Penduduk!C5*1000 -> 29874.379 | D19: =D5/Penduduk!C5*1000 -> 180975.78 | I19: =B15*1000000/281603799 -> 308540.45 | M19: 1000
A20: =A6 -> 2015 | B20: =B6/Penduduk!C6*1000 -> 162935.27 | C20: =C6/Penduduk!C6*1000 -> 27744.782 | D20: =D6/Penduduk!C6*1000 -> 190680.05 | E20: =B20/B19*100-100 -> 7.8317365 | F20: =C20/C19*100-100 -> -7.1285086 | G20: =D20/D19*100-100 -> 5.3621904 | K20: =C5/Penduduk!C5 -> 29.874379
A21: =A7 -> 2016 | B21: =B7/Penduduk!C7*1000 -> 173406.49 | C21: =C7/Penduduk!C7*1000 -> 29461.031 | D21: =D7/Penduduk!C7*1000 -> 202867.52 | E21: =B21/B20*100-100 -> 6.4266151 | F21: =C21/C20*100-100 -> 6.1858474 | G21: =D21/D20*100-100 -> 6.3915823 | I21: =B15/Penduduk!C15*1000000 -> 3.0854045e+08 | M21: 1000000 | N21: 6
A22: =A8 -> 2017 | B22: =B8/Penduduk!C8*1000 -> 187758.2 | C22: =C8/Penduduk!C8*1000 -> 36014.498 | D22: =D8/Penduduk!C8*1000 -> 223772.7 | E22: =B22/B21*100-100 -> 8.2763411 | F22: =C22/C21*100-100 -> 22.244527 | G22: =D22/D21*100-100 -> 10.304843 | I22: =I21/1000000000 -> 0.30854045
A23: =A9 -> 2018 | B23: =B9/Penduduk!C9*1000 -> 205241.94 | C23: =C9/Penduduk!C9*1000 -> 36065.67 | D23: =D9/Penduduk!C9*1000 -> 241307.61 | E23: =B23/B22*100-100 -> 9.3118372 | F23: =C23/C22*100-100 -> 0.14208457 | G23: =D23/D22*100-100 -> 7.8360359
A24: =A10 -> 2019 | B24: =B10/Penduduk!C10*1000 -> 217967.5 | C24: =C10/Penduduk!C10*1000 -> 34485.222 | D24: =D10/Penduduk!C10*1000 -> 252452.72 | E24: =B24/B23*100-100 -> 6.2002736 | F24: =C24/C23*100-100 -> -4.3821377 | G24: =D24/D23*100-100 -> 4.6186336
A25: =A11 -> 2020 | B25: =B11/Penduduk!C11*1000 -> 228762.89 | C25: =C11/Penduduk!C11*1000 -> 34006.155 | D25: =D11/Penduduk!C11*1000 -> 262769.05 | E25: =B25/B24*100-100 -> 4.9527527 | F25: =C25/C24*100-100 -> -1.3891971 | G25: =D25/D24*100-100 -> 4.0864378
A26: =A12 -> 2021 | B26: =B12/Penduduk!C12*1000 -> 248264.52 | C26: =C12/Penduduk!C12*1000 -> 52445.884 | D26: =D12/Penduduk!C12*1000 -> 300710.4 | E26: =B26/B25*100-100 -> 8.5248223 | F26: =C26/C25*100-100 -> 54.224682 | G26: =D26/D25*100-100 -> 14.439052
A27: =A13 -> 2022 | B27: =B13/Penduduk!C13*1000 -> 269632.17 | C27: =C13/Penduduk!C13*1000 -> 85941.479 | D27: =D13/Penduduk!C13*1000 -> 355573.65 | E27: =B27/B26*100-100 -> 8.606808 | F27: =C27/C26*100-100 -> 63.866967 | G27: =D27/D26*100-100 -> 18.244545
A28: =A14 -> 2023* | B28: =B14/Penduduk!C14*1000 -> 288606.86 | C28: =C14/Penduduk!C14*1000 -> 78328.707 | D28: =D14/Penduduk!C14*1000 -> 366935.57 | E28: =B28/B27*100-100 -> 7.0372498 | F28: =C28/C27*100-100 -> -8.8580882 | G28: =D28/D27*100-100 -> 3.1953767
A29: =A15 -> 2024** | B29: =B15/Penduduk!C15*1000 -> 308540.45 | C29: =C15/Penduduk!C15*1000 -> 65091.922 | D29: =D15/Penduduk!C15*1000 -> 373632.38 | E29: =B29/B28*100-100 -> 6.9068329 | F29: =C29/C28*100-100 -> -16.899022 | G29: =D29/D28*100-100 -> 1.8250638
A31: Tahun | B31: Nilai Penyusutan (Miliar Rp) | D31: Pertumbuhan (%)
B32: Konsumsi Barang Modal Tetap (Consumption of Fixed Capital) | C32: Deplesi Aset Lingkungan | D32: Aset yang Diproduksi (Produced Assets) | E32: Aset Alam (Non-Produced Assets)
A33: =A19 -> 2014 | B33: ='Neraca Terpadu'!C22 -> 1970519.4 | C33: ='Neraca Terpadu'!C24 -> 225532.93
A34: =A20 -> 2015 | B34: ='Neraca Terpadu'!I22 -> 2129438.2 | C34: ='Neraca Terpadu'!I24 -> 256352.15 | D34: =B34/B33*100-100 -> 8.0648173 | E34: =C34/C33*100-100 -> 13.665062
A35: =A21 -> 2016 | B35: ='Neraca Terpadu'!O22 -> 2035689.4 | C35: ='Neraca Terpadu'!O24 -> 193579.77 | D35: =B35/B34*100-100 -> -4.4025142 | E35: =C35/C34*100-100 -> -24.486778
A36: =A22 -> 2017 | B36: ='Neraca Terpadu'!U22 -> 2430937.4 | C36: ='Neraca Terpadu'!U24 -> 218010.01 | D36: =B36/B35*100-100 -> 19.415931 | E36: =C36/C35*100-100 -> 12.620245
A37: =A23 -> 2018 | B37: ='Neraca Terpadu'!AA22 -> 2800030.2 | C37: ='Neraca Terpadu'!AA24 -> 245697.33 | D37: =B37/B36*100-100 -> 15.183146 | E37: =C37/C36*100-100 -> 12.700022
A38: =A24 -> 2019 | B38: ='Neraca Terpadu'!AG22 -> 3168101.1 | C38: ='Neraca Terpadu'!AG24 -> 323473.01 | D38: =B38/B37*100-100 -> 13.145248 | E38: =C38/C37*100-100 -> 31.655079
A39: =A25 -> 2020 | B39: ='Neraca Terpadu'!AM22 -> 2943805 | C39: ='Neraca Terpadu'!AM24 -> 281808.55 | D39: =B39/B38*100-100 -> -7.0798284 | E39: =C39/C38*100-100 -> -12.88035
A40: =A26 -> 2021 | B40: ='Neraca Terpadu'!AS22 -> 3146409.1 | C40: ='Neraca Terpadu'!AS24 -> 355425.88 | D40: =B40/B39*100-100 -> 6.8823883 | E40: =C40/C39*100-100 -> 26.123169
A41: =A27 -> 2022 | B41: ='Neraca Terpadu'!AY22 -> 3686044.4 | C41: ='Neraca Terpadu'!AY24 -> 577815.02 | D41: =B41/B40*100-100 -> 17.15083 | E41: =C41/C40*100-100 -> 62.569767
A42: =A28 -> 2023* | B42: ='Neraca Terpadu'!BE22 -> 4138304.5 | C42: ='Neraca Terpadu'!BE24 -> 816417.99 | D42: =B42/B41*100-100 -> 12.269526 | E42: =C42/C41*100-100 -> 41.294005
A43: =A29 -> 2024** | B43: ='Neraca Terpadu'!BK22 -> 4426259.2 | C43: ='Neraca Terpadu'!BK24 -> 707021.45 | D43: =B43/B42*100-100 -> 6.9582751 | E43: =C43/C42*100-100 -> -13.399575
